Workbook

Sheet Start here
A1: Breakout 4B · compute it yourself, from the raw data
A3: Each sprint has one sheet where your group computes the numbers with ordinary Excel tools, from the data both administrations hold: the customs registers and declaration lines, the tax register and the VAT returns. 4B_lab.xlsx shows every number already computed; here you learn how they are made. When your number is right, the Check cell turns green.
A4: Colours: yellow = you type here (a number or a formula). Grey = given or worked for you. Purple = computed for you (a helper: string similarity, a model score, a median per sector); the Fields sheet says how. Navy = column names. Every threshold sits on the Parameters sheet.
A5: Stuck? Hint 1 is beside each step. Hint 2, the full formula, is on the Hints sheet and on the site. The coach (coach-4b) helps one step at a time. 4B_compute_worked.xlsx shows every formula filled in.
A7: When | B7: Sheet | D7: What you compute
A8: Sprint 1 | B8: S1 Match | D8: The 25 importers against the tax register: the exact join on the tax number, the match confidence from the similarities, the class at the dial. I17 is worked.
A9: Sprint 1 | B9: S1 Track B | D9: A real register: precision and recall on the labelled sample at three settings of the dial.
A10: Sprint 2 | B10: S2 Four lists | D10: From the declaration lines and the VAT returns: imports and import VAT paid, returns filed, import VAT deducted, sales; the four questions in order; VAT at stake; list 4 ranked and cut at the capacity. I01 is worked.
A11: Sprint 3 | B11: S3 Network | D11: From the customs registers: what each tax number serves (names, consignees, addresses, brokers), the rule, and what the tax register says about its director.
A12: Sprint 4 | B12: S4 Tax feeds customs | D12: With the tax audit file: does a tax adjustment found at random point to customs findings? The customs hit rate with and without a tax adjustment, and the lift.
A14: Everything in this workbook is synthetic (release data-v13). Published customs datasets record an irregularity on 1 to 8 lines in 100; in this lab the random draw finds 3 in 100.

Sheet Parameters
A1: Parameters · every threshold of the breakout in one place
A2: Every formula reads its threshold here. Change one, and every sheet follows. The weights and the dial are choices: say them out loud.
A4: parameter | B4: value | C4: note
A5: Weight of the name similarity | B5: 0.4 | C5: The deck's recipe; a choice, not a measurement.
A6: Weight of the address similarity | B6: 0.3 | C6: Idem.
A7: Weight of the director similarity | B7: 0.3 | C7: Idem.
A8: Dial: a link at or above | B8: 0.9 | C8: Set on the labelled sample (S1 Track B).
A9: Dial: a person reviews at or above | B9: 0.7 | C9: Below it: no link.
A10: VAT rate | B10: 0.1 | C10: The lab's rate.
A11: First period number of the last six returns | B11: 19 | C11: Periods 19 to 24 = 2026-04 to 2026-09.
A12: First period number of the last twelve returns | B12: 13 | C12: Periods 13 to 24 = 2025-10 to 2026-09.
A13: First customs month of the last twelve months | B13: 25 | C13: Months 25 to 36 = 2025-10 to 2026-09.
A14: Filing: at least this many of the last six returns | B14: 5 | C14: Question 2.
A15: Imports in its books: deducted ÷ paid at least | B15: 0.5 | C15: Question 3.
A16: Sold: sales ÷ imports at least | B16: 1 | C16: Question 4.
... A20: Network rule: turnover ÷ imports under | B20: 0.2 | C20: The 4B rule.

Sheet Tax register
A1: The tax register · 1,799 taxpayers as the tax administration holds them
A4: tax ID | B4: legal name | C4: trading name | D4: address | E4: district | F4: phone | G4: director | H4: registered on | I4: VAT registered | J4: status | K4: sector
A5: T100004 | B5: Metro Trading Co., Ltd | D5: Unit 21, 369 Airport Road | E5: North | F5: 0800178993 | G5: A. Tanaka | H5: 2022-08-09 | I5: TRUE | J5: active | K5: Vehicles and parts
A6: T100013 | B6: Prescott Imports Group Ltd | D6: 102 Temple Street | E6: East | F6: 0725292216 | G6: Kenji Mwangi | H6: 2023-03-18 | I6: TRUE | J6: active | K6: Vehicles and parts
A7: T100016 | B7: Saffron Trading & Sons | D7: 53 Garden Lane | E7: Capital | F7: 0471812185 | G7: Omar Rahman | H7: 2014-11-05 | I7: TRUE | J7: dormant | K7: General trading
A8: T100025 | B8: Harmony Fruits Co., Ltd | C8: Harmony Fruits Co., Ltd | D8: 297 Airport Road | E8: North | F8: 0328461006 | G8: Nadia Sato | H8: 2009-06-03 | I8: TRUE | J8: active | K8: Vehicles and parts
A9: T100033 | B9: Central Foods Limited | C9: Central Foods Limited | D9: 24 Harbour Road | E9: East | F9: 0401520138 | G9: Farid Ibrahim | H9: 2020-05-16 | I9: TRUE | J9: active | K9: Steel and construction
A10: T100038 | B10: Saffron Textiles Co. | C10: Saffron Textiles Co. | D10: 8 MILL ROAD | E10: North | F10: 0690619802 | G10: Grace Silva | H10: 2018-05-04 | I10: TRUE | J10: active | K10: Textiles and apparel
A11: T100052 | B11: Twin Rivers Textiles & Sons | D11: 321 Riverside | E11: South | F11: 0879024230 | G11: Amina Osei | H11: 2022-12-08 | I11: TRUE | J11: active | K11: Furniture and household
A12: T100056 | B12: Green Valley Imports Group Ltd | C12: Green Valley Imports Group Ltd | D12: 16 Industrial Estate | E12: West | F12: 0999463247 | G12: Somchai Osei | H12: 2008-08-25 | I12: TRUE | J12: active | K12: Steel and construction
A13: T100064 | B13: Aldergate Trading Company | D13: 71 Bazaar Lane | E13: Capital | F13: 0459332927 | G13: Omar Sato | H13: 2012-02-13 | I13: TRUE | J13: active | K13: Tobacco and beverages
A14: T100070 | B14: Silk Road Steel Co. | C14: Silk Road Steel Co. | D14: 346 Market Street | E14: North | F14: 0519965779 | G14: Farid Haddad | H14: 2010-12-11 | I14: TRUE | J14: active | K14: Pharmaceuticals
A15: T100082 | B15: Harmony Trading & Sons | D15: 199 Bazaar Lane | E15: North | F15: 0405422879 | G15: Amina Ibrahim | H15: 2014-09-01 | I15: TRUE | J15: active | K15: Steel and construction
A16: T100090 | B16: Twin Rivers Glow International Limited | C16: Twin Rivers Glow International Ltd | D16: Unit 10, 37 Station Road | E16: West | F16: 0232613013 | G16: Tomas Sato | H16: 2015-10-21 | I16: TRUE | J16: active | K16: Textiles and apparel
A17: T100097 | B17: Silk Road Industries Company | C17: Silk Depot | D17: 23 Airport Road | E17: East | F17: 0387995973 | G17: Priya Haddad | H17: 2010-07-10 | I17: TRUE | J17: active | K17: General trading
A18: T100104 | B18: Silver Logistics Co., Ltd | C18: Silver Logistics Co., Ltd | D18: 239 Airport Road | E18: Capital | F18: 0967270280 | G18: Samuel Sato | H18: 2015-02-11 | I18: TRUE | J18: active | K18: Textiles and apparel
A19: T100105 | B19: Saffron Electronics International Ltd | D19: 180 Garden Lane | E19: North | F19: 0413172306 | G19: Ravi Kowalski | H19: 2019-09-29 | I19: TRUE | J19: active | K19: Vehicles and parts
A20: T100116 | B20: Lotus Supply Partners Ltd | C20: Lotus Supply Partners Ltd | D20: 165 AIRPORT ROAD | E20: South | F20: 0297464461 | G20: Elena Haddad | H20: 2011-01-26 | I20: TRUE | J20: active | K20: Cosmetics and personal care
A21: T100119 | B21: Eastern Electronics & Sons | C21: Eastern Electronics & Sons | D21: 200 Harbour Road | E21: Coastal | F21: 0254068681 | G21: Nadia Sato | H21: 2011-03-15 | I21: TRUE | J21: active | K21: Cosmetics and personal care
A22: T100130 | B22: Royal Fruits Holdings Ltd | D22: 313 Market Street | E22: South | F22: 0269581004 | G22: B. Fernandes | H22: 2022-03-30 | I22: TRUE | J22: active | K22: Vehicles and parts
A23: T100134 | B23: Central Commercial Enterprises | C23: Central Commercial Enterprises | D23: Unit 13, 218 Industrial Estate | E23: East | F23: 0945440269 | G23: Priya Patel | H23: 2018-02-11 | I23: TRUE | J23: active | K23: Tobacco and beverages
A24: T100144 | B24: Crown Textiles & Sons | D24: 230 Garden Lane | E24: West | F24: 0806964313 | G24: Joseph Tanaka | H24: 2025-02-26 | I24: TRUE | J24: active | K24: Pharmaceuticals
A25: T100152 | B25: Crown Glow Group Limited | C25: Crown Glow Group Ltd | D25: 256 Market Street | E25: West | F25: 0980794230 | G25: Aisha Patel | H25: 2021-07-12 | I25: TRUE | J25: active | K25: Tobacco and beverages
A26: T100155 | B26: Silver Enterprises Limited | C26: Silver Enterprises Limited | D26: 21 Station Road | E26: South | F26: 0601335760 | G26: Ravi Sato | H26: 2013-11-30 | I26: TRUE | J26: active | K26: Textiles and apparel
A27: T100165 | B27: Pacific Glow Company | C27: Pacific Glow Co. | D27: 106 Station Rd | E27: Coastal | F27: 0229991183 | G27: Kenji Chen | H27: 2011-05-17 | I27: TRUE | J27: dormant | K27: Electronics
A28: T100173 | B28: Coral Supply Limited | C28: Coral Supply Limited | D28: 323 Bazaar Lane | E28: Coastal | F28: 0873719125 | G28: M. Sato | H28: 2025-11-14 | I28: TRUE | J28: active | K28: Food importers
A29: T100177 | B29: Aldergate Supply Co., Ltd | D29: 153 HARBOUR ROAD | E29: South | F29: 0229299704 | G29: Omar Haddad | H29: 2018-06-02 | I29: TRUE | J29: active | K29: Vehicles and parts
A30: T100193 | B30: Inverness Agro Co. | C30: Inverness Agro Co. | D30: 206 BAZAAR LANE | E30: Capital | F30: 0580341553 | G30: Daniel Mahmood | H30: 2009-07-06 | I30: TRUE | J30: active | K30: Fuel and chemicals
A31: T100201 | B31: Global Glow Limited | C31: Global Glow Ltd | D31: Unit 19, 83 Temple Street | E31: East | F31: 0510129904 | G31: Samuel Patel | H31: 2012-05-14 | I31: TRUE | J31: active | K31: Food importers
A32: T100208 | B32: Evergreen Pack Partners Limited | D32: 267 Riverside | E32: Coastal | F32: 0502506634 | G32: Samuel Okafor | H32: 2016-01-26 | I32: TRUE | J32: active | K32: Cosmetics and personal care
A33: T100211 | B33: Metro Living Partners Ltd | D33: 381 Temple Street | E33: South | F33: 0986965771 | G33: Daniel Ibrahim | H33: 2010-06-03 | I33: TRUE | J33: active | K33: Furniture and household
A34: T100219 | B34: Ashcombe Motors Co. | C34: Ashcombe Motors Co. | D34: 90 AIRPORT ROAD | E34: East | F34: 0611073084 | G34: Omar Rahman | H34: 2022-04-19 | I34: TRUE | J34: active | K34: Machinery
A35: T100225 | B35: Global Agro International Ltd | C35: Global Depot | D35: 260 Harbour Road | E35: Capital | F35: 0531652277 | G35: Amina Mensah | H35: 2020-11-14 | I35: TRUE | J35: active | K35: General trading
A36: T100236 | B36: Arden Supply Holdings Ltd | C36: Arden Supply Holdings Ltd | D36: 235 Mill Road | E36: North | F36: 0380927935 | G36: Grace Tanaka | H36: 2014-11-15 | I36: TRUE | J36: active | K36: Medical devices
A37: T100242 | B37: Metro Fruits Co. | C37: Metro Fruits Co. | D37: 139 Airport Road | E37: Coastal | F37: 0581524750 | G37: Omar Sato | H37: 2012-10-22 | I37: TRUE | J37: active | K37: Cosmetics and personal care
A38: T100251 | B38: Horizon Glow Co., Ltd | C38: Horizon Glow Co., Ltd | D38: 354 GARDEN LANE | E38: Capital | F38: 0719900946 | G38: Somchai Chen | H38: 2009-08-26 | I38: TRUE | J38: active | K38: Machinery
A39: T100257 | B39: Carrick Agro & Sons | D39: 320 Temple Street | E39: East | F39: 0506676501 | G39: Aisha Al-Sayed | H39: 2014-04-20 | I39: TRUE | J39: active | K39: Steel and construction
A40: T100260 | B40: Prescott Steel Holdings Ltd | C40: Prescott Steel Holdings Ltd | D40: 228 Industrial Estate | E40: North | F40: 0768739530 | G40: Tomas Mensah | H40: 2020-01-02 | I40: TRUE | J40: active | K40: Pharmaceuticals
A41: T100272 | B41: Central Imports Partners Limited | D41: 294 Station Rd | E41: East | F41: 0407340201 | G41: Ravi Bauer | H41: 2009-07-04 | I41: TRUE | J41: active | K41: Fuel and chemicals
A42: T100277 | B42: Delta Foods Limited | D42: 96 Garden Lane | E42: Coastal | F42: 0616961808 | G42: Samuel Patel | H42: 2011-01-17 | I42: TRUE | J42: active | K42: Textiles and apparel
A43: T100282 | B43: Dunmore Motors Limited | D43: Unit 12, 385 Mill Road | E43: Capital | F43: 0607781079 | G43: Ingrid Al-Sayed | H43: 2020-12-12 | I43: TRUE | J43: active | K43: General trading
A44: T100287 | B44: Lotus Enterprises International Ltd | C44: Lotus Enterprises International Ltd | D44: 364 Bazaar Lane | E44: North | F44: 0811280093 | G44: Ingrid Ibrahim | H44: 2014-08-09 | I44: TRUE | J44: active | K44: Vehicles and parts
A45: T100295 | B45: Lotus Distribution Holdings Ltd | C45: Lotus Distribution Holdings Ltd | D45: 110 Mill Road | E45: West | F45: 0972504259 | G45: S. Patel | H45: 2017-09-25 | I45: TRUE | J45: active | K45: Tobacco and beverages
A46: T100306 | B46: PRIME FRUITS ENTERPRISES | D46: 376 Airport Road | E46: Coastal | F46: 0317564105 | G46: Mei Mensah | H46: 2019-02-09 | I46: TRUE | J46: active | K46: Tobacco and beverages
A47: T100311 | B47: Royal Fruits Group Limited | D47: 132 Market Street | E47: Capital | F47: 0724082512 | G47: Kenji Osei | H47: 2024-07-26 | I47: TRUE | J47: active | K47: Furniture and household
A48: T100315 | B48: Green Valley Logistics Co. | C48: Green Valley Logistics Co. | D48: 346 Airport Road | E48: Capital | F48: 0683702104 | G48: B. Novak | H48: 2021-09-12 | I48: TRUE | J48: active | K48: General trading
A49: T100324 | B49: Star Steel Enterprises | C49: Star Steel Enterprises | D49: 208 Riverside | E49: West | F49: 0935052080 | G49: M. Sato | H49: 2013-09-10 | I49: TRUE | J49: active | K49: Cosmetics and personal care
A50: T100332 | B50: Golden Foods & Sons | D50: 263 Garden Lane | E50: West | F50: 0866529413 | G50: Joseph Chen | H50: 2021-02-10 | I50: TRUE | J50: active | K50: Tobacco and beverages
A51: T100341 | B51: Horizon Logistics Group Ltd | D51: 71 GARDEN LANE | E51: South | F51: 0816434202 | G51: Tomas Mahmood | H51: 2025-04-17 | I51: TRUE | J51: active | K51: General trading
A52: T100343 | B52: Saffron Electronics Partners Ltd | C52: Saffron Store | D52: 383 Station Road | E52: West | F52: 0778252915 | G52: Nadia Reyes | H52: 2010-09-14 | I52: TRUE | J52: active | K52: Fuel and chemicals
A53: T100356 | B53: Green Valley Steel Co. | C53: Green Trade | D53: 178 Market Street | E53: Coastal | F53: 0559711857 | G53: Hassan Al-Sayed | H53: 2021-12-27 | I53: TRUE | J53: active | K53: General trading
A54: T100360 | B54: Inverness Pack Limited | D54: 324 Industrial Estate | E54: Capital | F54: 0362842634 | G54: Somchai Tanaka | H54: 2022-12-17 | I54: TRUE | J54: active | K54: Tobacco and beverages
A55: T100374 | B55: Eastern Pack Enterprises | C55: Eastern Pack Enterprises | D55: 95 Harbour Road | E55: South | F55: 0561980789 | G55: Priya Osei | H55: 2015-10-21 | I55: TRUE | J55: active | K55: Cosmetics and personal care
A56: T100381 | B56: Aldergate Steel Group Ltd | C56: Aldergate Steel Group Ltd | D56: 321 Market Street | E56: West | F56: 0993671551 | G56: Ingrid Kowalski | H56: 2009-08-27 | I56: TRUE | J56: active | K56: Steel and construction
A57: T100388 | B57: Inverness Industries Group Ltd | C57: Inverness Industries Group Ltd | D57: 56 Garden Lane | E57: South | F57: 0354679037 | G57: Hassan Chen | H57: 2022-02-15 | I57: TRUE | J57: active | K57: Medical devices
A58: T100394 | B58: Central Textiles Limited | C58: Central Textiles Limited | D58: 240 Bazaar Lane | E58: North | F58: 0940022322 | G58: Samuel Chen | H58: 2015-12-25 | I58: TRUE | J58: active | K58: Textiles and apparel
A59: T100405 | B59: Harmony Electronics Enterprises | D59: 292 Bazaar Lane | E59: Coastal | F59: 0688231310 | G59: Farid Bauer | H59: 2012-11-09 | I59: TRUE | J59: dormant | K59: Electronics
A60: T100406 | B60: Twin Rivers Supply Enterprises | D60: 262 Temple Street | E60: Coastal | F60: 0934603203 | G60: Ravi Osei | H60: 2010-11-20 | I60: TRUE | J60: active | K60: Vehicles and parts
A61: T100415 | B61: Delta Living Partners Ltd | C61: Delta Living Partners Ltd | D61: 376 Harbour Road | E61: Capital | F61: 0273895229 | G61: Ingrid Kowalski | H61: 2009-04-15 | I61: TRUE | J61: active | K61: Medical devices
A62: T100420 | B62: United Commercial International Ltd | D62: 35 Airport Road | E62: South | F62: 0336945144 | G62: Farid Haddad | H62: 2020-04-07 | I62: TRUE | J62: active | K62: Food importers
A63: T100427 | B63: Golden Textiles Limited | C63: Golden Textiles Ltd | D63: 55 Riverside | E63: East | F63: 0674129122 | G63: Priya Bauer | H63: 2010-01-09 | I63: TRUE | J63: active | K63: Steel and construction
A64: T100440 | B64: Metro Motors Co., Ltd | C64: Metro Motors Co., Ltd | D64: 215 Bazaar Lane | E64: West | F64: 0929915234 | G64: Ingrid Al-Sayed | H64: 2013-04-28 | I64: TRUE | J64: active | K64: Vehicles and parts
A65: T100445 | B65: Cobalt Mobile Ltd | D65: 396 MILL ROAD | E65: Capital | F65: 0334789891 | G65: Nadia Sato | H65: 2015-04-27 | I65: TRUE | J65: active | K65: General trading
A66: T100450 | B66: Great Vellmoor Fruits Partners Limited | C66: Great Vellmoor Fruits Partners Ltd | D66: 395 Garden Lane | E66: North | F66: 0701160434 | G66: Mei Nguyen-Lee | H66: 2016-11-18 | I66: TRUE | J66: active | K66: Fuel and chemicals
A67: T100466 | B67: Pacific Enterprises Holdings Ltd | D67: 356 Station Road | E67: East | F67: 0254736740 | G67: Farid Sato | H67: 2008-12-28 | I67: TRUE | J67: active | K67: Fuel and chemicals
A68: T100474 | B68: Green Valley Fruits Co., Ltd | D68: 357 Market Street | E68: East | F68: 0584646483 | G68: Daniel Al-Sayed | H68: 2018-08-14 | I68: TRUE | J68: active | K68: Tobacco and beverages
A69: T100476 | B69: Evergreen Fruits Group Ltd | D69: 74 Bazaar Lane | E69: West | F69: 0673992353 | G69: Daniel Chen | H69: 2024-05-03 | I69: TRUE | J69: active | K69: Pharmaceuticals
A70: T100490 | B70: Carrick Enterprises Co. | D70: 143 Garden Lane | E70: South | F70: 0759443551 | G70: Mei Mahmood | H70: 2026-03-09 | I70: TRUE | J70: active | K70: Textiles and apparel
A71: T100497 | B71: Great Vellmoor Pack Holdings Limited | C71: Great Vellmoor Pack Holdings Ltd | D71: 368 STATION ROAD | E71: Capital | F71: 0244279675 | G71: Hassan Chen | H71: 2014-07-07 | I71: TRUE | J71: active | K71: Vehicles and parts
A72: T100510 | B72: GLOBAL PACK & SONS | C72: Global Pack & Sons | D72: 172 Mill Road | E72: South | F72: 0670197514 | G72: Hassan Bauer | H72: 2010-03-23 | I72: TRUE | J72: active | K72: Furniture and household
A73: T100516 | B73: Dunmore Imports & Sons | C73: Dunmore Imports & Sons | D73: 93 Riverside | E73: West | F73: 0802046839 | G73: Hassan Chen | H73: 2009-12-22 | I73: TRUE | J73: active | K73: Food importers
A74: T100519 | B74: HARMONY TEXTILES LIMITED | D74: 321 Market Street | E74: Coastal | F74: 0543950447 | G74: Farid Silva | H74: 2025-09-29 | I74: TRUE | J74: active | K74: Food importers
A75: T100529 | B75: United Imports Enterprises | D75: 343 Station Road | E75: South | F75: 0913727677 | G75: Ravi Mahmood | H75: 2022-01-18 | I75: TRUE | J75: active | K75: Textiles and apparel
A76: T100538 | B76: Metro Enterprises Co., Ltd | C76: Metro Centre | D76: 223 TEMPLE STREET | E76: Capital | F76: 0325939693 | G76: Priya Reyes | H76: 2020-02-24 | I76: TRUE | J76: active | K76: Electronics
A77: T100540 | B77: Orchid Imports Group Ltd | D77: 57 Market Street | E77: West | F77: 0201832970 | G77: S. Kowalski | H77: 2026-06-03 | I77: TRUE | J77: active | K77: Textiles and apparel
A78: T100551 | B78: Saffron Enterprises Limited | D78: 301 Airport Rd | E78: Capital | F78: 0878357885 | G78: Ravi Mensah | H78: 2016-07-26 | I78: TRUE | J78: active | K78: Cosmetics and personal care
A79: T100555 | B79: Saffron Agro Company | D79: 272 Airport Road | E79: South | F79: 0980859838 | G79: Lucia Rahman | H79: 2008-06-16 | I79: TRUE | J79: active | K79: Fuel and chemicals
A80: T100560 | B80: Crown Logistics Group Limited | D80: 237 Mill Road | E80: Coastal | F80: 0227583804 | G80: Lucia Mahmood | H80: 2012-05-21 | I80: TRUE | J80: active | K80: General trading
A81: T100569 | B81: HARMONY TEXTILES & SONS | C81: Harmony Textiles & Sons | D81: 283 Riverside | E81: North | F81: 0239486735 | G81: Grace Ibrahim | H81: 2014-02-10 | I81: TRUE | J81: active | K81: Textiles and apparel
A82: T100578 | B82: United Textiles & Sons | C82: United Textiles & Sons | D82: 127 Garden Lane | E82: Capital | F82: 0243967795 | G82: Kenji Mahmood | H82: 2015-07-25 | I82: TRUE | J82: active | K82: Textiles and apparel
A83: T100583 | B83: Green Valley Foods Ltd | C83: Green Valley Foods Ltd | D83: 16 Bazaar Lane | E83: North | F83: 0742748420 | G83: Samuel Al-Sayed | H83: 2009-07-17 | I83: TRUE | J83: active | K83: Furniture and household
A84: T100592 | B84: DELTA IMPORTS & SONS | C84: Delta Centre | D84: 344 Market Street | E84: South | F84: 0984665003 | G84: Amina Chen | H84: 2012-12-16 | I84: TRUE | J84: dormant | K84: Steel and construction
A85: T100605 | B85: Ocean Mobile Enterprises | D85: 152 Harbour Road | E85: West | F85: 0881804513 | G85: Tomas Chen | H85: 2009-04-16 | I85: TRUE | J85: active | K85: Tobacco and beverages
A86: T100614 | B86: Arden Imports Holdings Ltd | D86: 271 Airport Rd | E86: South | F86: 0449906798 | G86: Elena Rahman | H86: 2026-07-05 | I86: TRUE | J86: active | K86: Vehicles and parts
A87: T100616 | B87: United Trading Group Limited | C87: United Trading Group Ltd | D87: 350 Temple Street | E87: Capital | F87: 0971956293 | G87: Fatima Haddad | H87: 2012-02-11 | I87: TRUE | J87: active | K87: Electronics
A88: T100629 | B88: Blue Ocean Pack Co. | D88: 265 Industrial Estate | E88: East | F88: 0277251043 | G88: Amina Mahmood | H88: 2026-05-28 | I88: TRUE | J88: active | K88: Food importers
A89: T100631 | B89: Blue Ocean Glow International Ltd | C89: Blue Ocean Glow International Ltd | D89: 191 Garden Lane | E89: Coastal | F89: 0808004328 | G89: Ingrid Ibrahim | H89: 2020-02-17 | I89: TRUE | J89: active | K89: Tobacco and beverages
A90: T100639 | B90: Lotus Commercial & Sons | C90: Lotus Commercial & Sons | D90: 226 Riverside | E90: South | F90: 0359630815 | G90: Lucia Al-Sayed | H90: 2011-12-28 | I90: TRUE | J90: active | K90: Fuel and chemicals
A91: T100645 | B91: Sunrise Logistics & Sons | C91: Sunrise Logistics & Sons | D91: 344 Mill Road | E91: West | F91: 0423519421 | G91: Daniel Al-Sayed | H91: 2019-09-22 | I91: TRUE | J91: active | K91: Electronics
A92: T100651 | B92: Royal Motors Co. | D92: 1 Mill Road | E92: North | F92: 0326308351 | G92: A. Okafor | H92: 2011-06-11 | I92: TRUE | J92: active | K92: Machinery
A93: T100673 | B93: PACIFIC INDUSTRIES LIMITED | C93: Pacific Industries Limited | D93: 379 Harbour Rd | E93: East | F93: 0564932412 | G93: Samuel Bauer | H93: 2017-05-30 | I93: TRUE | J93: active | K93: Electronics
A94: T100680 | B94: United Foods Partners Limited | D94: 139 Harbour Rd | E94: East | F94: 0271789964 | G94: Tomas Fernandes | H94: 2020-01-01 | I94: TRUE | J94: active | K94: Furniture and household
A95: T100690 | B95: Carrick Distribution Holdings Ltd | D95: 96 GARDEN LANE | E95: West | F95: 0898448613 | G95: Lucia Nguyen-Lee | H95: 2019-02-05 | I95: TRUE | J95: active | K95: Machinery
A96: T100699 | B96: Lotus Commercial Co. | C96: Lotus Commercial Co. | D96: 56 Temple Street | E96: West | F96: 0292316512 | G96: B. Patel | H96: 2021-06-03 | I96: TRUE | J96: active | K96: Tobacco and beverages
A97: T100705 | B97: Cobalt Supply & Sons | D97: 303 Temple Street | E97: West | F97: 0799827590 | G97: Somchai Bauer | H97: 2009-01-25 | I97: TRUE | J97: active | K97: Fuel and chemicals
A98: T100707 | B98: Lotus Steel Holdings Ltd | D98: 199 Temple Street | E98: South | F98: 0320392602 | G98: Ingrid Silva | H98: 2020-03-22 | I98: TRUE | J98: active | K98: Medical devices
A99: T100720 | B99: Lotus Agro Co., Ltd | D99: Unit 11, 372 Riverside | E99: West | F99: 0442103092 | G99: Ingrid Silva | H99: 2013-08-23 | I99: TRUE | J99: active | K99: Fuel and chemicals
A100: T100723 | B100: Blue Ocean Logistics Ltd | D100: 329 Mill Road | E100: South | F100: 0757878511 | G100: Aisha Kowalski | H100: 2019-01-30 | I100: TRUE | J100: active | K100: Electronics
A101: T100729 | B101: Arden Fruits Limited | C101: Arden Fruits Ltd | D101: 3 RIVERSIDE | E101: South | F101: 0501969412 | G101: Fatima Osei | H101: 2011-12-10 | I101: TRUE | J101: active | K101: Food importers
A102: T100741 | B102: Sunrise Textiles Co., Ltd | C102: Sunrise Textiles Co., Ltd | D102: 228 Market Street | E102: Capital | F102: 0615813591 | G102: Aisha Chen | H102: 2019-03-29 | I102: TRUE | J102: active | K102: Electronics
...

Sheet Customs importers
A1: The customs importer register · 1,502 importer codes as customs holds them
A2: Columns K and L are yours (sprint 3): 1 the first time an address, or a broker, appears under a tax number. Rows 6 to 15 are worked.
A5: importer | B5: tax number | C5: legal name | D5: address | E5: district | F5: phone | G5: director | H5: default broker | I5: registered on | J5: sector | K5: first address under the number (1/0) | L5: first broker under the number (1/0)
A6: IMP00001 | B6: T100004 | C6: Metro Trading Co., Ltd | D6: 369 Airport Road | E6: North | F6: 0800178993 | G6: Aisha Tanaka | H6: BRK060 | I6: 2022-08-23 | J6: Vehicles and parts | K6: =IF(B6="","",IF(COUNTIFS($B$6:B6,B6,$D$6:D6,D6)=1,1,0)) | L6: =IF(B6="","",IF(COUNTIFS($B$6:B6,B6,$H$6:H6,H6)=1,1,0))
A7: IMP00002 | B7: T100013 | C7: Prescott Imports Group Ltd | D7: 102 Temple Street | E7: East | F7: 0844703272 | G7: Kenji Mwangi | H7: BRK078 | I7: 2022-05-14 | J7: Vehicles and parts | K7: =IF(B7="","",IF(COUNTIFS($B$6:B7,B7,$D$6:D7,D7)=1,1,0)) | L7: =IF(B7="","",IF(COUNTIFS($B$6:B7,B7,$H$6:H7,H7)=1,1,0))
A8: IMP00003 | B8: T100016 | C8: Saffron Trading & Sons | D8: 53 Garden Lane | E8: Capital | F8: 0973133835 | G8: Omar Rahman | H8: BRK054 | I8: 2014-02-07 | J8: General trading | K8: =IF(B8="","",IF(COUNTIFS($B$6:B8,B8,$D$6:D8,D8)=1,1,0)) | L8: =IF(B8="","",IF(COUNTIFS($B$6:B8,B8,$H$6:H8,H8)=1,1,0))
A9: IMP00004 | B9: T100025 | C9: Harmony Fruits Co., Ltd | D9: 297 Airport Road | E9: North | F9: 0328461006 | G9: Nadia Sato | H9: BRK080 | I9: 2008-08-08 | J9: Vehicles and parts | K9: =IF(B9="","",IF(COUNTIFS($B$6:B9,B9,$D$6:D9,D9)=1,1,0)) | L9: =IF(B9="","",IF(COUNTIFS($B$6:B9,B9,$H$6:H9,H9)=1,1,0))
A10: IMP00005 | B10: T100033 | C10: Central Foods Limited | D10: 24 Harbour Road | E10: East | F10: 0401520138 | G10: Farid Ibrahim | H10: BRK033 | I10: 2019-08-31 | J10: Steel and construction | K10: =IF(B10="","",IF(COUNTIFS($B$6:B10,B10,$D$6:D10,D10)=1,1,0)) | L10: =IF(B10="","",IF(COUNTIFS($B$6:B10,B10,$H$6:H10,H10)=1,1,0))
A11: IMP00006 | B11: T100033 | C11: Saffron Textiles Co. | D11: 8 Mill Road | E11: North | F11: 0690619802 | G11: Grace Silva | H11: BRK059 | I11: 2017-06-10 | J11: Textiles and apparel | K11: =IF(B11="","",IF(COUNTIFS($B$6:B11,B11,$D$6:D11,D11)=1,1,0)) | L11: =IF(B11="","",IF(COUNTIFS($B$6:B11,B11,$H$6:H11,H11)=1,1,0))
A12: IMP00007 | C12: Silk Road Enterprises Partners Ltd | D12: 241 Bazaar Lane | E12: Capital | F12: 0728834594 | G12: Somchai Al-Sayed | H12: BRK059 | I12: 2021-08-31 | J12: Tobacco and beverages | K12: =IF(B12="","",IF(COUNTIFS($B$6:B12,B12,$D$6:D12,D12)=1,1,0)) | L12: =IF(B12="","",IF(COUNTIFS($B$6:B12,B12,$H$6:H12,H12)=1,1,0))
A13: IMP00008 | B13: T100052 | C13: Twin Rivers Textiles & Sons | D13: 179 Harbour Road | E13: South | F13: 0879024230 | G13: Amina Osei | H13: BRK070 | I13: 2022-02-18 | J13: Furniture and household | K13: =IF(B13="","",IF(COUNTIFS($B$6:B13,B13,$D$6:D13,D13)=1,1,0)) | L13: =IF(B13="","",IF(COUNTIFS($B$6:B13,B13,$H$6:H13,H13)=1,1,0))
A14: IMP00009 | B14: T100056 | C14: Green Valley Imports Group Ltd | D14: 16 Industrial Estate | E14: West | F14: 0999463247 | G14: Somchai Osei | H14: BRK055 | I14: 2008-06-17 | J14: Steel and construction | K14: =IF(B14="","",IF(COUNTIFS($B$6:B14,B14,$D$6:D14,D14)=1,1,0)) | L14: =IF(B14="","",IF(COUNTIFS($B$6:B14,B14,$H$6:H14,H14)=1,1,0))
A15: IMP00010 | B15: T800064 | C15: Aldergate Trading Co. | D15: 71 Bazaar Lane | E15: Capital | F15: 0459332927 | G15: Omar Sato | H15: BRK071 | I15: 2011-08-14 | J15: Tobacco and beverages | K15: =IF(B15="","",IF(COUNTIFS($B$6:B15,B15,$D$6:D15,D15)=1,1,0)) | L15: =IF(B15="","",IF(COUNTIFS($B$6:B15,B15,$H$6:H15,H15)=1,1,0))
A16: IMP00011 | B16: T100070 | C16: Silk Road Steel Co. | D16: 346 Market Street | E16: North | F16: 0519965779 | G16: Farid Haddad | H16: BRK015 | I16: 2010-02-24 | J16: Pharmaceuticals
A17: IMP00012 | B17: T100082 | C17: Harmony Trading & Sons | D17: 199 Bazaar Lane | E17: North | F17: 0405422879 | G17: Amina Ibrahim | H17: BRK032 | I17: 2013-11-18 | J17: Steel and construction
A18: IMP00013 | B18: T100090 | C18: Twin Rivers Glow International Ltd | D18: 399 Temple Street | E18: West | F18: 0232613013 | G18: Tomas Sato | H18: BRK078 | I18: 2015-09-23 | J18: Textiles and apparel
A19: IMP00014 | B19: T100097 | C19: Silk Road Industries Co. | D19: 23 Airport Road | E19: East | F19: 0387995973 | G19: Priya Haddad | H19: BRK067 | I19: 2010-08-22 | J19: General trading
A20: IMP00015 | B20: T100104 | C20: Silver Logistics Co., Ltd | D20: 239 Airport Road | E20: Capital | F20: 0320904779 | G20: Samuel Sato | H20: BRK034 | I20: 2014-07-26 | J20: Textiles and apparel
A21: IMP00016 | B21: T100105 | C21: Saffron Electronics International Ltd | D21: 180 Garden Lane | E21: North | F21: 0413172306 | G21: Ravi Kowalski | H21: BRK049 | I21: 2019-05-04 | J21: Vehicles and parts
A22: IMP00017 | B22: T100116 | C22: Lotus Supply Partners Ltd | D22: 165 Airport Road | E22: South | F22: 0297464461 | G22: Elena Haddad | H22: BRK007 | I22: 2011-01-18 | J22: Cosmetics and personal care
A23: IMP00018 | B23: T100119 | C23: Eastern Electronics & Sons | D23: 200 Harbour Road | E23: Coastal | F23: 0254068681 | G23: Nadia Sato | H23: BRK058 | I23: 2010-10-22 | J23: Cosmetics and personal care
A24: IMP00019 | B24: T100130 | C24: Royal Fruits Holdings Ltd | D24: 313 Market Street | E24: South | F24: 0269581004 | G24: Daniel Fernandes | H24: BRK011 | I24: 2022-05-23 | J24: Vehicles and parts
A25: IMP00020 | B25: T100134 | C25: Central Commercial Enterprises | D25: 218 Industrial Estate | E25: East | F25: 0945440269 | G25: Priya Patel | H25: BRK051 | I25: 2017-03-04 | J25: Tobacco and beverages
A26: IMP00021 | B26: T100144 | C26: Crown Textiles & Sons | D26: 242 Station Road | E26: West | F26: 0806964313 | G26: Joseph Tanaka | H26: BRK009 | I26: 2024-04-19 | J26: Pharmaceuticals
A27: IMP00022 | B27: T100152 | C27: Crown Glow Group Ltd | D27: 256 Market Street | E27: West | F27: 0980794230 | G27: Aisha Patel | H27: BRK037 | I27: 2021-02-27 | J27: Tobacco and beverages
... A31: IMP00026 | B31: T100177 | C31: Aldergate Supply Co., Ltd | D31: 153 Harbour Road | E31: South | F31: 0229299704 | G31: Omar Haddad | H31: BRK001 | I31: 2018-03-05 | J31: Vehicles and parts
A32: IMP00027 | C32: Sunrise Steel Limited | D32: 274 Riverside | E32: Capital | F32: 0819529945 | G32: Samuel Mahmood | H32: BRK019 | I32: 2014-09-04 | J32: Tobacco and beverages
A33: IMP00028 | B33: T100193 | C33: Inverness Agro Co. | D33: 206 Bazaar Lane | E33: Capital | F33: 0580341553 | G33: Daniel Mahmood | H33: BRK021 | I33: 2009-02-04 | J33: Fuel and chemicals
A34: IMP00029 | B34: T100201 | C34: Global Glow Ltd | D34: 338 Garden Lane | E34: East | F34: 0510129904 | G34: Samuel Patel | H34: BRK061 | I34: 2012-07-01 | J34: Food importers
A35: IMP00030 | B35: T100208 | C35: Evergreen Pack Partners Ltd | D35: 267 Riverside | E35: Coastal | F35: 0502506634 | G35: Samuel Okafor | H35: BRK021 | I35: 2015-08-17 | J35: Cosmetics and personal care
A36: IMP00031 | B36: T100211 | C36: Metro Living Partners Ltd | D36: 381 Temple Street | E36: South | F36: 0986965771 | G36: Daniel Ibrahim | H36: BRK026 | I36: 2010-02-26 | J36: Furniture and household
A37: IMP00032 | B37: T100219 | C37: Ashcombe Motors Co. | D37: 90 Airport Road | E37: East | F37: 0611073084 | G37: Omar Rahman | H37: BRK028 | I37: 2021-10-24 | J37: Machinery
A38: IMP00033 | B38: T100225 | C38: Global Agro International Ltd | D38: 260 Harbour Road | E38: Capital | F38: 0531652277 | G38: Amina Mensah | H38: BRK019 | I38: 2020-12-03 | J38: General trading
A39: IMP00034 | B39: T100236 | C39: Arden Supply Holdings Ltd | D39: 235 Mill Road | E39: North | F39: 0516341289 | G39: Grace Tanaka | H39: BRK042 | I39: 2014-09-23 | J39: Medical devices
A40: IMP00035 | B40: T100242 | C40: Metro Fruits Co. | D40: 6 Market Street | E40: Coastal | F40: 0581524750 | G40: Omar Sato | H40: BRK070 | I40: 2012-11-25 | J40: Cosmetics and personal care
A41: IMP00036 | B41: T100251 | C41: Horizon Glow Co., Ltd | D41: 354 Garden Lane | E41: Capital | F41: 0719900946 | G41: Somchai Chen | H41: BRK066 | I41: 2009-06-02 | J41: Machinery
A42: IMP00037 | B42: T100257 | C42: Carrick Agro & Sons | D42: 320 Temple Street | E42: East | F42: 0506676501 | G42: Aisha Al-Sayed | H42: BRK074 | I42: 2014-03-09 | J42: Steel and construction
A43: IMP00038 | B43: T100260 | C43: Prescott Steel Holdings Ltd | D43: 228 Industrial Estate | E43: North | F43: 0697360622 | G43: Tomas Mensah | H43: BRK014 | I43: 2019-12-02 | J43: Pharmaceuticals
A44: IMP00039 | B44: T100272 | C44: Central Imports Partners Ltd | D44: 294 Station Road | E44: East | F44: 0407340201 | G44: Ravi Bauer | H44: BRK054 | I44: 2008-08-30 | J44: Fuel and chemicals
... A57: IMP00052 | B57: T100360 | C57: Inverness Pack Limited | D57: 324 Industrial Estate | E57: Capital | F57: 0362842634 | G57: Somchai Tanaka | H57: BRK004 | I57: 2021-11-29 | J57: Tobacco and beverages
A58: IMP00053 | C58: Twin Rivers Agro Group Ltd | D58: 180 Temple Street | E58: Capital | F58: 0599288408 | G58: Fatima Mensah | H58: BRK023 | I58: 2018-05-13 | J58: Tobacco and beverages
A59: IMP00054 | B59: T100374 | C59: Eastern Pack Enterprises | D59: 95 Harbour Road | E59: South | F59: 0964346721 | G59: Priya Osei | H59: BRK021 | I59: 2015-09-12 | J59: Cosmetics and personal care
A60: IMP00055 | B60: T100381 | C60: Aldergate Steel Group Ltd | D60: 321 Market Street | E60: West | F60: 0806933046 | G60: Ingrid Kowalski | H60: BRK067 | I60: 2009-03-19 | J60: Steel and construction
A61: IMP00056 | B61: T100388 | C61: Inverness Industries Group Ltd | D61: 56 Garden Lane | E61: South | F61: 0354679037 | G61: Hassan Chen | H61: BRK033 | I61: 2022-01-23 | J61: Medical devices
A62: IMP00057 | B62: T100394 | C62: Central Textiles Limited | D62: 240 Bazaar Lane | E62: North | F62: 0940022322 | G62: Samuel Chen | H62: BRK021 | I62: 2016-02-21 | J62: Textiles and apparel
A63: IMP00058 | B63: T100405 | C63: Harmony Electronics Enterprises | D63: 292 Bazaar Lane | E63: Coastal | F63: 0688231310 | G63: Farid Bauer | H63: BRK013 | I63: 2011-10-17 | J63: Electronics
A64: IMP00059 | B64: T100406 | C64: Twin Rivers Supply Enterprises | D64: 262 Temple Street | E64: Coastal | F64: 0934603203 | G64: Ravi Osei | H64: BRK017 | I64: 2010-10-15 | J64: Vehicles and parts
A65: IMP00060 | B65: T100415 | C65: Delta Living Partners Ltd | D65: 376 Harbour Road | E65: Capital | F65: 0273895229 | G65: Ingrid Kowalski | H65: BRK053 | I65: 2008-12-06 | J65: Medical devices
A66: IMP00061 | B66: T100420 | C66: United Commercial International Ltd | D66: 35 Airport Road | E66: South | F66: 0963216044 | G66: Farid Haddad | H66: BRK053 | I66: 2019-03-10 | J66: Food importers
A67: IMP00062 | B67: T100427 | C67: Golden Textiles Ltd | D67: 55 Riverside | E67: East | F67: 0654707181 | G67: Priya Bauer | H67: BRK006 | I67: 2009-05-20 | J67: Steel and construction
A68: IMP00063 | B68: T100440 | C68: Metro Motors Co., Ltd | D68: 215 Bazaar Lane | E68: West | F68: 0929915234 | G68: Ingrid Al-Sayed | H68: BRK038 | I68: 2013-02-28 | J68: Vehicles and parts
A69: IMP00064 | B69: T100445 | C69: Cobalt Mobile Ltd | D69: 396 Mill Road | E69: Capital | F69: 0334789891 | G69: Nadia Sato | H69: BRK047 | I69: 2015-02-12 | J69: General trading
A70: IMP00065 | B70: T100450 | C70: Great Vellmoor Fruits Partners Ltd | D70: 395 Garden Lane | E70: North | F70: 0529543157 | G70: Mei Nguyen-Lee | H70: BRK038 | I70: 2016-06-24 | J70: Fuel and chemicals
A71: IMP00066 | C71: Northern Agro Partners Ltd | D71: 273 Industrial Estate | E71: West | F71: 0392391880 | G71: Priya Al-Sayed | H71: BRK059 | I71: 2020-01-15 | J71: Tobacco and beverages
A72: IMP00067 | B72: T100466 | C72: Pacific Enterprises Holdings Ltd | D72: 356 Station Road | E72: East | F72: 0254736740 | G72: Farid Sato | H72: BRK021 | I72: 2008-10-06 | J72: Fuel and chemicals
A73: IMP00068 | B73: T300474 | C73: Green Valley Fruits Co., Ltd | D73: 357 Market Street | E73: East | F73: 0584646483 | G73: Daniel Al-Sayed | H73: BRK034 | I73: 2018-03-30 | J73: Tobacco and beverages
A74: IMP00069 | B74: T100476 | C74: Evergreen Fruits Group Ltd | D74: 74 Bazaar Lane | E74: West | F74: 0260191140 | G74: Daniel Chen | H74: BRK017 | I74: 2024-06-19 | J74: Pharmaceuticals
A75: IMP00070 | C75: Coral Fruits Group Ltd | D75: 95 Temple Street | E75: North | F75: 0960004082 | G75: Samuel Osei | H75: BRK051 | I75: 2009-04-12 | J75: Tobacco and beverages
A76: IMP00071 | B76: T100490 | C76: Carrick Enterprises Co. | D76: 56 Garden Lane | E76: South | F76: 0759443551 | G76: Mei Mahmood | H76: BRK028 | I76: 2025-12-31 | J76: Textiles and apparel
A77: IMP00072 | B77: T100497 | C77: Great Vellmoor Pack Holdings Ltd | D77: 368 Station Road | E77: Capital | F77: 0244279675 | G77: Hassan Chen | H77: BRK013 | I77: 2014-05-06 | J77: Vehicles and parts
A78: IMP00073 | B78: T100510 | C78: Global Pack & Sons | D78: 172 Mill Road | E78: South | F78: 0670197514 | G78: Hassan Bauer | H78: BRK065 | I78: 2010-04-04 | J78: Furniture and household
A79: IMP00074 | B79: T100516 | C79: Dunmore Imports & Sons | D79: 298 Garden Lane | E79: West | F79: 0298394705 | G79: Hassan Chen | H79: BRK008 | I79: 2009-11-12 | J79: Food importers
A80: IMP00075 | B80: T100519 | C80: Harmony Textiles Limited | D80: 321 Market Street | E80: Coastal | F80: 0543950447 | G80: Farid Silva | H80: BRK024 | I80: 2025-09-18 | J80: Food importers
A81: IMP00076 | B81: T100529 | C81: United Imports Enterprises | D81: 264 Mill Road | E81: South | F81: 0913727677 | G81: Ravi Mahmood | H81: BRK021 | I81: 2021-03-13 | J81: Textiles and apparel
A82: IMP00077 | B82: T100538 | C82: Metro Enterprises Co., Ltd | D82: 223 Temple Street | E82: Capital | F82: 0325939693 | G82: Priya Reyes | H82: BRK055 | I82: 2020-01-28 | J82: Electronics
A83: IMP00078 | B83: T100540 | C83: Orchid Imports Group Ltd | D83: 57 Market Street | E83: West | F83: 0201832970 | G83: Ingrid Kowalski | H83: BRK013 | I83: 2026-01-18 | J83: Textiles and apparel
A84: IMP00079 | B84: T100551 | C84: Saffron Enterprises Ltd | D84: 301 Airport Road | E84: Capital | F84: 0878357885 | G84: Ravi Mensah | H84: BRK021 | I84: 2016-06-05 | J84: Cosmetics and personal care
A85: IMP00080 | B85: T100555 | C85: Saffron Agro Co. | D85: 272 Airport Road | E85: South | F85: 0980859838 | G85: Lucia Rahman | H85: BRK064 | I85: 2008-02-15 | J85: Fuel and chemicals
A86: IMP00081 | B86: T100560 | C86: Crown Logistics Group Ltd | D86: 237 Mill Road | E86: Coastal | F86: 0227583804 | G86: Lucia Mahmood | H86: BRK021 | I86: 2011-10-02 | J86: General trading
A87: IMP00082 | B87: T100569 | C87: Harmony Textiles & Sons | D87: 2 Garden Lane | E87: North | F87: 0239486735 | G87: Grace Ibrahim | H87: BRK014 | I87: 2013-10-01 | J87: Textiles and apparel
... A90: IMP00085 | B90: T100592 | C90: Delta Imports & Sons | D90: 344 Market Street | E90: South | F90: 0984665003 | G90: Amina Chen | H90: BRK067 | I90: 2012-02-27 | J90: Steel and construction
A91: IMP00086 | C91: Central Supply & Sons | D91: 199 Harbour Road | E91: West | F91: 0844499201 | G91: Nadia Mwangi | H91: BRK050 | I91: 2018-11-21 | J91: Food importers
A92: IMP00087 | B92: T100605 | C92: Ocean Mobile Enterprises | D92: 152 Harbour Road | E92: West | F92: 0684849466 | G92: Tomas Chen | H92: BRK001 | I92: 2008-08-02 | J92: Tobacco and beverages
A93: IMP00088 | B93: T100614 | C93: Arden Imports Holdings Ltd | D93: 271 Airport Road | E93: South | F93: 0449906798 | G93: Elena Rahman | H93: BRK003 | I93: 2025-09-11 | J93: Vehicles and parts
A94: IMP00089 | B94: T100616 | C94: United Trading Group Ltd | D94: 98 Mill Road | E94: Capital | F94: 0971956293 | G94: Fatima Haddad | H94: BRK030 | I94: 2011-03-24 | J94: Electronics
A95: IMP00090 | B95: T100629 | C95: Blue Ocean Pack Co. | D95: 265 Industrial Estate | E95: East | F95: 0924877741 | G95: Amina Mahmood | H95: BRK063 | I95: 2025-12-16 | J95: Food importers
A96: IMP00091 | B96: T100631 | C96: Blue Ocean Glow International Ltd | D96: 191 Garden Lane | E96: Coastal | F96: 0808004328 | G96: Ingrid Ibrahim | H96: BRK055 | I96: 2020-01-31 | J96: Tobacco and beverages
A97: IMP00092 | B97: T100639 | C97: Lotus Commercial & Sons | D97: 226 Riverside | E97: South | F97: 0209160729 | G97: Lucia Al-Sayed | H97: BRK031 | I97: 2011-02-04 | J97: Fuel and chemicals
A98: IMP00093 | B98: T100645 | C98: Sunrise Logistics & Sons | D98: 344 Mill Road | E98: West | F98: 0423519421 | G98: Daniel Al-Sayed | H98: BRK062 | I98: 2019-05-09 | J98: Electronics
A99: IMP00094 | B99: T100651 | C99: Royal Motors Co. | D99: 1 Mill Road | E99: North | F99: 0326308351 | G99: Mei Okafor | H99: BRK014 | I99: 2010-05-28 | J99: Machinery
A100: IMP00095 | B100: T100033 | C100: Metro Supply International Ltd | D100: 24 Harbour Road | E100: East | F100: 0679477746 | G100: Daniel Osei | H100: BRK033 | I100: 2019-04-07 | J100: Tobacco and beverages
A101: IMP00096 | C101: Evergreen Logistics Limited | D101: 3 Airport Road | E101: Coastal | F101: 0704016114 | G101: Tomas Al-Sayed | H101: BRK059 | I101: 2010-12-16 | J101: Electronics
A102: IMP00097 | B102: T100673 | C102: Pacific Industries Limited | D102: 379 Harbour Road | E102: East | F102: 0564932412 | G102: Samuel Bauer | H102: BRK048 | I102: 2017-01-02 | J102: Electronics
A103: IMP00098 | B103: T100680 | C103: United Foods Partners Ltd | D103: 139 Harbour Road | E103: East | F103: 0271789964 | G103: Tomas Fernandes | H103: BRK037 | I103: 2019-03-22 | J103: Furniture and household
A104: IMP00099 | B104: T100690 | C104: Carrick Distribution Holdings Ltd | D104: 96 Garden Lane | E104: West | F104: 0898448613 | G104: Lucia Nguyen-Lee | H104: BRK080 | I104: 2019-02-11 | J104: Machinery
A105: IMP00100 | B105: T100699 | C105: Lotus Commercial Co. | D105: 56 Temple Street | E105: West | F105: 0292316512 | G105: Nadia Patel | H105: BRK038 | I105: 2021-06-23 | J105: Tobacco and beverages
A106: IMP00101 | B106: T100705 | C106: Cobalt Supply & Sons | D106: 303 Temple Street | E106: West | F106: 0799827590 | G106: Somchai Bauer | H106: BRK012 | I106: 2009-01-09 | J106: Fuel and chemicals
A107: IMP00102 | B107: T100707 | C107: Lotus Steel Holdings Ltd | D107: 199 Temple Street | E107: South | F107: 0320392602 | G107: Ingrid Silva | H107: BRK052 | I107: 2019-02-19 | J107: Medical devices
A108: IMP00103 | B108: T100720 | C108: Lotus Agro Co., Ltd | D108: 372 Riverside | E108: West | F108: 0442103092 | G108: Ingrid Silva | H108: BRK079 | I108: 2013-06-07 | J108: Fuel and chemicals
A109: IMP00104 | B109: T100723 | C109: Blue Ocean Logistics Ltd | D109: 329 Mill Road | E109: South | F109: 0757878511 | G109: Aisha Kowalski | H109: BRK049 | I109: 2018-08-29 | J109: Electronics
A110: IMP00105 | B110: T100729 | C110: Arden Fruits Ltd | D110: 3 Riverside | E110: South | F110: 0501969412 | G110: Fatima Osei | H110: BRK040 | I110: 2011-05-13 | J110: Food importers
A111: IMP00106 | B111: T100741 | C111: Sunrise Textiles Co., Ltd | D111: 228 Market Street | E111: Capital | F111: 0615813591 | G111: Aisha Chen | H111: BRK007 | I111: 2018-04-15 | J111: Electronics
A112: IMP00107 | B112: T100745 | C112: Metro Fruits Enterprises | D112: 369 Bazaar Lane | E112: North | F112: 0807497130 | G112: Daniel Al-Sayed | H112: BRK015 | I112: 2024-08-21 | J112: Electronics
A113: IMP00108 | B113: T100749 | C113: Great Vellmoor Motors Partners Ltd | D113: 373 Temple Street | E113: West | F113: 0533266170 | G113: Amina Al-Sayed | H113: BRK031 | I113: 2017-06-13 | J113: Electronics
... A124: IMP00119 | B124: T100831 | C124: Prime Agro Holdings Ltd | D124: 303 Mill Road | E124: Capital | F124: 0977047198 | G124: Omar Ibrahim | H124: BRK011 | I124: 2022-07-11 | J124: Machinery
A125: IMP00120 | C125: Ocean Foods Ltd | D125: 379 Mill Road | E125: East | F125: 0984942669 | G125: Priya Al-Sayed | H125: BRK019 | I125: 2017-09-25 | J125: Tobacco and beverages
A126: IMP00121 | B126: T100842 | C126: Phoenix Distribution Group Ltd | D126: 339 Industrial Estate | E126: North | F126: 0535824167 | G126: Fatima Kowalski | H126: BRK069 | I126: 2017-01-23 | J126: Machinery
A127: IMP00122 | B127: T100851 | C127: Sunrise Mobile Limited | D127: 307 Station Road | E127: Capital | F127: 0655304441 | G127: Fatima Bauer | H127: BRK026 | I127: 2025-09-05 | J127: Pharmaceuticals
A128: IMP00123 | B128: T100856 | C128: Meridian Agro Co., Ltd | D128: 31 Garden Lane | E128: South | F128: 0786862666 | G128: Ingrid Patel | H128: BRK056 | I128: 2019-06-17 | J128: General trading
A129: IMP00124 | B129: T100861 | C129: Prime Steel Group Ltd | D129: 135 Station Road | E129: South | F129: 0984009293 | G129: Priya Nguyen-Lee | H129: BRK022 | I129: 2009-04-29 | J129: Furniture and household
...

Sheet Consignees
A1: The consignee register · 2,002 parties goods are delivered to, as customs holds them
A4: consignee | B4: name | C4: address | D4: district | E4: importer | F4: tax number
A5: C00001 | B5: Metro Trading Co., Ltd | C5: 369 Airport Road | D5: North | E5: IMP00001 | F5: T100004
A6: C00002 | B6: Prescott Imports Group Ltd | C6: 102 Temple Street | D6: East | E6: IMP00002 | F6: T100013
A7: C00003 | B7: Saffron Trading & Sons | C7: 53 Garden Lane | D7: Capital | E7: IMP00003 | F7: T100016
A8: C00004 | B8: Harmony Fruits Co., Ltd | C8: 297 Airport Road | D8: North | E8: IMP00004 | F8: T100025
A9: C00005 | B9: Central Foods Limited | C9: 24 Harbour Road | D9: East | E9: IMP00005 | F9: T100033
A10: C00006 | B10: Saffron Textiles Co. | C10: 8 Mill Road | D10: North | E10: IMP00006 | F10: T100033
A11: C00007 | B11: Silk Road Enterprises Partners Ltd | C11: 241 Bazaar Lane | D11: Capital | E11: IMP00007
A12: C00008 | B12: Twin Rivers Textiles & Sons | C12: 179 Harbour Road | D12: South | E12: IMP00008 | F12: T100052
A13: C00009 | B13: Green Valley Imports Group Ltd | C13: 16 Industrial Estate | D13: West | E13: IMP00009 | F13: T100056
A14: C00010 | B14: Aldergate Trading Co. | C14: 71 Bazaar Lane | D14: Capital | E14: IMP00010 | F14: T800064
A15: C00011 | B15: Silk Road Steel Co. | C15: 346 Market Street | D15: North | E15: IMP00011 | F15: T100070
A16: C00012 | B16: Harmony Trading & Sons | C16: 199 Bazaar Lane | D16: North | E16: IMP00012 | F16: T100082
A17: C00013 | B17: Twin Rivers Glow International Ltd | C17: 399 Temple Street | D17: West | E17: IMP00013 | F17: T100090
A18: C00014 | B18: Silk Road Industries Co. | C18: 23 Airport Road | D18: East | E18: IMP00014 | F18: T100097
A19: C00015 | B19: Silver Logistics Co., Ltd | C19: 239 Airport Road | D19: Capital | E19: IMP00015 | F19: T100104
A20: C00016 | B20: Saffron Electronics International Ltd | C20: 180 Garden Lane | D20: North | E20: IMP00016 | F20: T100105
A21: C00017 | B21: Lotus Supply Partners Ltd | C21: 165 Airport Road | D21: South | E21: IMP00017 | F21: T100116
A22: C00018 | B22: Eastern Electronics & Sons | C22: 200 Harbour Road | D22: Coastal | E22: IMP00018 | F22: T100119
A23: C00019 | B23: Royal Fruits Holdings Ltd | C23: 313 Market Street | D23: South | E23: IMP00019 | F23: T100130
... A30: C00026 | B30: Aldergate Supply Co., Ltd | C30: 153 Harbour Road | D30: South | E30: IMP00026 | F30: T100177
A31: C00027 | B31: Sunrise Steel Limited | C31: 274 Riverside | D31: Capital | E31: IMP00027
A32: C00028 | B32: Inverness Agro Co. | C32: 206 Bazaar Lane | D32: Capital | E32: IMP00028 | F32: T100193
A33: C00029 | B33: Global Glow Ltd | C33: 338 Garden Lane | D33: East | E33: IMP00029 | F33: T100201
A34: C00030 | B34: Evergreen Pack Partners Ltd | C34: 267 Riverside | D34: Coastal | E34: IMP00030 | F34: T100208
A35: C00031 | B35: Metro Living Partners Ltd | C35: 381 Temple Street | D35: South | E35: IMP00031 | F35: T100211
A36: C00032 | B36: Ashcombe Motors Co. | C36: 90 Airport Road | D36: East | E36: IMP00032 | F36: T100219
A37: C00033 | B37: Global Agro International Ltd | C37: 260 Harbour Road | D37: Capital | E37: IMP00033 | F37: T100225
A38: C00034 | B38: Arden Supply Holdings Ltd | C38: 235 Mill Road | D38: North | E38: IMP00034 | F38: T100236
A39: C00035 | B39: Metro Fruits Co. | C39: 6 Market Street | D39: Coastal | E39: IMP00035 | F39: T100242
A40: C00036 | B40: Horizon Glow Co., Ltd | C40: 354 Garden Lane | D40: Capital | E40: IMP00036 | F40: T100251
A41: C00037 | B41: Carrick Agro & Sons | C41: 320 Temple Street | D41: East | E41: IMP00037 | F41: T100257
A42: C00038 | B42: Prescott Steel Holdings Ltd | C42: 228 Industrial Estate | D42: North | E42: IMP00038 | F42: T100260
A43: C00039 | B43: Central Imports Partners Ltd | C43: 294 Station Road | D43: East | E43: IMP00039 | F43: T100272
... A56: C00052 | B56: Inverness Pack Limited | C56: 324 Industrial Estate | D56: Capital | E56: IMP00052 | F56: T100360
A57: C00053 | B57: Twin Rivers Agro Group Ltd | C57: 180 Temple Street | D57: Capital | E57: IMP00053
A58: C00054 | B58: Eastern Pack Enterprises | C58: 95 Harbour Road | D58: South | E58: IMP00054 | F58: T100374
A59: C00055 | B59: Aldergate Steel Group Ltd | C59: 321 Market Street | D59: West | E59: IMP00055 | F59: T100381
A60: C00056 | B60: Inverness Industries Group Ltd | C60: 56 Garden Lane | D60: South | E60: IMP00056 | F60: T100388
A61: C00057 | B61: Central Textiles Limited | C61: 240 Bazaar Lane | D61: North | E61: IMP00057 | F61: T100394
A62: C00058 | B62: Harmony Electronics Enterprises | C62: 292 Bazaar Lane | D62: Coastal | E62: IMP00058 | F62: T100405
A63: C00059 | B63: Twin Rivers Supply Enterprises | C63: 262 Temple Street | D63: Coastal | E63: IMP00059 | F63: T100406
A64: C00060 | B64: Delta Living Partners Ltd | C64: 376 Harbour Road | D64: Capital | E64: IMP00060 | F64: T100415
A65: C00061 | B65: United Commercial International Ltd | C65: 35 Airport Road | D65: South | E65: IMP00061 | F65: T100420
A66: C00062 | B66: Golden Textiles Ltd | C66: 55 Riverside | D66: East | E66: IMP00062 | F66: T100427
A67: C00063 | B67: Metro Motors Co., Ltd | C67: 215 Bazaar Lane | D67: West | E67: IMP00063 | F67: T100440
A68: C00064 | B68: Cobalt Mobile Ltd | C68: 396 Mill Road | D68: Capital | E68: IMP00064 | F68: T100445
A69: C00065 | B69: Great Vellmoor Fruits Partners Ltd | C69: 395 Garden Lane | D69: North | E69: IMP00065 | F69: T100450
A70: C00066 | B70: Northern Agro Partners Ltd | C70: 273 Industrial Estate | D70: West | E70: IMP00066
A71: C00067 | B71: Pacific Enterprises Holdings Ltd | C71: 356 Station Road | D71: East | E71: IMP00067 | F71: T100466
A72: C00068 | B72: Green Valley Fruits Co., Ltd | C72: 357 Market Street | D72: East | E72: IMP00068 | F72: T300474
A73: C00069 | B73: Evergreen Fruits Group Ltd | C73: 74 Bazaar Lane | D73: West | E73: IMP00069 | F73: T100476
A74: C00070 | B74: Coral Fruits Group Ltd | C74: 95 Temple Street | D74: North | E74: IMP00070
A75: C00071 | B75: Carrick Enterprises Co. | C75: 56 Garden Lane | D75: South | E75: IMP00071 | F75: T100490
A76: C00072 | B76: Great Vellmoor Pack Holdings Ltd | C76: 368 Station Road | D76: Capital | E76: IMP00072 | F76: T100497
A77: C00073 | B77: Global Pack & Sons | C77: 172 Mill Road | D77: South | E77: IMP00073 | F77: T100510
A78: C00074 | B78: Dunmore Imports & Sons | C78: 298 Garden Lane | D78: West | E78: IMP00074 | F78: T100516
A79: C00075 | B79: Harmony Textiles Limited | C79: 321 Market Street | D79: Coastal | E79: IMP00075 | F79: T100519
A80: C00076 | B80: United Imports Enterprises | C80: 264 Mill Road | D80: South | E80: IMP00076 | F80: T100529
A81: C00077 | B81: Metro Enterprises Co., Ltd | C81: 223 Temple Street | D81: Capital | E81: IMP00077 | F81: T100538
A82: C00078 | B82: Orchid Imports Group Ltd | C82: 57 Market Street | D82: West | E82: IMP00078 | F82: T100540
A83: C00079 | B83: Saffron Enterprises Ltd | C83: 301 Airport Road | D83: Capital | E83: IMP00079 | F83: T100551
A84: C00080 | B84: Saffron Agro Co. | C84: 272 Airport Road | D84: South | E84: IMP00080 | F84: T100555
A85: C00081 | B85: Crown Logistics Group Ltd | C85: 237 Mill Road | D85: Coastal | E85: IMP00081 | F85: T100560
A86: C00082 | B86: Harmony Textiles & Sons | C86: 2 Garden Lane | D86: North | E86: IMP00082 | F86: T100569
... A89: C00085 | B89: Delta Imports & Sons | C89: 344 Market Street | D89: South | E89: IMP00085 | F89: T100592
A90: C00086 | B90: Central Supply & Sons | C90: 199 Harbour Road | D90: West | E90: IMP00086
A91: C00087 | B91: Ocean Mobile Enterprises | C91: 152 Harbour Road | D91: West | E91: IMP00087 | F91: T100605
A92: C00088 | B92: Arden Imports Holdings Ltd | C92: 271 Airport Road | D92: South | E92: IMP00088 | F92: T100614
A93: C00089 | B93: United Trading Group Ltd | C93: 98 Mill Road | D93: Capital | E93: IMP00089 | F93: T100616
A94: C00090 | B94: Blue Ocean Pack Co. | C94: 265 Industrial Estate | D94: East | E94: IMP00090 | F94: T100629
A95: C00091 | B95: Blue Ocean Glow International Ltd | C95: 191 Garden Lane | D95: Coastal | E95: IMP00091 | F95: T100631
A96: C00092 | B96: Lotus Commercial & Sons | C96: 226 Riverside | D96: South | E96: IMP00092 | F96: T100639
A97: C00093 | B97: Sunrise Logistics & Sons | C97: 344 Mill Road | D97: West | E97: IMP00093 | F97: T100645
A98: C00094 | B98: Royal Motors Co. | C98: 1 Mill Road | D98: North | E98: IMP00094 | F98: T100651
A99: C00095 | B99: Metro Supply International Ltd | C99: 24 Harbour Road | D99: East | E99: IMP00095 | F99: T100033
A100: C00096 | B100: Evergreen Logistics Limited | C100: 3 Airport Road | D100: Coastal | E100: IMP00096
A101: C00097 | B101: Pacific Industries Limited | C101: 379 Harbour Road | D101: East | E101: IMP00097 | F101: T100673
A102: C00098 | B102: United Foods Partners Ltd | C102: 139 Harbour Road | D102: East | E102: IMP00098 | F102: T100680
A103: C00099 | B103: Carrick Distribution Holdings Ltd | C103: 96 Garden Lane | D103: West | E103: IMP00099 | F103: T100690
A104: C00100 | B104: Lotus Commercial Co. | C104: 56 Temple Street | D104: West | E104: IMP00100 | F104: T100699
A105: C00101 | B105: Cobalt Supply & Sons | C105: 303 Temple Street | D105: West | E105: IMP00101 | F105: T100705
A106: C00102 | B106: Lotus Steel Holdings Ltd | C106: 199 Temple Street | D106: South | E106: IMP00102 | F106: T100707
A107: C00103 | B107: Lotus Agro Co., Ltd | C107: 372 Riverside | D107: West | E107: IMP00103 | F107: T100720
A108: C00104 | B108: Blue Ocean Logistics Ltd | C108: 329 Mill Road | D108: South | E108: IMP00104 | F108: T100723
A109: C00105 | B109: Arden Fruits Ltd | C109: 3 Riverside | D109: South | E109: IMP00105 | F109: T100729
A110: C00106 | B110: Sunrise Textiles Co., Ltd | C110: 228 Market Street | D110: Capital | E110: IMP00106 | F110: T100741
A111: C00107 | B111: Metro Fruits Enterprises | C111: 369 Bazaar Lane | D111: North | E111: IMP00107 | F111: T100745
A112: C00108 | B112: Great Vellmoor Motors Partners Ltd | C112: 373 Temple Street | D112: West | E112: IMP00108 | F112: T100749
... A123: C00119 | B123: Prime Agro Holdings Ltd | C123: 303 Mill Road | D123: Capital | E123: IMP00119 | F123: T100831
A124: C00120 | B124: Ocean Foods Ltd | C124: 379 Mill Road | D124: East | E124: IMP00120
A125: C00121 | B125: Phoenix Distribution Group Ltd | C125: 339 Industrial Estate | D125: North | E125: IMP00121 | F125: T100842
A126: C00122 | B126: Sunrise Mobile Limited | C126: 307 Station Road | D126: Capital | E126: IMP00122 | F126: T100851
A127: C00123 | B127: Meridian Agro Co., Ltd | C127: 31 Garden Lane | D127: South | E127: IMP00123 | F127: T100856
A128: C00124 | B128: Prime Steel Group Ltd | C128: 135 Station Road | D128: South | E128: IMP00124 | F128: T100861
A129: C00125 | B129: Silk Road Motors Holdings Ltd | C129: 22 Garden Lane | D129: North | E129: IMP00125 | F129: T100870
A130: C00126 | B130: Blue Ocean Medical Partners Ltd | C130: 33 Temple Street | D130: West | E130: IMP00126 | F130: T100879
A131: C00127 | B131: United Supply Co. | C131: 250 Riverside | D131: South | E131: IMP00127 | F131: T100885
A132: C00128 | B132: Phoenix Pack Limited | C132: 116 Station Road | D132: East | E132: IMP00128 | F132: T100895
...

Sheet Lines 12m
A1: The declaration lines that bear VAT, months 25 to 36, under the 25 tax numbers (and the lines of the five importers with no number)
A2: 12,320 lines, as exported. Lines that bear VAT: home use or release from a warehouse. A blank tax number means the declaration carried none.
A4: line | B4: date | C4: month | D4: importer | E4: tax number used to clear | F4: regime | G4: customs value (LCU) | H4: import VAT paid (LCU)
A5: L0171734 | B5: 2025-10-25 | C5: 25 | D5: IMP00005 | E5: T100033 | F5: home_use | G5: 1999563.4 | H5: 199956.34
A6: L0247648 | B6: 2026-09-18 | C6: 36 | D6: IMP00005 | E6: T100033 | F6: home_use | G6: 4314546.3 | H6: 474600.09
A7: L0236106 | B7: 2026-07-25 | C7: 34 | D7: IMP00006 | E7: T100033 | F7: home_use | G7: 2729997.3 | H7: 354899.65
A8: L0240642 | B8: 2026-08-16 | C8: 35 | D8: IMP00006 | E8: T100033 | F8: home_use | G8: 2091558.9 | H8: 271902.65
A9: L0166737 | B9: 2025-10-02 | C9: 25 | D9: IMP00095 | E9: T100033 | F9: home_use | G9: 947982.4 | H9: 118497.8
A10: L0166961 | B10: 2025-10-03 | C10: 25 | D10: IMP00095 | E10: T100033 | F10: home_use | G10: 784222.67 | H10: 98027.83
A11: L0169099 | B11: 2025-10-13 | C11: 25 | D11: IMP00095 | E11: T100033 | F11: home_use | G11: 81699.61 | H11: 8578.46
A12: L0170649 | B12: 2025-10-20 | C12: 25 | D12: IMP00095 | E12: T100033 | F12: home_use | G12: 501484.92 | H12: 65193.04
A13: L0173037 | B13: 2025-11-03 | C13: 26 | D13: IMP00095 | E13: T100033 | F13: home_use | G13: 908907.54 | H13: 106342.18
A14: L0184043 | B14: 2025-12-23 | C14: 27 | D14: IMP00095 | E14: T100033 | F14: home_use | G14: 1660461.2 | H14: 215859.95
A15: L0184294 | B15: 2025-12-24 | C15: 27 | D15: IMP00095 | E15: T100033 | F15: home_use | G15: 3006136.7 | H15: 375767.08
A16: L0184748 | B16: 2025-12-26 | C16: 27 | D16: IMP00095 | E16: T100033 | F16: home_use | G16: 532623.14 | H16: 69241.01
... A11318: L0250082 | B11318: 2026-09-28 | C11318: 36 | D11318: IMP01310 | E11318: T109167 | F11318: home_use | G11318: 1384760.8 | H11318: 138476.08
A11319: L0170213 | B11319: 2025-10-18 | C11319: 25 | D11319: IMP00147 | F11319: home_use | G11319: 3057472 | H11319: 305747.19
A11320: L0170459 | B11320: 2025-10-19 | C11320: 25 | D11320: IMP00147 | F11320: home_use | G11320: 2094467.4 | H11320: 209446.74
A11321: L0171537 | B11321: 2025-10-24 | C11321: 25 | D11321: IMP00147 | F11321: home_use | G11321: 1919281.7 | H11321: 191928.17
A11322: L0172800 | B11322: 2025-11-02 | C11322: 26 | D11322: IMP00147 | F11322: home_use | G11322: 2100944.3 | H11322: 210094.43
A11323: L0178920 | B11323: 2025-12-01 | C11323: 27 | D11323: IMP00147 | F11323: home_use | G11323: 3169131.7 | H11323: 316913.17
A11324: L0182007 | B11324: 2025-12-14 | C11324: 27 | D11324: IMP00147 | F11324: home_use | G11324: 822304.89 | H11324: 82230.49
A11325: L0186449 | B11325: 2026-01-05 | C11325: 28 | D11325: IMP00147 | F11325: home_use | G11325: 9906968.8 | H11325: 990696.88
A11326: L0193861 | B11326: 2026-02-06 | C11326: 29 | D11326: IMP00147 | F11326: home_use | G11326: 2132524.4 | H11326: 213252.44
A11327: L0195476 | B11327: 2026-02-12 | C11327: 29 | D11327: IMP00147 | F11327: home_use | G11327: 1783294 | H11327: 178329.4
A11328: L0196509 | B11328: 2026-02-16 | C11328: 29 | D11328: IMP00147 | F11328: home_use | G11328: 5102950.5 | H11328: 510295.05
A11329: L0196753 | B11329: 2026-02-17 | C11329: 29 | D11329: IMP00147 | F11329: home_use | G11329: 1009699.1 | H11329: 100969.91
A11330: L0203909 | B11330: 2026-03-16 | C11330: 30 | D11330: IMP00147 | F11330: home_use | G11330: 5120697.3 | H11330: 512069.73
... A12324: L0240849 | B12324: 2026-08-16 | C12324: 35 | D12324: IMP01481 | F12324: home_use | G12324: 3121163.4 | H12324: 333964.48

Sheet Returns
A1: The VAT returns · 24 monthly periods of every tax number the 25 importers can link to
A2: 600 returns, as the tax administration holds them. A return not filed carries blank amounts. Period number: 1 = 2024-10, 24 = 2026-09.
A4: tax ID | B4: period | C4: filed | D4: sales (LCU) | E4: purchases (LCU) | F4: import VAT deducted (LCU) | G4: period number
A5: T100033 | B5: 2024-10 | C5: 1 | D5: 59996 | E5: 239984 | F5: 0 | G5: 1
A6: T100033 | B6: 2024-11 | C6: 1 | D6: 66802 | E6: 267207 | F6: 0 | G6: 2
A7: T100033 | B7: 2024-12 | C7: 1 | D7: 47519 | E7: 190077 | F7: 0 | G7: 3
A8: T100033 | B8: 2025-01 | C8: 1 | D8: 302545 | E8: 2093577 | F8: 213366 | G8: 4
A9: T100033 | B9: 2025-02 | C9: 1 | D9: 51355 | E9: 205421 | F9: 0 | G9: 5
A10: T100033 | B10: 2025-03 | C10: 1 | D10: 55410 | E10: 221639 | F10: 0 | G10: 6
A11: T100033 | B11: 2025-04 | C11: 1 | D11: 84624 | E11: 338494 | F11: 0 | G11: 7
A12: T100033 | B12: 2025-05 | C12: 1 | D12: 103876 | E12: 415504 | F12: 0 | G12: 8
A13: T100033 | B13: 2025-06 | C13: 1 | D13: 124243 | E13: 496972 | F13: 0 | G13: 9
A14: T100033 | B14: 2025-07 | C14: 1 | D14: 88143 | E14: 352570 | F14: 0 | G14: 10
A15: T100033 | B15: 2025-08 | C15: 1 | D15: 70396 | E15: 281583 | F15: 0 | G15: 11
A16: T100033 | B16: 2025-09 | C16: 1 | D16: 52869 | E16: 211476 | F16: 0 | G16: 12
... A26: T100033 | B26: 2026-07 | C26: 1 | D26: 60447 | E26: 241789 | F26: 0 | G26: 22
A27: T100033 | B27: 2026-08 | C27: 0 | G27: 23
A28: T100033 | B28: 2026-09 | C28: 1 | D28: 692083 | E28: 4789146 | F28: 467491 | G28: 24
A29: T100070 | B29: 2024-10 | C29: 1 | D29: 306833 | E29: 1833154 | F29: 167257 | G29: 1
A30: T100070 | B30: 2024-11 | C30: 1 | D30: 2145197 | E30: 12816349 | F30: 1176098 | G30: 2
A31: T100070 | B31: 2024-12 | C31: 1 | D31: 1159576 | E31: 6927817 | F31: 629721 | G31: 3
A32: T100070 | B32: 2025-01 | C32: 1 | D32: 2558377 | E32: 15284868 | F32: 1402999 | G32: 4
A33: T100070 | B33: 2025-02 | C33: 1 | D33: 1332125 | E33: 7958697 | F33: 710312 | G33: 5
A34: T100070 | B34: 2025-03 | C34: 1 | D34: 960419 | E34: 5737963 | F34: 507189 | G34: 6
A35: T100070 | B35: 2025-04 | C35: 1 | D35: 2667385 | E35: 15936129 | F35: 1404238 | G35: 7
A36: T100070 | B36: 2025-05 | C36: 1 | D36: 97298 | E36: 581300 | F36: 60641 | G36: 8
A37: T100070 | B37: 2025-06 | C37: 1 | D37: 1372214 | E37: 8198210 | F37: 749700 | G37: 9
A38: T100070 | B38: 2025-07 | C38: 1 | D38: 1528694 | E38: 9133091 | F38: 844821 | G38: 10
A39: T100070 | B39: 2025-08 | C39: 1 | D39: 254227 | E39: 1518865 | F39: 135626 | G39: 11
... A42: T100070 | B42: 2025-11 | C42: 1 | D42: 661778 | E42: 3953752 | F42: 365132 | G42: 14
A43: T100070 | B43: 2025-12 | C43: 0 | G43: 15
A44: T100070 | B44: 2026-01 | C44: 1 | D44: 1121984 | E44: 6703224 | F44: 646984 | G44: 16
A45: T100070 | B45: 2026-02 | C45: 1 | D45: 1260182 | E45: 7528880 | F45: 685844 | G45: 17
A46: T100070 | B46: 2026-03 | C46: 1 | D46: 1202667 | E46: 7185261 | F46: 631723 | G46: 18
A47: T100070 | B47: 2026-04 | C47: 1 | D47: 3066290 | E47: 18319362 | F47: 1673697 | G47: 19
A48: T100070 | B48: 2026-05 | C48: 1 | D48: 1322678 | E48: 7902259 | F48: 695307 | G48: 20
A49: T100070 | B49: 2026-06 | C49: 1 | D49: 545344 | E49: 3258124 | F49: 296724 | G49: 21
A50: T100070 | B50: 2026-07 | C50: 1 | D50: 2967925 | E50: 17731687 | F50: 1634659 | G50: 22
A51: T100070 | B51: 2026-08 | C51: 1 | D51: 374374 | E51: 2236672 | F51: 205384 | G51: 23
A52: T100070 | B52: 2026-09 | C52: 1 | D52: 3866425 | E52: 23099720 | F52: 2119023 | G52: 24
A53: T100440 | B53: 2024-10 | C53: 1 | D53: 423210207 | E53: 330121806 | F53: 35467173 | G53: 1
A54: T100440 | B54: 2024-11 | C54: 0 | G54: 2
A55: T100440 | B55: 2024-12 | C55: 1 | D55: 438848620 | E55: 342320427 | F55: 37177767 | G55: 3
A56: T100440 | B56: 2025-01 | C56: 1 | D56: 407888742 | E56: 318170417 | F56: 34067870 | G56: 4
A57: T100440 | B57: 2025-02 | C57: 1 | D57: 503249474 | E57: 392555809 | F57: 43420354 | G57: 5
A58: T100440 | B58: 2025-03 | C58: 1 | D58: 448469767 | E58: 349825328 | F58: 38988742 | G58: 6
A59: T100440 | B59: 2025-04 | C59: 1 | D59: 510556320 | E59: 398255457 | F59: 43335596 | G59: 7
A60: T100440 | B60: 2025-05 | C60: 1 | D60: 453023532 | E60: 353377457 | F60: 37659425 | G60: 8
A61: T100440 | B61: 2025-06 | C61: 1 | D61: 494594746 | E61: 385804756 | F61: 42997238 | G61: 9
A62: T100440 | B62: 2025-07 | C62: 1 | D62: 556005046 | E62: 433707379 | F62: 48127396 | G62: 10
A63: T100440 | B63: 2025-08 | C63: 1 | D63: 435208032 | E63: 339480616 | F63: 37578394 | G63: 11
A64: T100440 | B64: 2025-09 | C64: 1 | D64: 434578364 | E64: 338989448 | F64: 37177853 | G64: 12
A65: T100440 | B65: 2025-10 | C65: 1 | D65: 424952459 | E65: 331480836 | F65: 37493467 | G65: 13
A66: T100440 | B66: 2025-11 | C66: 1 | D66: 373429345 | E66: 291290634 | F66: 32740124 | G66: 14
... A70: T100440 | B70: 2026-03 | C70: 1 | D70: 543004735 | E70: 423566589 | F70: 47593854 | G70: 18
A71: T100440 | B71: 2026-04 | C71: 0 | G71: 19
A72: T100440 | B72: 2026-05 | C72: 1 | D72: 526197991 | E72: 410456619 | F72: 44764706 | G72: 20
A73: T100440 | B73: 2026-06 | C73: 1 | D73: 515872165 | E73: 402209265 | F73: 44939706 | G73: 21
A74: T100440 | B74: 2026-07 | C74: 1 | D74: 432199483 | E74: 337133820 | F74: 36045203 | G74: 22
A75: T100440 | B75: 2026-08 | C75: 1 | D75: 443035494 | E75: 345586365 | F75: 37763365 | G75: 23
A76: T100440 | B76: 2026-09 | C76: 1 | D76: 414582272 | E76: 323391653 | F76: 35617370 | G76: 24
A77: T100466 | B77: 2024-10 | C77: 1 | D77: 92434314 | E77: 99937456 | F77: 9221528 | G77: 1
A78: T100466 | B78: 2024-11 | C78: 1 | D78: 99898295 | E78: 108007308 | F78: 9994179 | G78: 2
A79: T100466 | B79: 2024-12 | C79: 1 | D79: 131820078 | E79: 142520269 | F79: 12920568 | G79: 3
A80: T100466 | B80: 2025-01 | C80: 1 | D80: 21245576 | E80: 22844264 | F80: 2059328 | G80: 4
A81: T100466 | B81: 2025-02 | C81: 1 | D81: 130935200 | E81: 141563563 | F81: 12840169 | G81: 5
A82: T100466 | B82: 2025-03 | C82: 1 | D82: 84951846 | E82: 91847616 | F82: 8438615 | G82: 6
A83: T100466 | B83: 2025-04 | C83: 1 | D83: 133476792 | E83: 144311463 | F83: 13206198 | G83: 7
... A134: T102141 | B134: 2025-07 | C134: 1 | D134: 101794376 | E134: 79403905 | F134: 8122081 | G134: 10
A135: T102141 | B135: 2025-08 | C135: 0 | G135: 11
A136: T102141 | B136: 2025-09 | C136: 1 | D136: 81679831 | E136: 63713712 | F136: 6380429 | G136: 12
A137: T102141 | B137: 2025-10 | C137: 0 | G137: 13
A138: T102141 | B138: 2025-11 | C138: 1 | D138: 88771099 | E138: 69245200 | F138: 7108146 | G138: 14
A139: T102141 | B139: 2025-12 | C139: 1 | D139: 135309034 | E139: 105546751 | F139: 11158712 | G139: 15
A140: T102141 | B140: 2026-01 | C140: 1 | D140: 98946965 | E140: 77182805 | F140: 7793395 | G140: 16
A141: T102141 | B141: 2026-02 | C141: 1 | D141: 98546238 | E141: 76870221 | F141: 7919779 | G141: 17
A142: T102141 | B142: 2026-03 | C142: 1 | D142: 110872431 | E142: 86485171 | F142: 8986307 | G142: 18
A143: T102141 | B143: 2026-04 | C143: 1 | D143: 120779563 | E143: 94213152 | F143: 9594453 | G143: 19
A144: T102141 | B144: 2026-05 | C144: 1 | D144: 123260081 | E144: 96148060 | F144: 10141142 | G144: 20
A145: T102141 | B145: 2026-06 | C145: 0 | G145: 21
A146: T102141 | B146: 2026-07 | C146: 1 | D146: 105232169 | E146: 82085529 | F146: 8575426 | G146: 22
A147: T102141 | B147: 2026-08 | C147: 0 | G147: 23
A148: T102141 | B148: 2026-09 | C148: 1 | D148: 77168790 | E148: 60194910 | F148: 6258622 | G148: 24
A149: T102182 | B149: 2024-10 | C149: 1 | D149: 365205 | E149: 219123 | F149: 0 | G149: 1
A150: T102182 | B150: 2024-11 | C150: 1 | D150: 562410 | E150: 337446 | F150: 0 | G150: 2
A151: T102182 | B151: 2024-12 | C151: 1 | D151: 189864 | E151: 113918 | F151: 0 | G151: 3
A152: T102182 | B152: 2025-01 | C152: 1 | D152: 1421627 | E152: 1036797 | F152: 98932 | G152: 4
A153: T102182 | B153: 2025-02 | C153: 1 | D153: 3663023 | E153: 2671456 | F153: 249690 | G153: 5
A154: T102182 | B154: 2025-03 | C154: 1 | D154: 524659 | E154: 314795 | F154: 0 | G154: 6
A155: T102182 | B155: 2025-04 | C155: 1 | D155: 360238 | E155: 262723 | F155: 29554 | G155: 7
A156: T102182 | B156: 2025-05 | C156: 1 | D156: 608291 | E156: 364975 | F156: 0 | G156: 8
A157: T102182 | B157: 2025-06 | C157: 1 | D157: 1754653 | E157: 1279674 | F157: 120273 | G157: 9
A158: T102182 | B158: 2025-07 | C158: 1 | D158: 11477450 | E158: 8370545 | F158: 863094 | G158: 10
A159: T102182 | B159: 2025-08 | C159: 1 | D159: 449401 | E159: 269641 | F159: 0 | G159: 11
... A213: T103130 | B213: 2026-02 | C213: 1 | D213: 1122884009 | E213: 951451336 | F213: 84094826 | G213: 17
A214: T103130 | B214: 2026-03 | C214: 0 | G214: 18
A215: T103130 | B215: 2026-04 | C215: 1 | D215: 1135304625 | E215: 961975674 | F215: 84435134 | G215: 19
A216: T103130 | B216: 2026-05 | C216: 1 | D216: 1744551958 | E216: 1478208147 | F216: 134515009 | G216: 20
A217: T103130 | B217: 2026-06 | C217: 1 | D217: 807474004 | E217: 684195530 | F217: 63465679 | G217: 21
A218: T103130 | B218: 2026-07 | C218: 1 | D218: 639157270 | E218: 541576007 | F218: 47334735 | G218: 22
...

Sheet Sectors
A1: The usual sales over imports of each sector (computed for you)
A2: The median of sales ÷ imports over the tax numbers both sides know that filed at least 10 of their last 12 returns. A median per sector: computed for you.
A4: sector | B4: usual sales ÷ imports | C4: numbers in the median
A5: Cosmetics and personal care | B5: 1.53 | C5: 85
A6: Electronics | B6: 1.388 | C6: 85
A7: Food importers | B7: 1.4272497 | C7: 81
A8: Fuel and chemicals | B8: 1.3431467 | C8: 86
A9: Furniture and household | B9: 1.5845 | C9: 80
A10: General trading | B10: 1.4655 | C10: 90
A11: Machinery | B11: 1.4245 | C11: 82
A12: Medical devices | B12: 1.5223379 | C12: 85
A13: Pharmaceuticals | B13: 1.5179904 | C13: 79
A14: Steel and construction | B14: 1.3897967 | C14: 78
A15: Textiles and apparel | B15: 1.6816275 | C15: 108
A16: Tobacco and beverages | B16: 1.4557721 | C16: 76
A17: Vehicles and parts | B17: 1.477 | C17: 99

Sheet S1 Match
A1: Sprint 1 · the 25 importers against the tax register: who is who
A2: Each row: the importer as customs holds it, and the tax register's best candidate (found by a search on name and address). The similarities are computed for you (purple): how alike the two strings are once cleaned. I17 is worked in grey.
A3: Your choice: 4B_lab.xlsx (sheet Match A) already has every confidence, and 4B_compute_worked.xlsx every formula.
A5: Step | B5: What to do | H5: Your answer | I5: Check | J5: Hint 1 · the tool (the full formula is on the Hints sheet)
A6: 1 | B6: Column K: does the tax number on the declaration exist in the tax register, as typed? "matched", "not in the register" or "blank". Then: how many rows match exactly? | I6: =IF(H6="","",IF(ISNUMBER(H6),IF(ABS(H6-_check!$B$2)<=0.5,"✓ matches","✗ not yet: see the hint"),"✗ not yet: see the hint")) | J6: COUNTIF counts the number in the register's tax ID column; IF turns the count into a word.
A7: 2 | B7: Column P: the match confidence: name × 0.4 + address × 0.3 + director × 0.3, a missing field left out and the weights rescaled over the fields present. Then: I17's confidence. | I7: =IF(H7="","",IF(ISNUMBER(H7),IF(ABS(H7-_check!$B$3)<=0.0006,"✓ matches","✗ not yet: see the hint"),"✗ not yet: see the hint")) | J7: N() turns an empty cell into 0; ISNUMBER says which fields are present, so the division rescales the weights.
A8: 3 | B8: Column Q: the class at the dial: exact when the number matched; validated probable at or above the link line; review between the two lines (a person decides); no link below. Then: how many rows wait in the review band? | I8: =IF(H8="","",IF(ISNUMBER(H8),IF(ABS(H8-_check!$B$4)<=0.5,"✓ matches","✗ not yet: see the hint"),"✗ not yet: see the hint")) | J8: IF inside IF, reading the two lines of the dial on the Parameters sheet.
A9: 4 | B9: Column R: the tax number on the tax side: the declared number when exact; the register's candidate when validated probable; nothing otherwise. Then: how many of the 25 rows have a tax number on the tax side? | I9: =IF(H9="","",IF(ISNUMBER(H9),IF(ABS(H9-_check!$B$5)<=0.5,"✓ matches","✗ not yet: see the hint"),"✗ not yet: see the hint")) | J9: IF on the class. Then count the cells of column R that are not empty.
A10: 5 | B10: Your class (column S): the class at the dial, unless your group decides a review-band pair after reading both records. Lock class and confidence for the 25 on the site. | J10: A wrong link costs more than a missed one: a letter to the wrong trader. Count the four classes; do not quote one match rate.
A15: ref | B15: importer (customs) | C15: tax number on the declaration | D15: address (customs) | E15: phone (customs) | F15: director (customs) | G15: best candidate: tax ID | H15: best candidate: legal name | I15: best candidate: address | J15: best candidate: director | K15: tax number as typed | L15: name similarity | M15: address similarity | N15: director similarity | O15: phone match (1/0) | P15: confidence | Q15: class at the dial | R15: tax number on the tax side | S15: your class
A16: I01 | B16: Ocean Electronics Co., Ltd | C16: T103629 | D16: 222 Mill Road | E16: 0817809823 | F16: Somchai Rahman | G16: T103629 | H16: Ocean Electronics Co., Ltd | I16: 222 Mill Road | J16: Somchai Rahman | L16: 1 | M16: 1 | N16: 1 | O16: 1
A17: I02 | B17: Phoenix Glow Limited | C17: T105264 | D17: 248 Industrial Estate | E17: 0496195011 | F17: Tomas Tanaka | G17: T105264 | H17: Phoenix Glow Limited | I17: 248 Industrial Estate | J17: Tomas Tanaka | L17: 1 | M17: 1 | N17: 1 | O17: 1
A18: I03 | B18: Delta Fruits Holdings Ltd | C18: T106240 | D18: 340 Industrial Estate | E18: 0459640429 | F18: Joseph Rahman | G18: T106240 | H18: Delta Fruits Holdings Ltd | I18: 340 INDUSTRIAL ESTATE | J18: Joseph Rahman | L18: 1 | M18: 1 | N18: 1 | O18: 1
A19: I04 | B19: Great Vellmoor Steel Enterprises | C19: T102376 | D19: 43 Riverside | E19: 0913214249 | F19: Elena Haddad | G19: T102376 | H19: Great Vellmoor Steel Enterprises | I19: 43 Riverside | J19: Elena Haddad | L19: 1 | M19: 1 | N19: 1 | O19: 1
A20: I05 | B20: Carrick Electronics Group Ltd | C20: T106987 | D20: 375 Industrial Estate | E20: 0719832200 | F20: Farid Okafor | G20: T106987 | H20: Carrick Electronics Group Ltd | I20: 375 Industrial Estate | J20: Farid Okafor | L20: 1 | M20: 1 | N20: 1 | O20: 1
A21: I06 | B21: Carrick Agro Enterprises | C21: T107258 | D21: 18 Market Street | E21: 0545102251 | F21: Kenji Haddad | G21: T107258 | H21: Carrick Agro Enterprises | I21: 18 Market Street | J21: Kenji Haddad | L21: 1 | M21: 1 | N21: 1 | O21: 1
A22: I07 | B22: Cobalt Mobile & Sons | C22: T102141 | D22: 314 Industrial Estate | E22: 0965281846 | F22: Elena Haddad | G22: T102141 | H22: COBALT MOBILE & SONS | I22: 314 Industrial Estate | J22: Elena Haddad | L22: 1 | M22: 1 | N22: 1 | O22: 1
A23: I08 | B23: Central Imports International Ltd | D23: 350 Garden Lane | E23: 0471338762 | F23: Kenji Haddad | G23: T102182 | H23: Central Enterprises Ltd | I23: 302 Bazaar Lane | J23: Daniel Nguyen-Lee | L23: 1 | M23: 0.615 | N23: 0.345 | O23: 0
A24: I09 | B24: Phoenix Imports Partners Ltd | D24: 171 Garden Lane | E24: 0887356246 | F24: Nadia Chen | G24: T514418 | H24: Phoenix Holdings International Ltd | I24: 118 Mill Road | J24: Ravi Patel | L24: 1 | M24: 0.417 | N24: 0.4 | O24: 0
A25: I10 | B25: Global Electronics International Ltd | C25: T103130 | D25: 296 Temple Street | E25: 0941933516 | F25: Amina Al-Sayed | G25: T103130 | H25: Global Electronics International Limited | J25: Amina Al-Sayed | L25: 1 | N25: 1 | O25: 1
A26: I11 | B26: Central Foods Limited | C26: T100033 | D26: 24 Harbour Road | E26: 0401520138 | F26: Farid Ibrahim | G26: T100033 | H26: Central Foods Limited | I26: 24 Harbour Road | J26: Farid Ibrahim | L26: 1 | M26: 1 | N26: 1 | O26: 1
A27: I12 | B27: Ocean Medical Co., Ltd | D27: 362 Temple Street | E27: 0482336020 | F27: Hassan Tanaka | G27: T109212 | H27: Ocean Enterprises Holdings Ltd | I27: 292 Temple Street | J27: Elena Rahman | L27: 1 | M27: 0.846 | N27: 0.32 | O27: 0
A28: I13 | B28: Central Enterprises Co. | D28: 191 Garden Lane | E28: 0946646378 | F28: Hassan Kowalski | G28: T110150 | H28: Central Textiles International Ltd | I28: Unit 28, 160 Garden Lane | J28: Grace Osei | L28: 1 | M28: 0.846 | N28: 0.4 | O28: 0
A29: I14 | B29: Royal Agro Co., Ltd | C29: T108692 | D29: 191 Bazaar Lane | E29: 0382439044 | F29: Somchai Silva | G29: T108692 | H29: Royal Agro Co., Ltd | I29: 191 BAZAAR LANE | J29: Somchai Silva | L29: 1 | M29: 1 | N29: 1 | O29: 1
A30: I15 | B30: Silk Road Steel Co. | C30: T100070 | D30: 346 Market Street | E30: 0519965779 | F30: Farid Haddad | G30: T100070 | H30: Silk Road Steel Co. | I30: 346 Market Street | J30: Farid Haddad | L30: 1 | M30: 1 | N30: 1 | O30: 1
A31: I16 | B31: Carrick Trading & Sons | C31: T107617 | D31: 172 Airport Road | E31: 0803847861 | F31: Ingrid Sato | G31: T107617 | H31: Carrick Trading & Sons | I31: 172 Airport Road | J31: Ingrid Sato | L31: 1 | M31: 1 | N31: 1 | O31: 1
A32: I17 | B32: Ocean Industries Holdings Ltd | D32: 323 Station Road | E32: 0924121092 | F32: Joseph Tanaka | G32: T106372 | H32: Ocean Industries Enterprises | I32: 275 Station Road | J32: Tomas Mensah | K32: =IF(C32="","blank",IF(COUNTIF('Tax register'!$A$5:$A$1803,C32)>0,"matched","not in the register")) | L32: 1 | M32: 0.857 | N32: 0.4 | O32: 0 | P32: =IF(COUNT(L32:N32)=0,0,(Parameters!$B$5*N(L32)+Parameters!$B$6*N(M32)+Parameters!$B$7*N(N32))/(Parameters!$B$5*ISNUMBER(L32)+Parameters!$B$6*ISNUMBER(M32)+Parameters!$B$7*ISNUMBER(N32))) | Q32: =IF(K32="matched","exact",IF(P32>=Parameters!$B$8,"validated probable",IF(P32>=Parameters!$B$9,"review","no link"))) | R32: =IF(S32="exact",C32,IF(S32="validated probable",G32,"")) | S32: =Q32
A33: I18 | B33: Arden Living Co. | C33: T107992 | D33: 144 Riverside | E33: 0894167333 | F33: Samuel Kowalski | G33: T107992 | H33: Arden Living Co. | I33: 144 Riverside | J33: Samuel Kowalski | L33: 1 | M33: 1 | N33: 1 | O33: 1
A34: I19 | B34: Pacific Living Co. | C34: T109167 | D34: 329 Riverside | E34: 0346234502 | F34: Aisha Reyes | G34: T109167 | H34: Pacific Living Co. | I34: 329 Riverside | J34: Aisha Reyes | L34: 1 | M34: 1 | N34: 1 | O34: 1
A35: I20 | B35: Ocean Trading International Ltd | C35: T103425 | D35: 115 Harbour Road | E35: 0731410108 | F35: Nadia Al-Sayed | G35: T103425 | H35: Ocean Trading International Ltd | I35: 115 Harbour Road | J35: Nadia Al-Sayed | L35: 1 | M35: 1 | N35: 1 | O35: 1
A36: I21 | B36: Metro Motors Co., Ltd | C36: T100440 | D36: 215 Bazaar Lane | E36: 0929915234 | F36: Ingrid Al-Sayed | G36: T100440 | H36: Metro Motors Co., Ltd | I36: 215 Bazaar Lane | J36: Ingrid Al-Sayed | L36: 1 | M36: 1 | N36: 1 | O36: 1
A37: I22 | B37: Metro Steel Partners Ltd | C37: T106477 | D37: 358 Market Street | E37: 0402667378 | F37: Amina Bauer | G37: T106477 | H37: Metro Steel Partners Ltd | I37: 358 Market Street | J37: Amina Bauer | L37: 1 | M37: 1 | N37: 1 | O37: 1
A38: I23 | B38: Aldergate Agro Holdings Ltd | C38: T104498 | D38: 340 Garden Lane | E38: 0612702458 | F38: Daniel Osei | G38: T104498 | H38: Aldergate Agro Holdings Ltd | I38: 340 Garden Lane | J38: Daniel Osei | L38: 1 | M38: 1 | N38: 1 | O38: 1
A39: I24 | B39: Pacific Enterprises Holdings Ltd | C39: T100466 | D39: 356 Station Road | E39: 0254736740 | F39: Farid Sato | G39: T100466 | H39: Pacific Enterprises Holdings Ltd | I39: 356 Station Road | J39: Farid Sato | L39: 1 | M39: 1 | N39: 1 | O39: 1
A40: I25 | B40: Arden Fruits Enterprises | C40: T102011 | D40: 360 Harbour Road | E40: 0225352118 | F40: Mei Okafor | G40: T102015 | H40: ARDEN FRUITS ENTERPRISES | I40: 360 Harbour Road | J40: Mei Okafor | L40: 1 | M40: 1 | N40: 1 | O40: 1
A42: The worked case, I17: no number on the declaration; the register's best candidate T106372 · name 1.00, address 0.857, director 0.40: 0.4 × 1.00 + 0.3 × 0.857 + 0.3 × 0.40 = 0.777, in the review band. A person reads both records before any letter.

Sheet S1 Track B
A1: Sprint 1 · Track B: a real register, and where to set the dial
A2: Left: the matching recipe's best candidate for each of 3,200 customs rows, with its score (computed for you). Middle: 300 pairs a clerk checked by hand (1 = the same trader, 0 = not). Rows by number only; no name is read aloud.
A5: customs row | B5: register row | C5: score | D5: band | F5: customs row | G5: register row | H5: label (1 = same) | I5: its score | K5: at the dial | L5: 0.5 | M5: 0.7 | N5: 0.9
A6: C00001 | B6: R01223 | C6: 1 | D6: exact | F6: C00018 | G6: R00507 | H6: 0 | I6: =VLOOKUP(F6,$A$6:$C$3205,3,FALSE) | K6: pairs at or above (all rows) | L6: =COUNTIF($C$6:$C$3205,">="&L$5)
A7: C00002 | B7: R00398 | C7: 1 | D7: exact | F7: C00020 | G7: R01739 | H7: 1 | I7: =VLOOKUP(F7,$A$6:$C$3205,3,FALSE) | K7: sample pairs at or above | L7: =COUNTIF($I$6:$I$305,">="&L$5)
A8: C00003 | B8: R02417 | C8: 1 | D8: exact | F8: C00028 | G8: R01517 | H8: 1 | I8: =VLOOKUP(F8,$A$6:$C$3205,3,FALSE) | K8: precision: true links ÷ sample pairs at or above | L8: =IFERROR(COUNTIFS($I$6:$I$305,">="&L$5,$H$6:$H$305,1)/L7,"")
A9: C00004 | B9: R01899 | C9: 1 | D9: exact | F9: C00031 | G9: R01600 | H9: 1 | I9: =VLOOKUP(F9,$A$6:$C$3205,3,FALSE) | K9: recall: true links at or above ÷ all true links | L9: =IFERROR(COUNTIFS($I$6:$I$305,">="&L$5,$H$6:$H$305,1)/COUNTIF($H$6:$H$305,1),"")
A10: C00005 | B10: R02666 | C10: 1 | D10: exact | F10: C00037 | G10: R02691 | H10: 1 | I10: =VLOOKUP(F10,$A$6:$C$3205,3,FALSE)
A11: C00006 | B11: R02060 | C11: 1 | D11: exact | F11: C00049 | G11: R00866 | H11: 1 | K11: checks (rows 6 to 9) | L11: =IF(COUNT($I$6:$I$305)<300,"",IF(L6="","",IF(ISNUMBER(L6),IF(ABS(L6-_check!$B$6)<=0.5,"✓","✗"),"✗"))) | M11: =IF(COUNT($I$6:$I$305)<300,"",IF(M6="","",IF(ISNUMBER(M6),IF(ABS(M6-_check!$B$7)<=0.5,"✓","✗"),"✗"))) | N11: =IF(COUNT($I$6:$I$305)<300,"",IF(N6="","",IF(ISNUMBER(N6),IF(ABS(N6-_check!$B$8)<=0.5,"✓","✗"),"✗")))
A12: C00007 | B12: R01228 | C12: 1 | D12: exact | F12: C00059 | G12: R00785 | H12: 1 | L12: =IF(COUNT($I$6:$I$305)<300,"",IF(L7="","",IF(ISNUMBER(L7),IF(ABS(L7-_check!$B$9)<=0.5,"✓","✗"),"✗"))) | M12: =IF(COUNT($I$6:$I$305)<300,"",IF(M7="","",IF(ISNUMBER(M7),IF(ABS(M7-_check!$B$10)<=0.5,"✓","✗"),"✗"))) | N12: =IF(COUNT($I$6:$I$305)<300,"",IF(N7="","",IF(ISNUMBER(N7),IF(ABS(N7-_check!$B$11)<=0.5,"✓","✗"),"✗")))
A13: C00008 | B13: R00709 | C13: 1 | D13: exact | F13: C00062 | G13: R02603 | H13: 1 | L13: =IF(COUNT($I$6:$I$305)<300,"",IF(L8="","",IF(ISNUMBER(L8),IF(ABS(L8-_check!$B$12)<=0.0006,"✓","✗"),"✗"))) | M13: =IF(COUNT($I$6:$I$305)<300,"",IF(M8="","",IF(ISNUMBER(M8),IF(ABS(M8-_check!$B$13)<=0.0006,"✓","✗"),"✗"))) | N13: =IF(COUNT($I$6:$I$305)<300,"",IF(N8="","",IF(ISNUMBER(N8),IF(ABS(N8-_check!$B$14)<=0.0006,"✓","✗"),"✗")))
A14: C00009 | B14: R01515 | C14: 0.4259 | D14: no match | F14: C00073 | G14: R00465 | H14: 1 | L14: =IF(COUNT($I$6:$I$305)<300,"",IF(L9="","",IF(ISNUMBER(L9),IF(ABS(L9-_check!$B$15)<=0.0006,"✓","✗"),"✗"))) | M14: =IF(COUNT($I$6:$I$305)<300,"",IF(M9="","",IF(ISNUMBER(M9),IF(ABS(M9-_check!$B$16)<=0.0006,"✓","✗"),"✗"))) | N14: =IF(COUNT($I$6:$I$305)<300,"",IF(N9="","",IF(ISNUMBER(N9),IF(ABS(N9-_check!$B$17)<=0.0006,"✓","✗"),"✗")))
A15: C00010 | B15: R00624 | C15: 0.6541 | D15: no match | F15: C00079 | G15: R01142 | H15: 1
A16: C00011 | B16: R00446 | C16: 1 | D16: exact | F16: C00102 | G16: R01427 | H16: 1 | K16: Read the trade-off: a strict dial (0.9) is almost always right and misses most true links; a loose one (0.5) finds them and sends letters to the wrong trader. The sample is 300 pairs: a precision of 87% on 200 pairs can be anything from about 81% to 91%.
A17: C00012 | B17: R01431 | C17: 1 | D17: exact | F17: C00113 | G17: R00350 | H17: 1
A18: C00013 | B18: R02150 | C18: 1 | D18: exact | F18: C00120 | G18: R01761 | H18: 1
A19: C00014 | B19: R01423 | C19: 1 | D19: exact | F19: C00122 | G19: R01080 | H19: 1
A20: C00015 | B20: R01242 | C20: 0.6541 | D20: no match | F20: C00140 | G20: R00812 | H20: 1
A21: C00016 | B21: R02239 | C21: 1 | D21: exact | F21: C00142 | G21: R02154 | H21: 1
A22: C00017 | B22: R01133 | C22: 0.6541 | D22: no match | F22: C00147 | G22: R02873 | H22: 1
A23: C00018 | B23: R00507 | C23: 0.2202 | D23: no match | F23: C00148 | G23: R02192 | H23: 1
A24: C00019 | B24: R02036 | C24: 1 | D24: exact | F24: C00169 | G24: R02168 | H24: 1
A25: C00020 | B25: R01739 | C25: 0.7718 | D25: review | F25: C00171 | G25: R01471 | H25: 1
A26: C00021 | B26: R02476 | C26: 1 | D26: exact | F26: C00174 | G26: R01045 | H26: 1
A27: C00022 | B27: R00487 | C27: 1 | D27: exact | F27: C00190 | G27: R01903 | H27: 1
A28: C00023 | B28: R01823 | C28: 1 | D28: exact | F28: C00192 | G28: R01868 | H28: 1
... A305: C00300 | B305: R02870 | C305: 1 | D305: exact | F305: C03177 | G305: R00007 | H305: 1
A306: C00301 | B306: R01894 | C306: 0.7718 | D306: review
A307: C00302 | B307: R02400 | C307: 0.6541 | D307: no match
A308: C00303 | B308: R00726 | C308: 0.6541 | D308: no match
A309: C00304 | B309: R00152 | C309: 1 | D309: exact
A310: C00305 | B310: R02105 | C310: 0.7718 | D310: review
A311: C00306 | B311: R01953 | C311: 0.7942 | D311: review
A312: C00307 | B312: R02188 | C312: 1 | D312: exact
A313: C00308 | B313: R00577 | C313: 1 | D313: exact
A314: C00309 | B314: R02629 | C314: 0.6541 | D314: no match
A315: C00310 | B315: R01469 | C315: 1 | D315: exact
A316: C00311 | B316: R00689 | C316: 0.7718 | D316: review
A317: C00312 | B317: R00787 | C317: 1 | D317: exact
... A3205: C03200 | B3205: R02031 | C3205: 0.6541 | D3205: no match

Sheet S2 Four lists
A1: Sprint 2 · follow one import through both administrations: four questions, four lists
A2: A trader goes on the list of the first question it fails: 1 not known to tax, 2 not filing, 3 import not in its books, 4 sells below what it imports, else consistent for now. I01 is worked in grey. Your class comes from S1 Match, column S.
A3: Your choice: 4B_lab.xlsx (sheet Lists) already has every number. The checks assume the classes at the dial; if your group linked a review-band pair, its row will differ, and that is your call.
A5: Step | B5: What to do | H5: Your answer | I5: Check | J5: Hint 1 · the tool (the full formula is on the Hints sheet)
A6: 1 | B6: Columns H and I: imports and import VAT paid over the last twelve months, adding up the lines that bear VAT under the tax number used to clear (Lines 12m). With no number, under the importer's own code. Then: the imports of the 25, added up. | I6: =IF(H6="","",IF(ISNUMBER(H6),IF(ABS(H6-_check!$B$18)<=1,"✓ matches","✗ not yet: see the hint"),"✗ not yet: see the hint")) | J6: SUMIFS on the Lines 12m sheet, by tax number; IF the number is blank, by importer code.
A7: 2 | B7: Columns J to M: on the tax side (column G), the returns filed of the last six, the import VAT deducted and the sales over twelve months, and booked = deducted ÷ paid. Then: how many of the 25 filed all six of their last six returns? | I7: =IF(H7="","",IF(ISNUMBER(H7),IF(ABS(H7-_check!$B$19)<=0.5,"✓ matches","✗ not yet: see the hint"),"✗ not yet: see the hint")) | J7: COUNTIFS on the Returns sheet: the tax ID, filed = 1, period number ≥ 19. SUMIFS for the amounts, period number ≥ 13.
A8: 3 | B8: Columns N and O: sales ÷ imports, and the sector's usual (Sectors sheet). Column P: the first question failed (1 to 5). Column Q: the VAT at stake. Then: how many importers fail question 2 (not filing)? | I8: =IF(H8="","",IF(ISNUMBER(H8),IF(ABS(H8-_check!$B$20)<=0.5,"✓ matches","✗ not yet: see the hint"),"✗ not yet: see the hint")) | J8: IF inside IF, in the order of the four questions. VAT at stake, 10%: lists 1-2, VAT × imports × (usual − 1); lists 3-4, VAT × (imports × usual − sales); never below 0.
A9: 4 | B9: Column R: list 4 ranked by VAT at stake. Column S: the list, cut at the capacity. Then: the VAT at stake within capacity (lists 1 to 3, and list 4 up to the capacity). | I9: =IF(H9="","",IF(ISNUMBER(H9),IF(ABS(H9-_check!$B$21)<=1000,"✓ matches","✗ not yet: see the hint"),"✗ not yet: see the hint")) | J9: COUNTIFS counts the list-4 importers with more at stake. The summary table below adds up by list.
A10: 5 | B10: Columns T and U: the lead and the action for each list. Lock list, reason, lead and VAT at stake for the 25 on the site. | J10: List 1: tax, registration letter. List 2: tax, stop-filer letter. List 3: joint, ask for the books. List 4: tax with the customs data, desk audit, largest first.
A16: ref | B16: importer code | C16: tax number on the declaration | D16: importer (customs) | E16: sector | F16: your class (S1 Match) | G16: tax number on the tax side | H16: imports, 12 months (LCU) | I16: import VAT paid, 12 months (LCU) | J16: returns filed of the last 6 | K16: import VAT deducted, 12 months (LCU) | L16: booked (deducted ÷ paid) | M16: sales, 12 months (LCU) | N16: sales ÷ imports | O16: sector usual | P16: first question failed (1-5) | Q16: VAT at stake (LCU) | R16: rank on list 4 | S16: list | T16: check | U16: lead | V16: action
A17: I01 | B17: IMP00519 | C17: T103629 | D17: Ocean Electronics Co., Ltd | E17: Fuel and chemicals | F17: =IF('S1 Match'!S16="","",'S1 Match'!S16) | G17: =IF('S1 Match'!R16="","",'S1 Match'!R16) | H17: =IF(C17="",SUMIFS('Lines 12m'!$G$5:$G$12324,'Lines 12m'!$D$5:$D$12324,B17),SUMIFS('Lines 12m'!$G$5:$G$12324,'Lines 12m'!$E$5:$E$12324,C17)) | I17: =IF(C17="",SUMIFS('Lines 12m'!$H$5:$H$12324,'Lines 12m'!$D$5:$D$12324,B17),SUMIFS('Lines 12m'!$H$5:$H$12324,'Lines 12m'!$E$5:$E$12324,C17)) | J17: =IF(G17="","",COUNTIFS(Returns!$A$5:$A$604,G17,Returns!$C$5:$C$604,1,Returns!$G$5:$G$604,">="&Parameters!$B$11)) | K17: =IF(G17="","",SUMIFS(Returns!$F$5:$F$604,Returns!$A$5:$A$604,G17,Returns!$G$5:$G$604,">="&Parameters!$B$12)) | L17: =IF(OR(G17="",N(I17)=0),"",K17/I17) | M17: =IF(G17="","",SUMIFS(Returns!$D$5:$D$604,Returns!$A$5:$A$604,G17,Returns!$G$5:$G$604,">="&Parameters!$B$12)) | N17: =IF(OR(M17="",N(H17)=0),"",M17/H17) | O17: =IFERROR(VLOOKUP(E17,Sectors!$A$5:$B$17,2,FALSE),"") | P17: =IF(G17="",1,IF(J17<Parameters!$B$14,2,IF(L17<Parameters!$B$15,3,IF(N17<Parameters!$B$16,4,5)))) | Q17: =IF(P17<=2,MAX(0,Parameters!$B$10*H17*(O17-1)),IF(P17<=4,MAX(0,Parameters!$B$10*(H17*O17-M17)),0)) | R17: =IF(P17=4,COUNTIFS($P$17:$P$41,4,$Q$17:$Q$41,">"&Q17)+1,"") | S17: =IF(P17=4,IF(R17<=Parameters!$B$17,"4 desk audit, ranked by VAT at stake","4b below imports, beyond capacity"),CHOOSE(P17,"1 not known to tax","2 not filing","3 import not booked","","5 consistent for now")) | T17: =IF(OR(H17="",S17="",F17=""),"",IFERROR(IF(AND(ABS(H17-_check!$B$22)<=1,J17=_check!$B$23,ABS(N17-_check!$B$24)<=0.0006),"✓","✗"),"✗"))
A18: I02 | B18: IMP00753 | C18: T105264 | D18: Phoenix Glow Limited | E18: Textiles and apparel | F18: =IF('S1 Match'!S17="","",'S1 Match'!S17) | G18: =IF('S1 Match'!R17="","",'S1 Match'!R17) | T18: =IF(OR(H18="",S18="",F18=""),"",IFERROR(IF(AND(ABS(H18-_check!$B$25)<=1,J18=_check!$B$26,ABS(N18-_check!$B$27)<=0.0006),"✓","✗"),"✗"))
A19: I03 | B19: IMP00892 | C19: T106240 | D19: Delta Fruits Holdings Ltd | E19: General trading | F19: =IF('S1 Match'!S18="","",'S1 Match'!S18) | G19: =IF('S1 Match'!R18="","",'S1 Match'!R18) | T19: =IF(OR(H19="",S19="",F19=""),"",IFERROR(IF(AND(ABS(H19-_check!$B$28)<=1,J19=_check!$B$29,ABS(N19-_check!$B$30)<=0.0006),"✓","✗"),"✗"))
A20: I04 | B20: IMP00340 | C20: T102376 | D20: Great Vellmoor Steel Enterprises | E20: Fuel and chemicals | F20: =IF('S1 Match'!S19="","",'S1 Match'!S19) | G20: =IF('S1 Match'!R19="","",'S1 Match'!R19) | T20: =IF(OR(H20="",S20="",F20=""),"",IFERROR(IF(AND(ABS(H20-_check!$B$31)<=1,J20=_check!$B$32,ABS(N20-_check!$B$33)<=0.0006),"✓","✗"),"✗"))
A21: I05 | B21: IMP00999 | C21: T106987 | D21: Carrick Electronics Group Ltd | E21: Electronics | F21: =IF('S1 Match'!S20="","",'S1 Match'!S20) | G21: =IF('S1 Match'!R20="","",'S1 Match'!R20) | T21: =IF(OR(H21="",S21="",F21=""),"",IFERROR(IF(AND(ABS(H21-_check!$B$34)<=1,J21=_check!$B$35,ABS(N21-_check!$B$36)<=0.0006),"✓","✗"),"✗"))
A22: I06 | B22: IMP01037 | C22: T107258 | D22: Carrick Agro Enterprises | E22: Medical devices | F22: =IF('S1 Match'!S21="","",'S1 Match'!S21) | G22: =IF('S1 Match'!R21="","",'S1 Match'!R21) | T22: =IF(OR(H22="",S22="",F22=""),"",IFERROR(IF(AND(ABS(H22-_check!$B$37)<=1,J22=_check!$B$38,ABS(N22-_check!$B$39)<=0.0006),"✓","✗"),"✗"))
A23: I07 | B23: IMP00306 | C23: T102141 | D23: Cobalt Mobile & Sons | E23: Furniture and household | F23: =IF('S1 Match'!S22="","",'S1 Match'!S22) | G23: =IF('S1 Match'!R22="","",'S1 Match'!R22) | T23: =IF(OR(H23="",S23="",F23=""),"",IFERROR(IF(AND(ABS(H23-_check!$B$40)<=1,J23=_check!$B$41,ABS(N23-_check!$B$42)<=0.0006),"✓","✗"),"✗"))
A24: I08 | B24: IMP00147 | D24: Central Imports International Ltd | E24: Pharmaceuticals | F24: =IF('S1 Match'!S23="","",'S1 Match'!S23) | G24: =IF('S1 Match'!R23="","",'S1 Match'!R23) | T24: =IF(OR(H24="",S24="",F24=""),"",IFERROR(IF(AND(ABS(H24-_check!$B$43)<=1),"✓","✗"),"✗"))
A25: I09 | B25: IMP00721 | D25: Phoenix Imports Partners Ltd | E25: General trading | F25: =IF('S1 Match'!S24="","",'S1 Match'!S24) | G25: =IF('S1 Match'!R24="","",'S1 Match'!R24) | T25: =IF(OR(H25="",S25="",F25=""),"",IFERROR(IF(AND(ABS(H25-_check!$B$44)<=1),"✓","✗"),"✗"))
A26: I10 | B26: IMP00448 | C26: T103130 | D26: Global Electronics International Ltd | E26: Fuel and chemicals | F26: =IF('S1 Match'!S25="","",'S1 Match'!S25) | G26: =IF('S1 Match'!R25="","",'S1 Match'!R25) | T26: =IF(OR(H26="",S26="",F26=""),"",IFERROR(IF(AND(ABS(H26-_check!$B$45)<=1,J26=_check!$B$46,ABS(N26-_check!$B$47)<=0.0006),"✓","✗"),"✗"))
A27: I11 | B27: IMP00005 | C27: T100033 | D27: Central Foods Limited | E27: Steel and construction | F27: =IF('S1 Match'!S26="","",'S1 Match'!S26) | G27: =IF('S1 Match'!R26="","",'S1 Match'!R26) | T27: =IF(OR(H27="",S27="",F27=""),"",IFERROR(IF(AND(ABS(H27-_check!$B$48)<=1,J27=_check!$B$49,ABS(N27-_check!$B$50)<=0.0006),"✓","✗"),"✗"))
A28: I12 | B28: IMP00156 | D28: Ocean Medical Co., Ltd | E28: Tobacco and beverages | F28: =IF('S1 Match'!S27="","",'S1 Match'!S27) | G28: =IF('S1 Match'!R27="","",'S1 Match'!R27) | T28: =IF(OR(H28="",S28="",F28=""),"",IFERROR(IF(AND(ABS(H28-_check!$B$51)<=1),"✓","✗"),"✗"))
A29: I13 | B29: IMP00950 | D29: Central Enterprises Co. | E29: Tobacco and beverages | F29: =IF('S1 Match'!S28="","",'S1 Match'!S28) | G29: =IF('S1 Match'!R28="","",'S1 Match'!R28) | T29: =IF(OR(H29="",S29="",F29=""),"",IFERROR(IF(AND(ABS(H29-_check!$B$52)<=1),"✓","✗"),"✗"))
A30: I14 | B30: IMP01242 | C30: T108692 | D30: Royal Agro Co., Ltd | E30: Electronics | F30: =IF('S1 Match'!S29="","",'S1 Match'!S29) | G30: =IF('S1 Match'!R29="","",'S1 Match'!R29) | T30: =IF(OR(H30="",S30="",F30=""),"",IFERROR(IF(AND(ABS(H30-_check!$B$53)<=1,J30=_check!$B$54,ABS(N30-_check!$B$55)<=0.0006),"✓","✗"),"✗"))
A31: I15 | B31: IMP00011 | C31: T100070 | D31: Silk Road Steel Co. | E31: Pharmaceuticals | F31: =IF('S1 Match'!S30="","",'S1 Match'!S30) | G31: =IF('S1 Match'!R30="","",'S1 Match'!R30) | T31: =IF(OR(H31="",S31="",F31=""),"",IFERROR(IF(AND(ABS(H31-_check!$B$56)<=1,J31=_check!$B$57,ABS(N31-_check!$B$58)<=0.0006),"✓","✗"),"✗"))
A32: I16 | B32: IMP01089 | C32: T107617 | D32: Carrick Trading & Sons | E32: Machinery | F32: =IF('S1 Match'!S31="","",'S1 Match'!S31) | G32: =IF('S1 Match'!R31="","",'S1 Match'!R31) | T32: =IF(OR(H32="",S32="",F32=""),"",IFERROR(IF(AND(ABS(H32-_check!$B$59)<=1,J32=_check!$B$60,ABS(N32-_check!$B$61)<=0.0006),"✓","✗"),"✗"))
A33: I17 | B33: IMP01481 | D33: Ocean Industries Holdings Ltd | E33: Steel and construction | F33: =IF('S1 Match'!S32="","",'S1 Match'!S32) | G33: =IF('S1 Match'!R32="","",'S1 Match'!R32) | T33: =IF(OR(H33="",S33="",F33=""),"",IFERROR(IF(AND(ABS(H33-_check!$B$62)<=1),"✓","✗"),"✗"))
A34: I18 | B34: IMP01142 | C34: T107992 | D34: Arden Living Co. | E34: Fuel and chemicals | F34: =IF('S1 Match'!S33="","",'S1 Match'!S33) | G34: =IF('S1 Match'!R33="","",'S1 Match'!R33) | T34: =IF(OR(H34="",S34="",F34=""),"",IFERROR(IF(AND(ABS(H34-_check!$B$63)<=1,J34=_check!$B$64,ABS(N34-_check!$B$65)<=0.0006),"✓","✗"),"✗"))
A35: I19 | B35: IMP01310 | C35: T109167 | D35: Pacific Living Co. | E35: Textiles and apparel | F35: =IF('S1 Match'!S34="","",'S1 Match'!S34) | G35: =IF('S1 Match'!R34="","",'S1 Match'!R34) | T35: =IF(OR(H35="",S35="",F35=""),"",IFERROR(IF(AND(ABS(H35-_check!$B$66)<=1,J35=_check!$B$67,ABS(N35-_check!$B$68)<=0.0006),"✓","✗"),"✗"))
A36: I20 | B36: IMP00490 | C36: T103425 | D36: Ocean Trading International Ltd | E36: Machinery | F36: =IF('S1 Match'!S35="","",'S1 Match'!S35) | G36: =IF('S1 Match'!R35="","",'S1 Match'!R35) | T36: =IF(OR(H36="",S36="",F36=""),"",IFERROR(IF(AND(ABS(H36-_check!$B$69)<=1,J36=_check!$B$70,ABS(N36-_check!$B$71)<=0.0006),"✓","✗"),"✗"))
A37: I21 | B37: IMP00063 | C37: T100440 | D37: Metro Motors Co., Ltd | E37: Vehicles and parts | F37: =IF('S1 Match'!S36="","",'S1 Match'!S36) | G37: =IF('S1 Match'!R36="","",'S1 Match'!R36) | T37: =IF(OR(H37="",S37="",F37=""),"",IFERROR(IF(AND(ABS(H37-_check!$B$72)<=1,J37=_check!$B$73,ABS(N37-_check!$B$74)<=0.0006),"✓","✗"),"✗"))
A38: I22 | B38: IMP00926 | C38: T106477 | D38: Metro Steel Partners Ltd | E38: Fuel and chemicals | F38: =IF('S1 Match'!S37="","",'S1 Match'!S37) | G38: =IF('S1 Match'!R37="","",'S1 Match'!R37) | T38: =IF(OR(H38="",S38="",F38=""),"",IFERROR(IF(AND(ABS(H38-_check!$B$75)<=1,J38=_check!$B$76,ABS(N38-_check!$B$77)<=0.0006),"✓","✗"),"✗"))
A39: I23 | B39: IMP00643 | C39: T104498 | D39: Aldergate Agro Holdings Ltd | E39: Pharmaceuticals | F39: =IF('S1 Match'!S38="","",'S1 Match'!S38) | G39: =IF('S1 Match'!R38="","",'S1 Match'!R38) | T39: =IF(OR(H39="",S39="",F39=""),"",IFERROR(IF(AND(ABS(H39-_check!$B$78)<=1,J39=_check!$B$79,ABS(N39-_check!$B$80)<=0.0006),"✓","✗"),"✗"))
A40: I24 | B40: IMP00067 | C40: T100466 | D40: Pacific Enterprises Holdings Ltd | E40: Fuel and chemicals | F40: =IF('S1 Match'!S39="","",'S1 Match'!S39) | G40: =IF('S1 Match'!R39="","",'S1 Match'!R39) | T40: =IF(OR(H40="",S40="",F40=""),"",IFERROR(IF(AND(ABS(H40-_check!$B$81)<=1,J40=_check!$B$82,ABS(N40-_check!$B$83)<=0.0006),"✓","✗"),"✗"))
A41: I25 | B41: IMP00288 | C41: T102011 | D41: Arden Fruits Enterprises | E41: Cosmetics and personal care | F41: =IF('S1 Match'!S40="","",'S1 Match'!S40) | G41: =IF('S1 Match'!R40="","",'S1 Match'!R40) | T41: =IF(OR(H41="",S41="",F41=""),"",IFERROR(IF(AND(ABS(H41-_check!$B$84)<=1,J41=_check!$B$85,ABS(N41-_check!$B$86)<=0.0006),"✓","✗"),"✗"))
A44: list | C44: importers | D44: imports (LCU) | E44: VAT at stake (LCU)
A45: 1 not known to tax | C45: =COUNTIF($S$17:$S$41,A45) | D45: =SUMIF($S$17:$S$41,A45,$H$17:$H$41) | E45: =SUMIF($S$17:$S$41,A45,$Q$17:$Q$41) | F45: =IF(COUNTA($S$17:$S$41)<25,"",IF(C45="","",IF(ISNUMBER(C45),IF(ABS(C45-_check!$B$87)<=0.5,"✓","✗"),"✗"))) | G45: =IF(COUNTA($S$17:$S$41)<25,"",IF(E45="","",IF(ISNUMBER(E45),IF(ABS(E45-_check!$B$88)<=1000,"✓","✗"),"✗")))
A46: 2 not filing | C46: =COUNTIF($S$17:$S$41,A46) | D46: =SUMIF($S$17:$S$41,A46,$H$17:$H$41) | E46: =SUMIF($S$17:$S$41,A46,$Q$17:$Q$41) | F46: =IF(COUNTA($S$17:$S$41)<25,"",IF(C46="","",IF(ISNUMBER(C46),IF(ABS(C46-_check!$B$89)<=0.5,"✓","✗"),"✗"))) | G46: =IF(COUNTA($S$17:$S$41)<25,"",IF(E46="","",IF(ISNUMBER(E46),IF(ABS(E46-_check!$B$90)<=1000,"✓","✗"),"✗")))
A47: 3 import not booked | C47: =COUNTIF($S$17:$S$41,A47) | D47: =SUMIF($S$17:$S$41,A47,$H$17:$H$41) | E47: =SUMIF($S$17:$S$41,A47,$Q$17:$Q$41) | F47: =IF(COUNTA($S$17:$S$41)<25,"",IF(C47="","",IF(ISNUMBER(C47),IF(ABS(C47-_check!$B$91)<=0.5,"✓","✗"),"✗"))) | G47: =IF(COUNTA($S$17:$S$41)<25,"",IF(E47="","",IF(ISNUMBER(E47),IF(ABS(E47-_check!$B$92)<=1000,"✓","✗"),"✗")))
A48: 4 desk audit, ranked by VAT at stake | C48: =COUNTIF($S$17:$S$41,A48) | D48: =SUMIF($S$17:$S$41,A48,$H$17:$H$41) | E48: =SUMIF($S$17:$S$41,A48,$Q$17:$Q$41) | F48: =IF(COUNTA($S$17:$S$41)<25,"",IF(C48="","",IF(ISNUMBER(C48),IF(ABS(C48-_check!$B$93)<=0.5,"✓","✗"),"✗"))) | G48: =IF(COUNTA($S$17:$S$41)<25,"",IF(E48="","",IF(ISNUMBER(E48),IF(ABS(E48-_check!$B$94)<=1000,"✓","✗"),"✗")))
A49: 4b below imports, beyond capacity | C49: =COUNTIF($S$17:$S$41,A49) | D49: =SUMIF($S$17:$S$41,A49,$H$17:$H$41) | E49: =SUMIF($S$17:$S$41,A49,$Q$17:$Q$41) | F49: =IF(COUNTA($S$17:$S$41)<25,"",IF(C49="","",IF(ISNUMBER(C49),IF(ABS(C49-_check!$B$95)<=0.5,"✓","✗"),"✗"))) | G49: =IF(COUNTA($S$17:$S$41)<25,"",IF(E49="","",IF(ISNUMBER(E49),IF(ABS(E49-_check!$B$96)<=1000,"✓","✗"),"✗")))
A50: 5 consistent for now | C50: =COUNTIF($S$17:$S$41,A50) | D50: =SUMIF($S$17:$S$41,A50,$H$17:$H$41) | E50: =SUMIF($S$17:$S$41,A50,$Q$17:$Q$41) | F50: =IF(COUNTA($S$17:$S$41)<25,"",IF(C50="","",IF(ISNUMBER(C50),IF(ABS(C50-_check!$B$97)<=0.5,"✓","✗"),"✗"))) | G50: =IF(COUNTA($S$17:$S$41)<25,"",IF(E50="","",IF(ISNUMBER(E50),IF(ABS(E50-_check!$B$98)<=1000,"✓","✗"),"✗")))
A52: The worked case, I01: it filed 5 of its last six returns (at least 5: it files); it deducts 90% of the import VAT it paid (at least half: in its books); its sales are 0.96 times its imports (under 1): list 4, VAT at stake 0.10 × (imports × 1.343 − sales) = 60.9 M LCU.

Sheet S3 Network
A1: Sprint 3 · what each tax number serves: the four counts, the rule, and what the register says
A2: From the customs registers (Customs importers, Consignees): how many other importer codes clear under the number, how many consignees, addresses and brokers stand behind it. Then the rule, and the tax register's director. I01 is worked.
A4: Step | B4: What to do | H4: Your answer | I4: Check | J4: Hint 1 · the tool (the full formula is on the Hints sheet)
A5: 1 | B5: On the Customs importers sheet, columns K and L: 1 the first time an address, and a broker, appear under a tax number (rows 6 to 15 worked). Then, here, columns D to G for every number: names under it, consignees, addresses, brokers. Then: the most consignees under one tax number. | I5: =IF(H5="","",IF(ISNUMBER(H5),IF(ABS(H5-_check!$B$99)<=0.5,"✓ matches","✗ not yet: see the hint"),"✗ not yet: see the hint")) | J5: COUNTIF counts the importer codes under the number; minus 1 for the importer itself; plus its own consignee records. SUMIFS adds the first-time flags.
A6: 2 | B6: Column H and I: imports and sales ÷ imports, from S2. Column J: the rule: consignees at least 8, one address, sales under 20% of imports. Then: how many numbers does the rule flag? | I6: =IF(H6="","",IF(ISNUMBER(H6),IF(ABS(H6-_check!$B$100)<=0.5,"✓ matches","✗ not yet: see the hint"),"✗ not yet: see the hint")) | J6: AND inside IF; the thresholds are on the Parameters sheet.
A7: 3 | B7: Columns K to M: the tax register's director and status for the number, and how many companies that director runs in the register. Then: among the numbers with at least 8 consignees, the most companies one director runs in the register. | I7: =IF(H7="","",IF(ISNUMBER(H7),IF(ABS(H7-_check!$B$101)<=0.5,"✓ matches","✗ not yet: see the hint"),"✗ not yet: see the hint")) | J7: VLOOKUP into the Tax register; COUNTIF on its director column. SUMPRODUCT(MAX(…)) takes the largest value over the rows the condition keeps; "0"& reads an empty count as 0.
A8: 4 | B8: Name the two borrowed-name networks: one the rule finds, one only the register shows. Column N: your cluster. Lock on the site. | J8: The flag is the combination, not one count. A group company clearing for its subsidiaries has one director and its consignees at their own addresses: read the register before you call it a case.
A12: ref | B12: importer code | C12: tax number | D12: other names under the number | E12: consignees | F12: addresses | G12: brokers | H12: imports, 12 months (LCU) | I12: sales ÷ imports | J12: flag (the rule) | K12: register: director | L12: register: status | M12: companies this director runs (register) | N12: your cluster | O12: check
A13: I01 | B13: IMP00519 | C13: T103629 | D13: =COUNTIF('Customs importers'!$B$6:$B$1507,C13)-1 | E13: =D13+COUNTIF(Consignees!$E$5:$E$2006,B13) | F13: =SUMIFS('Customs importers'!$K$6:$K$1507,'Customs importers'!$B$6:$B$1507,C13) | G13: =SUMIFS('Customs importers'!$L$6:$L$1507,'Customs importers'!$B$6:$B$1507,C13) | H13: =IFERROR(VLOOKUP(A13,'S2 Four lists'!$A$17:$N$41,8,FALSE),"") | I13: =IFERROR(VLOOKUP(A13,'S2 Four lists'!$A$17:$N$41,14,FALSE),"") | J13: =IF(AND(E13>=Parameters!$B$18,F13<=Parameters!$B$19,I13<>"",N(I13)<Parameters!$B$20),1,0) | K13: =IFERROR(VLOOKUP(C13,'Tax register'!$A$5:$K$1803,7,FALSE),"") | L13: =IFERROR(VLOOKUP(C13,'Tax register'!$A$5:$K$1803,10,FALSE),"") | M13: =IF(K13="","",COUNTIF('Tax register'!$G$5:$G$1803,K13)) | O13: =IF(OR(COUNT(E13:G13)<3,COUNTA('Customs importers'!$K$6:$K$1507)<1502),"",IF(AND(E13=_check!$B$102,F13=_check!$B$103,G13=_check!$B$104),"✓","✗"))
A14: I02 | B14: IMP00753 | C14: T105264 | H14: =IFERROR(VLOOKUP(A14,'S2 Four lists'!$A$17:$N$41,8,FALSE),"") | I14: =IFERROR(VLOOKUP(A14,'S2 Four lists'!$A$17:$N$41,14,FALSE),"") | O14: =IF(OR(COUNT(E14:G14)<3,COUNTA('Customs importers'!$K$6:$K$1507)<1502),"",IF(AND(E14=_check!$B$105,F14=_check!$B$106,G14=_check!$B$107),"✓","✗"))
A15: I03 | B15: IMP00892 | C15: T106240 | H15: =IFERROR(VLOOKUP(A15,'S2 Four lists'!$A$17:$N$41,8,FALSE),"") | I15: =IFERROR(VLOOKUP(A15,'S2 Four lists'!$A$17:$N$41,14,FALSE),"") | O15: =IF(OR(COUNT(E15:G15)<3,COUNTA('Customs importers'!$K$6:$K$1507)<1502),"",IF(AND(E15=_check!$B$108,F15=_check!$B$109,G15=_check!$B$110),"✓","✗"))
A16: I04 | B16: IMP00340 | C16: T102376 | H16: =IFERROR(VLOOKUP(A16,'S2 Four lists'!$A$17:$N$41,8,FALSE),"") | I16: =IFERROR(VLOOKUP(A16,'S2 Four lists'!$A$17:$N$41,14,FALSE),"") | O16: =IF(OR(COUNT(E16:G16)<3,COUNTA('Customs importers'!$K$6:$K$1507)<1502),"",IF(AND(E16=_check!$B$111,F16=_check!$B$112,G16=_check!$B$113),"✓","✗"))
A17: I05 | B17: IMP00999 | C17: T106987 | H17: =IFERROR(VLOOKUP(A17,'S2 Four lists'!$A$17:$N$41,8,FALSE),"") | I17: =IFERROR(VLOOKUP(A17,'S2 Four lists'!$A$17:$N$41,14,FALSE),"") | O17: =IF(OR(COUNT(E17:G17)<3,COUNTA('Customs importers'!$K$6:$K$1507)<1502),"",IF(AND(E17=_check!$B$114,F17=_check!$B$115,G17=_check!$B$116),"✓","✗"))
A18: I06 | B18: IMP01037 | C18: T107258 | H18: =IFERROR(VLOOKUP(A18,'S2 Four lists'!$A$17:$N$41,8,FALSE),"") | I18: =IFERROR(VLOOKUP(A18,'S2 Four lists'!$A$17:$N$41,14,FALSE),"") | O18: =IF(OR(COUNT(E18:G18)<3,COUNTA('Customs importers'!$K$6:$K$1507)<1502),"",IF(AND(E18=_check!$B$117,F18=_check!$B$118,G18=_check!$B$119),"✓","✗"))
A19: I07 | B19: IMP00306 | C19: T102141 | H19: =IFERROR(VLOOKUP(A19,'S2 Four lists'!$A$17:$N$41,8,FALSE),"") | I19: =IFERROR(VLOOKUP(A19,'S2 Four lists'!$A$17:$N$41,14,FALSE),"") | O19: =IF(OR(COUNT(E19:G19)<3,COUNTA('Customs importers'!$K$6:$K$1507)<1502),"",IF(AND(E19=_check!$B$120,F19=_check!$B$121,G19=_check!$B$122),"✓","✗"))
A20: I10 | B20: IMP00448 | C20: T103130 | H20: =IFERROR(VLOOKUP(A20,'S2 Four lists'!$A$17:$N$41,8,FALSE),"") | I20: =IFERROR(VLOOKUP(A20,'S2 Four lists'!$A$17:$N$41,14,FALSE),"") | O20: =IF(OR(COUNT(E20:G20)<3,COUNTA('Customs importers'!$K$6:$K$1507)<1502),"",IF(AND(E20=_check!$B$123,F20=_check!$B$124,G20=_check!$B$125),"✓","✗"))
A21: I11 | B21: IMP00005 | C21: T100033 | H21: =IFERROR(VLOOKUP(A21,'S2 Four lists'!$A$17:$N$41,8,FALSE),"") | I21: =IFERROR(VLOOKUP(A21,'S2 Four lists'!$A$17:$N$41,14,FALSE),"") | O21: =IF(OR(COUNT(E21:G21)<3,COUNTA('Customs importers'!$K$6:$K$1507)<1502),"",IF(AND(E21=_check!$B$126,F21=_check!$B$127,G21=_check!$B$128),"✓","✗"))
A22: I14 | B22: IMP01242 | C22: T108692 | H22: =IFERROR(VLOOKUP(A22,'S2 Four lists'!$A$17:$N$41,8,FALSE),"") | I22: =IFERROR(VLOOKUP(A22,'S2 Four lists'!$A$17:$N$41,14,FALSE),"") | O22: =IF(OR(COUNT(E22:G22)<3,COUNTA('Customs importers'!$K$6:$K$1507)<1502),"",IF(AND(E22=_check!$B$129,F22=_check!$B$130,G22=_check!$B$131),"✓","✗"))
A23: I15 | B23: IMP00011 | C23: T100070 | H23: =IFERROR(VLOOKUP(A23,'S2 Four lists'!$A$17:$N$41,8,FALSE),"") | I23: =IFERROR(VLOOKUP(A23,'S2 Four lists'!$A$17:$N$41,14,FALSE),"") | O23: =IF(OR(COUNT(E23:G23)<3,COUNTA('Customs importers'!$K$6:$K$1507)<1502),"",IF(AND(E23=_check!$B$132,F23=_check!$B$133,G23=_check!$B$134),"✓","✗"))
A24: I16 | B24: IMP01089 | C24: T107617 | H24: =IFERROR(VLOOKUP(A24,'S2 Four lists'!$A$17:$N$41,8,FALSE),"") | I24: =IFERROR(VLOOKUP(A24,'S2 Four lists'!$A$17:$N$41,14,FALSE),"") | O24: =IF(OR(COUNT(E24:G24)<3,COUNTA('Customs importers'!$K$6:$K$1507)<1502),"",IF(AND(E24=_check!$B$135,F24=_check!$B$136,G24=_check!$B$137),"✓","✗"))
A25: I18 | B25: IMP01142 | C25: T107992 | H25: =IFERROR(VLOOKUP(A25,'S2 Four lists'!$A$17:$N$41,8,FALSE),"") | I25: =IFERROR(VLOOKUP(A25,'S2 Four lists'!$A$17:$N$41,14,FALSE),"") | O25: =IF(OR(COUNT(E25:G25)<3,COUNTA('Customs importers'!$K$6:$K$1507)<1502),"",IF(AND(E25=_check!$B$138,F25=_check!$B$139,G25=_check!$B$140),"✓","✗"))
A26: I19 | B26: IMP01310 | C26: T109167 | H26: =IFERROR(VLOOKUP(A26,'S2 Four lists'!$A$17:$N$41,8,FALSE),"") | I26: =IFERROR(VLOOKUP(A26,'S2 Four lists'!$A$17:$N$41,14,FALSE),"") | O26: =IF(OR(COUNT(E26:G26)<3,COUNTA('Customs importers'!$K$6:$K$1507)<1502),"",IF(AND(E26=_check!$B$141,F26=_check!$B$142,G26=_check!$B$143),"✓","✗"))
A27: I20 | B27: IMP00490 | C27: T103425 | H27: =IFERROR(VLOOKUP(A27,'S2 Four lists'!$A$17:$N$41,8,FALSE),"") | I27: =IFERROR(VLOOKUP(A27,'S2 Four lists'!$A$17:$N$41,14,FALSE),"") | O27: =IF(OR(COUNT(E27:G27)<3,COUNTA('Customs importers'!$K$6:$K$1507)<1502),"",IF(AND(E27=_check!$B$144,F27=_check!$B$145,G27=_check!$B$146),"✓","✗"))
A28: I21 | B28: IMP00063 | C28: T100440 | H28: =IFERROR(VLOOKUP(A28,'S2 Four lists'!$A$17:$N$41,8,FALSE),"") | I28: =IFERROR(VLOOKUP(A28,'S2 Four lists'!$A$17:$N$41,14,FALSE),"") | O28: =IF(OR(COUNT(E28:G28)<3,COUNTA('Customs importers'!$K$6:$K$1507)<1502),"",IF(AND(E28=_check!$B$147,F28=_check!$B$148,G28=_check!$B$149),"✓","✗"))
A29: I22 | B29: IMP00926 | C29: T106477 | H29: =IFERROR(VLOOKUP(A29,'S2 Four lists'!$A$17:$N$41,8,FALSE),"") | I29: =IFERROR(VLOOKUP(A29,'S2 Four lists'!$A$17:$N$41,14,FALSE),"") | O29: =IF(OR(COUNT(E29:G29)<3,COUNTA('Customs importers'!$K$6:$K$1507)<1502),"",IF(AND(E29=_check!$B$150,F29=_check!$B$151,G29=_check!$B$152),"✓","✗"))
A30: I23 | B30: IMP00643 | C30: T104498 | H30: =IFERROR(VLOOKUP(A30,'S2 Four lists'!$A$17:$N$41,8,FALSE),"") | I30: =IFERROR(VLOOKUP(A30,'S2 Four lists'!$A$17:$N$41,14,FALSE),"") | O30: =IF(OR(COUNT(E30:G30)<3,COUNTA('Customs importers'!$K$6:$K$1507)<1502),"",IF(AND(E30=_check!$B$153,F30=_check!$B$154,G30=_check!$B$155),"✓","✗"))
A31: I24 | B31: IMP00067 | C31: T100466 | H31: =IFERROR(VLOOKUP(A31,'S2 Four lists'!$A$17:$N$41,8,FALSE),"") | I31: =IFERROR(VLOOKUP(A31,'S2 Four lists'!$A$17:$N$41,14,FALSE),"") | O31: =IF(OR(COUNT(E31:G31)<3,COUNTA('Customs importers'!$K$6:$K$1507)<1502),"",IF(AND(E31=_check!$B$156,F31=_check!$B$157,G31=_check!$B$158),"✓","✗"))
A32: I25 | B32: IMP00288 | C32: T102011 | H32: =IFERROR(VLOOKUP(A32,'S2 Four lists'!$A$17:$N$41,8,FALSE),"") | I32: =IFERROR(VLOOKUP(A32,'S2 Four lists'!$A$17:$N$41,14,FALSE),"") | O32: =IF(OR(COUNT(E32:G32)<3,COUNTA('Customs importers'!$K$6:$K$1507)<1502),"",IF(AND(E32=_check!$B$159,F32=_check!$B$160,G32=_check!$B$161),"✓","✗"))
A34: The five importers with no tax number have no row here: nothing clears under a number they do not have. Spreading risk through shared links is a reason to ask, never a finding.

Sheet S4 Tax feeds customs
A1: Sprint 4 · results from tax feed customs: does a tax adjustment point to customs findings?
A2: Item 6 of the joint action: outcomes sent back, and used in the other agency's targeting. Tax audited a random sample of the tax numbers that clear imports, on the VAT periods 2024-10 to 2025-09, all completed before customs month 25. Customs controlled its own random draw in months 25 to 36. Join the two, and compare.
A6: Step | B6: What to do | H6: Your answer | I6: Check | J6: Hint 1 · the tool (the full formula is on the Hints sheet)
A7: 1 | B7: The tax audits (left): keep the random ones; column G, 1 when the audit found an adjustment. Then: how many random audits found an adjustment? | I7: =IF(H7="","",IF(ISNUMBER(H7),IF(ABS(H7-_check!$B$162)<=0.5,"✓ matches","✗ not yet: see the hint"),"✗ not yet: see the hint")) | J7: COUNTIFS on the selection basis and the outcome.
A8: 2 | B8: The customs random draw (right): column P, the tax result of the line's number: 1 adjustment, 0 audited with none, blank when not audited at random. | J8: COUNTIFS on the audit table by tax number.
A9: 3 | B9: The customs hit rate on lines whose number had a tax adjustment, and on lines whose number was audited with none. Then: the lift (the first ÷ the second). | I9: =IF(H9="","",IF(ISNUMBER(H9),IF(ABS(H9-_check!$B$163)<=0.01,"✓ matches","✗ not yet: see the hint"),"✗ not yet: see the hint")) | J9: COUNTIFS on the tax result and found = 1, divided by COUNTIFS on the tax result.
A10: 4 | B10: How many lines stand behind each rate? Write the joint action's item 6 from it: what customs asks tax to send back, how often, and how it enters the targeting. | J10: Fewer than 100 lines on a side is a small sample: say so beside the number.
A16: Lines with a tax adjustment: 256; with an audit and none: 1158. A rate on fewer than 100 lines can move a lot: give its range with it.
A20: audit | B20: tax ID | C20: selection basis | D20: selected on | E20: completed on | F20: audit type | G20: adjustment (1/0) | H20: outcome | I20: finding type | J20: tax assessed (LCU) | L20: line | M20: tax number used to clear | N20: month | O20: found (1/0) | P20: tax result (1/0)
A21: AUD00001 | B21: T100013 | C21: random | D21: 2025-01-15 | E21: 2025-08-02 | F21: field | G21: =IF(H21="adjustment",1,0) | H21: no adjustment | J21: 0 | L21: L0239440 | M21: T100052 | N21: 35 | O21: 0 | P21: =IF(COUNTIFS($B$21:$B$304,M21,$C$21:$C$304,"random")=0,"",IF(COUNTIFS($B$21:$B$304,M21,$C$21:$C$304,"random",$H$21:$H$304,"adjustment")>0,1,0))
A22: AUD00002 | B22: T100052 | C22: random | D22: 2025-01-15 | E22: 2025-02-21 | F22: desk | G22: =IF(H22="adjustment",1,0) | H22: no adjustment | J22: 0 | L22: L0171519 | M22: T100070 | N22: 25 | O22: 0 | P22: =IF(COUNTIFS($B$21:$B$304,M22,$C$21:$C$304,"random")=0,"",IF(COUNTIFS($B$21:$B$304,M22,$C$21:$C$304,"random",$H$21:$H$304,"adjustment")>0,1,0))
A23: AUD00003 | B23: T100056 | C23: random | D23: 2025-01-15 | E23: 2025-03-18 | F23: desk | G23: =IF(H23="adjustment",1,0) | H23: no adjustment | J23: 0 | L23: L0172344 | M23: T100070 | N23: 25 | O23: 0 | P23: =IF(COUNTIFS($B$21:$B$304,M23,$C$21:$C$304,"random")=0,"",IF(COUNTIFS($B$21:$B$304,M23,$C$21:$C$304,"random",$H$21:$H$304,"adjustment")>0,1,0))
A24: AUD00004 | B24: T100070 | C24: random | D24: 2025-01-15 | E24: 2025-06-04 | F24: desk | G24: =IF(H24="adjustment",1,0) | H24: adjustment | I24: a number lent to others | J24: 33298528 | L24: L0175019 | M24: T100070 | N24: 26 | O24: 0 | P24: =IF(COUNTIFS($B$21:$B$304,M24,$C$21:$C$304,"random")=0,"",IF(COUNTIFS($B$21:$B$304,M24,$C$21:$C$304,"random",$H$21:$H$304,"adjustment")>0,1,0))
A25: AUD00005 | B25: T100082 | C25: random | D25: 2025-01-15 | E25: 2025-02-20 | F25: desk | G25: =IF(H25="adjustment",1,0) | H25: adjustment | I25: sales not declared | J25: 669545 | L25: L0175329 | M25: T100070 | N25: 26 | O25: 0 | P25: =IF(COUNTIFS($B$21:$B$304,M25,$C$21:$C$304,"random")=0,"",IF(COUNTIFS($B$21:$B$304,M25,$C$21:$C$304,"random",$H$21:$H$304,"adjustment")>0,1,0))
A26: AUD00006 | B26: T100152 | C26: random | D26: 2025-01-15 | E26: 2025-04-27 | F26: desk | H26: no adjustment | J26: 0 | L26: L0181983 | M26: T100070 | N26: 27 | O26: 0
A27: AUD00007 | B27: T100165 | C27: random | D27: 2025-01-15 | E27: 2025-03-22 | F27: desk | H27: no adjustment | J27: 0 | L27: L0223288 | M27: T100070 | N27: 33 | O27: 0
A28: AUD00008 | B28: T100193 | C28: random | D28: 2025-01-15 | E28: 2025-05-16 | F28: field | H28: adjustment | I28: sales not declared | J28: 5916409 | L28: L0224650 | M28: T100070 | N28: 33 | O28: 0
A29: AUD00009 | B29: T100201 | C29: random | D29: 2025-01-15 | E29: 2025-04-18 | F29: desk | H29: no adjustment | J29: 0 | L29: L0225407 | M29: T100070 | N29: 33 | O29: 0
A30: AUD00010 | B30: T100260 | C30: random | D30: 2025-01-15 | E30: 2025-08-01 | F30: field | H30: adjustment | I30: sales not declared | J30: 2251836 | L30: L0237563 | M30: T100070 | N30: 35 | O30: 0
A31: AUD00011 | B31: T100374 | C31: random | D31: 2025-01-15 | E31: 2025-05-25 | F31: field | H31: adjustment | I31: sales not declared | J31: 432395 | L31: L0243729 | M31: T100070 | N31: 35 | O31: 1
A32: AUD00012 | B32: T100466 | C32: random | D32: 2025-01-15 | E32: 2025-04-29 | F32: desk | H32: no adjustment | J32: 0 | L32: L0244223 | M32: T100070 | N32: 36 | O32: 0
A33: AUD00013 | B33: T100476 | C33: random | D33: 2025-01-15 | E33: 2025-05-26 | F33: desk | H33: no adjustment | J33: 0 | L33: L0249893 | M33: T100070 | N33: 36 | O33: 0
A34: AUD00014 | B34: T100497 | C34: random | D34: 2025-01-15 | E34: 2025-05-26 | F34: desk | H34: no adjustment | J34: 0 | L34: L0219221 | M34: T100082 | N34: 32 | O34: 0
A35: AUD00015 | B35: T100510 | C35: random | D35: 2025-01-15 | E35: 2025-06-12 | F35: desk | H35: no adjustment | J35: 0 | L35: L0171963 | M35: T100152 | N35: 25 | O35: 0
A36: AUD00016 | B36: T100538 | C36: random | D36: 2025-01-15 | E36: 2025-05-03 | F36: desk | H36: no adjustment | J36: 0 | L36: L0201493 | M36: T100152 | N36: 30 | O36: 0
A37: AUD00017 | B37: T100614 | C37: random | D37: 2025-01-15 | E37: 2025-03-10 | F37: desk | H37: no adjustment | J37: 0 | L37: L0210996 | M37: T100152 | N37: 31 | O37: 0
A38: AUD00018 | B38: T100631 | C38: random | D38: 2025-01-15 | E38: 2025-09-07 | F38: field | H38: no adjustment | J38: 0 | L38: L0226660 | M38: T100152 | N38: 33 | O38: 0
A39: AUD00019 | B39: T100680 | C39: random | D39: 2025-01-15 | E39: 2025-03-21 | F39: desk | H39: no adjustment | J39: 0 | L39: L0166948 | M39: T100165 | N39: 25 | O39: 0
A40: AUD00020 | B40: T100699 | C40: random | D40: 2025-01-15 | E40: 2025-07-30 | F40: field | H40: adjustment | I40: sales not declared | J40: 2693976 | L40: L0224827 | M40: T100165 | N40: 33 | O40: 0
A41: AUD00021 | B41: T100705 | C41: random | D41: 2025-01-15 | E41: 2025-04-17 | F41: desk | H41: no adjustment | J41: 0 | L41: L0196483 | M41: T100193 | N41: 29 | O41: 0
A42: AUD00022 | B42: T100720 | C42: random | D42: 2025-01-15 | E42: 2025-05-29 | F42: desk | H42: adjustment | I42: sales not declared | J42: 7429383 | L42: L0169084 | M42: T100201 | N42: 25 | O42: 0
A43: AUD00023 | B43: T100729 | C43: random | D43: 2025-01-15 | E43: 2025-04-20 | F43: desk | H43: no adjustment | J43: 0 | L43: L0173944 | M43: T100260 | N43: 26 | O43: 0
A44: AUD00024 | B44: T100741 | C44: random | D44: 2025-01-15 | E44: 2025-04-01 | F44: desk | H44: no adjustment | J44: 0 | L44: L0177527 | M44: T100260 | N44: 26 | O44: 0
A45: AUD00025 | B45: T100758 | C45: random | D45: 2025-01-15 | E45: 2025-08-11 | F45: field | H45: no adjustment | J45: 0 | L45: L0181755 | M45: T100260 | N45: 27 | O45: 0
A46: AUD00026 | B46: T100781 | C46: random | D46: 2025-01-15 | E46: 2025-06-08 | F46: field | H46: adjustment | I46: sales not declared | J46: 3843901 | L46: L0204909 | M46: T100260 | N46: 30 | O46: 0
A47: AUD00027 | B47: T100799 | C47: random | D47: 2025-01-15 | E47: 2025-03-25 | F47: desk | H47: no adjustment | J47: 0 | L47: L0211000 | M47: T100260 | N47: 31 | O47: 0
A48: AUD00028 | B48: T100811 | C48: random | D48: 2025-01-15 | E48: 2025-08-23 | F48: field | H48: no adjustment | J48: 0 | L48: L0215113 | M48: T100260 | N48: 32 | O48: 0
A49: AUD00029 | B49: T100861 | C49: random | D49: 2025-01-15 | E49: 2025-03-25 | F49: desk | H49: no adjustment | J49: 0 | L49: L0240644 | M49: T100260 | N49: 35 | O49: 0
A50: AUD00030 | B50: T100870 | C50: random | D50: 2025-01-15 | E50: 2025-03-15 | F50: desk | H50: no adjustment | J50: 0 | L50: L0168457 | M50: T100466 | N50: 25 | O50: 0
A51: AUD00031 | B51: T100957 | C51: random | D51: 2025-01-15 | E51: 2025-08-25 | F51: field | H51: no adjustment | J51: 0 | L51: L0186176 | M51: T100466 | N51: 28 | O51: 0
A52: AUD00032 | B52: T100987 | C52: random | D52: 2025-01-15 | E52: 2025-07-18 | F52: field | H52: no adjustment | J52: 0 | L52: L0190780 | M52: T100466 | N52: 28 | O52: 0
A53: AUD00033 | B53: T101036 | C53: random | D53: 2025-01-15 | E53: 2025-03-23 | F53: desk | H53: no adjustment | J53: 0 | L53: L0195213 | M53: T100466 | N53: 29 | O53: 0
A54: AUD00034 | B54: T101148 | C54: random | D54: 2025-01-15 | E54: 2025-03-02 | F54: desk | H54: no adjustment | J54: 0 | L54: L0204162 | M54: T100466 | N54: 30 | O54: 0
A55: AUD00035 | B55: T101160 | C55: random | D55: 2025-01-15 | E55: 2025-07-14 | F55: field | H55: no adjustment | J55: 0 | L55: L0206575 | M55: T100466 | N55: 30 | O55: 0
A56: AUD00036 | B56: T101178 | C56: random | D56: 2025-01-15 | E56: 2025-07-08 | F56: field | H56: adjustment | I56: sales not declared | J56: 47262 | L56: L0209645 | M56: T100466 | N56: 31 | O56: 0
A57: AUD00037 | B57: T101202 | C57: random | D57: 2025-01-15 | E57: 2025-04-28 | F57: desk | H57: no adjustment | J57: 0 | L57: L0211020 | M57: T100466 | N57: 31 | O57: 0
A58: AUD00038 | B58: T101224 | C58: random | D58: 2025-01-15 | E58: 2025-03-17 | F58: desk | H58: no adjustment | J58: 0 | L58: L0211836 | M58: T100466 | N58: 31 | O58: 0
A59: AUD00039 | B59: T101250 | C59: random | D59: 2025-01-15 | E59: 2025-08-12 | F59: field | H59: no adjustment | J59: 0 | L59: L0236120 | M59: T100466 | N59: 34 | O59: 0
A60: AUD00040 | B60: T101362 | C60: random | D60: 2025-01-15 | E60: 2025-06-09 | F60: field | H60: no adjustment | J60: 0 | L60: L0241094 | M60: T100466 | N60: 35 | O60: 0
A61: AUD00041 | B61: T101426 | C61: random | D61: 2025-01-15 | E61: 2025-05-25 | F61: field | H61: no adjustment | J61: 0 | L61: L0170202 | M61: T100476 | N61: 25 | O61: 0
A62: AUD00042 | B62: T101451 | C62: random | D62: 2025-01-15 | E62: 2025-04-03 | F62: desk | H62: adjustment | I62: sales not declared | J62: 852176 | L62: L0177979 | M62: T100476 | N62: 26 | O62: 0
A63: AUD00043 | B63: T101458 | C63: random | D63: 2025-01-15 | E63: 2025-05-22 | F63: desk | H63: no adjustment | J63: 0 | L63: L0204671 | M63: T100476 | N63: 30 | O63: 0
A64: AUD00044 | B64: T101459 | C64: random | D64: 2025-01-15 | E64: 2025-03-17 | F64: desk | H64: no adjustment | J64: 0 | L64: L0206301 | M64: T100476 | N64: 30 | O64: 0
A65: AUD00045 | B65: T101550 | C65: random | D65: 2025-01-15 | E65: 2025-02-23 | F65: desk | H65: no adjustment | J65: 0 | L65: L0211321 | M65: T100476 | N65: 31 | O65: 0
A66: AUD00046 | B66: T101562 | C66: random | D66: 2025-01-15 | E66: 2025-06-08 | F66: desk | H66: no adjustment | J66: 0 | L66: L0217633 | M66: T100476 | N66: 32 | O66: 0
A67: AUD00047 | B67: T101651 | C67: random | D67: 2025-01-15 | E67: 2025-06-05 | F67: desk | H67: no adjustment | J67: 0 | L67: L0220039 | M67: T100476 | N67: 32 | O67: 0
A68: AUD00048 | B68: T101656 | C68: random | D68: 2025-01-15 | E68: 2025-04-11 | F68: desk | H68: no adjustment | J68: 0 | L68: L0227989 | M68: T100476 | N68: 33 | O68: 0
A69: AUD00049 | B69: T101660 | C69: random | D69: 2025-01-15 | E69: 2025-03-15 | F69: desk | H69: no adjustment | J69: 0 | L69: L0237360 | M69: T100476 | N69: 35 | O69: 0
A70: AUD00050 | B70: T101683 | C70: random | D70: 2025-01-15 | E70: 2025-03-08 | F70: desk | H70: no adjustment | J70: 0 | L70: L0244470 | M70: T100476 | N70: 36 | O70: 0
A71: AUD00051 | B71: T101700 | C71: random | D71: 2025-01-15 | E71: 2025-07-24 | F71: field | H71: no adjustment | J71: 0 | L71: L0246998 | M71: T100476 | N71: 36 | O71: 0
A72: AUD00052 | B72: T101824 | C72: random | D72: 2025-01-15 | E72: 2025-05-27 | F72: desk | H72: no adjustment | J72: 0 | L72: L0173700 | M72: T100497 | N72: 26 | O72: 0
A73: AUD00053 | B73: T101828 | C73: random | D73: 2025-01-15 | E73: 2025-06-07 | F73: field | H73: no adjustment | J73: 0 | L73: L0185411 | M73: T100497 | N73: 28 | O73: 0
A74: AUD00054 | B74: T101861 | C74: random | D74: 2025-01-15 | E74: 2025-03-19 | F74: desk | H74: no adjustment | J74: 0 | L74: L0191320 | M74: T100497 | N74: 28 | O74: 0
A75: AUD00055 | B75: T101970 | C75: random | D75: 2025-01-15 | E75: 2025-06-11 | F75: desk | H75: adjustment | I75: sales not declared | J75: 103007 | L75: L0223229 | M75: T100497 | N75: 33 | O75: 0
A76: AUD00056 | B76: T101983 | C76: random | D76: 2025-01-15 | E76: 2025-07-09 | F76: field | H76: no adjustment | J76: 0 | L76: L0236892 | M76: T100497 | N76: 34 | O76: 0
A77: AUD00057 | B77: T102074 | C77: random | D77: 2025-01-15 | E77: 2025-07-13 | F77: field | H77: no adjustment | J77: 0 | L77: L0171970 | M77: T100538 | N77: 25 | O77: 0
A78: AUD00058 | B78: T102096 | C78: random | D78: 2025-01-15 | E78: 2025-05-09 | F78: field | H78: no adjustment | J78: 0 | L78: L0177739 | M78: T100538 | N78: 26 | O78: 0
A79: AUD00059 | B79: T102294 | C79: random | D79: 2025-01-15 | E79: 2025-05-15 | F79: desk | H79: adjustment | I79: sales not declared | J79: 115812 | L79: L0179630 | M79: T100538 | N79: 27 | O79: 0
A80: AUD00060 | B80: T102357 | C80: random | D80: 2025-01-15 | E80: 2025-04-28 | F80: desk | H80: no adjustment | J80: 0 | L80: L0182916 | M80: T100538 | N80: 27 | O80: 0
A81: AUD00061 | B81: T102414 | C81: random | D81: 2025-01-15 | E81: 2025-05-25 | F81: desk | H81: no adjustment | J81: 0 | L81: L0184747 | M81: T100538 | N81: 27 | O81: 0
A82: AUD00062 | B82: T102469 | C82: random | D82: 2025-01-15 | E82: 2025-03-02 | F82: desk | H82: no adjustment | J82: 0 | L82: L0188248 | M82: T100538 | N82: 28 | O82: 0
A83: AUD00063 | B83: T102516 | C83: random | D83: 2025-01-15 | E83: 2025-04-17 | F83: desk | H83: no adjustment | J83: 0 | L83: L0188744 | M83: T100538 | N83: 28 | O83: 1
A84: AUD00064 | B84: T102520 | C84: random | D84: 2025-01-15 | E84: 2025-05-04 | F84: desk | H84: no adjustment | J84: 0 | L84: L0200432 | M84: T100538 | N84: 30 | O84: 0
A85: AUD00065 | B85: T102531 | C85: random | D85: 2025-01-15 | E85: 2025-07-05 | F85: field | H85: adjustment | I85: sales not declared | J85: 2987987 | L85: L0202568 | M85: T100538 | N85: 30 | O85: 0
A86: AUD00066 | B86: T102616 | C86: random | D86: 2025-01-15 | E86: 2025-08-11 | F86: field | H86: no adjustment | J86: 0 | L86: L0206021 | M86: T100538 | N86: 30 | O86: 1
A87: AUD00067 | B87: T102643 | C87: random | D87: 2025-01-15 | E87: 2025-04-18 | F87: desk | H87: adjustment | I87: sales not declared | J87: 148577 | L87: L0209118 | M87: T100538 | N87: 31 | O87: 0
A88: AUD00068 | B88: T102647 | C88: random | D88: 2025-01-15 | E88: 2025-06-01 | F88: field | H88: no adjustment | J88: 0 | L88: L0209394 | M88: T100538 | N88: 31 | O88: 0
A89: AUD00069 | B89: T102705 | C89: random | D89: 2025-01-15 | E89: 2025-06-14 | F89: field | H89: adjustment | I89: sales not declared | J89: 320740 | L89: L0212899 | M89: T100538 | N89: 31 | O89: 0
A90: AUD00070 | B90: T102740 | C90: random | D90: 2025-01-15 | E90: 2025-08-11 | F90: field | H90: no adjustment | J90: 0 | L90: L0216214 | M90: T100538 | N90: 32 | O90: 0
A91: AUD00071 | B91: T102784 | C91: random | D91: 2025-01-15 | E91: 2025-06-20 | F91: field | H91: adjustment | I91: sales not declared | J91: 536590 | L91: L0219772 | M91: T100538 | N91: 32 | O91: 0
A92: AUD00072 | B92: T103006 | C92: random | D92: 2025-01-15 | E92: 2025-06-09 | F92: desk | H92: adjustment | I92: sales not declared | J92: 118848 | L92: L0222226 | M92: T100538 | N92: 32 | O92: 0
A93: AUD00073 | B93: T103045 | C93: random | D93: 2025-01-15 | E93: 2025-02-17 | F93: desk | H93: no adjustment | J93: 0 | L93: L0231810 | M93: T100538 | N93: 34 | O93: 0
A94: AUD00074 | B94: T103082 | C94: random | D94: 2025-01-15 | E94: 2025-06-03 | F94: desk | H94: no adjustment | J94: 0 | L94: L0243989 | M94: T100538 | N94: 36 | O94: 0
A95: AUD00075 | B95: T103111 | C95: random | D95: 2025-01-15 | E95: 2025-05-24 | F95: field | H95: no adjustment | J95: 0 | L95: L0243990 | M95: T100538 | N95: 36 | O95: 0
A96: AUD00076 | B96: T103125 | C96: random | D96: 2025-01-15 | E96: 2025-03-02 | F96: desk | H96: no adjustment | J96: 0 | L96: L0244233 | M96: T100538 | N96: 36 | O96: 0
A97: AUD00077 | B97: T103173 | C97: random | D97: 2025-01-15 | E97: 2025-03-23 | F97: desk | H97: adjustment | I97: sales not declared | J97: 2213128 | L97: L0194918 | M97: T100631 | N97: 29 | O97: 0
A98: AUD00078 | B98: T103192 | C98: random | D98: 2025-01-15 | E98: 2025-05-16 | F98: desk | H98: adjustment | I98: sales not declared | J98: 1164804 | L98: L0198879 | M98: T100631 | N98: 29 | O98: 0
A99: AUD00079 | B99: T103274 | C99: random | D99: 2025-01-15 | E99: 2025-04-19 | F99: desk | H99: no adjustment | J99: 0 | L99: L0191062 | M99: T100680 | N99: 28 | O99: 0
A100: AUD00080 | B100: T103377 | C100: random | D100: 2025-01-15 | E100: 2025-08-26 | F100: field | H100: no adjustment | J100: 0 | L100: L0216495 | M100: T100680 | N100: 32 | O100: 0
A101: AUD00081 | B101: T103391 | C101: random | D101: 2025-01-15 | E101: 2025-05-27 | F101: desk | H101: no adjustment | J101: 0 | L101: L0221089 | M101: T100680 | N101: 32 | O101: 0
A102: AUD00082 | B102: T103425 | C102: random | D102: 2025-01-15 | E102: 2025-04-16 | F102: field | H102: no adjustment | J102: 0 | L102: L0229867 | M102: T100680 | N102: 33 | O102: 0
A103: AUD00083 | B103: T103507 | C103: random | D103: 2025-01-15 | E103: 2025-03-11 | F103: desk | H103: no adjustment | J103: 0 | L103: L0230348 | M103: T100680 | N103: 34 | O103: 0
A104: AUD00084 | B104: T103555 | C104: random | D104: 2025-01-15 | E104: 2025-08-18 | F104: field | H104: no adjustment | J104: 0 | L104: L0244236 | M104: T100680 | N104: 36 | O104: 0
A105: AUD00085 | B105: T103567 | C105: random | D105: 2025-01-15 | E105: 2025-02-20 | F105: desk | H105: no adjustment | J105: 0 | L105: L0247880 | M105: T100680 | N105: 36 | O105: 0
A106: AUD00086 | B106: T103572 | C106: random | D106: 2025-01-15 | E106: 2025-03-24 | F106: desk | H106: no adjustment | J106: 0 | L106: L0166962 | M106: T100699 | N106: 25 | O106: 0
A107: AUD00087 | B107: T103667 | C107: random | D107: 2025-01-15 | E107: 2025-04-28 | F107: desk | H107: no adjustment | J107: 0 | L107: L0169544 | M107: T100699 | N107: 25 | O107: 0
A108: AUD00088 | B108: T103761 | C108: random | D108: 2025-01-15 | E108: 2025-05-17 | F108: field | H108: no adjustment | J108: 0 | L108: L0171109 | M108: T100699 | N108: 25 | O108: 0
A109: AUD00089 | B109: T103835 | C109: random | D109: 2025-01-15 | E109: 2025-03-27 | F109: desk | H109: no adjustment | J109: 0 | L109: L0174627 | M109: T100699 | N109: 26 | O109: 0
A110: AUD00090 | B110: T103855 | C110: random | D110: 2025-01-15 | E110: 2025-04-15 | F110: field | H110: no adjustment | J110: 0 | L110: L0175562 | M110: T100699 | N110: 26 | O110: 0
... A119: AUD00099 | B119: T104345 | C119: random | D119: 2025-01-15 | E119: 2025-05-16 | F119: desk | H119: no adjustment | J119: 0 | L119: L0195975 | M119: T100699 | N119: 29 | O119: 0
...

Sheet Joint action
A1: Sprint 4 · the joint action: Breakout 4A's seven items, written from the customs side
A2: Written against your lists (S2) and networks (S3). A lock without an owner in each agency, or without a window and a held-out group, is not an action.
A4: 1 · One risk, one population (how many importers, how much VAT at stake)
A5: 2 · The key between the two (the tax number, or your matching rule and who checks the middle band)
A6: 3 · Explainable reasons (the check that put each trader on the list)
A7: 4 · A repeatable data flow (what customs sends, how often)
A8: 5 · An owner in each agency (by name)
A9: 6 · Outcomes sent back (registered? audited? amount assessed? and how customs uses them: S4)
A10: 7 · A window and a test (4 to 12 weeks, a group held out at random, the number read at the end)

Sheet Fields
A1: Fields · what every column means
A2: Purple columns are computed for you (a helper): the line says how. Everything else is as recorded, or yours to compute.
A4: sheet | B4: column | C4: what it means
A5: S1 Match | B5: best candidate (tax ID, legal name, address, director) | C5: the tax register's record most like the customs record, found by a search on cleaned name and address: the candidate, not a match.
A6: S1 Match | B6: name · address · director similarity (computed for you) | C6: how alike the two strings are once cleaned (lower case, punctuation and legal suffixes out, Rd to Road): 0 nothing in common, 1 the same. Empty when one side has no value.
A7: S1 Match | B7: phone match (computed for you) | C7: 1 when both sides hold the same number, digits only.
A8: Lines 12m | B8: tax number used to clear | C8: the tax identifier typed on the declaration; blank when none was given.
A9: Returns | B9: import VAT deducted | C9: the import VAT the trader deducts on its return: VAT it paid at the border and takes back.
A10: Sectors | B10: usual sales ÷ imports (computed for you) | C10: the median of sales ÷ imports in the sector, over the numbers both sides know that filed at least 10 of their last 12 returns.
A11: Customs importers | B11: first address · first broker under the number (yours) | C11: 1 on the first row where an address (or a default broker) appears under a tax number, counting from the top; their sum per number is the count of distinct addresses (or brokers).
A12: S3 Network | B12: consignees | C12: every party clearing under the number: the other importer codes declaring under it, plus the importer's own consignee records.
A13: S4 Tax feeds customs | B13: selection basis | C13: random: drawn at random before any list, to measure; targeted: chosen for a reason (a refund claim, third-party information, a customs referral), so it cannot measure.
A14: S4 Tax feeds customs | B14: found (customs) | C14: 1 when the customs control of the random-draw line found an irregularity.

Sheet Hints
A1: Hints · the full formula for every step (open only when stuck)
A2: Type the formula exactly as written, starting with =. Cell addresses are those of the sheet in column A. A $ sign keeps a cell fixed when you copy the formula down.
A4: sheet | B4: step | C4: what to do | D4: hint 1 · the tool | E4: hint 2 · the formula
A5: S1 Match | B5: 1 | C5: Column K: does the tax number on the declaration exist in the tax register, as typed? "matched", "not in the register" or "blank". Then: how many rows match exactly? | D5: COUNTIF counts the number in the register's tax ID column; IF turns the count into a word. | E5: In K17: =IF(C17="","blank",IF(COUNTIF('Tax register'!$A$5:$A$1803,C17)>0,"matched","not in the register")) Here: =COUNTIF(K16:K40,"matched")
A6: S1 Match | B6: 2 | C6: Column P: the match confidence: name × 0.4 + address × 0.3 + director × 0.3, a missing field left out and the weights rescaled over the fields present. Then: I17's confidence. | D6: N() turns an empty cell into 0; ISNUMBER says which fields are present, so the division rescales the weights. | E6: In P17: =IF(COUNT(L17:N17)=0,0,(Parameters!$B$5*N(L17)+Parameters!$B$6*N(M17)+Parameters!$B$7*N(N17))/(Parameters!$B$5*ISNUMBER(L17)+Parameters!$B$6*ISNUMBER(M17)+Parameters!$B$7*ISNUMBER(N17)))
A7: S1 Match | B7: 3 | C7: Column Q: the class at the dial: exact when the number matched; validated probable at or above the link line; review between the two lines (a person decides); no link below. Then: how many rows wait in the review band? | D7: IF inside IF, reading the two lines of the dial on the Parameters sheet. | E7: In Q17: =IF(K17="matched","exact",IF(P17>=Parameters!$B$8,"validated probable",IF(P17>=Parameters!$B$9,"review","no link"))) Here: =COUNTIF(Q16:Q40,"review")
A8: S1 Match | B8: 4 | C8: Column R: the tax number on the tax side: the declared number when exact; the register's candidate when validated probable; nothing otherwise. Then: how many of the 25 rows have a tax number on the tax side? | D8: IF on the class. Then count the cells of column R that are not empty. | E8: In R17: =IF(S17="exact",C17,IF(S17="validated probable",G17,"")) Here: =SUMPRODUCT(--(R16:R40<>""))
A9: S1 Match | B9: 5 | C9: Your class (column S): the class at the dial, unless your group decides a review-band pair after reading both records. Lock class and confidence for the 25 on the site. | D9: A wrong link costs more than a missed one: a letter to the wrong trader. Count the four classes; do not quote one match rate. | E9: Column S: =Q17 (copy down), then overwrite a review-band row only with a reason written beside it.
A10: S1 Track B | B10: 1 | C10: Bring each sample pair's score from the table on the left. | D10: VLOOKUP by the customs row. | E10: In I11: =VLOOKUP(F11,$A$6:$C$3205,3,FALSE) copy down to row 305
A11: S1 Track B | B11: 2 | C11: At 0.7 and 0.9: pairs at or above, sample pairs at or above, precision, recall. Column L (0.5) is worked. | D11: COUNTIF with ">="& the dial; COUNTIFS adds the label = 1 condition. | E11: Select L6:L9, copy, paste into M6 and N6: the formulas read the dial in row 5 of their own column.
A12: S2 Four lists | B12: 1 | C12: Columns H and I: imports and import VAT paid over the last twelve months, adding up the lines that bear VAT under the tax number used to clear (Lines 12m). With no number, under the importer's own code. Then: the imports of the 25, added up. | D12: SUMIFS on the Lines 12m sheet, by tax number; IF the number is blank, by importer code. | E12: In H18: =IF(C18="",SUMIFS('Lines 12m'!$G$5:$G$12324,'Lines 12m'!$D$5:$D$12324,B18),SUMIFS('Lines 12m'!$G$5:$G$12324,'Lines 12m'!$E$5:$E$12324,C18)) I: the same with the VAT column 'Lines 12m'!$H$5:$H$12324 Here: =SUM(H17:H41)
A13: S2 Four lists | B13: 2 | C13: Columns J to M: on the tax side (column G), the returns filed of the last six, the import VAT deducted and the sales over twelve months, and booked = deducted ÷ paid. Then: how many of the 25 filed all six of their last six returns? | D13: COUNTIFS on the Returns sheet: the tax ID, filed = 1, period number ≥ 19. SUMIFS for the amounts, period number ≥ 13. | E13: In J18: =IF(G18="","",COUNTIFS(Returns!$A$5:$A$604,G18,Returns!$C$5:$C$604,1,Returns!$G$5:$G$604,">="&Parameters!$B$11)) K: =IF(G18="","",SUMIFS(Returns!$F$5:$F$604,Returns!$A$5:$A$604,G18,Returns!$G$5:$G$604,">="&Parameters!$B$12)) L: =IF(OR(G18="",N(I18)=0),"",K18/I18) M: =IF(G18="","",SUMIFS(Returns!$D$5:$D$604,Returns!$A$5:$A$604,G18,Returns!$G$5:$G$604,">="&Parameters!$B$12)) Here: =COUNTIF(J17:J41,6)
A14: S2 Four lists | B14: 3 | C14: Columns N and O: sales ÷ imports, and the sector's usual (Sectors sheet). Column P: the first question failed (1 to 5). Column Q: the VAT at stake. Then: how many importers fail question 2 (not filing)? | D14: IF inside IF, in the order of the four questions. VAT at stake, 10%: lists 1-2, VAT × imports × (usual − 1); lists 3-4, VAT × (imports × usual − sales); never below 0. | E14: In P18: =IF(G18="",1,IF(J18<Parameters!$B$14,2,IF(L18<Parameters!$B$15,3,IF(N18<Parameters!$B$16,4,5)))) Q: =IF(P18<=2,MAX(0,Parameters!$B$10*H18*(O18-1)),IF(P18<=4,MAX(0,Parameters!$B$10*(H18*O18-M18)),0)) Here: =COUNTIF(P17:P41,2)
A15: S2 Four lists | B15: 4 | C15: Column R: list 4 ranked by VAT at stake. Column S: the list, cut at the capacity. Then: the VAT at stake within capacity (lists 1 to 3, and list 4 up to the capacity). | D15: COUNTIFS counts the list-4 importers with more at stake. The summary table below adds up by list. | E15: In R18: =IF(P18=4,COUNTIFS($P$17:$P$41,4,$Q$17:$Q$41,">"&Q18)+1,"") Here: =SUMIF(P17:P41,"<=3",Q17:Q41)+SUMIFS(Q17:Q41,P17:P41,4,R17:R41,"<="&Parameters!$B$17)
... A24: S4 Tax feeds customs | B24: 4 | C24: How many lines stand behind each rate? Write the joint action's item 6 from it: what customs asks tax to send back, how often, and how it enters the targeting. | D24: Fewer than 100 lines on a side is a small sample: say so beside the number. | E24: A lift is a reason to look, with its range; never a finding on a trader.

Sheet _check
A1: name | B1: value
A2: S1 exact | B2: 19
A3: S1 conf I17 | B3: 0.777
A4: S1 review | B4: 3
A5: S1 numbers on the tax side | B5: 20
A6: TB pairs at 0.5 | B6: 3118
A7: TB pairs at 0.7 | B7: 2724
A8: TB pairs at 0.9 | B8: 2312
A9: TB sample pa 0.5 | B9: 278
A10: TB sample pa 0.7 | B10: 200
A11: TB sample pa 0.9 | B11: 100
A12: TB precision 0.5 | B12: 0.87410072
A13: TB precision 0.7 | B13: 0.865
... A163: S4 lift | B163: 1.3766984
