Workbook

Sheet Start here
A1: Breakout 4B · compute it yourself · WORKED VERSION (every formula filled in)
A3: Each sprint has a worksheet where your group computes its numbers with ordinary Excel tools, from the raw rows both administrations hold (the customs registers and declaration lines, the tax register, the VAT returns, the tax audits), and records its findings. 4B_lab.xlsx shows every number already computed; here you learn how they are made. When your number is right, the Check cell turns green.
A4: Three kinds of sheets. Worksheets (S1 Match to S4 Tax feeds customs): your steps, your answers and their checks; their raw columns are rows copied from the raw sheets (the line above each block says which). Raw sheets (Customs importers, Consignees, Brokers, Tax register, VAT returns, VAT filings, Declarations, Controls, Tax audits): the rows of workshop_extract.xlsx unchanged, under the extract's headers (row 3) and codes (row 4); the first line of each says how to rebuild it from the extract and how many rows it has, the second which of the extract's columns it carries. Tax audits is CSV only (tax_audits.csv). Helper sheets (Similarities, Sectors): computed for you, because they need a script; the first lines say how.
A5: Colours: yellow = you type here (a number or a formula). Grey = given or worked for you (I01 and its number T103629 through every sheet; I17 on S1 Match too). Purple = computed for you (a helper: string similarity, a model score, a median per sector; the Fields sheet and the sheet's first lines say how). White = as recorded. Navy = column names. Every threshold sits on the Parameters sheet: change one there and every formula follows. A formula always starts with = . To copy a formula down a whole column: click the cell, then double-click the small square at its bottom-right corner.
A6: Step 0, for confident groups: open workshop_extract.xlsx, rebuild a raw sheet (or a worksheet's block) with the filter its first line gives, and compare the row count; on S2 Four lists, type the count of the lines block in AD6. Stuck? Hint 1 is beside each step. Hint 2, the full formula, is on the Hints sheet and on the site. The coach (coach-4b) helps one step at a time. 4B_compute_worked.xlsx shows every formula filled in.
A8: When | B8: Sheet | D8: What you compute
A9: Sprint 1 | B9: S1 Match | D9: The 25 importers against the tax register: the exact join on the tax number, the candidate's record and the phone match (joins on the Tax register), the match confidence from the similarities (computed for you), the class at the dial. I17 is worked.
A10: Sprint 1 | B10: S1 Track B | D10: A real register: precision and recall on the labelled sample at three settings of the dial.
A11: Sprint 2 | B11: S2 Four lists | D11: From the raw lines and returns: the month of each line and the period number of each return, then imports and import VAT paid, returns filed, import VAT deducted, sales; the four questions in order; VAT at stake; list 4 ranked and cut at the capacity. I01 is worked.
A12: Sprint 3 | B12: S3 Network | D12: From the customs registers: what each tax number serves (names, consignees, addresses, brokers, the first two from a block of the register's rows), the rule, and what the tax register says about its director.
A13: Sprint 4 | B13: S4 Tax feeds customs | D13: With the tax audit file: does a tax adjustment found at random point to customs findings? Each line's control result (Controls), the customs hit rate with and without a tax adjustment, and the lift.
A14: Thresholds | B14: Parameters | D14: Every threshold of the breakout: the weights and the dial, the VAT rate, the periods and months of the last six and twelve, the four questions, the capacity, the network rule, and where the months and the VAT periods start.
A15: Helpers | B15: Similarities, Sectors | D15: Computed for you (purple), each with one line on how.
A16: Raw sheets | B16: Customs importers, Consignees, Brokers, Tax register, VAT returns, VAT filings, Declarations, Controls, Tax audits | D16: Customs importers: 1,502 rows; Consignees: 2,002 rows; Brokers: 80 rows; Tax register: 1,799 rows; VAT returns: 600 rows; VAT filings: 600 rows; Declarations: 13,517 rows; Controls: 1,414 rows; Tax audits: 284 rows. Each first line says how to rebuild it from the extract.
A18: Everything in this workbook is synthetic (release data-v13). Published customs datasets record an irregularity on 1 to 8 lines in 100; in this lab the random draw finds 3 in 100.

Sheet Parameters
A1: Parameters · every threshold of the breakout in one place
A2: Every formula reads its threshold here. Change one, and every sheet follows. The weights and the dial are choices: say them out loud. Rows 21 to 24 say where the months and the VAT periods start, for the month and the period number you derive on S2 Four lists.
A4: parameter | B4: value | C4: note
A5: Weight of the name similarity | B5: 0.4 | C5: The deck's recipe; a choice, not a measurement.
A6: Weight of the address similarity | B6: 0.3 | C6: Idem.
A7: Weight of the director similarity | B7: 0.3 | C7: Idem.
A8: Dial: a link at or above | B8: 0.9 | C8: Set on the labelled sample (S1 Track B).
A9: Dial: a person reviews at or above | B9: 0.7 | C9: Below it: no link.
A10: VAT rate | B10: 0.1 | C10: The lab's rate.
A11: First period number of the last six returns | B11: 19 | C11: Periods 19 to 24 = 2026-04 to 2026-09.
A12: First period number of the last twelve returns | B12: 13 | C12: Periods 13 to 24 = 2025-10 to 2026-09.
A13: First customs month of the last twelve months | B13: 25 | C13: Months 25 to 36 = 2025-10 to 2026-09.
A14: Filing: at least this many of the last six returns | B14: 5 | C14: Question 2.
A15: Imports in its books: deducted ÷ paid at least | B15: 0.5 | C15: Question 3.
A16: Sold: sales ÷ imports at least | B16: 1 | C16: Question 4.
... A21: VAT period 1: its year | B21: 2024 | C21: Period number 1 = 2024-10, 24 = 2026-09: period number = (year − this) × 12 + month − the row below + 1.
A22: VAT period 1: its calendar month | B22: 10
A23: Customs month 1: its year | B23: 2023 | C23: Month 1 = October 2023, month 36 = September 2026: month = (year − this) × 12 + calendar month − the row below + 1.
A24: Customs month 1: its calendar month | B24: 10

Sheet S1 Match
A1: Sprint 1 · the 25 importers against the tax register: who is who
A2: Each row: the importer as customs holds it (columns A to F and T, rows copied from the Customs importers sheet for the 25 importer codes of the breakout), and the tax register's best candidate (column G, found by a search on name and address). The candidate and the similarities are computed for you (purple, from the Similarities sheet): how alike the two strings are once cleaned. I01 and I17 are worked in grey.
A3: Your choice: 4B_lab.xlsx (sheet Match A) already has every confidence, and 4B_compute_worked.xlsx every formula.
A5: Step | B5: What to do | H5: Your answer | I5: Check | J5: Hint 1 · the tool (the full formula is on the Hints sheet)
A6: 1 | B6: Column K: does the tax number on the declaration exist in the tax register, as typed? "matched", "not in the register" or "blank". Then: how many rows match exactly? | H6: =COUNTIF(K16:K40,"matched") | I6: =IF(H6="","",IF(ISNUMBER(H6),IF(ABS(H6-_check!$B$2)<=0.5,"✓ matches","✗ not yet: see the hint"),"✗ not yet: see the hint")) | J6: COUNTIF counts the number in the register's tax ID column; IF turns the count into a word.
A7: 2 | B7: Column P: the match confidence: name × 0.4 + address × 0.3 + director × 0.3, a missing field left out and the weights rescaled over the fields present. Then: I17's confidence. | H7: =P32 | I7: =IF(H7="","",IF(ISNUMBER(H7),IF(ABS(H7-_check!$B$3)<=0.0006,"✓ matches","✗ not yet: see the hint"),"✗ not yet: see the hint")) | J7: N() turns an empty cell into 0; ISNUMBER says which fields are present, so the division rescales the weights.
A8: 3 | B8: Column Q: the class at the dial: exact when the number matched; validated probable at or above the link line; review between the two lines (a person decides); no link below. Then: how many rows wait in the review band? | H8: =COUNTIF(Q16:Q40,"review") | I8: =IF(H8="","",IF(ISNUMBER(H8),IF(ABS(H8-_check!$B$4)<=0.5,"✓ matches","✗ not yet: see the hint"),"✗ not yet: see the hint")) | J8: IF inside IF, reading the two lines of the dial on the Parameters sheet.
A9: 4 | B9: Column R: the tax number on the tax side: the declared number when exact; the register's candidate when validated probable; nothing otherwise. Then: how many of the 25 rows have a tax number on the tax side? | H9: =SUMPRODUCT(--(R16:R40<>"")) | I9: =IF(H9="","",IF(ISNUMBER(H9),IF(ABS(H9-_check!$B$5)<=0.5,"✓ matches","✗ not yet: see the hint"),"✗ not yet: see the hint")) | J9: IF on the class. Then count the cells of column R that are not empty.
A10: 5 | B10: Your class (column S): the class at the dial, unless your group decides a review-band pair after reading both records. Lock class and confidence for the 25 on the site. | J10: A wrong link costs more than a missed one: a letter to the wrong trader. Count the four classes; do not quote one match rate.
A11: 6 | B11: Before step 5, columns H to J: the candidate's record from the Tax register (legal name, address, director), so that a person can read both records; column O: 1 when the candidate's phone is the customs phone. Then: how many of the 25 pairs share the phone? | H11: =SUM(O16:O40) | I11: =IF(H11="","",IF(ISNUMBER(H11),IF(ABS(H11-_check!$B$164)<=0.5,"✓ matches","✗ not yet: see the hint"),"✗ not yet: see the hint")) | J11: VLOOKUP finds the candidate's tax number (column G) in the first column of the Tax register and returns its 2nd column (legal name), 4th (address), 7th (director) or 6th (phone); IFERROR leaves a missing one empty.
A15: ref | B15: importer (customs) | C15: tax number on the declaration | D15: address (customs) | E15: phone (customs) | F15: director (customs) | G15: best candidate: tax ID · computed for you | H15: best candidate: legal name (you) | I15: best candidate: address (you) | J15: best candidate: director (you) | K15: tax number as typed | L15: name similarity · computed for you | M15: address similarity · computed for you | N15: director similarity · computed for you | O15: phone match (1/0) · you | P15: confidence | Q15: class at the dial | R15: tax number on the tax side | S15: your class | T15: importer code
A16: I01 | B16: Ocean Electronics Co., Ltd | C16: T103629 | D16: 222 Mill Road | E16: 0817809823 | F16: Somchai Rahman | G16: T103629 | H16: =IFERROR(VLOOKUP($G16,'Tax register'!$A$5:$K$1803,2,FALSE),"") | I16: =IFERROR(VLOOKUP($G16,'Tax register'!$A$5:$K$1803,4,FALSE),"") | J16: =IFERROR(VLOOKUP($G16,'Tax register'!$A$5:$K$1803,7,FALSE),"") | K16: =IF(C16="","blank",IF(COUNTIF('Tax register'!$A$5:$A$1803,C16)>0,"matched","not in the register")) | L16: 1 | M16: 1 | N16: 1 | O16: =IF(IFERROR(VLOOKUP($G16,'Tax register'!$A$5:$K$1803,6,FALSE),"")=E16,1,0) | P16: =IF(COUNT(L16:N16)=0,0,(Parameters!$B$5*N(L16)+Parameters!$B$6*N(M16)+Parameters!$B$7*N(N16))/(Parameters!$B$5*ISNUMBER(L16)+Parameters!$B$6*ISNUMBER(M16)+Parameters!$B$7*ISNUMBER(N16))) | Q16: =IF(K16="matched","exact",IF(P16>=Parameters!$B$8,"validated probable",IF(P16>=Parameters!$B$9,"review","no link"))) | R16: =IF(S16="exact",C16,IF(S16="validated probable",G16,"")) | S16: =Q16 | T16: IMP00519
A17: I02 | B17: Phoenix Glow Limited | C17: T105264 | D17: 248 Industrial Estate | E17: 0496195011 | F17: Tomas Tanaka | G17: T105264 | H17: =IFERROR(VLOOKUP($G17,'Tax register'!$A$5:$K$1803,2,FALSE),"") | I17: =IFERROR(VLOOKUP($G17,'Tax register'!$A$5:$K$1803,4,FALSE),"") | J17: =IFERROR(VLOOKUP($G17,'Tax register'!$A$5:$K$1803,7,FALSE),"") | K17: =IF(C17="","blank",IF(COUNTIF('Tax register'!$A$5:$A$1803,C17)>0,"matched","not in the register")) | L17: 1 | M17: 1 | N17: 1 | O17: =IF(IFERROR(VLOOKUP($G17,'Tax register'!$A$5:$K$1803,6,FALSE),"")=E17,1,0) | P17: =IF(COUNT(L17:N17)=0,0,(Parameters!$B$5*N(L17)+Parameters!$B$6*N(M17)+Parameters!$B$7*N(N17))/(Parameters!$B$5*ISNUMBER(L17)+Parameters!$B$6*ISNUMBER(M17)+Parameters!$B$7*ISNUMBER(N17))) | Q17: =IF(K17="matched","exact",IF(P17>=Parameters!$B$8,"validated probable",IF(P17>=Parameters!$B$9,"review","no link"))) | R17: =IF(S17="exact",C17,IF(S17="validated probable",G17,"")) | S17: =Q17 | T17: IMP00753
A18: I03 | B18: Delta Fruits Holdings Ltd | C18: T106240 | D18: 340 Industrial Estate | E18: 0459640429 | F18: Joseph Rahman | G18: T106240 | H18: =IFERROR(VLOOKUP($G18,'Tax register'!$A$5:$K$1803,2,FALSE),"") | I18: =IFERROR(VLOOKUP($G18,'Tax register'!$A$5:$K$1803,4,FALSE),"") | J18: =IFERROR(VLOOKUP($G18,'Tax register'!$A$5:$K$1803,7,FALSE),"") | K18: =IF(C18="","blank",IF(COUNTIF('Tax register'!$A$5:$A$1803,C18)>0,"matched","not in the register")) | L18: 1 | M18: 1 | N18: 1 | O18: =IF(IFERROR(VLOOKUP($G18,'Tax register'!$A$5:$K$1803,6,FALSE),"")=E18,1,0) | P18: =IF(COUNT(L18:N18)=0,0,(Parameters!$B$5*N(L18)+Parameters!$B$6*N(M18)+Parameters!$B$7*N(N18))/(Parameters!$B$5*ISNUMBER(L18)+Parameters!$B$6*ISNUMBER(M18)+Parameters!$B$7*ISNUMBER(N18))) | Q18: =IF(K18="matched","exact",IF(P18>=Parameters!$B$8,"validated probable",IF(P18>=Parameters!$B$9,"review","no link"))) | R18: =IF(S18="exact",C18,IF(S18="validated probable",G18,"")) | S18: =Q18 | T18: IMP00892
A19: I04 | B19: Great Vellmoor Steel Enterprises | C19: T102376 | D19: 43 Riverside | E19: 0913214249 | F19: Elena Haddad | G19: T102376 | H19: =IFERROR(VLOOKUP($G19,'Tax register'!$A$5:$K$1803,2,FALSE),"") | I19: =IFERROR(VLOOKUP($G19,'Tax register'!$A$5:$K$1803,4,FALSE),"") | J19: =IFERROR(VLOOKUP($G19,'Tax register'!$A$5:$K$1803,7,FALSE),"") | K19: =IF(C19="","blank",IF(COUNTIF('Tax register'!$A$5:$A$1803,C19)>0,"matched","not in the register")) | L19: 1 | M19: 1 | N19: 1 | O19: =IF(IFERROR(VLOOKUP($G19,'Tax register'!$A$5:$K$1803,6,FALSE),"")=E19,1,0) | P19: =IF(COUNT(L19:N19)=0,0,(Parameters!$B$5*N(L19)+Parameters!$B$6*N(M19)+Parameters!$B$7*N(N19))/(Parameters!$B$5*ISNUMBER(L19)+Parameters!$B$6*ISNUMBER(M19)+Parameters!$B$7*ISNUMBER(N19))) | Q19: =IF(K19="matched","exact",IF(P19>=Parameters!$B$8,"validated probable",IF(P19>=Parameters!$B$9,"review","no link"))) | R19: =IF(S19="exact",C19,IF(S19="validated probable",G19,"")) | S19: =Q19 | T19: IMP00340
A20: I05 | B20: Carrick Electronics Group Ltd | C20: T106987 | D20: 375 Industrial Estate | E20: 0719832200 | F20: Farid Okafor | G20: T106987 | H20: =IFERROR(VLOOKUP($G20,'Tax register'!$A$5:$K$1803,2,FALSE),"") | I20: =IFERROR(VLOOKUP($G20,'Tax register'!$A$5:$K$1803,4,FALSE),"") | J20: =IFERROR(VLOOKUP($G20,'Tax register'!$A$5:$K$1803,7,FALSE),"") | K20: =IF(C20="","blank",IF(COUNTIF('Tax register'!$A$5:$A$1803,C20)>0,"matched","not in the register")) | L20: 1 | M20: 1 | N20: 1 | O20: =IF(IFERROR(VLOOKUP($G20,'Tax register'!$A$5:$K$1803,6,FALSE),"")=E20,1,0) | P20: =IF(COUNT(L20:N20)=0,0,(Parameters!$B$5*N(L20)+Parameters!$B$6*N(M20)+Parameters!$B$7*N(N20))/(Parameters!$B$5*ISNUMBER(L20)+Parameters!$B$6*ISNUMBER(M20)+Parameters!$B$7*ISNUMBER(N20))) | Q20: =IF(K20="matched","exact",IF(P20>=Parameters!$B$8,"validated probable",IF(P20>=Parameters!$B$9,"review","no link"))) | R20: =IF(S20="exact",C20,IF(S20="validated probable",G20,"")) | S20: =Q20 | T20: IMP00999
A21: I06 | B21: Carrick Agro Enterprises | C21: T107258 | D21: 18 Market Street | E21: 0545102251 | F21: Kenji Haddad | G21: T107258 | H21: =IFERROR(VLOOKUP($G21,'Tax register'!$A$5:$K$1803,2,FALSE),"") | I21: =IFERROR(VLOOKUP($G21,'Tax register'!$A$5:$K$1803,4,FALSE),"") | J21: =IFERROR(VLOOKUP($G21,'Tax register'!$A$5:$K$1803,7,FALSE),"") | K21: =IF(C21="","blank",IF(COUNTIF('Tax register'!$A$5:$A$1803,C21)>0,"matched","not in the register")) | L21: 1 | M21: 1 | N21: 1 | O21: =IF(IFERROR(VLOOKUP($G21,'Tax register'!$A$5:$K$1803,6,FALSE),"")=E21,1,0) | P21: =IF(COUNT(L21:N21)=0,0,(Parameters!$B$5*N(L21)+Parameters!$B$6*N(M21)+Parameters!$B$7*N(N21))/(Parameters!$B$5*ISNUMBER(L21)+Parameters!$B$6*ISNUMBER(M21)+Parameters!$B$7*ISNUMBER(N21))) | Q21: =IF(K21="matched","exact",IF(P21>=Parameters!$B$8,"validated probable",IF(P21>=Parameters!$B$9,"review","no link"))) | R21: =IF(S21="exact",C21,IF(S21="validated probable",G21,"")) | S21: =Q21 | T21: IMP01037
A22: I07 | B22: Cobalt Mobile & Sons | C22: T102141 | D22: 314 Industrial Estate | E22: 0965281846 | F22: Elena Haddad | G22: T102141 | H22: =IFERROR(VLOOKUP($G22,'Tax register'!$A$5:$K$1803,2,FALSE),"") | I22: =IFERROR(VLOOKUP($G22,'Tax register'!$A$5:$K$1803,4,FALSE),"") | J22: =IFERROR(VLOOKUP($G22,'Tax register'!$A$5:$K$1803,7,FALSE),"") | K22: =IF(C22="","blank",IF(COUNTIF('Tax register'!$A$5:$A$1803,C22)>0,"matched","not in the register")) | L22: 1 | M22: 1 | N22: 1 | O22: =IF(IFERROR(VLOOKUP($G22,'Tax register'!$A$5:$K$1803,6,FALSE),"")=E22,1,0) | P22: =IF(COUNT(L22:N22)=0,0,(Parameters!$B$5*N(L22)+Parameters!$B$6*N(M22)+Parameters!$B$7*N(N22))/(Parameters!$B$5*ISNUMBER(L22)+Parameters!$B$6*ISNUMBER(M22)+Parameters!$B$7*ISNUMBER(N22))) | Q22: =IF(K22="matched","exact",IF(P22>=Parameters!$B$8,"validated probable",IF(P22>=Parameters!$B$9,"review","no link"))) | R22: =IF(S22="exact",C22,IF(S22="validated probable",G22,"")) | S22: =Q22 | T22: IMP00306
A23: I08 | B23: Central Imports International Ltd | D23: 350 Garden Lane | E23: 0471338762 | F23: Kenji Haddad | G23: T102182 | H23: =IFERROR(VLOOKUP($G23,'Tax register'!$A$5:$K$1803,2,FALSE),"") | I23: =IFERROR(VLOOKUP($G23,'Tax register'!$A$5:$K$1803,4,FALSE),"") | J23: =IFERROR(VLOOKUP($G23,'Tax register'!$A$5:$K$1803,7,FALSE),"") | K23: =IF(C23="","blank",IF(COUNTIF('Tax register'!$A$5:$A$1803,C23)>0,"matched","not in the register")) | L23: 1 | M23: 0.615 | N23: 0.345 | O23: =IF(IFERROR(VLOOKUP($G23,'Tax register'!$A$5:$K$1803,6,FALSE),"")=E23,1,0) | P23: =IF(COUNT(L23:N23)=0,0,(Parameters!$B$5*N(L23)+Parameters!$B$6*N(M23)+Parameters!$B$7*N(N23))/(Parameters!$B$5*ISNUMBER(L23)+Parameters!$B$6*ISNUMBER(M23)+Parameters!$B$7*ISNUMBER(N23))) | Q23: =IF(K23="matched","exact",IF(P23>=Parameters!$B$8,"validated probable",IF(P23>=Parameters!$B$9,"review","no link"))) | R23: =IF(S23="exact",C23,IF(S23="validated probable",G23,"")) | S23: =Q23 | T23: IMP00147
A24: I09 | B24: Phoenix Imports Partners Ltd | D24: 171 Garden Lane | E24: 0887356246 | F24: Nadia Chen | G24: T514418 | H24: =IFERROR(VLOOKUP($G24,'Tax register'!$A$5:$K$1803,2,FALSE),"") | I24: =IFERROR(VLOOKUP($G24,'Tax register'!$A$5:$K$1803,4,FALSE),"") | J24: =IFERROR(VLOOKUP($G24,'Tax register'!$A$5:$K$1803,7,FALSE),"") | K24: =IF(C24="","blank",IF(COUNTIF('Tax register'!$A$5:$A$1803,C24)>0,"matched","not in the register")) | L24: 1 | M24: 0.417 | N24: 0.4 | O24: =IF(IFERROR(VLOOKUP($G24,'Tax register'!$A$5:$K$1803,6,FALSE),"")=E24,1,0) | P24: =IF(COUNT(L24:N24)=0,0,(Parameters!$B$5*N(L24)+Parameters!$B$6*N(M24)+Parameters!$B$7*N(N24))/(Parameters!$B$5*ISNUMBER(L24)+Parameters!$B$6*ISNUMBER(M24)+Parameters!$B$7*ISNUMBER(N24))) | Q24: =IF(K24="matched","exact",IF(P24>=Parameters!$B$8,"validated probable",IF(P24>=Parameters!$B$9,"review","no link"))) | R24: =IF(S24="exact",C24,IF(S24="validated probable",G24,"")) | S24: =Q24 | T24: IMP00721
A25: I10 | B25: Global Electronics International Ltd | C25: T103130 | D25: 296 Temple Street | E25: 0941933516 | F25: Amina Al-Sayed | G25: T103130 | H25: =IFERROR(VLOOKUP($G25,'Tax register'!$A$5:$K$1803,2,FALSE),"") | I25: =IFERROR(VLOOKUP($G25,'Tax register'!$A$5:$K$1803,4,FALSE),"") | J25: =IFERROR(VLOOKUP($G25,'Tax register'!$A$5:$K$1803,7,FALSE),"") | K25: =IF(C25="","blank",IF(COUNTIF('Tax register'!$A$5:$A$1803,C25)>0,"matched","not in the register")) | L25: 1 | N25: 1 | O25: =IF(IFERROR(VLOOKUP($G25,'Tax register'!$A$5:$K$1803,6,FALSE),"")=E25,1,0) | P25: =IF(COUNT(L25:N25)=0,0,(Parameters!$B$5*N(L25)+Parameters!$B$6*N(M25)+Parameters!$B$7*N(N25))/(Parameters!$B$5*ISNUMBER(L25)+Parameters!$B$6*ISNUMBER(M25)+Parameters!$B$7*ISNUMBER(N25))) | Q25: =IF(K25="matched","exact",IF(P25>=Parameters!$B$8,"validated probable",IF(P25>=Parameters!$B$9,"review","no link"))) | R25: =IF(S25="exact",C25,IF(S25="validated probable",G25,"")) | S25: =Q25 | T25: IMP00448
A26: I11 | B26: Central Foods Limited | C26: T100033 | D26: 24 Harbour Road | E26: 0401520138 | F26: Farid Ibrahim | G26: T100033 | H26: =IFERROR(VLOOKUP($G26,'Tax register'!$A$5:$K$1803,2,FALSE),"") | I26: =IFERROR(VLOOKUP($G26,'Tax register'!$A$5:$K$1803,4,FALSE),"") | J26: =IFERROR(VLOOKUP($G26,'Tax register'!$A$5:$K$1803,7,FALSE),"") | K26: =IF(C26="","blank",IF(COUNTIF('Tax register'!$A$5:$A$1803,C26)>0,"matched","not in the register")) | L26: 1 | M26: 1 | N26: 1 | O26: =IF(IFERROR(VLOOKUP($G26,'Tax register'!$A$5:$K$1803,6,FALSE),"")=E26,1,0) | P26: =IF(COUNT(L26:N26)=0,0,(Parameters!$B$5*N(L26)+Parameters!$B$6*N(M26)+Parameters!$B$7*N(N26))/(Parameters!$B$5*ISNUMBER(L26)+Parameters!$B$6*ISNUMBER(M26)+Parameters!$B$7*ISNUMBER(N26))) | Q26: =IF(K26="matched","exact",IF(P26>=Parameters!$B$8,"validated probable",IF(P26>=Parameters!$B$9,"review","no link"))) | R26: =IF(S26="exact",C26,IF(S26="validated probable",G26,"")) | S26: =Q26 | T26: IMP00005
A27: I12 | B27: Ocean Medical Co., Ltd | D27: 362 Temple Street | E27: 0482336020 | F27: Hassan Tanaka | G27: T109212 | H27: =IFERROR(VLOOKUP($G27,'Tax register'!$A$5:$K$1803,2,FALSE),"") | I27: =IFERROR(VLOOKUP($G27,'Tax register'!$A$5:$K$1803,4,FALSE),"") | J27: =IFERROR(VLOOKUP($G27,'Tax register'!$A$5:$K$1803,7,FALSE),"") | K27: =IF(C27="","blank",IF(COUNTIF('Tax register'!$A$5:$A$1803,C27)>0,"matched","not in the register")) | L27: 1 | M27: 0.846 | N27: 0.32 | O27: =IF(IFERROR(VLOOKUP($G27,'Tax register'!$A$5:$K$1803,6,FALSE),"")=E27,1,0) | P27: =IF(COUNT(L27:N27)=0,0,(Parameters!$B$5*N(L27)+Parameters!$B$6*N(M27)+Parameters!$B$7*N(N27))/(Parameters!$B$5*ISNUMBER(L27)+Parameters!$B$6*ISNUMBER(M27)+Parameters!$B$7*ISNUMBER(N27))) | Q27: =IF(K27="matched","exact",IF(P27>=Parameters!$B$8,"validated probable",IF(P27>=Parameters!$B$9,"review","no link"))) | R27: =IF(S27="exact",C27,IF(S27="validated probable",G27,"")) | S27: =Q27 | T27: IMP00156
A28: I13 | B28: Central Enterprises Co. | D28: 191 Garden Lane | E28: 0946646378 | F28: Hassan Kowalski | G28: T110150 | H28: =IFERROR(VLOOKUP($G28,'Tax register'!$A$5:$K$1803,2,FALSE),"") | I28: =IFERROR(VLOOKUP($G28,'Tax register'!$A$5:$K$1803,4,FALSE),"") | J28: =IFERROR(VLOOKUP($G28,'Tax register'!$A$5:$K$1803,7,FALSE),"") | K28: =IF(C28="","blank",IF(COUNTIF('Tax register'!$A$5:$A$1803,C28)>0,"matched","not in the register")) | L28: 1 | M28: 0.846 | N28: 0.4 | O28: =IF(IFERROR(VLOOKUP($G28,'Tax register'!$A$5:$K$1803,6,FALSE),"")=E28,1,0) | P28: =IF(COUNT(L28:N28)=0,0,(Parameters!$B$5*N(L28)+Parameters!$B$6*N(M28)+Parameters!$B$7*N(N28))/(Parameters!$B$5*ISNUMBER(L28)+Parameters!$B$6*ISNUMBER(M28)+Parameters!$B$7*ISNUMBER(N28))) | Q28: =IF(K28="matched","exact",IF(P28>=Parameters!$B$8,"validated probable",IF(P28>=Parameters!$B$9,"review","no link"))) | R28: =IF(S28="exact",C28,IF(S28="validated probable",G28,"")) | S28: =Q28 | T28: IMP00950
A29: I14 | B29: Royal Agro Co., Ltd | C29: T108692 | D29: 191 Bazaar Lane | E29: 0382439044 | F29: Somchai Silva | G29: T108692 | H29: =IFERROR(VLOOKUP($G29,'Tax register'!$A$5:$K$1803,2,FALSE),"") | I29: =IFERROR(VLOOKUP($G29,'Tax register'!$A$5:$K$1803,4,FALSE),"") | J29: =IFERROR(VLOOKUP($G29,'Tax register'!$A$5:$K$1803,7,FALSE),"") | K29: =IF(C29="","blank",IF(COUNTIF('Tax register'!$A$5:$A$1803,C29)>0,"matched","not in the register")) | L29: 1 | M29: 1 | N29: 1 | O29: =IF(IFERROR(VLOOKUP($G29,'Tax register'!$A$5:$K$1803,6,FALSE),"")=E29,1,0) | P29: =IF(COUNT(L29:N29)=0,0,(Parameters!$B$5*N(L29)+Parameters!$B$6*N(M29)+Parameters!$B$7*N(N29))/(Parameters!$B$5*ISNUMBER(L29)+Parameters!$B$6*ISNUMBER(M29)+Parameters!$B$7*ISNUMBER(N29))) | Q29: =IF(K29="matched","exact",IF(P29>=Parameters!$B$8,"validated probable",IF(P29>=Parameters!$B$9,"review","no link"))) | R29: =IF(S29="exact",C29,IF(S29="validated probable",G29,"")) | S29: =Q29 | T29: IMP01242
A30: I15 | B30: Silk Road Steel Co. | C30: T100070 | D30: 346 Market Street | E30: 0519965779 | F30: Farid Haddad | G30: T100070 | H30: =IFERROR(VLOOKUP($G30,'Tax register'!$A$5:$K$1803,2,FALSE),"") | I30: =IFERROR(VLOOKUP($G30,'Tax register'!$A$5:$K$1803,4,FALSE),"") | J30: =IFERROR(VLOOKUP($G30,'Tax register'!$A$5:$K$1803,7,FALSE),"") | K30: =IF(C30="","blank",IF(COUNTIF('Tax register'!$A$5:$A$1803,C30)>0,"matched","not in the register")) | L30: 1 | M30: 1 | N30: 1 | O30: =IF(IFERROR(VLOOKUP($G30,'Tax register'!$A$5:$K$1803,6,FALSE),"")=E30,1,0) | P30: =IF(COUNT(L30:N30)=0,0,(Parameters!$B$5*N(L30)+Parameters!$B$6*N(M30)+Parameters!$B$7*N(N30))/(Parameters!$B$5*ISNUMBER(L30)+Parameters!$B$6*ISNUMBER(M30)+Parameters!$B$7*ISNUMBER(N30))) | Q30: =IF(K30="matched","exact",IF(P30>=Parameters!$B$8,"validated probable",IF(P30>=Parameters!$B$9,"review","no link"))) | R30: =IF(S30="exact",C30,IF(S30="validated probable",G30,"")) | S30: =Q30 | T30: IMP00011
A31: I16 | B31: Carrick Trading & Sons | C31: T107617 | D31: 172 Airport Road | E31: 0803847861 | F31: Ingrid Sato | G31: T107617 | H31: =IFERROR(VLOOKUP($G31,'Tax register'!$A$5:$K$1803,2,FALSE),"") | I31: =IFERROR(VLOOKUP($G31,'Tax register'!$A$5:$K$1803,4,FALSE),"") | J31: =IFERROR(VLOOKUP($G31,'Tax register'!$A$5:$K$1803,7,FALSE),"") | K31: =IF(C31="","blank",IF(COUNTIF('Tax register'!$A$5:$A$1803,C31)>0,"matched","not in the register")) | L31: 1 | M31: 1 | N31: 1 | O31: =IF(IFERROR(VLOOKUP($G31,'Tax register'!$A$5:$K$1803,6,FALSE),"")=E31,1,0) | P31: =IF(COUNT(L31:N31)=0,0,(Parameters!$B$5*N(L31)+Parameters!$B$6*N(M31)+Parameters!$B$7*N(N31))/(Parameters!$B$5*ISNUMBER(L31)+Parameters!$B$6*ISNUMBER(M31)+Parameters!$B$7*ISNUMBER(N31))) | Q31: =IF(K31="matched","exact",IF(P31>=Parameters!$B$8,"validated probable",IF(P31>=Parameters!$B$9,"review","no link"))) | R31: =IF(S31="exact",C31,IF(S31="validated probable",G31,"")) | S31: =Q31 | T31: IMP01089
A32: I17 | B32: Ocean Industries Holdings Ltd | D32: 323 Station Road | E32: 0924121092 | F32: Joseph Tanaka | G32: T106372 | H32: =IFERROR(VLOOKUP($G32,'Tax register'!$A$5:$K$1803,2,FALSE),"") | I32: =IFERROR(VLOOKUP($G32,'Tax register'!$A$5:$K$1803,4,FALSE),"") | J32: =IFERROR(VLOOKUP($G32,'Tax register'!$A$5:$K$1803,7,FALSE),"") | K32: =IF(C32="","blank",IF(COUNTIF('Tax register'!$A$5:$A$1803,C32)>0,"matched","not in the register")) | L32: 1 | M32: 0.857 | N32: 0.4 | O32: =IF(IFERROR(VLOOKUP($G32,'Tax register'!$A$5:$K$1803,6,FALSE),"")=E32,1,0) | P32: =IF(COUNT(L32:N32)=0,0,(Parameters!$B$5*N(L32)+Parameters!$B$6*N(M32)+Parameters!$B$7*N(N32))/(Parameters!$B$5*ISNUMBER(L32)+Parameters!$B$6*ISNUMBER(M32)+Parameters!$B$7*ISNUMBER(N32))) | Q32: =IF(K32="matched","exact",IF(P32>=Parameters!$B$8,"validated probable",IF(P32>=Parameters!$B$9,"review","no link"))) | R32: =IF(S32="exact",C32,IF(S32="validated probable",G32,"")) | S32: =Q32 | T32: IMP01481
A33: I18 | B33: Arden Living Co. | C33: T107992 | D33: 144 Riverside | E33: 0894167333 | F33: Samuel Kowalski | G33: T107992 | H33: =IFERROR(VLOOKUP($G33,'Tax register'!$A$5:$K$1803,2,FALSE),"") | I33: =IFERROR(VLOOKUP($G33,'Tax register'!$A$5:$K$1803,4,FALSE),"") | J33: =IFERROR(VLOOKUP($G33,'Tax register'!$A$5:$K$1803,7,FALSE),"") | K33: =IF(C33="","blank",IF(COUNTIF('Tax register'!$A$5:$A$1803,C33)>0,"matched","not in the register")) | L33: 1 | M33: 1 | N33: 1 | O33: =IF(IFERROR(VLOOKUP($G33,'Tax register'!$A$5:$K$1803,6,FALSE),"")=E33,1,0) | P33: =IF(COUNT(L33:N33)=0,0,(Parameters!$B$5*N(L33)+Parameters!$B$6*N(M33)+Parameters!$B$7*N(N33))/(Parameters!$B$5*ISNUMBER(L33)+Parameters!$B$6*ISNUMBER(M33)+Parameters!$B$7*ISNUMBER(N33))) | Q33: =IF(K33="matched","exact",IF(P33>=Parameters!$B$8,"validated probable",IF(P33>=Parameters!$B$9,"review","no link"))) | R33: =IF(S33="exact",C33,IF(S33="validated probable",G33,"")) | S33: =Q33 | T33: IMP01142
A34: I19 | B34: Pacific Living Co. | C34: T109167 | D34: 329 Riverside | E34: 0346234502 | F34: Aisha Reyes | G34: T109167 | H34: =IFERROR(VLOOKUP($G34,'Tax register'!$A$5:$K$1803,2,FALSE),"") | I34: =IFERROR(VLOOKUP($G34,'Tax register'!$A$5:$K$1803,4,FALSE),"") | J34: =IFERROR(VLOOKUP($G34,'Tax register'!$A$5:$K$1803,7,FALSE),"") | K34: =IF(C34="","blank",IF(COUNTIF('Tax register'!$A$5:$A$1803,C34)>0,"matched","not in the register")) | L34: 1 | M34: 1 | N34: 1 | O34: =IF(IFERROR(VLOOKUP($G34,'Tax register'!$A$5:$K$1803,6,FALSE),"")=E34,1,0) | P34: =IF(COUNT(L34:N34)=0,0,(Parameters!$B$5*N(L34)+Parameters!$B$6*N(M34)+Parameters!$B$7*N(N34))/(Parameters!$B$5*ISNUMBER(L34)+Parameters!$B$6*ISNUMBER(M34)+Parameters!$B$7*ISNUMBER(N34))) | Q34: =IF(K34="matched","exact",IF(P34>=Parameters!$B$8,"validated probable",IF(P34>=Parameters!$B$9,"review","no link"))) | R34: =IF(S34="exact",C34,IF(S34="validated probable",G34,"")) | S34: =Q34 | T34: IMP01310
A35: I20 | B35: Ocean Trading International Ltd | C35: T103425 | D35: 115 Harbour Road | E35: 0731410108 | F35: Nadia Al-Sayed | G35: T103425 | H35: =IFERROR(VLOOKUP($G35,'Tax register'!$A$5:$K$1803,2,FALSE),"") | I35: =IFERROR(VLOOKUP($G35,'Tax register'!$A$5:$K$1803,4,FALSE),"") | J35: =IFERROR(VLOOKUP($G35,'Tax register'!$A$5:$K$1803,7,FALSE),"") | K35: =IF(C35="","blank",IF(COUNTIF('Tax register'!$A$5:$A$1803,C35)>0,"matched","not in the register")) | L35: 1 | M35: 1 | N35: 1 | O35: =IF(IFERROR(VLOOKUP($G35,'Tax register'!$A$5:$K$1803,6,FALSE),"")=E35,1,0) | P35: =IF(COUNT(L35:N35)=0,0,(Parameters!$B$5*N(L35)+Parameters!$B$6*N(M35)+Parameters!$B$7*N(N35))/(Parameters!$B$5*ISNUMBER(L35)+Parameters!$B$6*ISNUMBER(M35)+Parameters!$B$7*ISNUMBER(N35))) | Q35: =IF(K35="matched","exact",IF(P35>=Parameters!$B$8,"validated probable",IF(P35>=Parameters!$B$9,"review","no link"))) | R35: =IF(S35="exact",C35,IF(S35="validated probable",G35,"")) | S35: =Q35 | T35: IMP00490
A36: I21 | B36: Metro Motors Co., Ltd | C36: T100440 | D36: 215 Bazaar Lane | E36: 0929915234 | F36: Ingrid Al-Sayed | G36: T100440 | H36: =IFERROR(VLOOKUP($G36,'Tax register'!$A$5:$K$1803,2,FALSE),"") | I36: =IFERROR(VLOOKUP($G36,'Tax register'!$A$5:$K$1803,4,FALSE),"") | J36: =IFERROR(VLOOKUP($G36,'Tax register'!$A$5:$K$1803,7,FALSE),"") | K36: =IF(C36="","blank",IF(COUNTIF('Tax register'!$A$5:$A$1803,C36)>0,"matched","not in the register")) | L36: 1 | M36: 1 | N36: 1 | O36: =IF(IFERROR(VLOOKUP($G36,'Tax register'!$A$5:$K$1803,6,FALSE),"")=E36,1,0) | P36: =IF(COUNT(L36:N36)=0,0,(Parameters!$B$5*N(L36)+Parameters!$B$6*N(M36)+Parameters!$B$7*N(N36))/(Parameters!$B$5*ISNUMBER(L36)+Parameters!$B$6*ISNUMBER(M36)+Parameters!$B$7*ISNUMBER(N36))) | Q36: =IF(K36="matched","exact",IF(P36>=Parameters!$B$8,"validated probable",IF(P36>=Parameters!$B$9,"review","no link"))) | R36: =IF(S36="exact",C36,IF(S36="validated probable",G36,"")) | S36: =Q36 | T36: IMP00063
A37: I22 | B37: Metro Steel Partners Ltd | C37: T106477 | D37: 358 Market Street | E37: 0402667378 | F37: Amina Bauer | G37: T106477 | H37: =IFERROR(VLOOKUP($G37,'Tax register'!$A$5:$K$1803,2,FALSE),"") | I37: =IFERROR(VLOOKUP($G37,'Tax register'!$A$5:$K$1803,4,FALSE),"") | J37: =IFERROR(VLOOKUP($G37,'Tax register'!$A$5:$K$1803,7,FALSE),"") | K37: =IF(C37="","blank",IF(COUNTIF('Tax register'!$A$5:$A$1803,C37)>0,"matched","not in the register")) | L37: 1 | M37: 1 | N37: 1 | O37: =IF(IFERROR(VLOOKUP($G37,'Tax register'!$A$5:$K$1803,6,FALSE),"")=E37,1,0) | P37: =IF(COUNT(L37:N37)=0,0,(Parameters!$B$5*N(L37)+Parameters!$B$6*N(M37)+Parameters!$B$7*N(N37))/(Parameters!$B$5*ISNUMBER(L37)+Parameters!$B$6*ISNUMBER(M37)+Parameters!$B$7*ISNUMBER(N37))) | Q37: =IF(K37="matched","exact",IF(P37>=Parameters!$B$8,"validated probable",IF(P37>=Parameters!$B$9,"review","no link"))) | R37: =IF(S37="exact",C37,IF(S37="validated probable",G37,"")) | S37: =Q37 | T37: IMP00926
A38: I23 | B38: Aldergate Agro Holdings Ltd | C38: T104498 | D38: 340 Garden Lane | E38: 0612702458 | F38: Daniel Osei | G38: T104498 | H38: =IFERROR(VLOOKUP($G38,'Tax register'!$A$5:$K$1803,2,FALSE),"") | I38: =IFERROR(VLOOKUP($G38,'Tax register'!$A$5:$K$1803,4,FALSE),"") | J38: =IFERROR(VLOOKUP($G38,'Tax register'!$A$5:$K$1803,7,FALSE),"") | K38: =IF(C38="","blank",IF(COUNTIF('Tax register'!$A$5:$A$1803,C38)>0,"matched","not in the register")) | L38: 1 | M38: 1 | N38: 1 | O38: =IF(IFERROR(VLOOKUP($G38,'Tax register'!$A$5:$K$1803,6,FALSE),"")=E38,1,0) | P38: =IF(COUNT(L38:N38)=0,0,(Parameters!$B$5*N(L38)+Parameters!$B$6*N(M38)+Parameters!$B$7*N(N38))/(Parameters!$B$5*ISNUMBER(L38)+Parameters!$B$6*ISNUMBER(M38)+Parameters!$B$7*ISNUMBER(N38))) | Q38: =IF(K38="matched","exact",IF(P38>=Parameters!$B$8,"validated probable",IF(P38>=Parameters!$B$9,"review","no link"))) | R38: =IF(S38="exact",C38,IF(S38="validated probable",G38,"")) | S38: =Q38 | T38: IMP00643
A39: I24 | B39: Pacific Enterprises Holdings Ltd | C39: T100466 | D39: 356 Station Road | E39: 0254736740 | F39: Farid Sato | G39: T100466 | H39: =IFERROR(VLOOKUP($G39,'Tax register'!$A$5:$K$1803,2,FALSE),"") | I39: =IFERROR(VLOOKUP($G39,'Tax register'!$A$5:$K$1803,4,FALSE),"") | J39: =IFERROR(VLOOKUP($G39,'Tax register'!$A$5:$K$1803,7,FALSE),"") | K39: =IF(C39="","blank",IF(COUNTIF('Tax register'!$A$5:$A$1803,C39)>0,"matched","not in the register")) | L39: 1 | M39: 1 | N39: 1 | O39: =IF(IFERROR(VLOOKUP($G39,'Tax register'!$A$5:$K$1803,6,FALSE),"")=E39,1,0) | P39: =IF(COUNT(L39:N39)=0,0,(Parameters!$B$5*N(L39)+Parameters!$B$6*N(M39)+Parameters!$B$7*N(N39))/(Parameters!$B$5*ISNUMBER(L39)+Parameters!$B$6*ISNUMBER(M39)+Parameters!$B$7*ISNUMBER(N39))) | Q39: =IF(K39="matched","exact",IF(P39>=Parameters!$B$8,"validated probable",IF(P39>=Parameters!$B$9,"review","no link"))) | R39: =IF(S39="exact",C39,IF(S39="validated probable",G39,"")) | S39: =Q39 | T39: IMP00067
A40: I25 | B40: Arden Fruits Enterprises | C40: T102011 | D40: 360 Harbour Road | E40: 0225352118 | F40: Mei Okafor | G40: T102015 | H40: =IFERROR(VLOOKUP($G40,'Tax register'!$A$5:$K$1803,2,FALSE),"") | I40: =IFERROR(VLOOKUP($G40,'Tax register'!$A$5:$K$1803,4,FALSE),"") | J40: =IFERROR(VLOOKUP($G40,'Tax register'!$A$5:$K$1803,7,FALSE),"") | K40: =IF(C40="","blank",IF(COUNTIF('Tax register'!$A$5:$A$1803,C40)>0,"matched","not in the register")) | L40: 1 | M40: 1 | N40: 1 | O40: =IF(IFERROR(VLOOKUP($G40,'Tax register'!$A$5:$K$1803,6,FALSE),"")=E40,1,0) | P40: =IF(COUNT(L40:N40)=0,0,(Parameters!$B$5*N(L40)+Parameters!$B$6*N(M40)+Parameters!$B$7*N(N40))/(Parameters!$B$5*ISNUMBER(L40)+Parameters!$B$6*ISNUMBER(M40)+Parameters!$B$7*ISNUMBER(N40))) | Q40: =IF(K40="matched","exact",IF(P40>=Parameters!$B$8,"validated probable",IF(P40>=Parameters!$B$9,"review","no link"))) | R40: =IF(S40="exact",C40,IF(S40="validated probable",G40,"")) | S40: =Q40 | T40: IMP00288
A42: The worked case, I17: no number on the declaration; the register's best candidate T106372 · name 1.00, address 0.857, director 0.40: 0.4 × 1.00 + 0.3 × 0.857 + 0.3 × 0.40 = 0.777, in the review band. A person reads both records before any letter.

Sheet S1 Track B
A1: Sprint 1 · Track B: a real register, and where to set the dial
A2: Left: the matching recipe's best candidate for each of 3,200 customs rows, with its score (computed for you). Middle: 300 pairs a clerk checked by hand (1 = the same trader, 0 = not). Rows by number only; no name is read aloud.
A3: Computed for you (purple): the score, by a script that compares cleaned names and addresses of a public register (match_scores.csv). The labels are a clerk's (trackB_labelled_sample.csv). Both are lab files: the extract does not carry them.
A5: customs row | B5: register row | C5: score | D5: band | F5: customs row | G5: register row | H5: label (1 = same) | I5: its score | K5: at the dial | L5: 0.5 | M5: 0.7 | N5: 0.9
A6: C00001 | B6: R01223 | C6: 1 | D6: exact | F6: C00018 | G6: R00507 | H6: 0 | I6: =VLOOKUP(F6,$A$6:$C$3205,3,FALSE) | K6: pairs at or above (all rows) | L6: =COUNTIF($C$6:$C$3205,">="&L$5) | M6: =COUNTIF($C$6:$C$3205,">="&M$5) | N6: =COUNTIF($C$6:$C$3205,">="&N$5)
A7: C00002 | B7: R00398 | C7: 1 | D7: exact | F7: C00020 | G7: R01739 | H7: 1 | I7: =VLOOKUP(F7,$A$6:$C$3205,3,FALSE) | K7: sample pairs at or above | L7: =COUNTIF($I$6:$I$305,">="&L$5) | M7: =COUNTIF($I$6:$I$305,">="&M$5) | N7: =COUNTIF($I$6:$I$305,">="&N$5)
A8: C00003 | B8: R02417 | C8: 1 | D8: exact | F8: C00028 | G8: R01517 | H8: 1 | I8: =VLOOKUP(F8,$A$6:$C$3205,3,FALSE) | K8: precision: true links ÷ sample pairs at or above | L8: =IFERROR(COUNTIFS($I$6:$I$305,">="&L$5,$H$6:$H$305,1)/L7,"") | M8: =IFERROR(COUNTIFS($I$6:$I$305,">="&M$5,$H$6:$H$305,1)/M7,"") | N8: =IFERROR(COUNTIFS($I$6:$I$305,">="&N$5,$H$6:$H$305,1)/N7,"")
A9: C00004 | B9: R01899 | C9: 1 | D9: exact | F9: C00031 | G9: R01600 | H9: 1 | I9: =VLOOKUP(F9,$A$6:$C$3205,3,FALSE) | K9: recall: true links at or above ÷ all true links | L9: =IFERROR(COUNTIFS($I$6:$I$305,">="&L$5,$H$6:$H$305,1)/COUNTIF($H$6:$H$305,1),"") | M9: =IFERROR(COUNTIFS($I$6:$I$305,">="&M$5,$H$6:$H$305,1)/COUNTIF($H$6:$H$305,1),"") | N9: =IFERROR(COUNTIFS($I$6:$I$305,">="&N$5,$H$6:$H$305,1)/COUNTIF($H$6:$H$305,1),"")
A10: C00005 | B10: R02666 | C10: 1 | D10: exact | F10: C00037 | G10: R02691 | H10: 1 | I10: =VLOOKUP(F10,$A$6:$C$3205,3,FALSE)
A11: C00006 | B11: R02060 | C11: 1 | D11: exact | F11: C00049 | G11: R00866 | H11: 1 | I11: =VLOOKUP(F11,$A$6:$C$3205,3,FALSE) | K11: checks (rows 6 to 9) | L11: =IF(COUNT($I$6:$I$305)<300,"",IF(L6="","",IF(ISNUMBER(L6),IF(ABS(L6-_check!$B$6)<=0.5,"✓","✗"),"✗"))) | M11: =IF(COUNT($I$6:$I$305)<300,"",IF(M6="","",IF(ISNUMBER(M6),IF(ABS(M6-_check!$B$7)<=0.5,"✓","✗"),"✗"))) | N11: =IF(COUNT($I$6:$I$305)<300,"",IF(N6="","",IF(ISNUMBER(N6),IF(ABS(N6-_check!$B$8)<=0.5,"✓","✗"),"✗")))
A12: C00007 | B12: R01228 | C12: 1 | D12: exact | F12: C00059 | G12: R00785 | H12: 1 | I12: =VLOOKUP(F12,$A$6:$C$3205,3,FALSE) | L12: =IF(COUNT($I$6:$I$305)<300,"",IF(L7="","",IF(ISNUMBER(L7),IF(ABS(L7-_check!$B$9)<=0.5,"✓","✗"),"✗"))) | M12: =IF(COUNT($I$6:$I$305)<300,"",IF(M7="","",IF(ISNUMBER(M7),IF(ABS(M7-_check!$B$10)<=0.5,"✓","✗"),"✗"))) | N12: =IF(COUNT($I$6:$I$305)<300,"",IF(N7="","",IF(ISNUMBER(N7),IF(ABS(N7-_check!$B$11)<=0.5,"✓","✗"),"✗")))
A13: C00008 | B13: R00709 | C13: 1 | D13: exact | F13: C00062 | G13: R02603 | H13: 1 | I13: =VLOOKUP(F13,$A$6:$C$3205,3,FALSE) | L13: =IF(COUNT($I$6:$I$305)<300,"",IF(L8="","",IF(ISNUMBER(L8),IF(ABS(L8-_check!$B$12)<=0.0006,"✓","✗"),"✗"))) | M13: =IF(COUNT($I$6:$I$305)<300,"",IF(M8="","",IF(ISNUMBER(M8),IF(ABS(M8-_check!$B$13)<=0.0006,"✓","✗"),"✗"))) | N13: =IF(COUNT($I$6:$I$305)<300,"",IF(N8="","",IF(ISNUMBER(N8),IF(ABS(N8-_check!$B$14)<=0.0006,"✓","✗"),"✗")))
A14: C00009 | B14: R01515 | C14: 0.4259 | D14: no match | F14: C00073 | G14: R00465 | H14: 1 | I14: =VLOOKUP(F14,$A$6:$C$3205,3,FALSE) | L14: =IF(COUNT($I$6:$I$305)<300,"",IF(L9="","",IF(ISNUMBER(L9),IF(ABS(L9-_check!$B$15)<=0.0006,"✓","✗"),"✗"))) | M14: =IF(COUNT($I$6:$I$305)<300,"",IF(M9="","",IF(ISNUMBER(M9),IF(ABS(M9-_check!$B$16)<=0.0006,"✓","✗"),"✗"))) | N14: =IF(COUNT($I$6:$I$305)<300,"",IF(N9="","",IF(ISNUMBER(N9),IF(ABS(N9-_check!$B$17)<=0.0006,"✓","✗"),"✗")))
A15: C00010 | B15: R00624 | C15: 0.6541 | D15: no match | F15: C00079 | G15: R01142 | H15: 1 | I15: =VLOOKUP(F15,$A$6:$C$3205,3,FALSE)
A16: C00011 | B16: R00446 | C16: 1 | D16: exact | F16: C00102 | G16: R01427 | H16: 1 | I16: =VLOOKUP(F16,$A$6:$C$3205,3,FALSE) | K16: Read the trade-off: a strict dial (0.9) is almost always right and misses most true links; a loose one (0.5) finds them and sends letters to the wrong trader. The sample is 300 pairs: a precision of 87% on 200 pairs can be anything from about 81% to 91%.
A17: C00012 | B17: R01431 | C17: 1 | D17: exact | F17: C00113 | G17: R00350 | H17: 1 | I17: =VLOOKUP(F17,$A$6:$C$3205,3,FALSE)
A18: C00013 | B18: R02150 | C18: 1 | D18: exact | F18: C00120 | G18: R01761 | H18: 1 | I18: =VLOOKUP(F18,$A$6:$C$3205,3,FALSE)
A19: C00014 | B19: R01423 | C19: 1 | D19: exact | F19: C00122 | G19: R01080 | H19: 1 | I19: =VLOOKUP(F19,$A$6:$C$3205,3,FALSE)
A20: C00015 | B20: R01242 | C20: 0.6541 | D20: no match | F20: C00140 | G20: R00812 | H20: 1 | I20: =VLOOKUP(F20,$A$6:$C$3205,3,FALSE)
A21: C00016 | B21: R02239 | C21: 1 | D21: exact | F21: C00142 | G21: R02154 | H21: 1 | I21: =VLOOKUP(F21,$A$6:$C$3205,3,FALSE)
A22: C00017 | B22: R01133 | C22: 0.6541 | D22: no match | F22: C00147 | G22: R02873 | H22: 1 | I22: =VLOOKUP(F22,$A$6:$C$3205,3,FALSE)
A23: C00018 | B23: R00507 | C23: 0.2202 | D23: no match | F23: C00148 | G23: R02192 | H23: 1 | I23: =VLOOKUP(F23,$A$6:$C$3205,3,FALSE)
A24: C00019 | B24: R02036 | C24: 1 | D24: exact | F24: C00169 | G24: R02168 | H24: 1 | I24: =VLOOKUP(F24,$A$6:$C$3205,3,FALSE)
A25: C00020 | B25: R01739 | C25: 0.7718 | D25: review | F25: C00171 | G25: R01471 | H25: 1 | I25: =VLOOKUP(F25,$A$6:$C$3205,3,FALSE)
A26: C00021 | B26: R02476 | C26: 1 | D26: exact | F26: C00174 | G26: R01045 | H26: 1 | I26: =VLOOKUP(F26,$A$6:$C$3205,3,FALSE)
A27: C00022 | B27: R00487 | C27: 1 | D27: exact | F27: C00190 | G27: R01903 | H27: 1 | I27: =VLOOKUP(F27,$A$6:$C$3205,3,FALSE)
A28: C00023 | B28: R01823 | C28: 1 | D28: exact | F28: C00192 | G28: R01868 | H28: 1 | I28: =VLOOKUP(F28,$A$6:$C$3205,3,FALSE)
... A305: C00300 | B305: R02870 | C305: 1 | D305: exact | F305: C03177 | G305: R00007 | H305: 1 | I305: =VLOOKUP(F305,$A$6:$C$3205,3,FALSE)
A306: C00301 | B306: R01894 | C306: 0.7718 | D306: review
A307: C00302 | B307: R02400 | C307: 0.6541 | D307: no match
A308: C00303 | B308: R00726 | C308: 0.6541 | D308: no match
A309: C00304 | B309: R00152 | C309: 1 | D309: exact
A310: C00305 | B310: R02105 | C310: 0.7718 | D310: review
A311: C00306 | B311: R01953 | C311: 0.7942 | D311: review
A312: C00307 | B312: R02188 | C312: 1 | D312: exact
A313: C00308 | B313: R00577 | C313: 1 | D313: exact
A314: C00309 | B314: R02629 | C314: 0.6541 | D314: no match
A315: C00310 | B315: R01469 | C315: 1 | D315: exact
A316: C00311 | B316: R00689 | C316: 0.7718 | D316: review
A317: C00312 | B317: R00787 | C317: 1 | D317: exact
... A3205: C03200 | B3205: R02031 | C3205: 0.6541 | D3205: no match

Sheet S2 Four lists
A1: Sprint 2 · follow one import through both administrations: four questions, four lists
A2: A trader goes on the list of the first question it fails: 1 not known to tax, 2 not filing, 3 import not in its books, 4 sells below what it imports, else consistent for now. I01 is worked in grey. Your class comes from S1 Match, column S. You compute from the two blocks on the right: the lines that bear VAT (rows copied from the Declarations sheet) and the VAT returns (rows copied from the VAT returns sheet); first the steps above them (0, 6 and 7).
A3: Your choice: 4B_lab.xlsx (sheet Lists) already has every number. The checks assume the classes at the dial; if your group linked a review-band pair, its row will differ, and that is your call.
A5: Step | B5: What to do | H5: Your answer | I5: Check | J5: Hint 1 · the tool (the full formula is on the Hints sheet) | X5: Step | Y5: What to do (the columns the extract does not carry: before step 1) | AD5: Your answer | AE5: Check | AG5: Hint 1 (the full formula is on the Hints sheet)
A6: 1 | B6: Columns H and I: imports and import VAT paid over the last twelve months (month 25 on, Parameters), adding up the lines of the lines block on the right (columns X to AE) under the tax number used to clear; with no number, under the importer's own code. They read the month of each line (step 6). Then: the imports of the 25, added up. | H6: =SUM(H17:H41) | I6: =IF(H6="","",IF(ISNUMBER(H6),IF(ABS(H6-_check!$B$18)<=1,"✓ matches","✗ not yet: see the hint"),"✗ not yet: see the hint")) | J6: SUMIFS on the lines block: the value column, by tax number and from the first month of the last twelve; IF the number is blank, by importer code. | X6: 0 | Y6: Step 0, for confident groups: rebuild the lines block from the extract (the line above it says how) and compare the row count. How many lines does the block hold? | AD6: =COUNTA(X17:X12336) | AE6: =IF(AD6="","",IF(ISNUMBER(AD6),IF(ABS(AD6-_check!$B$165)<=0.5,"✓ matches","✗ not yet: see the hint"),"✗ not yet: see the hint")) | AG6: On the extract, filter Declarations on the regime, the date lodged and the tax numbers. Here, COUNTA counts the filled cells of the block's line column.
A7: 2 | B7: Columns J to M: on the tax side (column G), from the returns block on the right (columns AG to AM; they read the period number, step 7): the returns filed of the last six, the import VAT deducted and the sales over twelve months, and booked = deducted ÷ paid. Then: how many of the 25 filed all six of their last six returns? | H7: =COUNTIF(J17:J41,6) | I7: =IF(H7="","",IF(ISNUMBER(H7),IF(ABS(H7-_check!$B$19)<=0.5,"✓ matches","✗ not yet: see the hint"),"✗ not yet: see the hint")) | J7: COUNTIFS on the returns block: the tax number, filed = 1, period number ≥ 19. SUMIFS for the amounts, period number ≥ 13. | X7: 6 | Y7: In the lines block, column AE: the month (1 to 36) of each line, from the date lodged: October 2023 is month 1 (Parameters). T103629's lines are worked; copy down to the last row. How many lines were lodged in month 36? | AD7: =COUNTIF(AE17:AE12336,36) | AE7: =IF(AD7="","",IF(ISNUMBER(AD7),IF(ABS(AD7-_check!$B$166)<=0.5,"✓ matches","✗ not yet: see the hint"),"✗ not yet: see the hint")) | AG7: The date is text (year-month-day): LEFT takes the year, MID the calendar month. Then COUNTIF.
A8: 3 | B8: Columns N and O: sales ÷ imports, and the sector's usual (Sectors sheet). Column P: the first question failed (1 to 5). Column Q: the VAT at stake. Then: how many importers fail question 2 (not filing)? | H8: =COUNTIF(P17:P41,2) | I8: =IF(H8="","",IF(ISNUMBER(H8),IF(ABS(H8-_check!$B$20)<=0.5,"✓ matches","✗ not yet: see the hint"),"✗ not yet: see the hint")) | J8: IF inside IF, in the order of the four questions. VAT at stake, 10%: lists 1-2, VAT × imports × (usual − 1); lists 3-4, VAT × (imports × usual − sales); never below 0. | X8: 7 | Y8: In the returns block, column AM: the period number (1 to 24) of each return, from the period: 2024-10 is period 1 (Parameters). T103629's returns are worked; copy down. How many returns fall in the last twelve periods (period number 13 or more)? | AD8: =COUNTIF(AM17:AM616,">="&Parameters!$B$12) | AE8: =IF(AD8="","",IF(ISNUMBER(AD8),IF(ABS(AD8-_check!$B$167)<=0.5,"✓ matches","✗ not yet: see the hint"),"✗ not yet: see the hint")) | AG8: The period is text (year-month): LEFT and MID again. COUNTIF with ">="& the first period number of the last twelve (Parameters).
A9: 4 | B9: Column R: list 4 ranked by VAT at stake. Column S: the list, cut at the capacity. Then: the VAT at stake within capacity (lists 1 to 3, and list 4 up to the capacity). | H9: =SUMIF(P17:P41,"<=3",Q17:Q41)+SUMIFS(Q17:Q41,P17:P41,4,R17:R41,"<="&Parameters!$B$17) | I9: =IF(H9="","",IF(ISNUMBER(H9),IF(ABS(H9-_check!$B$21)<=1000,"✓ matches","✗ not yet: see the hint"),"✗ not yet: see the hint")) | J9: COUNTIFS counts the list-4 importers with more at stake. The summary table below adds up by list.
A10: 5 | B10: Columns T and U: the lead and the action for each list. Lock list, reason, lead and VAT at stake for the 25 on the site. | J10: List 1: tax, registration letter. List 2: tax, stop-filer letter. List 3: joint, ask for the books. List 4: tax with the customs data, desk audit, largest first.
X14: The lines block (row 17 on): rows copied from the Declarations sheet, as recorded: the lines that bear VAT (home use or release from a warehouse) lodged in months 25 to 36 under the 20 tax numbers of column C, and the lines with no number of the five importers that have none; T103629's first (48 lines, the worked number), then by tax number: 12,320 rows. Column AE is yours (step 6).
AG15: The returns block (row 17 on): rows copied from the VAT returns sheet, as recorded: the 600 returns of the 25 tax numbers the 25 importers can link to (column C, and the register's candidates of S1 Match column G), T103629's first. Column AM is yours (step 7).
A16: ref | B16: importer code | C16: tax number on the declaration | D16: importer (customs) | E16: sector | F16: your class (S1 Match) | G16: tax number on the tax side | H16: imports, 12 months (LCU) | I16: import VAT paid, 12 months (LCU) | J16: returns filed of the last 6 | K16: import VAT deducted, 12 months (LCU) | L16: booked (deducted ÷ paid) | M16: sales, 12 months (LCU) | N16: sales ÷ imports | O16: sector usual | P16: first question failed (1-5) | Q16: VAT at stake (LCU) | R16: rank on list 4 | S16: list | T16: check | U16: lead | V16: action | X16: line | Y16: date lodged | Z16: regime | AA16: importer | AB16: tax number as declared | AC16: customs value (LCU) | AD16: import VAT (LCU) | AE16: month (1-36) · you | AG16: tax number | AH16: period | AI16: filed (1 = yes) | AJ16: sales (LCU) | AK16: purchases (LCU) | AL16: import VAT deducted (LCU) | AM16: period number (1-24) · you
A17: I01 | B17: IMP00519 | C17: T103629 | D17: Ocean Electronics Co., Ltd | E17: Fuel and chemicals | F17: =IF('S1 Match'!S16="","",'S1 Match'!S16) | G17: =IF('S1 Match'!R16="","",'S1 Match'!R16) | H17: =IF(C17="",SUMIFS($AC$17:$AC$12336,$AA$17:$AA$12336,B17,$AE$17:$AE$12336,">="&Parameters!$B$13),SUMIFS($AC$17:$AC$12336,$AB$17:$AB$12336,C17,$AE$17:$AE$12336,">="&Parameters!$B$13)) | I17: =IF(C17="",SUMIFS($AD$17:$AD$12336,$AA$17:$AA$12336,B17,$AE$17:$AE$12336,">="&Parameters!$B$13),SUMIFS($AD$17:$AD$12336,$AB$17:$AB$12336,C17,$AE$17:$AE$12336,">="&Parameters!$B$13)) | J17: =IF(G17="","",COUNTIFS($AG$17:$AG$616,G17,$AI$17:$AI$616,1,$AM$17:$AM$616,">="&Parameters!$B$11)) | K17: =IF(G17="","",SUMIFS($AL$17:$AL$616,$AG$17:$AG$616,G17,$AM$17:$AM$616,">="&Parameters!$B$12)) | L17: =IF(OR(G17="",N(I17)=0),"",K17/I17) | M17: =IF(G17="","",SUMIFS($AJ$17:$AJ$616,$AG$17:$AG$616,G17,$AM$17:$AM$616,">="&Parameters!$B$12)) | N17: =IF(OR(M17="",N(H17)=0),"",M17/H17) | O17: =IFERROR(VLOOKUP(E17,Sectors!$A$5:$B$17,2,FALSE),"") | P17: =IF(G17="",1,IF(J17<Parameters!$B$14,2,IF(L17<Parameters!$B$15,3,IF(N17<Parameters!$B$16,4,5)))) | Q17: =IF(P17<=2,MAX(0,Parameters!$B$10*H17*(O17-1)),IF(P17<=4,MAX(0,Parameters!$B$10*(H17*O17-M17)),0)) | R17: =IF(COUNT($Q$17:$Q$41)<25,"",IF(P17=4,COUNTIFS($P$17:$P$41,4,$Q$17:$Q$41,">"&Q17)+1,"")) | S17: =IF(P17=4,IF(R17="","4 desk audit, ranked by VAT at stake",IF(R17<=Parameters!$B$17,"4 desk audit, ranked by VAT at stake","4b below imports, beyond capacity")),CHOOSE(P17,"1 not known to tax","2 not filing","3 import not booked","","5 consistent for now")) | T17: =IF(OR(H17="",S17="",F17=""),"",IFERROR(IF(AND(ABS(H17-_check!$B$22)<=1,J17=_check!$B$23,ABS(N17-_check!$B$24)<=0.0006),"✓","✗"),"✗")) | X17: L0167865 | Y17: 2025-10-07 | Z17: home_use | AA17: IMP00519 | AB17: T103629 | AC17: 2591057.5 | AD17: 272061.04 | AE17: =(LEFT(Y17,4)-Parameters!$B$23)*12+MID(Y17,6,2)-Parameters!$B$24+1 | AG17: T103629 | AH17: 2024-10 | AI17: 1 | AJ17: 135204943 | AK17: 141092703 | AL17: 13054509 | AM17: =(LEFT(AH17,4)-Parameters!$B$21)*12+MID(AH17,6,2)-Parameters!$B$22+1
A18: I02 | B18: IMP00753 | C18: T105264 | D18: Phoenix Glow Limited | E18: Textiles and apparel | F18: =IF('S1 Match'!S17="","",'S1 Match'!S17) | G18: =IF('S1 Match'!R17="","",'S1 Match'!R17) | H18: =IF(C18="",SUMIFS($AC$17:$AC$12336,$AA$17:$AA$12336,B18,$AE$17:$AE$12336,">="&Parameters!$B$13),SUMIFS($AC$17:$AC$12336,$AB$17:$AB$12336,C18,$AE$17:$AE$12336,">="&Parameters!$B$13)) | I18: =IF(C18="",SUMIFS($AD$17:$AD$12336,$AA$17:$AA$12336,B18,$AE$17:$AE$12336,">="&Parameters!$B$13),SUMIFS($AD$17:$AD$12336,$AB$17:$AB$12336,C18,$AE$17:$AE$12336,">="&Parameters!$B$13)) | J18: =IF(G18="","",COUNTIFS($AG$17:$AG$616,G18,$AI$17:$AI$616,1,$AM$17:$AM$616,">="&Parameters!$B$11)) | K18: =IF(G18="","",SUMIFS($AL$17:$AL$616,$AG$17:$AG$616,G18,$AM$17:$AM$616,">="&Parameters!$B$12)) | L18: =IF(OR(G18="",N(I18)=0),"",K18/I18) | M18: =IF(G18="","",SUMIFS($AJ$17:$AJ$616,$AG$17:$AG$616,G18,$AM$17:$AM$616,">="&Parameters!$B$12)) | N18: =IF(OR(M18="",N(H18)=0),"",M18/H18) | O18: =IFERROR(VLOOKUP(E18,Sectors!$A$5:$B$17,2,FALSE),"") | P18: =IF(G18="",1,IF(J18<Parameters!$B$14,2,IF(L18<Parameters!$B$15,3,IF(N18<Parameters!$B$16,4,5)))) | Q18: =IF(P18<=2,MAX(0,Parameters!$B$10*H18*(O18-1)),IF(P18<=4,MAX(0,Parameters!$B$10*(H18*O18-M18)),0)) | R18: =IF(P18=4,COUNTIFS($P$17:$P$41,4,$Q$17:$Q$41,">"&Q18)+1,"") | S18: =IF(P18=4,IF(R18<=Parameters!$B$17,"4 desk audit, ranked by VAT at stake","4b below imports, beyond capacity"),CHOOSE(P18,"1 not known to tax","2 not filing","3 import not booked","","5 consistent for now")) | T18: =IF(OR(H18="",S18="",F18=""),"",IFERROR(IF(AND(ABS(H18-_check!$B$25)<=1,J18=_check!$B$26,ABS(N18-_check!$B$27)<=0.0006),"✓","✗"),"✗")) | X18: L0169800 | Y18: 2025-10-16 | Z18: home_use | AA18: IMP00519 | AB18: T103629 | AC18: 18915339 | AD18: 1891533.9 | AE18: =(LEFT(Y18,4)-Parameters!$B$23)*12+MID(Y18,6,2)-Parameters!$B$24+1 | AG18: T103629 | AH18: 2024-11 | AI18: 1 | AJ18: 139784358 | AK18: 145871538 | AL18: 13303999 | AM18: =(LEFT(AH18,4)-Parameters!$B$21)*12+MID(AH18,6,2)-Parameters!$B$22+1
A19: I03 | B19: IMP00892 | C19: T106240 | D19: Delta Fruits Holdings Ltd | E19: General trading | F19: =IF('S1 Match'!S18="","",'S1 Match'!S18) | G19: =IF('S1 Match'!R18="","",'S1 Match'!R18) | H19: =IF(C19="",SUMIFS($AC$17:$AC$12336,$AA$17:$AA$12336,B19,$AE$17:$AE$12336,">="&Parameters!$B$13),SUMIFS($AC$17:$AC$12336,$AB$17:$AB$12336,C19,$AE$17:$AE$12336,">="&Parameters!$B$13)) | I19: =IF(C19="",SUMIFS($AD$17:$AD$12336,$AA$17:$AA$12336,B19,$AE$17:$AE$12336,">="&Parameters!$B$13),SUMIFS($AD$17:$AD$12336,$AB$17:$AB$12336,C19,$AE$17:$AE$12336,">="&Parameters!$B$13)) | J19: =IF(G19="","",COUNTIFS($AG$17:$AG$616,G19,$AI$17:$AI$616,1,$AM$17:$AM$616,">="&Parameters!$B$11)) | K19: =IF(G19="","",SUMIFS($AL$17:$AL$616,$AG$17:$AG$616,G19,$AM$17:$AM$616,">="&Parameters!$B$12)) | L19: =IF(OR(G19="",N(I19)=0),"",K19/I19) | M19: =IF(G19="","",SUMIFS($AJ$17:$AJ$616,$AG$17:$AG$616,G19,$AM$17:$AM$616,">="&Parameters!$B$12)) | N19: =IF(OR(M19="",N(H19)=0),"",M19/H19) | O19: =IFERROR(VLOOKUP(E19,Sectors!$A$5:$B$17,2,FALSE),"") | P19: =IF(G19="",1,IF(J19<Parameters!$B$14,2,IF(L19<Parameters!$B$15,3,IF(N19<Parameters!$B$16,4,5)))) | Q19: =IF(P19<=2,MAX(0,Parameters!$B$10*H19*(O19-1)),IF(P19<=4,MAX(0,Parameters!$B$10*(H19*O19-M19)),0)) | R19: =IF(P19=4,COUNTIFS($P$17:$P$41,4,$Q$17:$Q$41,">"&Q19)+1,"") | S19: =IF(P19=4,IF(R19<=Parameters!$B$17,"4 desk audit, ranked by VAT at stake","4b below imports, beyond capacity"),CHOOSE(P19,"1 not known to tax","2 not filing","3 import not booked","","5 consistent for now")) | T19: =IF(OR(H19="",S19="",F19=""),"",IFERROR(IF(AND(ABS(H19-_check!$B$28)<=1,J19=_check!$B$29,ABS(N19-_check!$B$30)<=0.0006),"✓","✗"),"✗")) | X19: L0170266 | Y19: 2025-10-18 | Z19: home_use | AA19: IMP00519 | AB19: T103629 | AC19: 11895689 | AD19: 1368004.3 | AE19: =(LEFT(Y19,4)-Parameters!$B$23)*12+MID(Y19,6,2)-Parameters!$B$24+1 | AG19: T103629 | AH19: 2024-12 | AI19: 1 | AJ19: 189409600 | AK19: 197657807 | AL19: 17993668 | AM19: =(LEFT(AH19,4)-Parameters!$B$21)*12+MID(AH19,6,2)-Parameters!$B$22+1
A20: I04 | B20: IMP00340 | C20: T102376 | D20: Great Vellmoor Steel Enterprises | E20: Fuel and chemicals | F20: =IF('S1 Match'!S19="","",'S1 Match'!S19) | G20: =IF('S1 Match'!R19="","",'S1 Match'!R19) | H20: =IF(C20="",SUMIFS($AC$17:$AC$12336,$AA$17:$AA$12336,B20,$AE$17:$AE$12336,">="&Parameters!$B$13),SUMIFS($AC$17:$AC$12336,$AB$17:$AB$12336,C20,$AE$17:$AE$12336,">="&Parameters!$B$13)) | I20: =IF(C20="",SUMIFS($AD$17:$AD$12336,$AA$17:$AA$12336,B20,$AE$17:$AE$12336,">="&Parameters!$B$13),SUMIFS($AD$17:$AD$12336,$AB$17:$AB$12336,C20,$AE$17:$AE$12336,">="&Parameters!$B$13)) | J20: =IF(G20="","",COUNTIFS($AG$17:$AG$616,G20,$AI$17:$AI$616,1,$AM$17:$AM$616,">="&Parameters!$B$11)) | K20: =IF(G20="","",SUMIFS($AL$17:$AL$616,$AG$17:$AG$616,G20,$AM$17:$AM$616,">="&Parameters!$B$12)) | L20: =IF(OR(G20="",N(I20)=0),"",K20/I20) | M20: =IF(G20="","",SUMIFS($AJ$17:$AJ$616,$AG$17:$AG$616,G20,$AM$17:$AM$616,">="&Parameters!$B$12)) | N20: =IF(OR(M20="",N(H20)=0),"",M20/H20) | O20: =IFERROR(VLOOKUP(E20,Sectors!$A$5:$B$17,2,FALSE),"") | P20: =IF(G20="",1,IF(J20<Parameters!$B$14,2,IF(L20<Parameters!$B$15,3,IF(N20<Parameters!$B$16,4,5)))) | Q20: =IF(P20<=2,MAX(0,Parameters!$B$10*H20*(O20-1)),IF(P20<=4,MAX(0,Parameters!$B$10*(H20*O20-M20)),0)) | R20: =IF(P20=4,COUNTIFS($P$17:$P$41,4,$Q$17:$Q$41,">"&Q20)+1,"") | S20: =IF(P20=4,IF(R20<=Parameters!$B$17,"4 desk audit, ranked by VAT at stake","4b below imports, beyond capacity"),CHOOSE(P20,"1 not known to tax","2 not filing","3 import not booked","","5 consistent for now")) | T20: =IF(OR(H20="",S20="",F20=""),"",IFERROR(IF(AND(ABS(H20-_check!$B$31)<=1,J20=_check!$B$32,ABS(N20-_check!$B$33)<=0.0006),"✓","✗"),"✗")) | X20: L0172414 | Y20: 2025-10-28 | Z20: home_use | AA20: IMP00519 | AB20: T103629 | AC20: 7420869 | AD20: 779191.24 | AE20: =(LEFT(Y20,4)-Parameters!$B$23)*12+MID(Y20,6,2)-Parameters!$B$24+1 | AG20: T103629 | AH20: 2025-01 | AI20: 1 | AJ20: 53949516 | AK20: 56298852 | AL20: 5207983 | AM20: =(LEFT(AH20,4)-Parameters!$B$21)*12+MID(AH20,6,2)-Parameters!$B$22+1
A21: I05 | B21: IMP00999 | C21: T106987 | D21: Carrick Electronics Group Ltd | E21: Electronics | F21: =IF('S1 Match'!S20="","",'S1 Match'!S20) | G21: =IF('S1 Match'!R20="","",'S1 Match'!R20) | H21: =IF(C21="",SUMIFS($AC$17:$AC$12336,$AA$17:$AA$12336,B21,$AE$17:$AE$12336,">="&Parameters!$B$13),SUMIFS($AC$17:$AC$12336,$AB$17:$AB$12336,C21,$AE$17:$AE$12336,">="&Parameters!$B$13)) | I21: =IF(C21="",SUMIFS($AD$17:$AD$12336,$AA$17:$AA$12336,B21,$AE$17:$AE$12336,">="&Parameters!$B$13),SUMIFS($AD$17:$AD$12336,$AB$17:$AB$12336,C21,$AE$17:$AE$12336,">="&Parameters!$B$13)) | J21: =IF(G21="","",COUNTIFS($AG$17:$AG$616,G21,$AI$17:$AI$616,1,$AM$17:$AM$616,">="&Parameters!$B$11)) | K21: =IF(G21="","",SUMIFS($AL$17:$AL$616,$AG$17:$AG$616,G21,$AM$17:$AM$616,">="&Parameters!$B$12)) | L21: =IF(OR(G21="",N(I21)=0),"",K21/I21) | M21: =IF(G21="","",SUMIFS($AJ$17:$AJ$616,$AG$17:$AG$616,G21,$AM$17:$AM$616,">="&Parameters!$B$12)) | N21: =IF(OR(M21="",N(H21)=0),"",M21/H21) | O21: =IFERROR(VLOOKUP(E21,Sectors!$A$5:$B$17,2,FALSE),"") | P21: =IF(G21="",1,IF(J21<Parameters!$B$14,2,IF(L21<Parameters!$B$15,3,IF(N21<Parameters!$B$16,4,5)))) | Q21: =IF(P21<=2,MAX(0,Parameters!$B$10*H21*(O21-1)),IF(P21<=4,MAX(0,Parameters!$B$10*(H21*O21-M21)),0)) | R21: =IF(P21=4,COUNTIFS($P$17:$P$41,4,$Q$17:$Q$41,">"&Q21)+1,"") | S21: =IF(P21=4,IF(R21<=Parameters!$B$17,"4 desk audit, ranked by VAT at stake","4b below imports, beyond capacity"),CHOOSE(P21,"1 not known to tax","2 not filing","3 import not booked","","5 consistent for now")) | T21: =IF(OR(H21="",S21="",F21=""),"",IFERROR(IF(AND(ABS(H21-_check!$B$34)<=1,J21=_check!$B$35,ABS(N21-_check!$B$36)<=0.0006),"✓","✗"),"✗")) | X21: L0175617 | Y21: 2025-11-14 | Z21: home_use | AA21: IMP00519 | AB21: T103629 | AC21: 2962327.8 | AD21: 311044.42 | AE21: =(LEFT(Y21,4)-Parameters!$B$23)*12+MID(Y21,6,2)-Parameters!$B$24+1 | AG21: T103629 | AH21: 2025-02 | AI21: 1 | AJ21: 162229768 | AK21: 169294377 | AL21: 14947581 | AM21: =(LEFT(AH21,4)-Parameters!$B$21)*12+MID(AH21,6,2)-Parameters!$B$22+1
A22: I06 | B22: IMP01037 | C22: T107258 | D22: Carrick Agro Enterprises | E22: Medical devices | F22: =IF('S1 Match'!S21="","",'S1 Match'!S21) | G22: =IF('S1 Match'!R21="","",'S1 Match'!R21) | H22: =IF(C22="",SUMIFS($AC$17:$AC$12336,$AA$17:$AA$12336,B22,$AE$17:$AE$12336,">="&Parameters!$B$13),SUMIFS($AC$17:$AC$12336,$AB$17:$AB$12336,C22,$AE$17:$AE$12336,">="&Parameters!$B$13)) | I22: =IF(C22="",SUMIFS($AD$17:$AD$12336,$AA$17:$AA$12336,B22,$AE$17:$AE$12336,">="&Parameters!$B$13),SUMIFS($AD$17:$AD$12336,$AB$17:$AB$12336,C22,$AE$17:$AE$12336,">="&Parameters!$B$13)) | J22: =IF(G22="","",COUNTIFS($AG$17:$AG$616,G22,$AI$17:$AI$616,1,$AM$17:$AM$616,">="&Parameters!$B$11)) | K22: =IF(G22="","",SUMIFS($AL$17:$AL$616,$AG$17:$AG$616,G22,$AM$17:$AM$616,">="&Parameters!$B$12)) | L22: =IF(OR(G22="",N(I22)=0),"",K22/I22) | M22: =IF(G22="","",SUMIFS($AJ$17:$AJ$616,$AG$17:$AG$616,G22,$AM$17:$AM$616,">="&Parameters!$B$12)) | N22: =IF(OR(M22="",N(H22)=0),"",M22/H22) | O22: =IFERROR(VLOOKUP(E22,Sectors!$A$5:$B$17,2,FALSE),"") | P22: =IF(G22="",1,IF(J22<Parameters!$B$14,2,IF(L22<Parameters!$B$15,3,IF(N22<Parameters!$B$16,4,5)))) | Q22: =IF(P22<=2,MAX(0,Parameters!$B$10*H22*(O22-1)),IF(P22<=4,MAX(0,Parameters!$B$10*(H22*O22-M22)),0)) | R22: =IF(P22=4,COUNTIFS($P$17:$P$41,4,$Q$17:$Q$41,">"&Q22)+1,"") | S22: =IF(P22=4,IF(R22<=Parameters!$B$17,"4 desk audit, ranked by VAT at stake","4b below imports, beyond capacity"),CHOOSE(P22,"1 not known to tax","2 not filing","3 import not booked","","5 consistent for now")) | T22: =IF(OR(H22="",S22="",F22=""),"",IFERROR(IF(AND(ABS(H22-_check!$B$37)<=1,J22=_check!$B$38,ABS(N22-_check!$B$39)<=0.0006),"✓","✗"),"✗")) | X22: L0177147 | Y22: 2025-11-21 | Z22: home_use | AA22: IMP00519 | AB22: T103629 | AC22: 1838070 | AD22: 211378.05 | AE22: =(LEFT(Y22,4)-Parameters!$B$23)*12+MID(Y22,6,2)-Parameters!$B$24+1 | AG22: T103629 | AH22: 2025-03 | AI22: 1 | AJ22: 144600399 | AK22: 150897303 | AL22: 13289978 | AM22: =(LEFT(AH22,4)-Parameters!$B$21)*12+MID(AH22,6,2)-Parameters!$B$22+1
A23: I07 | B23: IMP00306 | C23: T102141 | D23: Cobalt Mobile & Sons | E23: Furniture and household | F23: =IF('S1 Match'!S22="","",'S1 Match'!S22) | G23: =IF('S1 Match'!R22="","",'S1 Match'!R22) | H23: =IF(C23="",SUMIFS($AC$17:$AC$12336,$AA$17:$AA$12336,B23,$AE$17:$AE$12336,">="&Parameters!$B$13),SUMIFS($AC$17:$AC$12336,$AB$17:$AB$12336,C23,$AE$17:$AE$12336,">="&Parameters!$B$13)) | I23: =IF(C23="",SUMIFS($AD$17:$AD$12336,$AA$17:$AA$12336,B23,$AE$17:$AE$12336,">="&Parameters!$B$13),SUMIFS($AD$17:$AD$12336,$AB$17:$AB$12336,C23,$AE$17:$AE$12336,">="&Parameters!$B$13)) | J23: =IF(G23="","",COUNTIFS($AG$17:$AG$616,G23,$AI$17:$AI$616,1,$AM$17:$AM$616,">="&Parameters!$B$11)) | K23: =IF(G23="","",SUMIFS($AL$17:$AL$616,$AG$17:$AG$616,G23,$AM$17:$AM$616,">="&Parameters!$B$12)) | L23: =IF(OR(G23="",N(I23)=0),"",K23/I23) | M23: =IF(G23="","",SUMIFS($AJ$17:$AJ$616,$AG$17:$AG$616,G23,$AM$17:$AM$616,">="&Parameters!$B$12)) | N23: =IF(OR(M23="",N(H23)=0),"",M23/H23) | O23: =IFERROR(VLOOKUP(E23,Sectors!$A$5:$B$17,2,FALSE),"") | P23: =IF(G23="",1,IF(J23<Parameters!$B$14,2,IF(L23<Parameters!$B$15,3,IF(N23<Parameters!$B$16,4,5)))) | Q23: =IF(P23<=2,MAX(0,Parameters!$B$10*H23*(O23-1)),IF(P23<=4,MAX(0,Parameters!$B$10*(H23*O23-M23)),0)) | R23: =IF(P23=4,COUNTIFS($P$17:$P$41,4,$Q$17:$Q$41,">"&Q23)+1,"") | S23: =IF(P23=4,IF(R23<=Parameters!$B$17,"4 desk audit, ranked by VAT at stake","4b below imports, beyond capacity"),CHOOSE(P23,"1 not known to tax","2 not filing","3 import not booked","","5 consistent for now")) | T23: =IF(OR(H23="",S23="",F23=""),"",IFERROR(IF(AND(ABS(H23-_check!$B$40)<=1,J23=_check!$B$41,ABS(N23-_check!$B$42)<=0.0006),"✓","✗"),"✗")) | X23: L0178969 | Y23: 2025-12-01 | Z23: home_use | AA23: IMP00519 | AB23: T103629 | AC23: 7242997.7 | AD23: 760514.76 | AE23: =(LEFT(Y23,4)-Parameters!$B$23)*12+MID(Y23,6,2)-Parameters!$B$24+1 | AG23: T103629 | AH23: 2025-04 | AI23: 1 | AJ23: 257832175 | AK23: 269059975 | AL23: 24432952 | AM23: =(LEFT(AH23,4)-Parameters!$B$21)*12+MID(AH23,6,2)-Parameters!$B$22+1
A24: I08 | B24: IMP00147 | D24: Central Imports International Ltd | E24: Pharmaceuticals | F24: =IF('S1 Match'!S23="","",'S1 Match'!S23) | G24: =IF('S1 Match'!R23="","",'S1 Match'!R23) | H24: =IF(C24="",SUMIFS($AC$17:$AC$12336,$AA$17:$AA$12336,B24,$AE$17:$AE$12336,">="&Parameters!$B$13),SUMIFS($AC$17:$AC$12336,$AB$17:$AB$12336,C24,$AE$17:$AE$12336,">="&Parameters!$B$13)) | I24: =IF(C24="",SUMIFS($AD$17:$AD$12336,$AA$17:$AA$12336,B24,$AE$17:$AE$12336,">="&Parameters!$B$13),SUMIFS($AD$17:$AD$12336,$AB$17:$AB$12336,C24,$AE$17:$AE$12336,">="&Parameters!$B$13)) | J24: =IF(G24="","",COUNTIFS($AG$17:$AG$616,G24,$AI$17:$AI$616,1,$AM$17:$AM$616,">="&Parameters!$B$11)) | K24: =IF(G24="","",SUMIFS($AL$17:$AL$616,$AG$17:$AG$616,G24,$AM$17:$AM$616,">="&Parameters!$B$12)) | L24: =IF(OR(G24="",N(I24)=0),"",K24/I24) | M24: =IF(G24="","",SUMIFS($AJ$17:$AJ$616,$AG$17:$AG$616,G24,$AM$17:$AM$616,">="&Parameters!$B$12)) | N24: =IF(OR(M24="",N(H24)=0),"",M24/H24) | O24: =IFERROR(VLOOKUP(E24,Sectors!$A$5:$B$17,2,FALSE),"") | P24: =IF(G24="",1,IF(J24<Parameters!$B$14,2,IF(L24<Parameters!$B$15,3,IF(N24<Parameters!$B$16,4,5)))) | Q24: =IF(P24<=2,MAX(0,Parameters!$B$10*H24*(O24-1)),IF(P24<=4,MAX(0,Parameters!$B$10*(H24*O24-M24)),0)) | R24: =IF(P24=4,COUNTIFS($P$17:$P$41,4,$Q$17:$Q$41,">"&Q24)+1,"") | S24: =IF(P24=4,IF(R24<=Parameters!$B$17,"4 desk audit, ranked by VAT at stake","4b below imports, beyond capacity"),CHOOSE(P24,"1 not known to tax","2 not filing","3 import not booked","","5 consistent for now")) | T24: =IF(OR(H24="",S24="",F24=""),"",IFERROR(IF(AND(ABS(H24-_check!$B$43)<=1),"✓","✗"),"✗")) | X24: L0182729 | Y24: 2025-12-17 | Z24: home_use | AA24: IMP00519 | AB24: T103629 | AC24: 9354323.2 | AD24: 935432.32 | AE24: =(LEFT(Y24,4)-Parameters!$B$23)*12+MID(Y24,6,2)-Parameters!$B$24+1 | AG24: T103629 | AH24: 2025-05 | AI24: 1 | AJ24: 153838756 | AK24: 160537962 | AL24: 14160045 | AM24: =(LEFT(AH24,4)-Parameters!$B$21)*12+MID(AH24,6,2)-Parameters!$B$22+1
A25: I09 | B25: IMP00721 | D25: Phoenix Imports Partners Ltd | E25: General trading | F25: =IF('S1 Match'!S24="","",'S1 Match'!S24) | G25: =IF('S1 Match'!R24="","",'S1 Match'!R24) | H25: =IF(C25="",SUMIFS($AC$17:$AC$12336,$AA$17:$AA$12336,B25,$AE$17:$AE$12336,">="&Parameters!$B$13),SUMIFS($AC$17:$AC$12336,$AB$17:$AB$12336,C25,$AE$17:$AE$12336,">="&Parameters!$B$13)) | I25: =IF(C25="",SUMIFS($AD$17:$AD$12336,$AA$17:$AA$12336,B25,$AE$17:$AE$12336,">="&Parameters!$B$13),SUMIFS($AD$17:$AD$12336,$AB$17:$AB$12336,C25,$AE$17:$AE$12336,">="&Parameters!$B$13)) | J25: =IF(G25="","",COUNTIFS($AG$17:$AG$616,G25,$AI$17:$AI$616,1,$AM$17:$AM$616,">="&Parameters!$B$11)) | K25: =IF(G25="","",SUMIFS($AL$17:$AL$616,$AG$17:$AG$616,G25,$AM$17:$AM$616,">="&Parameters!$B$12)) | L25: =IF(OR(G25="",N(I25)=0),"",K25/I25) | M25: =IF(G25="","",SUMIFS($AJ$17:$AJ$616,$AG$17:$AG$616,G25,$AM$17:$AM$616,">="&Parameters!$B$12)) | N25: =IF(OR(M25="",N(H25)=0),"",M25/H25) | O25: =IFERROR(VLOOKUP(E25,Sectors!$A$5:$B$17,2,FALSE),"") | P25: =IF(G25="",1,IF(J25<Parameters!$B$14,2,IF(L25<Parameters!$B$15,3,IF(N25<Parameters!$B$16,4,5)))) | Q25: =IF(P25<=2,MAX(0,Parameters!$B$10*H25*(O25-1)),IF(P25<=4,MAX(0,Parameters!$B$10*(H25*O25-M25)),0)) | R25: =IF(P25=4,COUNTIFS($P$17:$P$41,4,$Q$17:$Q$41,">"&Q25)+1,"") | S25: =IF(P25=4,IF(R25<=Parameters!$B$17,"4 desk audit, ranked by VAT at stake","4b below imports, beyond capacity"),CHOOSE(P25,"1 not known to tax","2 not filing","3 import not booked","","5 consistent for now")) | T25: =IF(OR(H25="",S25="",F25=""),"",IFERROR(IF(AND(ABS(H25-_check!$B$44)<=1),"✓","✗"),"✗")) | X25: L0184350 | Y25: 2025-12-24 | Z25: home_use | AA25: IMP00519 | AB25: T103629 | AC25: 1252051.2 | AD25: 143985.89 | AE25: =(LEFT(Y25,4)-Parameters!$B$23)*12+MID(Y25,6,2)-Parameters!$B$24+1 | AG25: T103629 | AH25: 2025-06 | AI25: 1 | AJ25: 90969784 | AK25: 94931239 | AL25: 8441798 | AM25: =(LEFT(AH25,4)-Parameters!$B$21)*12+MID(AH25,6,2)-Parameters!$B$22+1
A26: I10 | B26: IMP00448 | C26: T103130 | D26: Global Electronics International Ltd | E26: Fuel and chemicals | F26: =IF('S1 Match'!S25="","",'S1 Match'!S25) | G26: =IF('S1 Match'!R25="","",'S1 Match'!R25) | H26: =IF(C26="",SUMIFS($AC$17:$AC$12336,$AA$17:$AA$12336,B26,$AE$17:$AE$12336,">="&Parameters!$B$13),SUMIFS($AC$17:$AC$12336,$AB$17:$AB$12336,C26,$AE$17:$AE$12336,">="&Parameters!$B$13)) | I26: =IF(C26="",SUMIFS($AD$17:$AD$12336,$AA$17:$AA$12336,B26,$AE$17:$AE$12336,">="&Parameters!$B$13),SUMIFS($AD$17:$AD$12336,$AB$17:$AB$12336,C26,$AE$17:$AE$12336,">="&Parameters!$B$13)) | J26: =IF(G26="","",COUNTIFS($AG$17:$AG$616,G26,$AI$17:$AI$616,1,$AM$17:$AM$616,">="&Parameters!$B$11)) | K26: =IF(G26="","",SUMIFS($AL$17:$AL$616,$AG$17:$AG$616,G26,$AM$17:$AM$616,">="&Parameters!$B$12)) | L26: =IF(OR(G26="",N(I26)=0),"",K26/I26) | M26: =IF(G26="","",SUMIFS($AJ$17:$AJ$616,$AG$17:$AG$616,G26,$AM$17:$AM$616,">="&Parameters!$B$12)) | N26: =IF(OR(M26="",N(H26)=0),"",M26/H26) | O26: =IFERROR(VLOOKUP(E26,Sectors!$A$5:$B$17,2,FALSE),"") | P26: =IF(G26="",1,IF(J26<Parameters!$B$14,2,IF(L26<Parameters!$B$15,3,IF(N26<Parameters!$B$16,4,5)))) | Q26: =IF(P26<=2,MAX(0,Parameters!$B$10*H26*(O26-1)),IF(P26<=4,MAX(0,Parameters!$B$10*(H26*O26-M26)),0)) | R26: =IF(P26=4,COUNTIFS($P$17:$P$41,4,$Q$17:$Q$41,">"&Q26)+1,"") | S26: =IF(P26=4,IF(R26<=Parameters!$B$17,"4 desk audit, ranked by VAT at stake","4b below imports, beyond capacity"),CHOOSE(P26,"1 not known to tax","2 not filing","3 import not booked","","5 consistent for now")) | T26: =IF(OR(H26="",S26="",F26=""),"",IFERROR(IF(AND(ABS(H26-_check!$B$45)<=1,J26=_check!$B$46,ABS(N26-_check!$B$47)<=0.0006),"✓","✗"),"✗")) | X26: L0186512 | Y26: 2026-01-05 | Z26: home_use | AA26: IMP00519 | AB26: T103629 | AC26: 13421704 | AD26: 1342170.4 | AE26: =(LEFT(Y26,4)-Parameters!$B$23)*12+MID(Y26,6,2)-Parameters!$B$24+1 | AG26: T103629 | AH26: 2025-07 | AI26: 1 | AJ26: 107883462 | AK26: 112581456 | AL26: 10397955 | AM26: =(LEFT(AH26,4)-Parameters!$B$21)*12+MID(AH26,6,2)-Parameters!$B$22+1
A27: I11 | B27: IMP00005 | C27: T100033 | D27: Central Foods Limited | E27: Steel and construction | F27: =IF('S1 Match'!S26="","",'S1 Match'!S26) | G27: =IF('S1 Match'!R26="","",'S1 Match'!R26) | H27: =IF(C27="",SUMIFS($AC$17:$AC$12336,$AA$17:$AA$12336,B27,$AE$17:$AE$12336,">="&Parameters!$B$13),SUMIFS($AC$17:$AC$12336,$AB$17:$AB$12336,C27,$AE$17:$AE$12336,">="&Parameters!$B$13)) | I27: =IF(C27="",SUMIFS($AD$17:$AD$12336,$AA$17:$AA$12336,B27,$AE$17:$AE$12336,">="&Parameters!$B$13),SUMIFS($AD$17:$AD$12336,$AB$17:$AB$12336,C27,$AE$17:$AE$12336,">="&Parameters!$B$13)) | J27: =IF(G27="","",COUNTIFS($AG$17:$AG$616,G27,$AI$17:$AI$616,1,$AM$17:$AM$616,">="&Parameters!$B$11)) | K27: =IF(G27="","",SUMIFS($AL$17:$AL$616,$AG$17:$AG$616,G27,$AM$17:$AM$616,">="&Parameters!$B$12)) | L27: =IF(OR(G27="",N(I27)=0),"",K27/I27) | M27: =IF(G27="","",SUMIFS($AJ$17:$AJ$616,$AG$17:$AG$616,G27,$AM$17:$AM$616,">="&Parameters!$B$12)) | N27: =IF(OR(M27="",N(H27)=0),"",M27/H27) | O27: =IFERROR(VLOOKUP(E27,Sectors!$A$5:$B$17,2,FALSE),"") | P27: =IF(G27="",1,IF(J27<Parameters!$B$14,2,IF(L27<Parameters!$B$15,3,IF(N27<Parameters!$B$16,4,5)))) | Q27: =IF(P27<=2,MAX(0,Parameters!$B$10*H27*(O27-1)),IF(P27<=4,MAX(0,Parameters!$B$10*(H27*O27-M27)),0)) | R27: =IF(P27=4,COUNTIFS($P$17:$P$41,4,$Q$17:$Q$41,">"&Q27)+1,"") | S27: =IF(P27=4,IF(R27<=Parameters!$B$17,"4 desk audit, ranked by VAT at stake","4b below imports, beyond capacity"),CHOOSE(P27,"1 not known to tax","2 not filing","3 import not booked","","5 consistent for now")) | T27: =IF(OR(H27="",S27="",F27=""),"",IFERROR(IF(AND(ABS(H27-_check!$B$48)<=1,J27=_check!$B$49,ABS(N27-_check!$B$50)<=0.0006),"✓","✗"),"✗")) | X27: L0187799 | Y27: 2026-01-10 | Z27: warehouse_out | AA27: IMP00519 | AB27: T103629 | AC27: 83000106 | AD27: 8300010.6 | AE27: =(LEFT(Y27,4)-Parameters!$B$23)*12+MID(Y27,6,2)-Parameters!$B$24+1 | AG27: T103629 | AH27: 2025-08 | AI27: 1 | AJ27: 26613516 | AK27: 27772453 | AL27: 2431972 | AM27: =(LEFT(AH27,4)-Parameters!$B$21)*12+MID(AH27,6,2)-Parameters!$B$22+1
A28: I12 | B28: IMP00156 | D28: Ocean Medical Co., Ltd | E28: Tobacco and beverages | F28: =IF('S1 Match'!S27="","",'S1 Match'!S27) | G28: =IF('S1 Match'!R27="","",'S1 Match'!R27) | H28: =IF(C28="",SUMIFS($AC$17:$AC$12336,$AA$17:$AA$12336,B28,$AE$17:$AE$12336,">="&Parameters!$B$13),SUMIFS($AC$17:$AC$12336,$AB$17:$AB$12336,C28,$AE$17:$AE$12336,">="&Parameters!$B$13)) | I28: =IF(C28="",SUMIFS($AD$17:$AD$12336,$AA$17:$AA$12336,B28,$AE$17:$AE$12336,">="&Parameters!$B$13),SUMIFS($AD$17:$AD$12336,$AB$17:$AB$12336,C28,$AE$17:$AE$12336,">="&Parameters!$B$13)) | J28: =IF(G28="","",COUNTIFS($AG$17:$AG$616,G28,$AI$17:$AI$616,1,$AM$17:$AM$616,">="&Parameters!$B$11)) | K28: =IF(G28="","",SUMIFS($AL$17:$AL$616,$AG$17:$AG$616,G28,$AM$17:$AM$616,">="&Parameters!$B$12)) | L28: =IF(OR(G28="",N(I28)=0),"",K28/I28) | M28: =IF(G28="","",SUMIFS($AJ$17:$AJ$616,$AG$17:$AG$616,G28,$AM$17:$AM$616,">="&Parameters!$B$12)) | N28: =IF(OR(M28="",N(H28)=0),"",M28/H28) | O28: =IFERROR(VLOOKUP(E28,Sectors!$A$5:$B$17,2,FALSE),"") | P28: =IF(G28="",1,IF(J28<Parameters!$B$14,2,IF(L28<Parameters!$B$15,3,IF(N28<Parameters!$B$16,4,5)))) | Q28: =IF(P28<=2,MAX(0,Parameters!$B$10*H28*(O28-1)),IF(P28<=4,MAX(0,Parameters!$B$10*(H28*O28-M28)),0)) | R28: =IF(P28=4,COUNTIFS($P$17:$P$41,4,$Q$17:$Q$41,">"&Q28)+1,"") | S28: =IF(P28=4,IF(R28<=Parameters!$B$17,"4 desk audit, ranked by VAT at stake","4b below imports, beyond capacity"),CHOOSE(P28,"1 not known to tax","2 not filing","3 import not booked","","5 consistent for now")) | T28: =IF(OR(H28="",S28="",F28=""),"",IFERROR(IF(AND(ABS(H28-_check!$B$51)<=1),"✓","✗"),"✗")) | X28: L0189342 | Y28: 2026-01-16 | Z28: home_use | AA28: IMP00519 | AB28: T103629 | AC28: 39741614 | AD28: 3974161.4 | AE28: =(LEFT(Y28,4)-Parameters!$B$23)*12+MID(Y28,6,2)-Parameters!$B$24+1 | AG28: T103629 | AH28: 2025-09 | AI28: 1 | AJ28: 17889049 | AK28: 18668062 | AL28: 1738749 | AM28: =(LEFT(AH28,4)-Parameters!$B$21)*12+MID(AH28,6,2)-Parameters!$B$22+1
A29: I13 | B29: IMP00950 | D29: Central Enterprises Co. | E29: Tobacco and beverages | F29: =IF('S1 Match'!S28="","",'S1 Match'!S28) | G29: =IF('S1 Match'!R28="","",'S1 Match'!R28) | H29: =IF(C29="",SUMIFS($AC$17:$AC$12336,$AA$17:$AA$12336,B29,$AE$17:$AE$12336,">="&Parameters!$B$13),SUMIFS($AC$17:$AC$12336,$AB$17:$AB$12336,C29,$AE$17:$AE$12336,">="&Parameters!$B$13)) | I29: =IF(C29="",SUMIFS($AD$17:$AD$12336,$AA$17:$AA$12336,B29,$AE$17:$AE$12336,">="&Parameters!$B$13),SUMIFS($AD$17:$AD$12336,$AB$17:$AB$12336,C29,$AE$17:$AE$12336,">="&Parameters!$B$13)) | J29: =IF(G29="","",COUNTIFS($AG$17:$AG$616,G29,$AI$17:$AI$616,1,$AM$17:$AM$616,">="&Parameters!$B$11)) | K29: =IF(G29="","",SUMIFS($AL$17:$AL$616,$AG$17:$AG$616,G29,$AM$17:$AM$616,">="&Parameters!$B$12)) | L29: =IF(OR(G29="",N(I29)=0),"",K29/I29) | M29: =IF(G29="","",SUMIFS($AJ$17:$AJ$616,$AG$17:$AG$616,G29,$AM$17:$AM$616,">="&Parameters!$B$12)) | N29: =IF(OR(M29="",N(H29)=0),"",M29/H29) | O29: =IFERROR(VLOOKUP(E29,Sectors!$A$5:$B$17,2,FALSE),"") | P29: =IF(G29="",1,IF(J29<Parameters!$B$14,2,IF(L29<Parameters!$B$15,3,IF(N29<Parameters!$B$16,4,5)))) | Q29: =IF(P29<=2,MAX(0,Parameters!$B$10*H29*(O29-1)),IF(P29<=4,MAX(0,Parameters!$B$10*(H29*O29-M29)),0)) | R29: =IF(P29=4,COUNTIFS($P$17:$P$41,4,$Q$17:$Q$41,">"&Q29)+1,"") | S29: =IF(P29=4,IF(R29<=Parameters!$B$17,"4 desk audit, ranked by VAT at stake","4b below imports, beyond capacity"),CHOOSE(P29,"1 not known to tax","2 not filing","3 import not booked","","5 consistent for now")) | T29: =IF(OR(H29="",S29="",F29=""),"",IFERROR(IF(AND(ABS(H29-_check!$B$52)<=1),"✓","✗"),"✗")) | X29: L0191642 | Y29: 2026-01-25 | Z29: home_use | AA29: IMP00519 | AB29: T103629 | AC29: 68765500 | AD29: 6876550 | AE29: =(LEFT(Y29,4)-Parameters!$B$23)*12+MID(Y29,6,2)-Parameters!$B$24+1 | AG29: T103629 | AH29: 2025-10 | AI29: 1 | AJ29: 43422561 | AK29: 45313480 | AL29: 4371468 | AM29: =(LEFT(AH29,4)-Parameters!$B$21)*12+MID(AH29,6,2)-Parameters!$B$22+1
A30: I14 | B30: IMP01242 | C30: T108692 | D30: Royal Agro Co., Ltd | E30: Electronics | F30: =IF('S1 Match'!S29="","",'S1 Match'!S29) | G30: =IF('S1 Match'!R29="","",'S1 Match'!R29) | H30: =IF(C30="",SUMIFS($AC$17:$AC$12336,$AA$17:$AA$12336,B30,$AE$17:$AE$12336,">="&Parameters!$B$13),SUMIFS($AC$17:$AC$12336,$AB$17:$AB$12336,C30,$AE$17:$AE$12336,">="&Parameters!$B$13)) | I30: =IF(C30="",SUMIFS($AD$17:$AD$12336,$AA$17:$AA$12336,B30,$AE$17:$AE$12336,">="&Parameters!$B$13),SUMIFS($AD$17:$AD$12336,$AB$17:$AB$12336,C30,$AE$17:$AE$12336,">="&Parameters!$B$13)) | J30: =IF(G30="","",COUNTIFS($AG$17:$AG$616,G30,$AI$17:$AI$616,1,$AM$17:$AM$616,">="&Parameters!$B$11)) | K30: =IF(G30="","",SUMIFS($AL$17:$AL$616,$AG$17:$AG$616,G30,$AM$17:$AM$616,">="&Parameters!$B$12)) | L30: =IF(OR(G30="",N(I30)=0),"",K30/I30) | M30: =IF(G30="","",SUMIFS($AJ$17:$AJ$616,$AG$17:$AG$616,G30,$AM$17:$AM$616,">="&Parameters!$B$12)) | N30: =IF(OR(M30="",N(H30)=0),"",M30/H30) | O30: =IFERROR(VLOOKUP(E30,Sectors!$A$5:$B$17,2,FALSE),"") | P30: =IF(G30="",1,IF(J30<Parameters!$B$14,2,IF(L30<Parameters!$B$15,3,IF(N30<Parameters!$B$16,4,5)))) | Q30: =IF(P30<=2,MAX(0,Parameters!$B$10*H30*(O30-1)),IF(P30<=4,MAX(0,Parameters!$B$10*(H30*O30-M30)),0)) | R30: =IF(P30=4,COUNTIFS($P$17:$P$41,4,$Q$17:$Q$41,">"&Q30)+1,"") | S30: =IF(P30=4,IF(R30<=Parameters!$B$17,"4 desk audit, ranked by VAT at stake","4b below imports, beyond capacity"),CHOOSE(P30,"1 not known to tax","2 not filing","3 import not booked","","5 consistent for now")) | T30: =IF(OR(H30="",S30="",F30=""),"",IFERROR(IF(AND(ABS(H30-_check!$B$53)<=1,J30=_check!$B$54,ABS(N30-_check!$B$55)<=0.0006),"✓","✗"),"✗")) | X30: L0193152 | Y30: 2026-02-03 | Z30: home_use | AA30: IMP00519 | AB30: T103629 | AC30: 61258602 | AD30: 6125860.2 | AE30: =(LEFT(Y30,4)-Parameters!$B$23)*12+MID(Y30,6,2)-Parameters!$B$24+1 | AG30: T103629 | AH30: 2025-11 | AI30: 1 | AJ30: 5106087 | AK30: 5328442 | AL30: 531339 | AM30: =(LEFT(AH30,4)-Parameters!$B$21)*12+MID(AH30,6,2)-Parameters!$B$22+1
A31: I15 | B31: IMP00011 | C31: T100070 | D31: Silk Road Steel Co. | E31: Pharmaceuticals | F31: =IF('S1 Match'!S30="","",'S1 Match'!S30) | G31: =IF('S1 Match'!R30="","",'S1 Match'!R30) | H31: =IF(C31="",SUMIFS($AC$17:$AC$12336,$AA$17:$AA$12336,B31,$AE$17:$AE$12336,">="&Parameters!$B$13),SUMIFS($AC$17:$AC$12336,$AB$17:$AB$12336,C31,$AE$17:$AE$12336,">="&Parameters!$B$13)) | I31: =IF(C31="",SUMIFS($AD$17:$AD$12336,$AA$17:$AA$12336,B31,$AE$17:$AE$12336,">="&Parameters!$B$13),SUMIFS($AD$17:$AD$12336,$AB$17:$AB$12336,C31,$AE$17:$AE$12336,">="&Parameters!$B$13)) | J31: =IF(G31="","",COUNTIFS($AG$17:$AG$616,G31,$AI$17:$AI$616,1,$AM$17:$AM$616,">="&Parameters!$B$11)) | K31: =IF(G31="","",SUMIFS($AL$17:$AL$616,$AG$17:$AG$616,G31,$AM$17:$AM$616,">="&Parameters!$B$12)) | L31: =IF(OR(G31="",N(I31)=0),"",K31/I31) | M31: =IF(G31="","",SUMIFS($AJ$17:$AJ$616,$AG$17:$AG$616,G31,$AM$17:$AM$616,">="&Parameters!$B$12)) | N31: =IF(OR(M31="",N(H31)=0),"",M31/H31) | O31: =IFERROR(VLOOKUP(E31,Sectors!$A$5:$B$17,2,FALSE),"") | P31: =IF(G31="",1,IF(J31<Parameters!$B$14,2,IF(L31<Parameters!$B$15,3,IF(N31<Parameters!$B$16,4,5)))) | Q31: =IF(P31<=2,MAX(0,Parameters!$B$10*H31*(O31-1)),IF(P31<=4,MAX(0,Parameters!$B$10*(H31*O31-M31)),0)) | R31: =IF(P31=4,COUNTIFS($P$17:$P$41,4,$Q$17:$Q$41,">"&Q31)+1,"") | S31: =IF(P31=4,IF(R31<=Parameters!$B$17,"4 desk audit, ranked by VAT at stake","4b below imports, beyond capacity"),CHOOSE(P31,"1 not known to tax","2 not filing","3 import not booked","","5 consistent for now")) | T31: =IF(OR(H31="",S31="",F31=""),"",IFERROR(IF(AND(ABS(H31-_check!$B$56)<=1,J31=_check!$B$57,ABS(N31-_check!$B$58)<=0.0006),"✓","✗"),"✗")) | X31: L0194436 | Y31: 2026-02-08 | Z31: home_use | AA31: IMP00519 | AB31: T103629 | AC31: 5927046 | AD31: 622339.83 | AE31: =(LEFT(Y31,4)-Parameters!$B$23)*12+MID(Y31,6,2)-Parameters!$B$24+1 | AG31: T103629 | AH31: 2025-12 | AI31: 0 | AM31: =(LEFT(AH31,4)-Parameters!$B$21)*12+MID(AH31,6,2)-Parameters!$B$22+1
A32: I16 | B32: IMP01089 | C32: T107617 | D32: Carrick Trading & Sons | E32: Machinery | F32: =IF('S1 Match'!S31="","",'S1 Match'!S31) | G32: =IF('S1 Match'!R31="","",'S1 Match'!R31) | H32: =IF(C32="",SUMIFS($AC$17:$AC$12336,$AA$17:$AA$12336,B32,$AE$17:$AE$12336,">="&Parameters!$B$13),SUMIFS($AC$17:$AC$12336,$AB$17:$AB$12336,C32,$AE$17:$AE$12336,">="&Parameters!$B$13)) | I32: =IF(C32="",SUMIFS($AD$17:$AD$12336,$AA$17:$AA$12336,B32,$AE$17:$AE$12336,">="&Parameters!$B$13),SUMIFS($AD$17:$AD$12336,$AB$17:$AB$12336,C32,$AE$17:$AE$12336,">="&Parameters!$B$13)) | J32: =IF(G32="","",COUNTIFS($AG$17:$AG$616,G32,$AI$17:$AI$616,1,$AM$17:$AM$616,">="&Parameters!$B$11)) | K32: =IF(G32="","",SUMIFS($AL$17:$AL$616,$AG$17:$AG$616,G32,$AM$17:$AM$616,">="&Parameters!$B$12)) | L32: =IF(OR(G32="",N(I32)=0),"",K32/I32) | M32: =IF(G32="","",SUMIFS($AJ$17:$AJ$616,$AG$17:$AG$616,G32,$AM$17:$AM$616,">="&Parameters!$B$12)) | N32: =IF(OR(M32="",N(H32)=0),"",M32/H32) | O32: =IFERROR(VLOOKUP(E32,Sectors!$A$5:$B$17,2,FALSE),"") | P32: =IF(G32="",1,IF(J32<Parameters!$B$14,2,IF(L32<Parameters!$B$15,3,IF(N32<Parameters!$B$16,4,5)))) | Q32: =IF(P32<=2,MAX(0,Parameters!$B$10*H32*(O32-1)),IF(P32<=4,MAX(0,Parameters!$B$10*(H32*O32-M32)),0)) | R32: =IF(P32=4,COUNTIFS($P$17:$P$41,4,$Q$17:$Q$41,">"&Q32)+1,"") | S32: =IF(P32=4,IF(R32<=Parameters!$B$17,"4 desk audit, ranked by VAT at stake","4b below imports, beyond capacity"),CHOOSE(P32,"1 not known to tax","2 not filing","3 import not booked","","5 consistent for now")) | T32: =IF(OR(H32="",S32="",F32=""),"",IFERROR(IF(AND(ABS(H32-_check!$B$59)<=1,J32=_check!$B$60,ABS(N32-_check!$B$61)<=0.0006),"✓","✗"),"✗")) | X32: L0194990 | Y32: 2026-02-10 | Z32: home_use | AA32: IMP00519 | AB32: T103629 | AC32: 1.3345751e+08 | AD32: 13345751 | AE32: =(LEFT(Y32,4)-Parameters!$B$23)*12+MID(Y32,6,2)-Parameters!$B$24+1 | AG32: T103629 | AH32: 2026-01 | AI32: 1 | AJ32: 217978797 | AK32: 227471105 | AL32: 20421903 | AM32: =(LEFT(AH32,4)-Parameters!$B$21)*12+MID(AH32,6,2)-Parameters!$B$22+1
A33: I17 | B33: IMP01481 | D33: Ocean Industries Holdings Ltd | E33: Steel and construction | F33: =IF('S1 Match'!S32="","",'S1 Match'!S32) | G33: =IF('S1 Match'!R32="","",'S1 Match'!R32) | H33: =IF(C33="",SUMIFS($AC$17:$AC$12336,$AA$17:$AA$12336,B33,$AE$17:$AE$12336,">="&Parameters!$B$13),SUMIFS($AC$17:$AC$12336,$AB$17:$AB$12336,C33,$AE$17:$AE$12336,">="&Parameters!$B$13)) | I33: =IF(C33="",SUMIFS($AD$17:$AD$12336,$AA$17:$AA$12336,B33,$AE$17:$AE$12336,">="&Parameters!$B$13),SUMIFS($AD$17:$AD$12336,$AB$17:$AB$12336,C33,$AE$17:$AE$12336,">="&Parameters!$B$13)) | J33: =IF(G33="","",COUNTIFS($AG$17:$AG$616,G33,$AI$17:$AI$616,1,$AM$17:$AM$616,">="&Parameters!$B$11)) | K33: =IF(G33="","",SUMIFS($AL$17:$AL$616,$AG$17:$AG$616,G33,$AM$17:$AM$616,">="&Parameters!$B$12)) | L33: =IF(OR(G33="",N(I33)=0),"",K33/I33) | M33: =IF(G33="","",SUMIFS($AJ$17:$AJ$616,$AG$17:$AG$616,G33,$AM$17:$AM$616,">="&Parameters!$B$12)) | N33: =IF(OR(M33="",N(H33)=0),"",M33/H33) | O33: =IFERROR(VLOOKUP(E33,Sectors!$A$5:$B$17,2,FALSE),"") | P33: =IF(G33="",1,IF(J33<Parameters!$B$14,2,IF(L33<Parameters!$B$15,3,IF(N33<Parameters!$B$16,4,5)))) | Q33: =IF(P33<=2,MAX(0,Parameters!$B$10*H33*(O33-1)),IF(P33<=4,MAX(0,Parameters!$B$10*(H33*O33-M33)),0)) | R33: =IF(P33=4,COUNTIFS($P$17:$P$41,4,$Q$17:$Q$41,">"&Q33)+1,"") | S33: =IF(P33=4,IF(R33<=Parameters!$B$17,"4 desk audit, ranked by VAT at stake","4b below imports, beyond capacity"),CHOOSE(P33,"1 not known to tax","2 not filing","3 import not booked","","5 consistent for now")) | T33: =IF(OR(H33="",S33="",F33=""),"",IFERROR(IF(AND(ABS(H33-_check!$B$62)<=1),"✓","✗"),"✗")) | X33: L0195784 | Y33: 2026-02-13 | Z33: home_use | AA33: IMP00519 | AB33: T103629 | AC33: 33024090 | AD33: 3302409 | AE33: =(LEFT(Y33,4)-Parameters!$B$23)*12+MID(Y33,6,2)-Parameters!$B$24+1 | AG33: T103629 | AH33: 2026-02 | AI33: 1 | AJ33: 310645644 | AK33: 324173309 | AL33: 29121908 | AM33: =(LEFT(AH33,4)-Parameters!$B$21)*12+MID(AH33,6,2)-Parameters!$B$22+1
A34: I18 | B34: IMP01142 | C34: T107992 | D34: Arden Living Co. | E34: Fuel and chemicals | F34: =IF('S1 Match'!S33="","",'S1 Match'!S33) | G34: =IF('S1 Match'!R33="","",'S1 Match'!R33) | H34: =IF(C34="",SUMIFS($AC$17:$AC$12336,$AA$17:$AA$12336,B34,$AE$17:$AE$12336,">="&Parameters!$B$13),SUMIFS($AC$17:$AC$12336,$AB$17:$AB$12336,C34,$AE$17:$AE$12336,">="&Parameters!$B$13)) | I34: =IF(C34="",SUMIFS($AD$17:$AD$12336,$AA$17:$AA$12336,B34,$AE$17:$AE$12336,">="&Parameters!$B$13),SUMIFS($AD$17:$AD$12336,$AB$17:$AB$12336,C34,$AE$17:$AE$12336,">="&Parameters!$B$13)) | J34: =IF(G34="","",COUNTIFS($AG$17:$AG$616,G34,$AI$17:$AI$616,1,$AM$17:$AM$616,">="&Parameters!$B$11)) | K34: =IF(G34="","",SUMIFS($AL$17:$AL$616,$AG$17:$AG$616,G34,$AM$17:$AM$616,">="&Parameters!$B$12)) | L34: =IF(OR(G34="",N(I34)=0),"",K34/I34) | M34: =IF(G34="","",SUMIFS($AJ$17:$AJ$616,$AG$17:$AG$616,G34,$AM$17:$AM$616,">="&Parameters!$B$12)) | N34: =IF(OR(M34="",N(H34)=0),"",M34/H34) | O34: =IFERROR(VLOOKUP(E34,Sectors!$A$5:$B$17,2,FALSE),"") | P34: =IF(G34="",1,IF(J34<Parameters!$B$14,2,IF(L34<Parameters!$B$15,3,IF(N34<Parameters!$B$16,4,5)))) | Q34: =IF(P34<=2,MAX(0,Parameters!$B$10*H34*(O34-1)),IF(P34<=4,MAX(0,Parameters!$B$10*(H34*O34-M34)),0)) | R34: =IF(P34=4,COUNTIFS($P$17:$P$41,4,$Q$17:$Q$41,">"&Q34)+1,"") | S34: =IF(P34=4,IF(R34<=Parameters!$B$17,"4 desk audit, ranked by VAT at stake","4b below imports, beyond capacity"),CHOOSE(P34,"1 not known to tax","2 not filing","3 import not booked","","5 consistent for now")) | T34: =IF(OR(H34="",S34="",F34=""),"",IFERROR(IF(AND(ABS(H34-_check!$B$63)<=1,J34=_check!$B$64,ABS(N34-_check!$B$65)<=0.0006),"✓","✗"),"✗")) | X34: L0198435 | Y34: 2026-02-23 | Z34: home_use | AA34: IMP00519 | AB34: T103629 | AC34: 58380777 | AD34: 5838077.7 | AE34: =(LEFT(Y34,4)-Parameters!$B$23)*12+MID(Y34,6,2)-Parameters!$B$24+1 | AG34: T103629 | AH34: 2026-03 | AI34: 1 | AJ34: 23170540 | AK34: 24179546 | AL34: 2266273 | AM34: =(LEFT(AH34,4)-Parameters!$B$21)*12+MID(AH34,6,2)-Parameters!$B$22+1
A35: I19 | B35: IMP01310 | C35: T109167 | D35: Pacific Living Co. | E35: Textiles and apparel | F35: =IF('S1 Match'!S34="","",'S1 Match'!S34) | G35: =IF('S1 Match'!R34="","",'S1 Match'!R34) | H35: =IF(C35="",SUMIFS($AC$17:$AC$12336,$AA$17:$AA$12336,B35,$AE$17:$AE$12336,">="&Parameters!$B$13),SUMIFS($AC$17:$AC$12336,$AB$17:$AB$12336,C35,$AE$17:$AE$12336,">="&Parameters!$B$13)) | I35: =IF(C35="",SUMIFS($AD$17:$AD$12336,$AA$17:$AA$12336,B35,$AE$17:$AE$12336,">="&Parameters!$B$13),SUMIFS($AD$17:$AD$12336,$AB$17:$AB$12336,C35,$AE$17:$AE$12336,">="&Parameters!$B$13)) | J35: =IF(G35="","",COUNTIFS($AG$17:$AG$616,G35,$AI$17:$AI$616,1,$AM$17:$AM$616,">="&Parameters!$B$11)) | K35: =IF(G35="","",SUMIFS($AL$17:$AL$616,$AG$17:$AG$616,G35,$AM$17:$AM$616,">="&Parameters!$B$12)) | L35: =IF(OR(G35="",N(I35)=0),"",K35/I35) | M35: =IF(G35="","",SUMIFS($AJ$17:$AJ$616,$AG$17:$AG$616,G35,$AM$17:$AM$616,">="&Parameters!$B$12)) | N35: =IF(OR(M35="",N(H35)=0),"",M35/H35) | O35: =IFERROR(VLOOKUP(E35,Sectors!$A$5:$B$17,2,FALSE),"") | P35: =IF(G35="",1,IF(J35<Parameters!$B$14,2,IF(L35<Parameters!$B$15,3,IF(N35<Parameters!$B$16,4,5)))) | Q35: =IF(P35<=2,MAX(0,Parameters!$B$10*H35*(O35-1)),IF(P35<=4,MAX(0,Parameters!$B$10*(H35*O35-M35)),0)) | R35: =IF(P35=4,COUNTIFS($P$17:$P$41,4,$Q$17:$Q$41,">"&Q35)+1,"") | S35: =IF(P35=4,IF(R35<=Parameters!$B$17,"4 desk audit, ranked by VAT at stake","4b below imports, beyond capacity"),CHOOSE(P35,"1 not known to tax","2 not filing","3 import not booked","","5 consistent for now")) | T35: =IF(OR(H35="",S35="",F35=""),"",IFERROR(IF(AND(ABS(H35-_check!$B$66)<=1,J35=_check!$B$67,ABS(N35-_check!$B$68)<=0.0006),"✓","✗"),"✗")) | X35: L0200511 | Y35: 2026-03-03 | Z35: home_use | AA35: IMP00519 | AB35: T103629 | AC35: 12775719 | AD35: 1277571.9 | AE35: =(LEFT(Y35,4)-Parameters!$B$23)*12+MID(Y35,6,2)-Parameters!$B$24+1 | AG35: T103629 | AH35: 2026-04 | AI35: 1 | AJ35: 136780865 | AK35: 142737252 | AL35: 13026730 | AM35: =(LEFT(AH35,4)-Parameters!$B$21)*12+MID(AH35,6,2)-Parameters!$B$22+1
A36: I20 | B36: IMP00490 | C36: T103425 | D36: Ocean Trading International Ltd | E36: Machinery | F36: =IF('S1 Match'!S35="","",'S1 Match'!S35) | G36: =IF('S1 Match'!R35="","",'S1 Match'!R35) | H36: =IF(C36="",SUMIFS($AC$17:$AC$12336,$AA$17:$AA$12336,B36,$AE$17:$AE$12336,">="&Parameters!$B$13),SUMIFS($AC$17:$AC$12336,$AB$17:$AB$12336,C36,$AE$17:$AE$12336,">="&Parameters!$B$13)) | I36: =IF(C36="",SUMIFS($AD$17:$AD$12336,$AA$17:$AA$12336,B36,$AE$17:$AE$12336,">="&Parameters!$B$13),SUMIFS($AD$17:$AD$12336,$AB$17:$AB$12336,C36,$AE$17:$AE$12336,">="&Parameters!$B$13)) | J36: =IF(G36="","",COUNTIFS($AG$17:$AG$616,G36,$AI$17:$AI$616,1,$AM$17:$AM$616,">="&Parameters!$B$11)) | K36: =IF(G36="","",SUMIFS($AL$17:$AL$616,$AG$17:$AG$616,G36,$AM$17:$AM$616,">="&Parameters!$B$12)) | L36: =IF(OR(G36="",N(I36)=0),"",K36/I36) | M36: =IF(G36="","",SUMIFS($AJ$17:$AJ$616,$AG$17:$AG$616,G36,$AM$17:$AM$616,">="&Parameters!$B$12)) | N36: =IF(OR(M36="",N(H36)=0),"",M36/H36) | O36: =IFERROR(VLOOKUP(E36,Sectors!$A$5:$B$17,2,FALSE),"") | P36: =IF(G36="",1,IF(J36<Parameters!$B$14,2,IF(L36<Parameters!$B$15,3,IF(N36<Parameters!$B$16,4,5)))) | Q36: =IF(P36<=2,MAX(0,Parameters!$B$10*H36*(O36-1)),IF(P36<=4,MAX(0,Parameters!$B$10*(H36*O36-M36)),0)) | R36: =IF(P36=4,COUNTIFS($P$17:$P$41,4,$Q$17:$Q$41,">"&Q36)+1,"") | S36: =IF(P36=4,IF(R36<=Parameters!$B$17,"4 desk audit, ranked by VAT at stake","4b below imports, beyond capacity"),CHOOSE(P36,"1 not known to tax","2 not filing","3 import not booked","","5 consistent for now")) | T36: =IF(OR(H36="",S36="",F36=""),"",IFERROR(IF(AND(ABS(H36-_check!$B$69)<=1,J36=_check!$B$70,ABS(N36-_check!$B$71)<=0.0006),"✓","✗"),"✗")) | X36: L0201826 | Y36: 2026-03-08 | Z36: home_use | AA36: IMP00519 | AB36: T103629 | AC36: 2084536.7 | AD36: 218876.35 | AE36: =(LEFT(Y36,4)-Parameters!$B$23)*12+MID(Y36,6,2)-Parameters!$B$24+1 | AG36: T103629 | AH36: 2026-05 | AI36: 0 | AM36: =(LEFT(AH36,4)-Parameters!$B$21)*12+MID(AH36,6,2)-Parameters!$B$22+1
A37: I21 | B37: IMP00063 | C37: T100440 | D37: Metro Motors Co., Ltd | E37: Vehicles and parts | F37: =IF('S1 Match'!S36="","",'S1 Match'!S36) | G37: =IF('S1 Match'!R36="","",'S1 Match'!R36) | H37: =IF(C37="",SUMIFS($AC$17:$AC$12336,$AA$17:$AA$12336,B37,$AE$17:$AE$12336,">="&Parameters!$B$13),SUMIFS($AC$17:$AC$12336,$AB$17:$AB$12336,C37,$AE$17:$AE$12336,">="&Parameters!$B$13)) | I37: =IF(C37="",SUMIFS($AD$17:$AD$12336,$AA$17:$AA$12336,B37,$AE$17:$AE$12336,">="&Parameters!$B$13),SUMIFS($AD$17:$AD$12336,$AB$17:$AB$12336,C37,$AE$17:$AE$12336,">="&Parameters!$B$13)) | J37: =IF(G37="","",COUNTIFS($AG$17:$AG$616,G37,$AI$17:$AI$616,1,$AM$17:$AM$616,">="&Parameters!$B$11)) | K37: =IF(G37="","",SUMIFS($AL$17:$AL$616,$AG$17:$AG$616,G37,$AM$17:$AM$616,">="&Parameters!$B$12)) | L37: =IF(OR(G37="",N(I37)=0),"",K37/I37) | M37: =IF(G37="","",SUMIFS($AJ$17:$AJ$616,$AG$17:$AG$616,G37,$AM$17:$AM$616,">="&Parameters!$B$12)) | N37: =IF(OR(M37="",N(H37)=0),"",M37/H37) | O37: =IFERROR(VLOOKUP(E37,Sectors!$A$5:$B$17,2,FALSE),"") | P37: =IF(G37="",1,IF(J37<Parameters!$B$14,2,IF(L37<Parameters!$B$15,3,IF(N37<Parameters!$B$16,4,5)))) | Q37: =IF(P37<=2,MAX(0,Parameters!$B$10*H37*(O37-1)),IF(P37<=4,MAX(0,Parameters!$B$10*(H37*O37-M37)),0)) | R37: =IF(P37=4,COUNTIFS($P$17:$P$41,4,$Q$17:$Q$41,">"&Q37)+1,"") | S37: =IF(P37=4,IF(R37<=Parameters!$B$17,"4 desk audit, ranked by VAT at stake","4b below imports, beyond capacity"),CHOOSE(P37,"1 not known to tax","2 not filing","3 import not booked","","5 consistent for now")) | T37: =IF(OR(H37="",S37="",F37=""),"",IFERROR(IF(AND(ABS(H37-_check!$B$72)<=1,J37=_check!$B$73,ABS(N37-_check!$B$74)<=0.0006),"✓","✗"),"✗")) | X37: L0203968 | Y37: 2026-03-16 | Z37: home_use | AA37: IMP00519 | AB37: T103629 | AC37: 2068993.5 | AD37: 217244.32 | AE37: =(LEFT(Y37,4)-Parameters!$B$23)*12+MID(Y37,6,2)-Parameters!$B$24+1 | AG37: T103629 | AH37: 2026-06 | AI37: 1 | AJ37: 63537301 | AK37: 66304156 | AL37: 6013239 | AM37: =(LEFT(AH37,4)-Parameters!$B$21)*12+MID(AH37,6,2)-Parameters!$B$22+1
A38: I22 | B38: IMP00926 | C38: T106477 | D38: Metro Steel Partners Ltd | E38: Fuel and chemicals | F38: =IF('S1 Match'!S37="","",'S1 Match'!S37) | G38: =IF('S1 Match'!R37="","",'S1 Match'!R37) | H38: =IF(C38="",SUMIFS($AC$17:$AC$12336,$AA$17:$AA$12336,B38,$AE$17:$AE$12336,">="&Parameters!$B$13),SUMIFS($AC$17:$AC$12336,$AB$17:$AB$12336,C38,$AE$17:$AE$12336,">="&Parameters!$B$13)) | I38: =IF(C38="",SUMIFS($AD$17:$AD$12336,$AA$17:$AA$12336,B38,$AE$17:$AE$12336,">="&Parameters!$B$13),SUMIFS($AD$17:$AD$12336,$AB$17:$AB$12336,C38,$AE$17:$AE$12336,">="&Parameters!$B$13)) | J38: =IF(G38="","",COUNTIFS($AG$17:$AG$616,G38,$AI$17:$AI$616,1,$AM$17:$AM$616,">="&Parameters!$B$11)) | K38: =IF(G38="","",SUMIFS($AL$17:$AL$616,$AG$17:$AG$616,G38,$AM$17:$AM$616,">="&Parameters!$B$12)) | L38: =IF(OR(G38="",N(I38)=0),"",K38/I38) | M38: =IF(G38="","",SUMIFS($AJ$17:$AJ$616,$AG$17:$AG$616,G38,$AM$17:$AM$616,">="&Parameters!$B$12)) | N38: =IF(OR(M38="",N(H38)=0),"",M38/H38) | O38: =IFERROR(VLOOKUP(E38,Sectors!$A$5:$B$17,2,FALSE),"") | P38: =IF(G38="",1,IF(J38<Parameters!$B$14,2,IF(L38<Parameters!$B$15,3,IF(N38<Parameters!$B$16,4,5)))) | Q38: =IF(P38<=2,MAX(0,Parameters!$B$10*H38*(O38-1)),IF(P38<=4,MAX(0,Parameters!$B$10*(H38*O38-M38)),0)) | R38: =IF(P38=4,COUNTIFS($P$17:$P$41,4,$Q$17:$Q$41,">"&Q38)+1,"") | S38: =IF(P38=4,IF(R38<=Parameters!$B$17,"4 desk audit, ranked by VAT at stake","4b below imports, beyond capacity"),CHOOSE(P38,"1 not known to tax","2 not filing","3 import not booked","","5 consistent for now")) | T38: =IF(OR(H38="",S38="",F38=""),"",IFERROR(IF(AND(ABS(H38-_check!$B$75)<=1,J38=_check!$B$76,ABS(N38-_check!$B$77)<=0.0006),"✓","✗"),"✗")) | X38: L0204724 | Y38: 2026-03-19 | Z38: home_use | AA38: IMP00519 | AB38: T103629 | AC38: 4854125.6 | AD38: 558224.44 | AE38: =(LEFT(Y38,4)-Parameters!$B$23)*12+MID(Y38,6,2)-Parameters!$B$24+1 | AG38: T103629 | AH38: 2026-07 | AI38: 1 | AJ38: 370016094 | AK38: 386129159 | AL38: 35245894 | AM38: =(LEFT(AH38,4)-Parameters!$B$21)*12+MID(AH38,6,2)-Parameters!$B$22+1
A39: I23 | B39: IMP00643 | C39: T104498 | D39: Aldergate Agro Holdings Ltd | E39: Pharmaceuticals | F39: =IF('S1 Match'!S38="","",'S1 Match'!S38) | G39: =IF('S1 Match'!R38="","",'S1 Match'!R38) | H39: =IF(C39="",SUMIFS($AC$17:$AC$12336,$AA$17:$AA$12336,B39,$AE$17:$AE$12336,">="&Parameters!$B$13),SUMIFS($AC$17:$AC$12336,$AB$17:$AB$12336,C39,$AE$17:$AE$12336,">="&Parameters!$B$13)) | I39: =IF(C39="",SUMIFS($AD$17:$AD$12336,$AA$17:$AA$12336,B39,$AE$17:$AE$12336,">="&Parameters!$B$13),SUMIFS($AD$17:$AD$12336,$AB$17:$AB$12336,C39,$AE$17:$AE$12336,">="&Parameters!$B$13)) | J39: =IF(G39="","",COUNTIFS($AG$17:$AG$616,G39,$AI$17:$AI$616,1,$AM$17:$AM$616,">="&Parameters!$B$11)) | K39: =IF(G39="","",SUMIFS($AL$17:$AL$616,$AG$17:$AG$616,G39,$AM$17:$AM$616,">="&Parameters!$B$12)) | L39: =IF(OR(G39="",N(I39)=0),"",K39/I39) | M39: =IF(G39="","",SUMIFS($AJ$17:$AJ$616,$AG$17:$AG$616,G39,$AM$17:$AM$616,">="&Parameters!$B$12)) | N39: =IF(OR(M39="",N(H39)=0),"",M39/H39) | O39: =IFERROR(VLOOKUP(E39,Sectors!$A$5:$B$17,2,FALSE),"") | P39: =IF(G39="",1,IF(J39<Parameters!$B$14,2,IF(L39<Parameters!$B$15,3,IF(N39<Parameters!$B$16,4,5)))) | Q39: =IF(P39<=2,MAX(0,Parameters!$B$10*H39*(O39-1)),IF(P39<=4,MAX(0,Parameters!$B$10*(H39*O39-M39)),0)) | R39: =IF(P39=4,COUNTIFS($P$17:$P$41,4,$Q$17:$Q$41,">"&Q39)+1,"") | S39: =IF(P39=4,IF(R39<=Parameters!$B$17,"4 desk audit, ranked by VAT at stake","4b below imports, beyond capacity"),CHOOSE(P39,"1 not known to tax","2 not filing","3 import not booked","","5 consistent for now")) | T39: =IF(OR(H39="",S39="",F39=""),"",IFERROR(IF(AND(ABS(H39-_check!$B$78)<=1,J39=_check!$B$79,ABS(N39-_check!$B$80)<=0.0006),"✓","✗"),"✗")) | X39: L0207782 | Y39: 2026-04-02 | Z39: home_use | AA39: IMP00519 | AB39: T103629 | AC39: 12389883 | AD39: 1238988.3 | AE39: =(LEFT(Y39,4)-Parameters!$B$23)*12+MID(Y39,6,2)-Parameters!$B$24+1 | AG39: T103629 | AH39: 2026-08 | AI39: 1 | AJ39: 208119473 | AK39: 217182437 | AL39: 19071565 | AM39: =(LEFT(AH39,4)-Parameters!$B$21)*12+MID(AH39,6,2)-Parameters!$B$22+1
A40: I24 | B40: IMP00067 | C40: T100466 | D40: Pacific Enterprises Holdings Ltd | E40: Fuel and chemicals | F40: =IF('S1 Match'!S39="","",'S1 Match'!S39) | G40: =IF('S1 Match'!R39="","",'S1 Match'!R39) | H40: =IF(C40="",SUMIFS($AC$17:$AC$12336,$AA$17:$AA$12336,B40,$AE$17:$AE$12336,">="&Parameters!$B$13),SUMIFS($AC$17:$AC$12336,$AB$17:$AB$12336,C40,$AE$17:$AE$12336,">="&Parameters!$B$13)) | I40: =IF(C40="",SUMIFS($AD$17:$AD$12336,$AA$17:$AA$12336,B40,$AE$17:$AE$12336,">="&Parameters!$B$13),SUMIFS($AD$17:$AD$12336,$AB$17:$AB$12336,C40,$AE$17:$AE$12336,">="&Parameters!$B$13)) | J40: =IF(G40="","",COUNTIFS($AG$17:$AG$616,G40,$AI$17:$AI$616,1,$AM$17:$AM$616,">="&Parameters!$B$11)) | K40: =IF(G40="","",SUMIFS($AL$17:$AL$616,$AG$17:$AG$616,G40,$AM$17:$AM$616,">="&Parameters!$B$12)) | L40: =IF(OR(G40="",N(I40)=0),"",K40/I40) | M40: =IF(G40="","",SUMIFS($AJ$17:$AJ$616,$AG$17:$AG$616,G40,$AM$17:$AM$616,">="&Parameters!$B$12)) | N40: =IF(OR(M40="",N(H40)=0),"",M40/H40) | O40: =IFERROR(VLOOKUP(E40,Sectors!$A$5:$B$17,2,FALSE),"") | P40: =IF(G40="",1,IF(J40<Parameters!$B$14,2,IF(L40<Parameters!$B$15,3,IF(N40<Parameters!$B$16,4,5)))) | Q40: =IF(P40<=2,MAX(0,Parameters!$B$10*H40*(O40-1)),IF(P40<=4,MAX(0,Parameters!$B$10*(H40*O40-M40)),0)) | R40: =IF(P40=4,COUNTIFS($P$17:$P$41,4,$Q$17:$Q$41,">"&Q40)+1,"") | S40: =IF(P40=4,IF(R40<=Parameters!$B$17,"4 desk audit, ranked by VAT at stake","4b below imports, beyond capacity"),CHOOSE(P40,"1 not known to tax","2 not filing","3 import not booked","","5 consistent for now")) | T40: =IF(OR(H40="",S40="",F40=""),"",IFERROR(IF(AND(ABS(H40-_check!$B$81)<=1,J40=_check!$B$82,ABS(N40-_check!$B$83)<=0.0006),"✓","✗"),"✗")) | X40: L0208650 | Y40: 2026-04-05 | Z40: home_use | AA40: IMP00519 | AB40: T103629 | AC40: 3774427 | AD40: 396314.83 | AE40: =(LEFT(Y40,4)-Parameters!$B$23)*12+MID(Y40,6,2)-Parameters!$B$24+1 | AG40: T103629 | AH40: 2026-09 | AI40: 1 | AJ40: 128715295 | AK40: 134320451 | AL40: 12435653 | AM40: =(LEFT(AH40,4)-Parameters!$B$21)*12+MID(AH40,6,2)-Parameters!$B$22+1
A41: I25 | B41: IMP00288 | C41: T102011 | D41: Arden Fruits Enterprises | E41: Cosmetics and personal care | F41: =IF('S1 Match'!S40="","",'S1 Match'!S40) | G41: =IF('S1 Match'!R40="","",'S1 Match'!R40) | H41: =IF(C41="",SUMIFS($AC$17:$AC$12336,$AA$17:$AA$12336,B41,$AE$17:$AE$12336,">="&Parameters!$B$13),SUMIFS($AC$17:$AC$12336,$AB$17:$AB$12336,C41,$AE$17:$AE$12336,">="&Parameters!$B$13)) | I41: =IF(C41="",SUMIFS($AD$17:$AD$12336,$AA$17:$AA$12336,B41,$AE$17:$AE$12336,">="&Parameters!$B$13),SUMIFS($AD$17:$AD$12336,$AB$17:$AB$12336,C41,$AE$17:$AE$12336,">="&Parameters!$B$13)) | J41: =IF(G41="","",COUNTIFS($AG$17:$AG$616,G41,$AI$17:$AI$616,1,$AM$17:$AM$616,">="&Parameters!$B$11)) | K41: =IF(G41="","",SUMIFS($AL$17:$AL$616,$AG$17:$AG$616,G41,$AM$17:$AM$616,">="&Parameters!$B$12)) | L41: =IF(OR(G41="",N(I41)=0),"",K41/I41) | M41: =IF(G41="","",SUMIFS($AJ$17:$AJ$616,$AG$17:$AG$616,G41,$AM$17:$AM$616,">="&Parameters!$B$12)) | N41: =IF(OR(M41="",N(H41)=0),"",M41/H41) | O41: =IFERROR(VLOOKUP(E41,Sectors!$A$5:$B$17,2,FALSE),"") | P41: =IF(G41="",1,IF(J41<Parameters!$B$14,2,IF(L41<Parameters!$B$15,3,IF(N41<Parameters!$B$16,4,5)))) | Q41: =IF(P41<=2,MAX(0,Parameters!$B$10*H41*(O41-1)),IF(P41<=4,MAX(0,Parameters!$B$10*(H41*O41-M41)),0)) | R41: =IF(P41=4,COUNTIFS($P$17:$P$41,4,$Q$17:$Q$41,">"&Q41)+1,"") | S41: =IF(P41=4,IF(R41<=Parameters!$B$17,"4 desk audit, ranked by VAT at stake","4b below imports, beyond capacity"),CHOOSE(P41,"1 not known to tax","2 not filing","3 import not booked","","5 consistent for now")) | T41: =IF(OR(H41="",S41="",F41=""),"",IFERROR(IF(AND(ABS(H41-_check!$B$84)<=1,J41=_check!$B$85,ABS(N41-_check!$B$86)<=0.0006),"✓","✗"),"✗")) | X41: L0212170 | Y41: 2026-04-18 | Z41: home_use | AA41: IMP00519 | AB41: T103629 | AC41: 83173199 | AD41: 8317319.9 | AE41: =(LEFT(Y41,4)-Parameters!$B$23)*12+MID(Y41,6,2)-Parameters!$B$24+1 | AG41: T100033 | AH41: 2024-10 | AI41: 1 | AJ41: 59996 | AK41: 239984 | AL41: 0 | AM41: =(LEFT(AH41,4)-Parameters!$B$21)*12+MID(AH41,6,2)-Parameters!$B$22+1
X42: L0213249 | Y42: 2026-04-22 | Z42: home_use | AA42: IMP00519 | AB42: T103629 | AC42: 29254610 | AD42: 2925461 | AE42: =(LEFT(Y42,4)-Parameters!$B$23)*12+MID(Y42,6,2)-Parameters!$B$24+1 | AG42: T100033 | AH42: 2024-11 | AI42: 1 | AJ42: 66802 | AK42: 267207 | AL42: 0 | AM42: =(LEFT(AH42,4)-Parameters!$B$21)*12+MID(AH42,6,2)-Parameters!$B$22+1
X43: L0218229 | Y43: 2026-05-12 | Z43: home_use | AA43: IMP00519 | AB43: T103629 | AC43: 42056208 | AD43: 4205620.8 | AE43: =(LEFT(Y43,4)-Parameters!$B$23)*12+MID(Y43,6,2)-Parameters!$B$24+1 | AG43: T100033 | AH43: 2024-12 | AI43: 1 | AJ43: 47519 | AK43: 190077 | AL43: 0 | AM43: =(LEFT(AH43,4)-Parameters!$B$21)*12+MID(AH43,6,2)-Parameters!$B$22+1
A44: list | C44: importers | D44: imports (LCU) | E44: VAT at stake (LCU) | X44: L0219310 | Y44: 2026-05-16 | Z44: warehouse_out | AA44: IMP00519 | AB44: T103629 | AC44: 49570827 | AD44: 4957082.7 | AE44: =(LEFT(Y44,4)-Parameters!$B$23)*12+MID(Y44,6,2)-Parameters!$B$24+1 | AG44: T100033 | AH44: 2025-01 | AI44: 1 | AJ44: 302545 | AK44: 2093577 | AL44: 213366 | AM44: =(LEFT(AH44,4)-Parameters!$B$21)*12+MID(AH44,6,2)-Parameters!$B$22+1
A45: 1 not known to tax | C45: =COUNTIF($S$17:$S$41,A45) | D45: =SUMIF($S$17:$S$41,A45,$H$17:$H$41) | E45: =SUMIF($S$17:$S$41,A45,$Q$17:$Q$41) | F45: =IF(COUNTA($S$17:$S$41)<25,"",IF(C45="","",IF(ISNUMBER(C45),IF(ABS(C45-_check!$B$87)<=0.5,"✓","✗"),"✗"))) | G45: =IF(COUNTA($S$17:$S$41)<25,"",IF(E45="","",IF(ISNUMBER(E45),IF(ABS(E45-_check!$B$88)<=1000,"✓","✗"),"✗"))) | X45: L0219311 | Y45: 2026-05-16 | Z45: home_use | AA45: IMP00519 | AB45: T103629 | AC45: 7043288.6 | AD45: 704328.86 | AE45: =(LEFT(Y45,4)-Parameters!$B$23)*12+MID(Y45,6,2)-Parameters!$B$24+1 | AG45: T100033 | AH45: 2025-02 | AI45: 1 | AJ45: 51355 | AK45: 205421 | AL45: 0 | AM45: =(LEFT(AH45,4)-Parameters!$B$21)*12+MID(AH45,6,2)-Parameters!$B$22+1
A46: 2 not filing | C46: =COUNTIF($S$17:$S$41,A46) | D46: =SUMIF($S$17:$S$41,A46,$H$17:$H$41) | E46: =SUMIF($S$17:$S$41,A46,$Q$17:$Q$41) | F46: =IF(COUNTA($S$17:$S$41)<25,"",IF(C46="","",IF(ISNUMBER(C46),IF(ABS(C46-_check!$B$89)<=0.5,"✓","✗"),"✗"))) | G46: =IF(COUNTA($S$17:$S$41)<25,"",IF(E46="","",IF(ISNUMBER(E46),IF(ABS(E46-_check!$B$90)<=1000,"✓","✗"),"✗"))) | X46: L0219831 | Y46: 2026-05-18 | Z46: home_use | AA46: IMP00519 | AB46: T103629 | AC46: 10345190 | AD46: 1086245 | AE46: =(LEFT(Y46,4)-Parameters!$B$23)*12+MID(Y46,6,2)-Parameters!$B$24+1 | AG46: T100033 | AH46: 2025-03 | AI46: 1 | AJ46: 55410 | AK46: 221639 | AL46: 0 | AM46: =(LEFT(AH46,4)-Parameters!$B$21)*12+MID(AH46,6,2)-Parameters!$B$22+1
A47: 3 import not booked | C47: =COUNTIF($S$17:$S$41,A47) | D47: =SUMIF($S$17:$S$41,A47,$H$17:$H$41) | E47: =SUMIF($S$17:$S$41,A47,$Q$17:$Q$41) | F47: =IF(COUNTA($S$17:$S$41)<25,"",IF(C47="","",IF(ISNUMBER(C47),IF(ABS(C47-_check!$B$91)<=0.5,"✓","✗"),"✗"))) | G47: =IF(COUNTA($S$17:$S$41)<25,"",IF(E47="","",IF(ISNUMBER(E47),IF(ABS(E47-_check!$B$92)<=1000,"✓","✗"),"✗"))) | X47: L0219832 | Y47: 2026-05-18 | Z47: home_use | AA47: IMP00519 | AB47: T103629 | AC47: 31659563 | AD47: 3165956.3 | AE47: =(LEFT(Y47,4)-Parameters!$B$23)*12+MID(Y47,6,2)-Parameters!$B$24+1 | AG47: T100033 | AH47: 2025-04 | AI47: 1 | AJ47: 84624 | AK47: 338494 | AL47: 0 | AM47: =(LEFT(AH47,4)-Parameters!$B$21)*12+MID(AH47,6,2)-Parameters!$B$22+1
A48: 4 desk audit, ranked by VAT at stake | C48: =COUNTIF($S$17:$S$41,A48) | D48: =SUMIF($S$17:$S$41,A48,$H$17:$H$41) | E48: =SUMIF($S$17:$S$41,A48,$Q$17:$Q$41) | F48: =IF(COUNTA($S$17:$S$41)<25,"",IF(C48="","",IF(ISNUMBER(C48),IF(ABS(C48-_check!$B$93)<=0.5,"✓","✗"),"✗"))) | G48: =IF(COUNTA($S$17:$S$41)<25,"",IF(E48="","",IF(ISNUMBER(E48),IF(ABS(E48-_check!$B$94)<=1000,"✓","✗"),"✗"))) | X48: L0223296 | Y48: 2026-06-03 | Z48: home_use | AA48: IMP00519 | AB48: T103629 | AC48: 25666385 | AD48: 2566638.5 | AE48: =(LEFT(Y48,4)-Parameters!$B$23)*12+MID(Y48,6,2)-Parameters!$B$24+1 | AG48: T100033 | AH48: 2025-05 | AI48: 1 | AJ48: 103876 | AK48: 415504 | AL48: 0 | AM48: =(LEFT(AH48,4)-Parameters!$B$21)*12+MID(AH48,6,2)-Parameters!$B$22+1
A49: 4b below imports, beyond capacity | C49: =COUNTIF($S$17:$S$41,A49) | D49: =SUMIF($S$17:$S$41,A49,$H$17:$H$41) | E49: =SUMIF($S$17:$S$41,A49,$Q$17:$Q$41) | F49: =IF(COUNTA($S$17:$S$41)<25,"",IF(C49="","",IF(ISNUMBER(C49),IF(ABS(C49-_check!$B$95)<=0.5,"✓","✗"),"✗"))) | G49: =IF(COUNTA($S$17:$S$41)<25,"",IF(E49="","",IF(ISNUMBER(E49),IF(ABS(E49-_check!$B$96)<=1000,"✓","✗"),"✗"))) | X49: L0223824 | Y49: 2026-06-05 | Z49: home_use | AA49: IMP00519 | AB49: T103629 | AC49: 1963988.9 | AD49: 206218.83 | AE49: =(LEFT(Y49,4)-Parameters!$B$23)*12+MID(Y49,6,2)-Parameters!$B$24+1 | AG49: T100033 | AH49: 2025-06 | AI49: 1 | AJ49: 124243 | AK49: 496972 | AL49: 0 | AM49: =(LEFT(AH49,4)-Parameters!$B$21)*12+MID(AH49,6,2)-Parameters!$B$22+1
A50: 5 consistent for now | C50: =COUNTIF($S$17:$S$41,A50) | D50: =SUMIF($S$17:$S$41,A50,$H$17:$H$41) | E50: =SUMIF($S$17:$S$41,A50,$Q$17:$Q$41) | F50: =IF(COUNTA($S$17:$S$41)<25,"",IF(C50="","",IF(ISNUMBER(C50),IF(ABS(C50-_check!$B$97)<=0.5,"✓","✗"),"✗"))) | G50: =IF(COUNTA($S$17:$S$41)<25,"",IF(E50="","",IF(ISNUMBER(E50),IF(ABS(E50-_check!$B$98)<=1000,"✓","✗"),"✗"))) | X50: L0225181 | Y50: 2026-06-10 | Z50: home_use | AA50: IMP00519 | AB50: T103629 | AC50: 2284763.3 | AD50: 239900.14 | AE50: =(LEFT(Y50,4)-Parameters!$B$23)*12+MID(Y50,6,2)-Parameters!$B$24+1 | AG50: T100033 | AH50: 2025-07 | AI50: 1 | AJ50: 88143 | AK50: 352570 | AL50: 0 | AM50: =(LEFT(AH50,4)-Parameters!$B$21)*12+MID(AH50,6,2)-Parameters!$B$22+1
X51: L0226478 | Y51: 2026-06-15 | Z51: home_use | AA51: IMP00519 | AB51: T103629 | AC51: 1714025.5 | AD51: 179972.68 | AE51: =(LEFT(Y51,4)-Parameters!$B$23)*12+MID(Y51,6,2)-Parameters!$B$24+1 | AG51: T100033 | AH51: 2025-08 | AI51: 1 | AJ51: 70396 | AK51: 281583 | AL51: 0 | AM51: =(LEFT(AH51,4)-Parameters!$B$21)*12+MID(AH51,6,2)-Parameters!$B$22+1
A52: The worked case, I01: it filed 5 of its last six returns (at least 5: it files); it deducts 90% of the import VAT it paid (at least half: in its books); its sales are 0.96 times its imports (under 1): list 4, VAT at stake 0.10 × (imports × 1.343 − sales) = 60.9 M LCU. Its rank on list 4 shows once your rows are in: it ranks every row's VAT at stake; until then its list reads list 4, before the cut at the capacity. | X52: L0229393 | Y52: 2026-06-26 | Z52: home_use | AA52: IMP00519 | AB52: T103629 | AC52: 28104311 | AD52: 2810431.1 | AE52: =(LEFT(Y52,4)-Parameters!$B$23)*12+MID(Y52,6,2)-Parameters!$B$24+1 | AG52: T100033 | AH52: 2025-09 | AI52: 1 | AJ52: 52869 | AK52: 211476 | AL52: 0 | AM52: =(LEFT(AH52,4)-Parameters!$B$21)*12+MID(AH52,6,2)-Parameters!$B$22+1
X53: L0230900 | Y53: 2026-07-04 | Z53: home_use | AA53: IMP00519 | AB53: T103629 | AC53: 2.2926267e+08 | AD53: 22926267 | AE53: =(LEFT(Y53,4)-Parameters!$B$23)*12+MID(Y53,6,2)-Parameters!$B$24+1 | AG53: T100033 | AH53: 2025-10 | AI53: 1 | AJ53: 320744 | AK53: 2219515 | AL53: 204865 | AM53: =(LEFT(AH53,4)-Parameters!$B$21)*12+MID(AH53,6,2)-Parameters!$B$22+1
X54: L0232659 | Y54: 2026-07-11 | Z54: home_use | AA54: IMP00519 | AB54: T103629 | AC54: 12933972 | AD54: 1293397.2 | AE54: =(LEFT(Y54,4)-Parameters!$B$23)*12+MID(Y54,6,2)-Parameters!$B$24+1 | AG54: T100033 | AH54: 2025-11 | AI54: 1 | AJ54: 43500 | AK54: 174001 | AL54: 0 | AM54: =(LEFT(AH54,4)-Parameters!$B$21)*12+MID(AH54,6,2)-Parameters!$B$22+1
X55: L0234421 | Y55: 2026-07-18 | Z55: home_use | AA55: IMP00519 | AB55: T103629 | AC55: 41193963 | AD55: 4119396.3 | AE55: =(LEFT(Y55,4)-Parameters!$B$23)*12+MID(Y55,6,2)-Parameters!$B$24+1 | AG55: T100033 | AH55: 2025-12 | AI55: 1 | AJ55: 49252 | AK55: 197007 | AL55: 0 | AM55: =(LEFT(AH55,4)-Parameters!$B$21)*12+MID(AH55,6,2)-Parameters!$B$22+1
X56: L0235930 | Y56: 2026-07-24 | Z56: home_use | AA56: IMP00519 | AB56: T103629 | AC56: 64473504 | AD56: 6447350.4 | AE56: =(LEFT(Y56,4)-Parameters!$B$23)*12+MID(Y56,6,2)-Parameters!$B$24+1 | AG56: T100033 | AH56: 2026-01 | AI56: 1 | AJ56: 88113 | AK56: 352452 | AL56: 0 | AM56: =(LEFT(AH56,4)-Parameters!$B$21)*12+MID(AH56,6,2)-Parameters!$B$22+1
X57: L0237642 | Y57: 2026-08-03 | Z57: home_use | AA57: IMP00519 | AB57: T103629 | AC57: 63033048 | AD57: 6303304.8 | AE57: =(LEFT(Y57,4)-Parameters!$B$23)*12+MID(Y57,6,2)-Parameters!$B$24+1 | AG57: T100033 | AH57: 2026-02 | AI57: 1 | AJ57: 62045 | AK57: 248181 | AL57: 0 | AM57: =(LEFT(AH57,4)-Parameters!$B$21)*12+MID(AH57,6,2)-Parameters!$B$22+1
X58: L0237643 | Y58: 2026-08-03 | Z58: home_use | AA58: IMP00519 | AB58: T103629 | AC58: 38309345 | AD58: 3830934.5 | AE58: =(LEFT(Y58,4)-Parameters!$B$23)*12+MID(Y58,6,2)-Parameters!$B$24+1 | AG58: T100033 | AH58: 2026-03 | AI58: 1 | AJ58: 72841 | AK58: 291364 | AL58: 0 | AM58: =(LEFT(AH58,4)-Parameters!$B$21)*12+MID(AH58,6,2)-Parameters!$B$22+1
X59: L0237644 | Y59: 2026-08-03 | Z59: home_use | AA59: IMP00519 | AB59: T103629 | AC59: 18825318 | AD59: 1882531.8 | AE59: =(LEFT(Y59,4)-Parameters!$B$23)*12+MID(Y59,6,2)-Parameters!$B$24+1 | AG59: T100033 | AH59: 2026-04 | AI59: 1 | AJ59: 75573 | AK59: 302292 | AL59: 0 | AM59: =(LEFT(AH59,4)-Parameters!$B$21)*12+MID(AH59,6,2)-Parameters!$B$22+1
X60: L0237877 | Y60: 2026-08-04 | Z60: home_use | AA60: IMP00519 | AB60: T103629 | AC60: 19155440 | AD60: 1915544 | AE60: =(LEFT(Y60,4)-Parameters!$B$23)*12+MID(Y60,6,2)-Parameters!$B$24+1 | AG60: T100033 | AH60: 2026-05 | AI60: 1 | AJ60: 36257 | AK60: 145027 | AL60: 0 | AM60: =(LEFT(AH60,4)-Parameters!$B$21)*12+MID(AH60,6,2)-Parameters!$B$22+1
X61: L0241701 | Y61: 2026-08-20 | Z61: home_use | AA61: IMP00519 | AB61: T103629 | AC61: 56336703 | AD61: 5633670.3 | AE61: =(LEFT(Y61,4)-Parameters!$B$23)*12+MID(Y61,6,2)-Parameters!$B$24+1 | AG61: T100033 | AH61: 2026-06 | AI61: 1 | AJ61: 27686 | AK61: 110746 | AL61: 0 | AM61: =(LEFT(AH61,4)-Parameters!$B$21)*12+MID(AH61,6,2)-Parameters!$B$22+1
X62: L0244293 | Y62: 2026-09-03 | Z62: home_use | AA62: IMP00519 | AB62: T103629 | AC62: 39028557 | AD62: 3902855.7 | AE62: =(LEFT(Y62,4)-Parameters!$B$23)*12+MID(Y62,6,2)-Parameters!$B$24+1 | AG62: T100033 | AH62: 2026-07 | AI62: 1 | AJ62: 60447 | AK62: 241789 | AL62: 0 | AM62: =(LEFT(AH62,4)-Parameters!$B$21)*12+MID(AH62,6,2)-Parameters!$B$22+1
X63: L0245222 | Y63: 2026-09-07 | Z63: home_use | AA63: IMP00519 | AB63: T103629 | AC63: 55459771 | AD63: 5545977.1 | AE63: =(LEFT(Y63,4)-Parameters!$B$23)*12+MID(Y63,6,2)-Parameters!$B$24+1 | AG63: T100033 | AH63: 2026-08 | AI63: 0 | AM63: =(LEFT(AH63,4)-Parameters!$B$21)*12+MID(AH63,6,2)-Parameters!$B$22+1
X64: L0247487 | Y64: 2026-09-17 | Z64: home_use | AA64: IMP00519 | AB64: T103629 | AC64: 26521088 | AD64: 2652108.8 | AE64: =(LEFT(Y64,4)-Parameters!$B$23)*12+MID(Y64,6,2)-Parameters!$B$24+1 | AG64: T100033 | AH64: 2026-09 | AI64: 1 | AJ64: 692083 | AK64: 4789146 | AL64: 467491 | AM64: =(LEFT(AH64,4)-Parameters!$B$21)*12+MID(AH64,6,2)-Parameters!$B$22+1
X65: L0171734 | Y65: 2025-10-25 | Z65: home_use | AA65: IMP00005 | AB65: T100033 | AC65: 1999563.4 | AD65: 199956.34 | AE65: =(LEFT(Y65,4)-Parameters!$B$23)*12+MID(Y65,6,2)-Parameters!$B$24+1 | AG65: T100070 | AH65: 2024-10 | AI65: 1 | AJ65: 306833 | AK65: 1833154 | AL65: 167257 | AM65: =(LEFT(AH65,4)-Parameters!$B$21)*12+MID(AH65,6,2)-Parameters!$B$22+1
X66: L0247648 | Y66: 2026-09-18 | Z66: home_use | AA66: IMP00005 | AB66: T100033 | AC66: 4314546.3 | AD66: 474600.09 | AE66: =(LEFT(Y66,4)-Parameters!$B$23)*12+MID(Y66,6,2)-Parameters!$B$24+1 | AG66: T100070 | AH66: 2024-11 | AI66: 1 | AJ66: 2145197 | AK66: 12816349 | AL66: 1176098 | AM66: =(LEFT(AH66,4)-Parameters!$B$21)*12+MID(AH66,6,2)-Parameters!$B$22+1
X67: L0236106 | Y67: 2026-07-25 | Z67: home_use | AA67: IMP00006 | AB67: T100033 | AC67: 2729997.3 | AD67: 354899.65 | AE67: =(LEFT(Y67,4)-Parameters!$B$23)*12+MID(Y67,6,2)-Parameters!$B$24+1 | AG67: T100070 | AH67: 2024-12 | AI67: 1 | AJ67: 1159576 | AK67: 6927817 | AL67: 629721 | AM67: =(LEFT(AH67,4)-Parameters!$B$21)*12+MID(AH67,6,2)-Parameters!$B$22+1
X68: L0240642 | Y68: 2026-08-16 | Z68: home_use | AA68: IMP00006 | AB68: T100033 | AC68: 2091558.9 | AD68: 271902.65 | AE68: =(LEFT(Y68,4)-Parameters!$B$23)*12+MID(Y68,6,2)-Parameters!$B$24+1 | AG68: T100070 | AH68: 2025-01 | AI68: 1 | AJ68: 2558377 | AK68: 15284868 | AL68: 1402999 | AM68: =(LEFT(AH68,4)-Parameters!$B$21)*12+MID(AH68,6,2)-Parameters!$B$22+1
X69: L0166737 | Y69: 2025-10-02 | Z69: home_use | AA69: IMP00095 | AB69: T100033 | AC69: 947982.4 | AD69: 118497.8 | AE69: =(LEFT(Y69,4)-Parameters!$B$23)*12+MID(Y69,6,2)-Parameters!$B$24+1 | AG69: T100070 | AH69: 2025-02 | AI69: 1 | AJ69: 1332125 | AK69: 7958697 | AL69: 710312 | AM69: =(LEFT(AH69,4)-Parameters!$B$21)*12+MID(AH69,6,2)-Parameters!$B$22+1
X70: L0166961 | Y70: 2025-10-03 | Z70: home_use | AA70: IMP00095 | AB70: T100033 | AC70: 784222.67 | AD70: 98027.83 | AE70: =(LEFT(Y70,4)-Parameters!$B$23)*12+MID(Y70,6,2)-Parameters!$B$24+1 | AG70: T100070 | AH70: 2025-03 | AI70: 1 | AJ70: 960419 | AK70: 5737963 | AL70: 507189 | AM70: =(LEFT(AH70,4)-Parameters!$B$21)*12+MID(AH70,6,2)-Parameters!$B$22+1
X71: L0169099 | Y71: 2025-10-13 | Z71: home_use | AA71: IMP00095 | AB71: T100033 | AC71: 81699.61 | AD71: 8578.46 | AE71: =(LEFT(Y71,4)-Parameters!$B$23)*12+MID(Y71,6,2)-Parameters!$B$24+1 | AG71: T100070 | AH71: 2025-04 | AI71: 1 | AJ71: 2667385 | AK71: 15936129 | AL71: 1404238 | AM71: =(LEFT(AH71,4)-Parameters!$B$21)*12+MID(AH71,6,2)-Parameters!$B$22+1
X72: L0170649 | Y72: 2025-10-20 | Z72: home_use | AA72: IMP00095 | AB72: T100033 | AC72: 501484.92 | AD72: 65193.04 | AE72: =(LEFT(Y72,4)-Parameters!$B$23)*12+MID(Y72,6,2)-Parameters!$B$24+1 | AG72: T100070 | AH72: 2025-05 | AI72: 1 | AJ72: 97298 | AK72: 581300 | AL72: 60641 | AM72: =(LEFT(AH72,4)-Parameters!$B$21)*12+MID(AH72,6,2)-Parameters!$B$22+1
X73: L0173037 | Y73: 2025-11-03 | Z73: home_use | AA73: IMP00095 | AB73: T100033 | AC73: 908907.54 | AD73: 106342.18 | AE73: =(LEFT(Y73,4)-Parameters!$B$23)*12+MID(Y73,6,2)-Parameters!$B$24+1 | AG73: T100070 | AH73: 2025-06 | AI73: 1 | AJ73: 1372214 | AK73: 8198210 | AL73: 749700 | AM73: =(LEFT(AH73,4)-Parameters!$B$21)*12+MID(AH73,6,2)-Parameters!$B$22+1
X74: L0184043 | Y74: 2025-12-23 | Z74: home_use | AA74: IMP00095 | AB74: T100033 | AC74: 1660461.2 | AD74: 215859.95 | AE74: =(LEFT(Y74,4)-Parameters!$B$23)*12+MID(Y74,6,2)-Parameters!$B$24+1 | AG74: T100070 | AH74: 2025-07 | AI74: 1 | AJ74: 1528694 | AK74: 9133091 | AL74: 844821 | AM74: =(LEFT(AH74,4)-Parameters!$B$21)*12+MID(AH74,6,2)-Parameters!$B$22+1
X75: L0184294 | Y75: 2025-12-24 | Z75: home_use | AA75: IMP00095 | AB75: T100033 | AC75: 3006136.7 | AD75: 375767.08 | AE75: =(LEFT(Y75,4)-Parameters!$B$23)*12+MID(Y75,6,2)-Parameters!$B$24+1 | AG75: T100070 | AH75: 2025-08 | AI75: 1 | AJ75: 254227 | AK75: 1518865 | AL75: 135626 | AM75: =(LEFT(AH75,4)-Parameters!$B$21)*12+MID(AH75,6,2)-Parameters!$B$22+1
... X78: L0188745 | Y78: 2026-01-14 | Z78: home_use | AA78: IMP00095 | AB78: T100033 | AC78: 56503.59 | AD78: 5932.88 | AE78: =(LEFT(Y78,4)-Parameters!$B$23)*12+MID(Y78,6,2)-Parameters!$B$24+1 | AG78: T100070 | AH78: 2025-11 | AI78: 1 | AJ78: 661778 | AK78: 3953752 | AL78: 365132 | AM78: =(LEFT(AH78,4)-Parameters!$B$21)*12+MID(AH78,6,2)-Parameters!$B$22+1
X79: L0189537 | Y79: 2026-01-17 | Z79: home_use | AA79: IMP00095 | AB79: T100033 | AC79: 1688830.4 | AD79: 219547.95 | AE79: =(LEFT(Y79,4)-Parameters!$B$23)*12+MID(Y79,6,2)-Parameters!$B$24+1 | AG79: T100070 | AH79: 2025-12 | AI79: 0 | AM79: =(LEFT(AH79,4)-Parameters!$B$21)*12+MID(AH79,6,2)-Parameters!$B$22+1
X80: L0190557 | Y80: 2026-01-21 | Z80: home_use | AA80: IMP00095 | AB80: T100033 | AC80: 259775.85 | AD80: 27276.46 | AE80: =(LEFT(Y80,4)-Parameters!$B$23)*12+MID(Y80,6,2)-Parameters!$B$24+1 | AG80: T100070 | AH80: 2026-01 | AI80: 1 | AJ80: 1121984 | AK80: 6703224 | AL80: 646984 | AM80: =(LEFT(AH80,4)-Parameters!$B$21)*12+MID(AH80,6,2)-Parameters!$B$22+1
X81: L0190782 | Y81: 2026-01-22 | Z81: home_use | AA81: IMP00095 | AB81: T100033 | AC81: 1119471.1 | AD81: 117544.47 | AE81: =(LEFT(Y81,4)-Parameters!$B$23)*12+MID(Y81,6,2)-Parameters!$B$24+1 | AG81: T100070 | AH81: 2026-02 | AI81: 1 | AJ81: 1260182 | AK81: 7528880 | AL81: 685844 | AM81: =(LEFT(AH81,4)-Parameters!$B$21)*12+MID(AH81,6,2)-Parameters!$B$22+1
X82: L0193583 | Y82: 2026-02-05 | Z82: home_use | AA82: IMP00095 | AB82: T100033 | AC82: 157101.58 | AD82: 16495.67 | AE82: =(LEFT(Y82,4)-Parameters!$B$23)*12+MID(Y82,6,2)-Parameters!$B$24+1 | AG82: T100070 | AH82: 2026-03 | AI82: 1 | AJ82: 1202667 | AK82: 7185261 | AL82: 631723 | AM82: =(LEFT(AH82,4)-Parameters!$B$21)*12+MID(AH82,6,2)-Parameters!$B$22+1
X83: L0195463 | Y83: 2026-02-12 | Z83: home_use | AA83: IMP00095 | AB83: T100033 | AC83: 1356837.4 | AD83: 176388.87 | AE83: =(LEFT(Y83,4)-Parameters!$B$23)*12+MID(Y83,6,2)-Parameters!$B$24+1 | AG83: T100070 | AH83: 2026-04 | AI83: 1 | AJ83: 3066290 | AK83: 18319362 | AL83: 1673697 | AM83: =(LEFT(AH83,4)-Parameters!$B$21)*12+MID(AH83,6,2)-Parameters!$B$22+1
X84: L0198065 | Y84: 2026-02-22 | Z84: home_use | AA84: IMP00095 | AB84: T100033 | AC84: 3177831.6 | AD84: 397228.95 | AE84: =(LEFT(Y84,4)-Parameters!$B$23)*12+MID(Y84,6,2)-Parameters!$B$24+1 | AG84: T100070 | AH84: 2026-05 | AI84: 1 | AJ84: 1322678 | AK84: 7902259 | AL84: 695307 | AM84: =(LEFT(AH84,4)-Parameters!$B$21)*12+MID(AH84,6,2)-Parameters!$B$22+1
X85: L0198880 | Y85: 2026-02-25 | Z85: home_use | AA85: IMP00095 | AB85: T100033 | AC85: 1712153.6 | AD85: 222579.96 | AE85: =(LEFT(Y85,4)-Parameters!$B$23)*12+MID(Y85,6,2)-Parameters!$B$24+1 | AG85: T100070 | AH85: 2026-06 | AI85: 1 | AJ85: 545344 | AK85: 3258124 | AL85: 296724 | AM85: =(LEFT(AH85,4)-Parameters!$B$21)*12+MID(AH85,6,2)-Parameters!$B$22+1
X86: L0199142 | Y86: 2026-02-26 | Z86: home_use | AA86: IMP00095 | AB86: T100033 | AC86: 1755713.1 | AD86: 219464.14 | AE86: =(LEFT(Y86,4)-Parameters!$B$23)*12+MID(Y86,6,2)-Parameters!$B$24+1 | AG86: T100070 | AH86: 2026-07 | AI86: 1 | AJ86: 2967925 | AK86: 17731687 | AL86: 1634659 | AM86: =(LEFT(AH86,4)-Parameters!$B$21)*12+MID(AH86,6,2)-Parameters!$B$22+1
X87: L0203394 | Y87: 2026-03-14 | Z87: home_use | AA87: IMP00095 | AB87: T100033 | AC87: 8375626.9 | AD87: 1046953.4 | AE87: =(LEFT(Y87,4)-Parameters!$B$23)*12+MID(Y87,6,2)-Parameters!$B$24+1 | AG87: T100070 | AH87: 2026-08 | AI87: 1 | AJ87: 374374 | AK87: 2236672 | AL87: 205384 | AM87: =(LEFT(AH87,4)-Parameters!$B$21)*12+MID(AH87,6,2)-Parameters!$B$22+1
X88: L0207436 | Y88: 2026-04-01 | Z88: home_use | AA88: IMP00095 | AB88: T100033 | AC88: 1163091.4 | AD88: 151201.88 | AE88: =(LEFT(Y88,4)-Parameters!$B$23)*12+MID(Y88,6,2)-Parameters!$B$24+1 | AG88: T100070 | AH88: 2026-09 | AI88: 1 | AJ88: 3866425 | AK88: 23099720 | AL88: 2119023 | AM88: =(LEFT(AH88,4)-Parameters!$B$21)*12+MID(AH88,6,2)-Parameters!$B$22+1
X89: L0210728 | Y89: 2026-04-13 | Z89: home_use | AA89: IMP00095 | AB89: T100033 | AC89: 1211163.8 | AD89: 157451.29 | AE89: =(LEFT(Y89,4)-Parameters!$B$23)*12+MID(Y89,6,2)-Parameters!$B$24+1 | AG89: T100440 | AH89: 2024-10 | AI89: 1 | AJ89: 423210207 | AK89: 330121806 | AL89: 35467173 | AM89: =(LEFT(AH89,4)-Parameters!$B$21)*12+MID(AH89,6,2)-Parameters!$B$22+1
X90: L0211581 | Y90: 2026-04-16 | Z90: home_use | AA90: IMP00095 | AB90: T100033 | AC90: 139623.61 | AD90: 14660.48 | AE90: =(LEFT(Y90,4)-Parameters!$B$23)*12+MID(Y90,6,2)-Parameters!$B$24+1 | AG90: T100440 | AH90: 2024-11 | AI90: 0 | AM90: =(LEFT(AH90,4)-Parameters!$B$21)*12+MID(AH90,6,2)-Parameters!$B$22+1
X91: L0214304 | Y91: 2026-04-26 | Z91: home_use | AA91: IMP00095 | AB91: T100033 | AC91: 1494319.9 | AD91: 156903.59 | AE91: =(LEFT(Y91,4)-Parameters!$B$23)*12+MID(Y91,6,2)-Parameters!$B$24+1 | AG91: T100440 | AH91: 2024-12 | AI91: 1 | AJ91: 438848620 | AK91: 342320427 | AL91: 37177767 | AM91: =(LEFT(AH91,4)-Parameters!$B$21)*12+MID(AH91,6,2)-Parameters!$B$22+1
X92: L0214826 | Y92: 2026-04-28 | Z92: home_use | AA92: IMP00095 | AB92: T100033 | AC92: 2675346.3 | AD92: 347795.01 | AE92: =(LEFT(Y92,4)-Parameters!$B$23)*12+MID(Y92,6,2)-Parameters!$B$24+1 | AG92: T100440 | AH92: 2025-01 | AI92: 1 | AJ92: 407888742 | AK92: 318170417 | AL92: 34067870 | AM92: =(LEFT(AH92,4)-Parameters!$B$21)*12+MID(AH92,6,2)-Parameters!$B$22+1
X93: L0214827 | Y93: 2026-04-28 | Z93: warehouse_out | AA93: IMP00095 | AB93: T100033 | AC93: 247965.74 | AD93: 27276.23 | AE93: =(LEFT(Y93,4)-Parameters!$B$23)*12+MID(Y93,6,2)-Parameters!$B$24+1 | AG93: T100440 | AH93: 2025-02 | AI93: 1 | AJ93: 503249474 | AK93: 392555809 | AL93: 43420354 | AM93: =(LEFT(AH93,4)-Parameters!$B$21)*12+MID(AH93,6,2)-Parameters!$B$22+1
X94: L0215126 | Y94: 2026-05-01 | Z94: home_use | AA94: IMP00095 | AB94: T100033 | AC94: 1838081.2 | AD94: 238950.56 | AE94: =(LEFT(Y94,4)-Parameters!$B$23)*12+MID(Y94,6,2)-Parameters!$B$24+1 | AG94: T100440 | AH94: 2025-03 | AI94: 1 | AJ94: 448469767 | AK94: 349825328 | AL94: 38988742 | AM94: =(LEFT(AH94,4)-Parameters!$B$21)*12+MID(AH94,6,2)-Parameters!$B$22+1
X95: L0216216 | Y95: 2026-05-05 | Z95: home_use | AA95: IMP00095 | AB95: T100033 | AC95: 769789.77 | AD95: 80827.93 | AE95: =(LEFT(Y95,4)-Parameters!$B$23)*12+MID(Y95,6,2)-Parameters!$B$24+1 | AG95: T100440 | AH95: 2025-04 | AI95: 1 | AJ95: 510556320 | AK95: 398255457 | AL95: 43335596 | AM95: =(LEFT(AH95,4)-Parameters!$B$21)*12+MID(AH95,6,2)-Parameters!$B$22+1
X96: L0216777 | Y96: 2026-05-07 | Z96: home_use | AA96: IMP00095 | AB96: T100033 | AC96: 1103842.1 | AD96: 143499.48 | AE96: =(LEFT(Y96,4)-Parameters!$B$23)*12+MID(Y96,6,2)-Parameters!$B$24+1 | AG96: T100440 | AH96: 2025-05 | AI96: 1 | AJ96: 453023532 | AK96: 353377457 | AL96: 37659425 | AM96: =(LEFT(AH96,4)-Parameters!$B$21)*12+MID(AH96,6,2)-Parameters!$B$22+1
X97: L0230574 | Y97: 2026-07-03 | Z97: home_use | AA97: IMP00095 | AB97: T100033 | AC97: 248514.66 | AD97: 27336.61 | AE97: =(LEFT(Y97,4)-Parameters!$B$23)*12+MID(Y97,6,2)-Parameters!$B$24+1 | AG97: T100440 | AH97: 2025-06 | AI97: 1 | AJ97: 494594746 | AK97: 385804756 | AL97: 42997238 | AM97: =(LEFT(AH97,4)-Parameters!$B$21)*12+MID(AH97,6,2)-Parameters!$B$22+1
X98: L0238265 | Y98: 2026-08-06 | Z98: home_use | AA98: IMP00095 | AB98: T100033 | AC98: 5752777.4 | AD98: 719097.18 | AE98: =(LEFT(Y98,4)-Parameters!$B$23)*12+MID(Y98,6,2)-Parameters!$B$24+1 | AG98: T100440 | AH98: 2025-07 | AI98: 1 | AJ98: 556005046 | AK98: 433707379 | AL98: 48127396 | AM98: =(LEFT(AH98,4)-Parameters!$B$21)*12+MID(AH98,6,2)-Parameters!$B$22+1
X99: L0248114 | Y99: 2026-09-20 | Z99: home_use | AA99: IMP00095 | AB99: T100033 | AC99: 1153406.9 | AD99: 149942.9 | AE99: =(LEFT(Y99,4)-Parameters!$B$23)*12+MID(Y99,6,2)-Parameters!$B$24+1 | AG99: T100440 | AH99: 2025-08 | AI99: 1 | AJ99: 435208032 | AK99: 339480616 | AL99: 37578394 | AM99: =(LEFT(AH99,4)-Parameters!$B$21)*12+MID(AH99,6,2)-Parameters!$B$22+1
X100: L0248115 | Y100: 2026-09-20 | Z100: home_use | AA100: IMP00095 | AB100: T100033 | AC100: 1653223.4 | AD100: 214919.05 | AE100: =(LEFT(Y100,4)-Parameters!$B$23)*12+MID(Y100,6,2)-Parameters!$B$24+1 | AG100: T100440 | AH100: 2025-09 | AI100: 1 | AJ100: 434578364 | AK100: 338989448 | AL100: 37177853 | AM100: =(LEFT(AH100,4)-Parameters!$B$21)*12+MID(AH100,6,2)-Parameters!$B$22+1
X101: L0249699 | Y101: 2026-09-27 | Z101: home_use | AA101: IMP00095 | AB101: T100033 | AC101: 1331415.4 | AD101: 173084.01 | AE101: =(LEFT(Y101,4)-Parameters!$B$23)*12+MID(Y101,6,2)-Parameters!$B$24+1 | AG101: T100440 | AH101: 2025-10 | AI101: 1 | AJ101: 424952459 | AK101: 331480836 | AL101: 37493467 | AM101: =(LEFT(AH101,4)-Parameters!$B$21)*12+MID(AH101,6,2)-Parameters!$B$22+1
X102: L0178914 | Y102: 2025-12-01 | Z102: home_use | AA102: IMP00133 | AB102: T100033 | AC102: 206283.99 | AD102: 24754.08 | AE102: =(LEFT(Y102,4)-Parameters!$B$23)*12+MID(Y102,6,2)-Parameters!$B$24+1 | AG102: T100440 | AH102: 2025-11 | AI102: 1 | AJ102: 373429345 | AK102: 291290634 | AL102: 32740124 | AM102: =(LEFT(AH102,4)-Parameters!$B$21)*12+MID(AH102,6,2)-Parameters!$B$22+1
... X106: L0215137 | Y106: 2026-05-01 | Z106: home_use | AA106: IMP00133 | AB106: T100033 | AC106: 2235533 | AD106: 272735.02 | AE106: =(LEFT(Y106,4)-Parameters!$B$23)*12+MID(Y106,6,2)-Parameters!$B$24+1 | AG106: T100440 | AH106: 2026-03 | AI106: 1 | AJ106: 543004735 | AK106: 423566589 | AL106: 47593854 | AM106: =(LEFT(AH106,4)-Parameters!$B$21)*12+MID(AH106,6,2)-Parameters!$B$22+1
X107: L0217646 | Y107: 2026-05-10 | Z107: home_use | AA107: IMP00133 | AB107: T100033 | AC107: 1768309.4 | AD107: 215733.74 | AE107: =(LEFT(Y107,4)-Parameters!$B$23)*12+MID(Y107,6,2)-Parameters!$B$24+1 | AG107: T100440 | AH107: 2026-04 | AI107: 0 | AM107: =(LEFT(AH107,4)-Parameters!$B$21)*12+MID(AH107,6,2)-Parameters!$B$22+1
X108: L0224062 | Y108: 2026-06-06 | Z108: home_use | AA108: IMP00133 | AB108: T100033 | AC108: 1499923.4 | AD108: 175491.04 | AE108: =(LEFT(Y108,4)-Parameters!$B$23)*12+MID(Y108,6,2)-Parameters!$B$24+1 | AG108: T100440 | AH108: 2026-05 | AI108: 1 | AJ108: 526197991 | AK108: 410456619 | AL108: 44764706 | AM108: =(LEFT(AH108,4)-Parameters!$B$21)*12+MID(AH108,6,2)-Parameters!$B$22+1
X109: L0229078 | Y109: 2026-06-25 | Z109: home_use | AA109: IMP00133 | AB109: T100033 | AC109: 403721.21 | AD109: 52483.76 | AE109: =(LEFT(Y109,4)-Parameters!$B$23)*12+MID(Y109,6,2)-Parameters!$B$24+1 | AG109: T100440 | AH109: 2026-06 | AI109: 1 | AJ109: 515872165 | AK109: 402209265 | AL109: 44939706 | AM109: =(LEFT(AH109,4)-Parameters!$B$21)*12+MID(AH109,6,2)-Parameters!$B$22+1
...

Sheet S3 Network
A1: Sprint 3 · what each tax number serves: the four counts, the rule, and what the register says
A2: From the customs registers (Customs importers, Consignees): how many other importer codes clear under the number, how many consignees, addresses and brokers stand behind it. Then the rule, and the tax register's director. I01 is worked. The addresses and brokers are counted in the block on the right (rows copied from the Customs importers sheet).
A4: Step | B4: What to do | H4: Your answer | I4: Check | J4: Hint 1 · the tool (the full formula is on the Hints sheet)
A5: 1 | B5: In the block on the right (columns Q to V: every importer code registered under the 20 numbers, rows copied from the Customs importers sheet), columns U and V: 1 the first time an address, and a broker, appear under a tax number (T103629's row is worked). Then, here, columns D to G for every number: names under it, consignees, addresses, brokers. Then: the most consignees under one tax number. | H5: =MAX(E13:E32) | I5: =IF(H5="","",IF(ISNUMBER(H5),IF(ABS(H5-_check!$B$99)<=0.5,"✓ matches","✗ not yet: see the hint"),"✗ not yet: see the hint")) | J5: COUNTIF counts the importer codes under the number; minus 1 for the importer itself; plus its own consignee records. SUMIFS adds the first-time flags.
A6: 2 | B6: Column H and I: imports and sales ÷ imports, from S2. Column J: the rule: consignees at least 8, one address, sales under 20% of imports. Then: how many numbers does the rule flag? | H6: =SUM(J13:J32) | I6: =IF(H6="","",IF(ISNUMBER(H6),IF(ABS(H6-_check!$B$100)<=0.5,"✓ matches","✗ not yet: see the hint"),"✗ not yet: see the hint")) | J6: AND inside IF; the thresholds are on the Parameters sheet.
A7: 3 | B7: Columns K to M: the tax register's director and status for the number, and how many companies that director runs in the register. Then: among the numbers with at least 8 consignees, the most companies one director runs in the register. | H7: =SUMPRODUCT(MAX((E13:E32>=Parameters!$B$18)*("0"&M13:M32))) | I7: =IF(H7="","",IF(ISNUMBER(H7),IF(ABS(H7-_check!$B$101)<=0.5,"✓ matches","✗ not yet: see the hint"),"✗ not yet: see the hint")) | J7: VLOOKUP into the Tax register; COUNTIF on its director column. SUMPRODUCT(MAX(…)) takes the largest value over the rows the condition keeps; "0"& reads an empty count as 0.
A8: 4 | B8: Name the two borrowed-name networks: one the rule finds, one only the register shows. Column N: your cluster. Lock on the site. | J8: The flag is the combination, not one count. A group company clearing for its subsidiaries has one director and its consignees at their own addresses: read the register before you call it a case.
Q11: The block (row 13 on): rows copied from the Customs importers sheet, as recorded, filtered on the 20 tax numbers of column C: every importer code registered under them, T103629's first (the worked number), then by tax number: 42 rows. Columns U and V are yours (step 1).
A12: ref | B12: importer code | C12: tax number | D12: other names under the number | E12: consignees | F12: addresses | G12: brokers | H12: imports, 12 months (LCU) | I12: sales ÷ imports | J12: flag (the rule) | K12: register: director | L12: register: status | M12: companies this director runs (register) | N12: your cluster | O12: check | Q12: importer | R12: tax number | S12: address | T12: usual broker | U12: first address under the number (1/0) · you | V12: first broker under the number (1/0) · you
A13: I01 | B13: IMP00519 | C13: T103629 | D13: =COUNTIF('Customs importers'!$B$5:$B$1506,C13)-1 | E13: =D13+COUNTIF(Consignees!$E$5:$E$2006,B13) | F13: =SUMIFS($U$13:$U$54,$R$13:$R$54,C13) | G13: =SUMIFS($V$13:$V$54,$R$13:$R$54,C13) | H13: =IFERROR(VLOOKUP(A13,'S2 Four lists'!$A$17:$N$41,8,FALSE),"") | I13: =IFERROR(VLOOKUP(A13,'S2 Four lists'!$A$17:$N$41,14,FALSE),"") | J13: =IF(AND(E13>=Parameters!$B$18,F13<=Parameters!$B$19,I13<>"",N(I13)<Parameters!$B$20),1,0) | K13: =IFERROR(VLOOKUP(C13,'Tax register'!$A$5:$K$1803,7,FALSE),"") | L13: =IFERROR(VLOOKUP(C13,'Tax register'!$A$5:$K$1803,10,FALSE),"") | M13: =IF(K13="","",COUNTIF('Tax register'!$G$5:$G$1803,K13)) | O13: =IF(OR(COUNT(E13:G13)<3,COUNT($U$13:$U$54)<42),"",IF(AND(E13=_check!$B$102,F13=_check!$B$103,G13=_check!$B$104),"✓","✗")) | Q13: IMP00519 | R13: T103629 | S13: 222 Mill Road | T13: BRK021 | U13: =IF(COUNTIFS($R$13:R13,R13,$S$13:S13,S13)=1,1,0) | V13: =IF(COUNTIFS($R$13:R13,R13,$T$13:T13,T13)=1,1,0)
A14: I02 | B14: IMP00753 | C14: T105264 | D14: =COUNTIF('Customs importers'!$B$5:$B$1506,C14)-1 | E14: =D14+COUNTIF(Consignees!$E$5:$E$2006,B14) | F14: =SUMIFS($U$13:$U$54,$R$13:$R$54,C14) | G14: =SUMIFS($V$13:$V$54,$R$13:$R$54,C14) | H14: =IFERROR(VLOOKUP(A14,'S2 Four lists'!$A$17:$N$41,8,FALSE),"") | I14: =IFERROR(VLOOKUP(A14,'S2 Four lists'!$A$17:$N$41,14,FALSE),"") | J14: =IF(AND(E14>=Parameters!$B$18,F14<=Parameters!$B$19,I14<>"",N(I14)<Parameters!$B$20),1,0) | K14: =IFERROR(VLOOKUP(C14,'Tax register'!$A$5:$K$1803,7,FALSE),"") | L14: =IFERROR(VLOOKUP(C14,'Tax register'!$A$5:$K$1803,10,FALSE),"") | M14: =IF(K14="","",COUNTIF('Tax register'!$G$5:$G$1803,K14)) | O14: =IF(OR(COUNT(E14:G14)<3,COUNT($U$13:$U$54)<42),"",IF(AND(E14=_check!$B$105,F14=_check!$B$106,G14=_check!$B$107),"✓","✗")) | Q14: IMP00005 | R14: T100033 | S14: 24 Harbour Road | T14: BRK033 | U14: =IF(COUNTIFS($R$13:R14,R14,$S$13:S14,S14)=1,1,0) | V14: =IF(COUNTIFS($R$13:R14,R14,$T$13:T14,T14)=1,1,0)
A15: I03 | B15: IMP00892 | C15: T106240 | D15: =COUNTIF('Customs importers'!$B$5:$B$1506,C15)-1 | E15: =D15+COUNTIF(Consignees!$E$5:$E$2006,B15) | F15: =SUMIFS($U$13:$U$54,$R$13:$R$54,C15) | G15: =SUMIFS($V$13:$V$54,$R$13:$R$54,C15) | H15: =IFERROR(VLOOKUP(A15,'S2 Four lists'!$A$17:$N$41,8,FALSE),"") | I15: =IFERROR(VLOOKUP(A15,'S2 Four lists'!$A$17:$N$41,14,FALSE),"") | J15: =IF(AND(E15>=Parameters!$B$18,F15<=Parameters!$B$19,I15<>"",N(I15)<Parameters!$B$20),1,0) | K15: =IFERROR(VLOOKUP(C15,'Tax register'!$A$5:$K$1803,7,FALSE),"") | L15: =IFERROR(VLOOKUP(C15,'Tax register'!$A$5:$K$1803,10,FALSE),"") | M15: =IF(K15="","",COUNTIF('Tax register'!$G$5:$G$1803,K15)) | O15: =IF(OR(COUNT(E15:G15)<3,COUNT($U$13:$U$54)<42),"",IF(AND(E15=_check!$B$108,F15=_check!$B$109,G15=_check!$B$110),"✓","✗")) | Q15: IMP00006 | R15: T100033 | S15: 8 Mill Road | T15: BRK059 | U15: =IF(COUNTIFS($R$13:R15,R15,$S$13:S15,S15)=1,1,0) | V15: =IF(COUNTIFS($R$13:R15,R15,$T$13:T15,T15)=1,1,0)
A16: I04 | B16: IMP00340 | C16: T102376 | D16: =COUNTIF('Customs importers'!$B$5:$B$1506,C16)-1 | E16: =D16+COUNTIF(Consignees!$E$5:$E$2006,B16) | F16: =SUMIFS($U$13:$U$54,$R$13:$R$54,C16) | G16: =SUMIFS($V$13:$V$54,$R$13:$R$54,C16) | H16: =IFERROR(VLOOKUP(A16,'S2 Four lists'!$A$17:$N$41,8,FALSE),"") | I16: =IFERROR(VLOOKUP(A16,'S2 Four lists'!$A$17:$N$41,14,FALSE),"") | J16: =IF(AND(E16>=Parameters!$B$18,F16<=Parameters!$B$19,I16<>"",N(I16)<Parameters!$B$20),1,0) | K16: =IFERROR(VLOOKUP(C16,'Tax register'!$A$5:$K$1803,7,FALSE),"") | L16: =IFERROR(VLOOKUP(C16,'Tax register'!$A$5:$K$1803,10,FALSE),"") | M16: =IF(K16="","",COUNTIF('Tax register'!$G$5:$G$1803,K16)) | O16: =IF(OR(COUNT(E16:G16)<3,COUNT($U$13:$U$54)<42),"",IF(AND(E16=_check!$B$111,F16=_check!$B$112,G16=_check!$B$113),"✓","✗")) | Q16: IMP00095 | R16: T100033 | S16: 24 Harbour Road | T16: BRK033 | U16: =IF(COUNTIFS($R$13:R16,R16,$S$13:S16,S16)=1,1,0) | V16: =IF(COUNTIFS($R$13:R16,R16,$T$13:T16,T16)=1,1,0)
A17: I05 | B17: IMP00999 | C17: T106987 | D17: =COUNTIF('Customs importers'!$B$5:$B$1506,C17)-1 | E17: =D17+COUNTIF(Consignees!$E$5:$E$2006,B17) | F17: =SUMIFS($U$13:$U$54,$R$13:$R$54,C17) | G17: =SUMIFS($V$13:$V$54,$R$13:$R$54,C17) | H17: =IFERROR(VLOOKUP(A17,'S2 Four lists'!$A$17:$N$41,8,FALSE),"") | I17: =IFERROR(VLOOKUP(A17,'S2 Four lists'!$A$17:$N$41,14,FALSE),"") | J17: =IF(AND(E17>=Parameters!$B$18,F17<=Parameters!$B$19,I17<>"",N(I17)<Parameters!$B$20),1,0) | K17: =IFERROR(VLOOKUP(C17,'Tax register'!$A$5:$K$1803,7,FALSE),"") | L17: =IFERROR(VLOOKUP(C17,'Tax register'!$A$5:$K$1803,10,FALSE),"") | M17: =IF(K17="","",COUNTIF('Tax register'!$G$5:$G$1803,K17)) | O17: =IF(OR(COUNT(E17:G17)<3,COUNT($U$13:$U$54)<42),"",IF(AND(E17=_check!$B$114,F17=_check!$B$115,G17=_check!$B$116),"✓","✗")) | Q17: IMP00133 | R17: T100033 | S17: 24 Harbour Road | T17: BRK033 | U17: =IF(COUNTIFS($R$13:R17,R17,$S$13:S17,S17)=1,1,0) | V17: =IF(COUNTIFS($R$13:R17,R17,$T$13:T17,T17)=1,1,0)
A18: I06 | B18: IMP01037 | C18: T107258 | D18: =COUNTIF('Customs importers'!$B$5:$B$1506,C18)-1 | E18: =D18+COUNTIF(Consignees!$E$5:$E$2006,B18) | F18: =SUMIFS($U$13:$U$54,$R$13:$R$54,C18) | G18: =SUMIFS($V$13:$V$54,$R$13:$R$54,C18) | H18: =IFERROR(VLOOKUP(A18,'S2 Four lists'!$A$17:$N$41,8,FALSE),"") | I18: =IFERROR(VLOOKUP(A18,'S2 Four lists'!$A$17:$N$41,14,FALSE),"") | J18: =IF(AND(E18>=Parameters!$B$18,F18<=Parameters!$B$19,I18<>"",N(I18)<Parameters!$B$20),1,0) | K18: =IFERROR(VLOOKUP(C18,'Tax register'!$A$5:$K$1803,7,FALSE),"") | L18: =IFERROR(VLOOKUP(C18,'Tax register'!$A$5:$K$1803,10,FALSE),"") | M18: =IF(K18="","",COUNTIF('Tax register'!$G$5:$G$1803,K18)) | O18: =IF(OR(COUNT(E18:G18)<3,COUNT($U$13:$U$54)<42),"",IF(AND(E18=_check!$B$117,F18=_check!$B$118,G18=_check!$B$119),"✓","✗")) | Q18: IMP00307 | R18: T100033 | S18: 24 Harbour Road | T18: BRK033 | U18: =IF(COUNTIFS($R$13:R18,R18,$S$13:S18,S18)=1,1,0) | V18: =IF(COUNTIFS($R$13:R18,R18,$T$13:T18,T18)=1,1,0)
A19: I07 | B19: IMP00306 | C19: T102141 | D19: =COUNTIF('Customs importers'!$B$5:$B$1506,C19)-1 | E19: =D19+COUNTIF(Consignees!$E$5:$E$2006,B19) | F19: =SUMIFS($U$13:$U$54,$R$13:$R$54,C19) | G19: =SUMIFS($V$13:$V$54,$R$13:$R$54,C19) | H19: =IFERROR(VLOOKUP(A19,'S2 Four lists'!$A$17:$N$41,8,FALSE),"") | I19: =IFERROR(VLOOKUP(A19,'S2 Four lists'!$A$17:$N$41,14,FALSE),"") | J19: =IF(AND(E19>=Parameters!$B$18,F19<=Parameters!$B$19,I19<>"",N(I19)<Parameters!$B$20),1,0) | K19: =IFERROR(VLOOKUP(C19,'Tax register'!$A$5:$K$1803,7,FALSE),"") | L19: =IFERROR(VLOOKUP(C19,'Tax register'!$A$5:$K$1803,10,FALSE),"") | M19: =IF(K19="","",COUNTIF('Tax register'!$G$5:$G$1803,K19)) | O19: =IF(OR(COUNT(E19:G19)<3,COUNT($U$13:$U$54)<42),"",IF(AND(E19=_check!$B$120,F19=_check!$B$121,G19=_check!$B$122),"✓","✗")) | Q19: IMP00464 | R19: T100033 | S19: 24 Harbour Road | T19: BRK033 | U19: =IF(COUNTIFS($R$13:R19,R19,$S$13:S19,S19)=1,1,0) | V19: =IF(COUNTIFS($R$13:R19,R19,$T$13:T19,T19)=1,1,0)
A20: I10 | B20: IMP00448 | C20: T103130 | D20: =COUNTIF('Customs importers'!$B$5:$B$1506,C20)-1 | E20: =D20+COUNTIF(Consignees!$E$5:$E$2006,B20) | F20: =SUMIFS($U$13:$U$54,$R$13:$R$54,C20) | G20: =SUMIFS($V$13:$V$54,$R$13:$R$54,C20) | H20: =IFERROR(VLOOKUP(A20,'S2 Four lists'!$A$17:$N$41,8,FALSE),"") | I20: =IFERROR(VLOOKUP(A20,'S2 Four lists'!$A$17:$N$41,14,FALSE),"") | J20: =IF(AND(E20>=Parameters!$B$18,F20<=Parameters!$B$19,I20<>"",N(I20)<Parameters!$B$20),1,0) | K20: =IFERROR(VLOOKUP(C20,'Tax register'!$A$5:$K$1803,7,FALSE),"") | L20: =IFERROR(VLOOKUP(C20,'Tax register'!$A$5:$K$1803,10,FALSE),"") | M20: =IF(K20="","",COUNTIF('Tax register'!$G$5:$G$1803,K20)) | O20: =IF(OR(COUNT(E20:G20)<3,COUNT($U$13:$U$54)<42),"",IF(AND(E20=_check!$B$123,F20=_check!$B$124,G20=_check!$B$125),"✓","✗")) | Q20: IMP00742 | R20: T100033 | S20: 24 Harbour Road | T20: BRK033 | U20: =IF(COUNTIFS($R$13:R20,R20,$S$13:S20,S20)=1,1,0) | V20: =IF(COUNTIFS($R$13:R20,R20,$T$13:T20,T20)=1,1,0)
A21: I11 | B21: IMP00005 | C21: T100033 | D21: =COUNTIF('Customs importers'!$B$5:$B$1506,C21)-1 | E21: =D21+COUNTIF(Consignees!$E$5:$E$2006,B21) | F21: =SUMIFS($U$13:$U$54,$R$13:$R$54,C21) | G21: =SUMIFS($V$13:$V$54,$R$13:$R$54,C21) | H21: =IFERROR(VLOOKUP(A21,'S2 Four lists'!$A$17:$N$41,8,FALSE),"") | I21: =IFERROR(VLOOKUP(A21,'S2 Four lists'!$A$17:$N$41,14,FALSE),"") | J21: =IF(AND(E21>=Parameters!$B$18,F21<=Parameters!$B$19,I21<>"",N(I21)<Parameters!$B$20),1,0) | K21: =IFERROR(VLOOKUP(C21,'Tax register'!$A$5:$K$1803,7,FALSE),"") | L21: =IFERROR(VLOOKUP(C21,'Tax register'!$A$5:$K$1803,10,FALSE),"") | M21: =IF(K21="","",COUNTIF('Tax register'!$G$5:$G$1803,K21)) | O21: =IF(OR(COUNT(E21:G21)<3,COUNT($U$13:$U$54)<42),"",IF(AND(E21=_check!$B$126,F21=_check!$B$127,G21=_check!$B$128),"✓","✗")) | Q21: IMP00990 | R21: T100033 | S21: 24 Harbour Road | T21: BRK033 | U21: =IF(COUNTIFS($R$13:R21,R21,$S$13:S21,S21)=1,1,0) | V21: =IF(COUNTIFS($R$13:R21,R21,$T$13:T21,T21)=1,1,0)
A22: I14 | B22: IMP01242 | C22: T108692 | D22: =COUNTIF('Customs importers'!$B$5:$B$1506,C22)-1 | E22: =D22+COUNTIF(Consignees!$E$5:$E$2006,B22) | F22: =SUMIFS($U$13:$U$54,$R$13:$R$54,C22) | G22: =SUMIFS($V$13:$V$54,$R$13:$R$54,C22) | H22: =IFERROR(VLOOKUP(A22,'S2 Four lists'!$A$17:$N$41,8,FALSE),"") | I22: =IFERROR(VLOOKUP(A22,'S2 Four lists'!$A$17:$N$41,14,FALSE),"") | J22: =IF(AND(E22>=Parameters!$B$18,F22<=Parameters!$B$19,I22<>"",N(I22)<Parameters!$B$20),1,0) | K22: =IFERROR(VLOOKUP(C22,'Tax register'!$A$5:$K$1803,7,FALSE),"") | L22: =IFERROR(VLOOKUP(C22,'Tax register'!$A$5:$K$1803,10,FALSE),"") | M22: =IF(K22="","",COUNTIF('Tax register'!$G$5:$G$1803,K22)) | O22: =IF(OR(COUNT(E22:G22)<3,COUNT($U$13:$U$54)<42),"",IF(AND(E22=_check!$B$129,F22=_check!$B$130,G22=_check!$B$131),"✓","✗")) | Q22: IMP01005 | R22: T100033 | S22: 24 Harbour Road | T22: BRK033 | U22: =IF(COUNTIFS($R$13:R22,R22,$S$13:S22,S22)=1,1,0) | V22: =IF(COUNTIFS($R$13:R22,R22,$T$13:T22,T22)=1,1,0)
A23: I15 | B23: IMP00011 | C23: T100070 | D23: =COUNTIF('Customs importers'!$B$5:$B$1506,C23)-1 | E23: =D23+COUNTIF(Consignees!$E$5:$E$2006,B23) | F23: =SUMIFS($U$13:$U$54,$R$13:$R$54,C23) | G23: =SUMIFS($V$13:$V$54,$R$13:$R$54,C23) | H23: =IFERROR(VLOOKUP(A23,'S2 Four lists'!$A$17:$N$41,8,FALSE),"") | I23: =IFERROR(VLOOKUP(A23,'S2 Four lists'!$A$17:$N$41,14,FALSE),"") | J23: =IF(AND(E23>=Parameters!$B$18,F23<=Parameters!$B$19,I23<>"",N(I23)<Parameters!$B$20),1,0) | K23: =IFERROR(VLOOKUP(C23,'Tax register'!$A$5:$K$1803,7,FALSE),"") | L23: =IFERROR(VLOOKUP(C23,'Tax register'!$A$5:$K$1803,10,FALSE),"") | M23: =IF(K23="","",COUNTIF('Tax register'!$G$5:$G$1803,K23)) | O23: =IF(OR(COUNT(E23:G23)<3,COUNT($U$13:$U$54)<42),"",IF(AND(E23=_check!$B$132,F23=_check!$B$133,G23=_check!$B$134),"✓","✗")) | Q23: IMP01223 | R23: T100033 | S23: 24 Harbour Road | T23: BRK033 | U23: =IF(COUNTIFS($R$13:R23,R23,$S$13:S23,S23)=1,1,0) | V23: =IF(COUNTIFS($R$13:R23,R23,$T$13:T23,T23)=1,1,0)
A24: I16 | B24: IMP01089 | C24: T107617 | D24: =COUNTIF('Customs importers'!$B$5:$B$1506,C24)-1 | E24: =D24+COUNTIF(Consignees!$E$5:$E$2006,B24) | F24: =SUMIFS($U$13:$U$54,$R$13:$R$54,C24) | G24: =SUMIFS($V$13:$V$54,$R$13:$R$54,C24) | H24: =IFERROR(VLOOKUP(A24,'S2 Four lists'!$A$17:$N$41,8,FALSE),"") | I24: =IFERROR(VLOOKUP(A24,'S2 Four lists'!$A$17:$N$41,14,FALSE),"") | J24: =IF(AND(E24>=Parameters!$B$18,F24<=Parameters!$B$19,I24<>"",N(I24)<Parameters!$B$20),1,0) | K24: =IFERROR(VLOOKUP(C24,'Tax register'!$A$5:$K$1803,7,FALSE),"") | L24: =IFERROR(VLOOKUP(C24,'Tax register'!$A$5:$K$1803,10,FALSE),"") | M24: =IF(K24="","",COUNTIF('Tax register'!$G$5:$G$1803,K24)) | O24: =IF(OR(COUNT(E24:G24)<3,COUNT($U$13:$U$54)<42),"",IF(AND(E24=_check!$B$135,F24=_check!$B$136,G24=_check!$B$137),"✓","✗")) | Q24: IMP01477 | R24: T100033 | S24: 24 Harbour Road | T24: BRK033 | U24: =IF(COUNTIFS($R$13:R24,R24,$S$13:S24,S24)=1,1,0) | V24: =IF(COUNTIFS($R$13:R24,R24,$T$13:T24,T24)=1,1,0)
A25: I18 | B25: IMP01142 | C25: T107992 | D25: =COUNTIF('Customs importers'!$B$5:$B$1506,C25)-1 | E25: =D25+COUNTIF(Consignees!$E$5:$E$2006,B25) | F25: =SUMIFS($U$13:$U$54,$R$13:$R$54,C25) | G25: =SUMIFS($V$13:$V$54,$R$13:$R$54,C25) | H25: =IFERROR(VLOOKUP(A25,'S2 Four lists'!$A$17:$N$41,8,FALSE),"") | I25: =IFERROR(VLOOKUP(A25,'S2 Four lists'!$A$17:$N$41,14,FALSE),"") | J25: =IF(AND(E25>=Parameters!$B$18,F25<=Parameters!$B$19,I25<>"",N(I25)<Parameters!$B$20),1,0) | K25: =IFERROR(VLOOKUP(C25,'Tax register'!$A$5:$K$1803,7,FALSE),"") | L25: =IFERROR(VLOOKUP(C25,'Tax register'!$A$5:$K$1803,10,FALSE),"") | M25: =IF(K25="","",COUNTIF('Tax register'!$G$5:$G$1803,K25)) | O25: =IF(OR(COUNT(E25:G25)<3,COUNT($U$13:$U$54)<42),"",IF(AND(E25=_check!$B$138,F25=_check!$B$139,G25=_check!$B$140),"✓","✗")) | Q25: IMP00011 | R25: T100070 | S25: 346 Market Street | T25: BRK015 | U25: =IF(COUNTIFS($R$13:R25,R25,$S$13:S25,S25)=1,1,0) | V25: =IF(COUNTIFS($R$13:R25,R25,$T$13:T25,T25)=1,1,0)
A26: I19 | B26: IMP01310 | C26: T109167 | D26: =COUNTIF('Customs importers'!$B$5:$B$1506,C26)-1 | E26: =D26+COUNTIF(Consignees!$E$5:$E$2006,B26) | F26: =SUMIFS($U$13:$U$54,$R$13:$R$54,C26) | G26: =SUMIFS($V$13:$V$54,$R$13:$R$54,C26) | H26: =IFERROR(VLOOKUP(A26,'S2 Four lists'!$A$17:$N$41,8,FALSE),"") | I26: =IFERROR(VLOOKUP(A26,'S2 Four lists'!$A$17:$N$41,14,FALSE),"") | J26: =IF(AND(E26>=Parameters!$B$18,F26<=Parameters!$B$19,I26<>"",N(I26)<Parameters!$B$20),1,0) | K26: =IFERROR(VLOOKUP(C26,'Tax register'!$A$5:$K$1803,7,FALSE),"") | L26: =IFERROR(VLOOKUP(C26,'Tax register'!$A$5:$K$1803,10,FALSE),"") | M26: =IF(K26="","",COUNTIF('Tax register'!$G$5:$G$1803,K26)) | O26: =IF(OR(COUNT(E26:G26)<3,COUNT($U$13:$U$54)<42),"",IF(AND(E26=_check!$B$141,F26=_check!$B$142,G26=_check!$B$143),"✓","✗")) | Q26: IMP00114 | R26: T100070 | S26: 346 Market Street | T26: BRK015 | U26: =IF(COUNTIFS($R$13:R26,R26,$S$13:S26,S26)=1,1,0) | V26: =IF(COUNTIFS($R$13:R26,R26,$T$13:T26,T26)=1,1,0)
A27: I20 | B27: IMP00490 | C27: T103425 | D27: =COUNTIF('Customs importers'!$B$5:$B$1506,C27)-1 | E27: =D27+COUNTIF(Consignees!$E$5:$E$2006,B27) | F27: =SUMIFS($U$13:$U$54,$R$13:$R$54,C27) | G27: =SUMIFS($V$13:$V$54,$R$13:$R$54,C27) | H27: =IFERROR(VLOOKUP(A27,'S2 Four lists'!$A$17:$N$41,8,FALSE),"") | I27: =IFERROR(VLOOKUP(A27,'S2 Four lists'!$A$17:$N$41,14,FALSE),"") | J27: =IF(AND(E27>=Parameters!$B$18,F27<=Parameters!$B$19,I27<>"",N(I27)<Parameters!$B$20),1,0) | K27: =IFERROR(VLOOKUP(C27,'Tax register'!$A$5:$K$1803,7,FALSE),"") | L27: =IFERROR(VLOOKUP(C27,'Tax register'!$A$5:$K$1803,10,FALSE),"") | M27: =IF(K27="","",COUNTIF('Tax register'!$G$5:$G$1803,K27)) | O27: =IF(OR(COUNT(E27:G27)<3,COUNT($U$13:$U$54)<42),"",IF(AND(E27=_check!$B$144,F27=_check!$B$145,G27=_check!$B$146),"✓","✗")) | Q27: IMP00129 | R27: T100070 | S27: 346 Market Street | T27: BRK015 | U27: =IF(COUNTIFS($R$13:R27,R27,$S$13:S27,S27)=1,1,0) | V27: =IF(COUNTIFS($R$13:R27,R27,$T$13:T27,T27)=1,1,0)
A28: I21 | B28: IMP00063 | C28: T100440 | D28: =COUNTIF('Customs importers'!$B$5:$B$1506,C28)-1 | E28: =D28+COUNTIF(Consignees!$E$5:$E$2006,B28) | F28: =SUMIFS($U$13:$U$54,$R$13:$R$54,C28) | G28: =SUMIFS($V$13:$V$54,$R$13:$R$54,C28) | H28: =IFERROR(VLOOKUP(A28,'S2 Four lists'!$A$17:$N$41,8,FALSE),"") | I28: =IFERROR(VLOOKUP(A28,'S2 Four lists'!$A$17:$N$41,14,FALSE),"") | J28: =IF(AND(E28>=Parameters!$B$18,F28<=Parameters!$B$19,I28<>"",N(I28)<Parameters!$B$20),1,0) | K28: =IFERROR(VLOOKUP(C28,'Tax register'!$A$5:$K$1803,7,FALSE),"") | L28: =IFERROR(VLOOKUP(C28,'Tax register'!$A$5:$K$1803,10,FALSE),"") | M28: =IF(K28="","",COUNTIF('Tax register'!$G$5:$G$1803,K28)) | O28: =IF(OR(COUNT(E28:G28)<3,COUNT($U$13:$U$54)<42),"",IF(AND(E28=_check!$B$147,F28=_check!$B$148,G28=_check!$B$149),"✓","✗")) | Q28: IMP00197 | R28: T100070 | S28: 346 Market Street | T28: BRK015 | U28: =IF(COUNTIFS($R$13:R28,R28,$S$13:S28,S28)=1,1,0) | V28: =IF(COUNTIFS($R$13:R28,R28,$T$13:T28,T28)=1,1,0)
A29: I22 | B29: IMP00926 | C29: T106477 | D29: =COUNTIF('Customs importers'!$B$5:$B$1506,C29)-1 | E29: =D29+COUNTIF(Consignees!$E$5:$E$2006,B29) | F29: =SUMIFS($U$13:$U$54,$R$13:$R$54,C29) | G29: =SUMIFS($V$13:$V$54,$R$13:$R$54,C29) | H29: =IFERROR(VLOOKUP(A29,'S2 Four lists'!$A$17:$N$41,8,FALSE),"") | I29: =IFERROR(VLOOKUP(A29,'S2 Four lists'!$A$17:$N$41,14,FALSE),"") | J29: =IF(AND(E29>=Parameters!$B$18,F29<=Parameters!$B$19,I29<>"",N(I29)<Parameters!$B$20),1,0) | K29: =IFERROR(VLOOKUP(C29,'Tax register'!$A$5:$K$1803,7,FALSE),"") | L29: =IFERROR(VLOOKUP(C29,'Tax register'!$A$5:$K$1803,10,FALSE),"") | M29: =IF(K29="","",COUNTIF('Tax register'!$G$5:$G$1803,K29)) | O29: =IF(OR(COUNT(E29:G29)<3,COUNT($U$13:$U$54)<42),"",IF(AND(E29=_check!$B$150,F29=_check!$B$151,G29=_check!$B$152),"✓","✗")) | Q29: IMP00295 | R29: T100070 | S29: 346 Market Street | T29: BRK015 | U29: =IF(COUNTIFS($R$13:R29,R29,$S$13:S29,S29)=1,1,0) | V29: =IF(COUNTIFS($R$13:R29,R29,$T$13:T29,T29)=1,1,0)
A30: I23 | B30: IMP00643 | C30: T104498 | D30: =COUNTIF('Customs importers'!$B$5:$B$1506,C30)-1 | E30: =D30+COUNTIF(Consignees!$E$5:$E$2006,B30) | F30: =SUMIFS($U$13:$U$54,$R$13:$R$54,C30) | G30: =SUMIFS($V$13:$V$54,$R$13:$R$54,C30) | H30: =IFERROR(VLOOKUP(A30,'S2 Four lists'!$A$17:$N$41,8,FALSE),"") | I30: =IFERROR(VLOOKUP(A30,'S2 Four lists'!$A$17:$N$41,14,FALSE),"") | J30: =IF(AND(E30>=Parameters!$B$18,F30<=Parameters!$B$19,I30<>"",N(I30)<Parameters!$B$20),1,0) | K30: =IFERROR(VLOOKUP(C30,'Tax register'!$A$5:$K$1803,7,FALSE),"") | L30: =IFERROR(VLOOKUP(C30,'Tax register'!$A$5:$K$1803,10,FALSE),"") | M30: =IF(K30="","",COUNTIF('Tax register'!$G$5:$G$1803,K30)) | O30: =IF(OR(COUNT(E30:G30)<3,COUNT($U$13:$U$54)<42),"",IF(AND(E30=_check!$B$153,F30=_check!$B$154,G30=_check!$B$155),"✓","✗")) | Q30: IMP00487 | R30: T100070 | S30: 346 Market Street | T30: BRK015 | U30: =IF(COUNTIFS($R$13:R30,R30,$S$13:S30,S30)=1,1,0) | V30: =IF(COUNTIFS($R$13:R30,R30,$T$13:T30,T30)=1,1,0)
A31: I24 | B31: IMP00067 | C31: T100466 | D31: =COUNTIF('Customs importers'!$B$5:$B$1506,C31)-1 | E31: =D31+COUNTIF(Consignees!$E$5:$E$2006,B31) | F31: =SUMIFS($U$13:$U$54,$R$13:$R$54,C31) | G31: =SUMIFS($V$13:$V$54,$R$13:$R$54,C31) | H31: =IFERROR(VLOOKUP(A31,'S2 Four lists'!$A$17:$N$41,8,FALSE),"") | I31: =IFERROR(VLOOKUP(A31,'S2 Four lists'!$A$17:$N$41,14,FALSE),"") | J31: =IF(AND(E31>=Parameters!$B$18,F31<=Parameters!$B$19,I31<>"",N(I31)<Parameters!$B$20),1,0) | K31: =IFERROR(VLOOKUP(C31,'Tax register'!$A$5:$K$1803,7,FALSE),"") | L31: =IFERROR(VLOOKUP(C31,'Tax register'!$A$5:$K$1803,10,FALSE),"") | M31: =IF(K31="","",COUNTIF('Tax register'!$G$5:$G$1803,K31)) | O31: =IF(OR(COUNT(E31:G31)<3,COUNT($U$13:$U$54)<42),"",IF(AND(E31=_check!$B$156,F31=_check!$B$157,G31=_check!$B$158),"✓","✗")) | Q31: IMP00708 | R31: T100070 | S31: 346 Market Street | T31: BRK015 | U31: =IF(COUNTIFS($R$13:R31,R31,$S$13:S31,S31)=1,1,0) | V31: =IF(COUNTIFS($R$13:R31,R31,$T$13:T31,T31)=1,1,0)
A32: I25 | B32: IMP00288 | C32: T102011 | D32: =COUNTIF('Customs importers'!$B$5:$B$1506,C32)-1 | E32: =D32+COUNTIF(Consignees!$E$5:$E$2006,B32) | F32: =SUMIFS($U$13:$U$54,$R$13:$R$54,C32) | G32: =SUMIFS($V$13:$V$54,$R$13:$R$54,C32) | H32: =IFERROR(VLOOKUP(A32,'S2 Four lists'!$A$17:$N$41,8,FALSE),"") | I32: =IFERROR(VLOOKUP(A32,'S2 Four lists'!$A$17:$N$41,14,FALSE),"") | J32: =IF(AND(E32>=Parameters!$B$18,F32<=Parameters!$B$19,I32<>"",N(I32)<Parameters!$B$20),1,0) | K32: =IFERROR(VLOOKUP(C32,'Tax register'!$A$5:$K$1803,7,FALSE),"") | L32: =IFERROR(VLOOKUP(C32,'Tax register'!$A$5:$K$1803,10,FALSE),"") | M32: =IF(K32="","",COUNTIF('Tax register'!$G$5:$G$1803,K32)) | O32: =IF(OR(COUNT(E32:G32)<3,COUNT($U$13:$U$54)<42),"",IF(AND(E32=_check!$B$159,F32=_check!$B$160,G32=_check!$B$161),"✓","✗")) | Q32: IMP00901 | R32: T100070 | S32: 346 Market Street | T32: BRK015 | U32: =IF(COUNTIFS($R$13:R32,R32,$S$13:S32,S32)=1,1,0) | V32: =IF(COUNTIFS($R$13:R32,R32,$T$13:T32,T32)=1,1,0)
Q33: IMP00939 | R33: T100070 | S33: 346 Market Street | T33: BRK015 | U33: =IF(COUNTIFS($R$13:R33,R33,$S$13:S33,S33)=1,1,0) | V33: =IF(COUNTIFS($R$13:R33,R33,$T$13:T33,T33)=1,1,0)
A34: The five importers with no tax number have no row here: nothing clears under a number they do not have. Spreading risk through shared links is a reason to ask, never a finding. | Q34: IMP01074 | R34: T100070 | S34: 346 Market Street | T34: BRK015 | U34: =IF(COUNTIFS($R$13:R34,R34,$S$13:S34,S34)=1,1,0) | V34: =IF(COUNTIFS($R$13:R34,R34,$T$13:T34,T34)=1,1,0)
Q35: IMP01181 | R35: T100070 | S35: 346 Market Street | T35: BRK015 | U35: =IF(COUNTIFS($R$13:R35,R35,$S$13:S35,S35)=1,1,0) | V35: =IF(COUNTIFS($R$13:R35,R35,$T$13:T35,T35)=1,1,0)
Q36: IMP01260 | R36: T100070 | S36: 346 Market Street | T36: BRK015 | U36: =IF(COUNTIFS($R$13:R36,R36,$S$13:S36,S36)=1,1,0) | V36: =IF(COUNTIFS($R$13:R36,R36,$T$13:T36,T36)=1,1,0)
Q37: IMP01399 | R37: T100070 | S37: 346 Market Street | T37: BRK015 | U37: =IF(COUNTIFS($R$13:R37,R37,$S$13:S37,S37)=1,1,0) | V37: =IF(COUNTIFS($R$13:R37,R37,$T$13:T37,T37)=1,1,0)
Q38: IMP00063 | R38: T100440 | S38: 215 Bazaar Lane | T38: BRK038 | U38: =IF(COUNTIFS($R$13:R38,R38,$S$13:S38,S38)=1,1,0) | V38: =IF(COUNTIFS($R$13:R38,R38,$T$13:T38,T38)=1,1,0)
Q39: IMP00067 | R39: T100466 | S39: 356 Station Road | T39: BRK021 | U39: =IF(COUNTIFS($R$13:R39,R39,$S$13:S39,S39)=1,1,0) | V39: =IF(COUNTIFS($R$13:R39,R39,$T$13:T39,T39)=1,1,0)
Q40: IMP00288 | R40: T102011 | S40: 360 Harbour Road | T40: BRK016 | U40: =IF(COUNTIFS($R$13:R40,R40,$S$13:S40,S40)=1,1,0) | V40: =IF(COUNTIFS($R$13:R40,R40,$T$13:T40,T40)=1,1,0)
Q41: IMP00306 | R41: T102141 | S41: 314 Industrial Estate | T41: BRK061 | U41: =IF(COUNTIFS($R$13:R41,R41,$S$13:S41,S41)=1,1,0) | V41: =IF(COUNTIFS($R$13:R41,R41,$T$13:T41,T41)=1,1,0)
Q42: IMP00340 | R42: T102376 | S42: 43 Riverside | T42: BRK015 | U42: =IF(COUNTIFS($R$13:R42,R42,$S$13:S42,S42)=1,1,0) | V42: =IF(COUNTIFS($R$13:R42,R42,$T$13:T42,T42)=1,1,0)
Q43: IMP00448 | R43: T103130 | S43: 296 Temple Street | T43: BRK046 | U43: =IF(COUNTIFS($R$13:R43,R43,$S$13:S43,S43)=1,1,0) | V43: =IF(COUNTIFS($R$13:R43,R43,$T$13:T43,T43)=1,1,0)
Q44: IMP00490 | R44: T103425 | S44: 115 Harbour Road | T44: BRK060 | U44: =IF(COUNTIFS($R$13:R44,R44,$S$13:S44,S44)=1,1,0) | V44: =IF(COUNTIFS($R$13:R44,R44,$T$13:T44,T44)=1,1,0)
Q45: IMP00643 | R45: T104498 | S45: 340 Garden Lane | T45: BRK044 | U45: =IF(COUNTIFS($R$13:R45,R45,$S$13:S45,S45)=1,1,0) | V45: =IF(COUNTIFS($R$13:R45,R45,$T$13:T45,T45)=1,1,0)
Q46: IMP00753 | R46: T105264 | S46: 248 Industrial Estate | T46: BRK017 | U46: =IF(COUNTIFS($R$13:R46,R46,$S$13:S46,S46)=1,1,0) | V46: =IF(COUNTIFS($R$13:R46,R46,$T$13:T46,T46)=1,1,0)
... Q54: IMP01310 | R54: T109167 | S54: 329 Riverside | T54: BRK069 | U54: =IF(COUNTIFS($R$13:R54,R54,$S$13:S54,S54)=1,1,0) | V54: =IF(COUNTIFS($R$13:R54,R54,$T$13:T54,T54)=1,1,0)

Sheet S4 Tax feeds customs
A1: Sprint 4 · results from tax feed customs: does a tax adjustment point to customs findings?
A2: Item 6 of the joint action: outcomes sent back, and used in the other agency's targeting. Tax audited a random sample of the tax numbers that clear imports, on the VAT periods 2024-10 to 2025-09, all completed before customs month 25. Customs controlled its own random draw in months 25 to 36. Join the two, and compare.
A6: Step | B6: What to do | H6: Your answer | I6: Check | J6: Hint 1 · the tool (the full formula is on the Hints sheet)
A7: 1 | B7: The tax audits (left): keep the random ones; column G, 1 when the audit found an adjustment. Then: how many random audits found an adjustment? | H7: =COUNTIFS(C21:C304,"random",H21:H304,"adjustment") | I7: =IF(H7="","",IF(ISNUMBER(H7),IF(ABS(H7-_check!$B$162)<=0.5,"✓ matches","✗ not yet: see the hint"),"✗ not yet: see the hint")) | J7: COUNTIFS on the selection basis and the outcome.
A8: 2 | B8: The customs random draw (right): column O, found: 1 when the Controls sheet says the control of the line found something; column P, the tax result of the line's number: 1 adjustment, 0 audited with none, blank when not audited at random. | J8: VLOOKUP into the Controls sheet (its 3rd column, the result) for found; COUNTIFS on the audit table by tax number for the tax result.
A9: 3 | B9: The customs hit rate on lines whose number had a tax adjustment, and on lines whose number was audited with none. Then: the lift (the first ÷ the second). | H9: =(COUNTIFS(P21:P1434,1,O21:O1434,1)/COUNTIF(P21:P1434,1))/(COUNTIFS(P21:P1434,0,O21:O1434,1)/COUNTIF(P21:P1434,0)) | I9: =IF(H9="","",IF(ISNUMBER(H9),IF(ABS(H9-_check!$B$163)<=0.01,"✓ matches","✗ not yet: see the hint"),"✗ not yet: see the hint")) | J9: COUNTIFS on the tax result and found = 1, divided by COUNTIFS on the tax result.
A10: 4 | B10: How many lines stand behind each rate? Write the joint action's item 6 from it: what customs asks tax to send back, how often, and how it enters the targeting. | J10: Fewer than 100 lines on a side is a small sample: say so beside the number.
A16: Count the lines behind each rate (step 4): a rate on fewer than 100 lines can move a lot: give its range with it.
A17: The tables from row 21: left, rows copied from the Tax audits sheet (tax_audits.csv), every audit, the random ones first (284 rows); right, rows copied from the Declarations sheet: the lines of months 25 to 36 that customs drew at random (Controls: selected by = random draw) under a number tax audited at random, by tax number (1,414 rows). Columns G, O and P are yours; their first five rows are worked.
A20: audit | B20: tax ID | C20: selection basis | D20: selected on | E20: completed on | F20: audit type | G20: adjustment (1/0) | H20: outcome | I20: finding type | J20: tax assessed (LCU) | L20: line | M20: tax number used to clear | N20: date lodged | O20: found (1/0) · you | P20: tax result (1/0) · you
A21: AUD00001 | B21: T100013 | C21: random | D21: 2025-01-15 | E21: 2025-08-02 | F21: field | G21: =IF(H21="adjustment",1,0) | H21: no adjustment | J21: 0 | L21: L0239440 | M21: T100052 | N21: 2026-08-11 | O21: =IFERROR(IF(VLOOKUP(L21,Controls!$A$5:$D$1418,3,FALSE)="finding",1,0),0) | P21: =IF(COUNTIFS($B$21:$B$304,M21,$C$21:$C$304,"random")=0,"",IF(COUNTIFS($B$21:$B$304,M21,$C$21:$C$304,"random",$H$21:$H$304,"adjustment")>0,1,0))
A22: AUD00002 | B22: T100052 | C22: random | D22: 2025-01-15 | E22: 2025-02-21 | F22: desk | G22: =IF(H22="adjustment",1,0) | H22: no adjustment | J22: 0 | L22: L0171519 | M22: T100070 | N22: 2025-10-24 | O22: =IFERROR(IF(VLOOKUP(L22,Controls!$A$5:$D$1418,3,FALSE)="finding",1,0),0) | P22: =IF(COUNTIFS($B$21:$B$304,M22,$C$21:$C$304,"random")=0,"",IF(COUNTIFS($B$21:$B$304,M22,$C$21:$C$304,"random",$H$21:$H$304,"adjustment")>0,1,0))
A23: AUD00003 | B23: T100056 | C23: random | D23: 2025-01-15 | E23: 2025-03-18 | F23: desk | G23: =IF(H23="adjustment",1,0) | H23: no adjustment | J23: 0 | L23: L0172344 | M23: T100070 | N23: 2025-10-27 | O23: =IFERROR(IF(VLOOKUP(L23,Controls!$A$5:$D$1418,3,FALSE)="finding",1,0),0) | P23: =IF(COUNTIFS($B$21:$B$304,M23,$C$21:$C$304,"random")=0,"",IF(COUNTIFS($B$21:$B$304,M23,$C$21:$C$304,"random",$H$21:$H$304,"adjustment")>0,1,0))
A24: AUD00004 | B24: T100070 | C24: random | D24: 2025-01-15 | E24: 2025-06-04 | F24: desk | G24: =IF(H24="adjustment",1,0) | H24: adjustment | I24: a number lent to others | J24: 33298528 | L24: L0175019 | M24: T100070 | N24: 2025-11-11 | O24: =IFERROR(IF(VLOOKUP(L24,Controls!$A$5:$D$1418,3,FALSE)="finding",1,0),0) | P24: =IF(COUNTIFS($B$21:$B$304,M24,$C$21:$C$304,"random")=0,"",IF(COUNTIFS($B$21:$B$304,M24,$C$21:$C$304,"random",$H$21:$H$304,"adjustment")>0,1,0))
A25: AUD00005 | B25: T100082 | C25: random | D25: 2025-01-15 | E25: 2025-02-20 | F25: desk | G25: =IF(H25="adjustment",1,0) | H25: adjustment | I25: sales not declared | J25: 669545 | L25: L0175329 | M25: T100070 | N25: 2025-11-13 | O25: =IFERROR(IF(VLOOKUP(L25,Controls!$A$5:$D$1418,3,FALSE)="finding",1,0),0) | P25: =IF(COUNTIFS($B$21:$B$304,M25,$C$21:$C$304,"random")=0,"",IF(COUNTIFS($B$21:$B$304,M25,$C$21:$C$304,"random",$H$21:$H$304,"adjustment")>0,1,0))
A26: AUD00006 | B26: T100152 | C26: random | D26: 2025-01-15 | E26: 2025-04-27 | F26: desk | G26: =IF(H26="adjustment",1,0) | H26: no adjustment | J26: 0 | L26: L0181983 | M26: T100070 | N26: 2025-12-14 | O26: =IFERROR(IF(VLOOKUP(L26,Controls!$A$5:$D$1418,3,FALSE)="finding",1,0),0) | P26: =IF(COUNTIFS($B$21:$B$304,M26,$C$21:$C$304,"random")=0,"",IF(COUNTIFS($B$21:$B$304,M26,$C$21:$C$304,"random",$H$21:$H$304,"adjustment")>0,1,0))
A27: AUD00007 | B27: T100165 | C27: random | D27: 2025-01-15 | E27: 2025-03-22 | F27: desk | G27: =IF(H27="adjustment",1,0) | H27: no adjustment | J27: 0 | L27: L0223288 | M27: T100070 | N27: 2026-06-03 | O27: =IFERROR(IF(VLOOKUP(L27,Controls!$A$5:$D$1418,3,FALSE)="finding",1,0),0) | P27: =IF(COUNTIFS($B$21:$B$304,M27,$C$21:$C$304,"random")=0,"",IF(COUNTIFS($B$21:$B$304,M27,$C$21:$C$304,"random",$H$21:$H$304,"adjustment")>0,1,0))
A28: AUD00008 | B28: T100193 | C28: random | D28: 2025-01-15 | E28: 2025-05-16 | F28: field | G28: =IF(H28="adjustment",1,0) | H28: adjustment | I28: sales not declared | J28: 5916409 | L28: L0224650 | M28: T100070 | N28: 2026-06-08 | O28: =IFERROR(IF(VLOOKUP(L28,Controls!$A$5:$D$1418,3,FALSE)="finding",1,0),0) | P28: =IF(COUNTIFS($B$21:$B$304,M28,$C$21:$C$304,"random")=0,"",IF(COUNTIFS($B$21:$B$304,M28,$C$21:$C$304,"random",$H$21:$H$304,"adjustment")>0,1,0))
A29: AUD00009 | B29: T100201 | C29: random | D29: 2025-01-15 | E29: 2025-04-18 | F29: desk | G29: =IF(H29="adjustment",1,0) | H29: no adjustment | J29: 0 | L29: L0225407 | M29: T100070 | N29: 2026-06-11 | O29: =IFERROR(IF(VLOOKUP(L29,Controls!$A$5:$D$1418,3,FALSE)="finding",1,0),0) | P29: =IF(COUNTIFS($B$21:$B$304,M29,$C$21:$C$304,"random")=0,"",IF(COUNTIFS($B$21:$B$304,M29,$C$21:$C$304,"random",$H$21:$H$304,"adjustment")>0,1,0))
A30: AUD00010 | B30: T100260 | C30: random | D30: 2025-01-15 | E30: 2025-08-01 | F30: field | G30: =IF(H30="adjustment",1,0) | H30: adjustment | I30: sales not declared | J30: 2251836 | L30: L0237563 | M30: T100070 | N30: 2026-08-02 | O30: =IFERROR(IF(VLOOKUP(L30,Controls!$A$5:$D$1418,3,FALSE)="finding",1,0),0) | P30: =IF(COUNTIFS($B$21:$B$304,M30,$C$21:$C$304,"random")=0,"",IF(COUNTIFS($B$21:$B$304,M30,$C$21:$C$304,"random",$H$21:$H$304,"adjustment")>0,1,0))
A31: AUD00011 | B31: T100374 | C31: random | D31: 2025-01-15 | E31: 2025-05-25 | F31: field | G31: =IF(H31="adjustment",1,0) | H31: adjustment | I31: sales not declared | J31: 432395 | L31: L0243729 | M31: T100070 | N31: 2026-08-28 | O31: =IFERROR(IF(VLOOKUP(L31,Controls!$A$5:$D$1418,3,FALSE)="finding",1,0),0) | P31: =IF(COUNTIFS($B$21:$B$304,M31,$C$21:$C$304,"random")=0,"",IF(COUNTIFS($B$21:$B$304,M31,$C$21:$C$304,"random",$H$21:$H$304,"adjustment")>0,1,0))
A32: AUD00012 | B32: T100466 | C32: random | D32: 2025-01-15 | E32: 2025-04-29 | F32: desk | G32: =IF(H32="adjustment",1,0) | H32: no adjustment | J32: 0 | L32: L0244223 | M32: T100070 | N32: 2026-09-03 | O32: =IFERROR(IF(VLOOKUP(L32,Controls!$A$5:$D$1418,3,FALSE)="finding",1,0),0) | P32: =IF(COUNTIFS($B$21:$B$304,M32,$C$21:$C$304,"random")=0,"",IF(COUNTIFS($B$21:$B$304,M32,$C$21:$C$304,"random",$H$21:$H$304,"adjustment")>0,1,0))
A33: AUD00013 | B33: T100476 | C33: random | D33: 2025-01-15 | E33: 2025-05-26 | F33: desk | G33: =IF(H33="adjustment",1,0) | H33: no adjustment | J33: 0 | L33: L0249893 | M33: T100070 | N33: 2026-09-28 | O33: =IFERROR(IF(VLOOKUP(L33,Controls!$A$5:$D$1418,3,FALSE)="finding",1,0),0) | P33: =IF(COUNTIFS($B$21:$B$304,M33,$C$21:$C$304,"random")=0,"",IF(COUNTIFS($B$21:$B$304,M33,$C$21:$C$304,"random",$H$21:$H$304,"adjustment")>0,1,0))
A34: AUD00014 | B34: T100497 | C34: random | D34: 2025-01-15 | E34: 2025-05-26 | F34: desk | G34: =IF(H34="adjustment",1,0) | H34: no adjustment | J34: 0 | L34: L0219221 | M34: T100082 | N34: 2026-05-16 | O34: =IFERROR(IF(VLOOKUP(L34,Controls!$A$5:$D$1418,3,FALSE)="finding",1,0),0) | P34: =IF(COUNTIFS($B$21:$B$304,M34,$C$21:$C$304,"random")=0,"",IF(COUNTIFS($B$21:$B$304,M34,$C$21:$C$304,"random",$H$21:$H$304,"adjustment")>0,1,0))
A35: AUD00015 | B35: T100510 | C35: random | D35: 2025-01-15 | E35: 2025-06-12 | F35: desk | G35: =IF(H35="adjustment",1,0) | H35: no adjustment | J35: 0 | L35: L0171963 | M35: T100152 | N35: 2025-10-26 | O35: =IFERROR(IF(VLOOKUP(L35,Controls!$A$5:$D$1418,3,FALSE)="finding",1,0),0) | P35: =IF(COUNTIFS($B$21:$B$304,M35,$C$21:$C$304,"random")=0,"",IF(COUNTIFS($B$21:$B$304,M35,$C$21:$C$304,"random",$H$21:$H$304,"adjustment")>0,1,0))
A36: AUD00016 | B36: T100538 | C36: random | D36: 2025-01-15 | E36: 2025-05-03 | F36: desk | G36: =IF(H36="adjustment",1,0) | H36: no adjustment | J36: 0 | L36: L0201493 | M36: T100152 | N36: 2026-03-07 | O36: =IFERROR(IF(VLOOKUP(L36,Controls!$A$5:$D$1418,3,FALSE)="finding",1,0),0) | P36: =IF(COUNTIFS($B$21:$B$304,M36,$C$21:$C$304,"random")=0,"",IF(COUNTIFS($B$21:$B$304,M36,$C$21:$C$304,"random",$H$21:$H$304,"adjustment")>0,1,0))
A37: AUD00017 | B37: T100614 | C37: random | D37: 2025-01-15 | E37: 2025-03-10 | F37: desk | G37: =IF(H37="adjustment",1,0) | H37: no adjustment | J37: 0 | L37: L0210996 | M37: T100152 | N37: 2026-04-14 | O37: =IFERROR(IF(VLOOKUP(L37,Controls!$A$5:$D$1418,3,FALSE)="finding",1,0),0) | P37: =IF(COUNTIFS($B$21:$B$304,M37,$C$21:$C$304,"random")=0,"",IF(COUNTIFS($B$21:$B$304,M37,$C$21:$C$304,"random",$H$21:$H$304,"adjustment")>0,1,0))
A38: AUD00018 | B38: T100631 | C38: random | D38: 2025-01-15 | E38: 2025-09-07 | F38: field | G38: =IF(H38="adjustment",1,0) | H38: no adjustment | J38: 0 | L38: L0226660 | M38: T100152 | N38: 2026-06-16 | O38: =IFERROR(IF(VLOOKUP(L38,Controls!$A$5:$D$1418,3,FALSE)="finding",1,0),0) | P38: =IF(COUNTIFS($B$21:$B$304,M38,$C$21:$C$304,"random")=0,"",IF(COUNTIFS($B$21:$B$304,M38,$C$21:$C$304,"random",$H$21:$H$304,"adjustment")>0,1,0))
A39: AUD00019 | B39: T100680 | C39: random | D39: 2025-01-15 | E39: 2025-03-21 | F39: desk | G39: =IF(H39="adjustment",1,0) | H39: no adjustment | J39: 0 | L39: L0166948 | M39: T100165 | N39: 2025-10-03 | O39: =IFERROR(IF(VLOOKUP(L39,Controls!$A$5:$D$1418,3,FALSE)="finding",1,0),0) | P39: =IF(COUNTIFS($B$21:$B$304,M39,$C$21:$C$304,"random")=0,"",IF(COUNTIFS($B$21:$B$304,M39,$C$21:$C$304,"random",$H$21:$H$304,"adjustment")>0,1,0))
A40: AUD00020 | B40: T100699 | C40: random | D40: 2025-01-15 | E40: 2025-07-30 | F40: field | G40: =IF(H40="adjustment",1,0) | H40: adjustment | I40: sales not declared | J40: 2693976 | L40: L0224827 | M40: T100165 | N40: 2026-06-09 | O40: =IFERROR(IF(VLOOKUP(L40,Controls!$A$5:$D$1418,3,FALSE)="finding",1,0),0) | P40: =IF(COUNTIFS($B$21:$B$304,M40,$C$21:$C$304,"random")=0,"",IF(COUNTIFS($B$21:$B$304,M40,$C$21:$C$304,"random",$H$21:$H$304,"adjustment")>0,1,0))
A41: AUD00021 | B41: T100705 | C41: random | D41: 2025-01-15 | E41: 2025-04-17 | F41: desk | G41: =IF(H41="adjustment",1,0) | H41: no adjustment | J41: 0 | L41: L0196483 | M41: T100193 | N41: 2026-02-16 | O41: =IFERROR(IF(VLOOKUP(L41,Controls!$A$5:$D$1418,3,FALSE)="finding",1,0),0) | P41: =IF(COUNTIFS($B$21:$B$304,M41,$C$21:$C$304,"random")=0,"",IF(COUNTIFS($B$21:$B$304,M41,$C$21:$C$304,"random",$H$21:$H$304,"adjustment")>0,1,0))
A42: AUD00022 | B42: T100720 | C42: random | D42: 2025-01-15 | E42: 2025-05-29 | F42: desk | G42: =IF(H42="adjustment",1,0) | H42: adjustment | I42: sales not declared | J42: 7429383 | L42: L0169084 | M42: T100201 | N42: 2025-10-13 | O42: =IFERROR(IF(VLOOKUP(L42,Controls!$A$5:$D$1418,3,FALSE)="finding",1,0),0) | P42: =IF(COUNTIFS($B$21:$B$304,M42,$C$21:$C$304,"random")=0,"",IF(COUNTIFS($B$21:$B$304,M42,$C$21:$C$304,"random",$H$21:$H$304,"adjustment")>0,1,0))
A43: AUD00023 | B43: T100729 | C43: random | D43: 2025-01-15 | E43: 2025-04-20 | F43: desk | G43: =IF(H43="adjustment",1,0) | H43: no adjustment | J43: 0 | L43: L0173944 | M43: T100260 | N43: 2025-11-07 | O43: =IFERROR(IF(VLOOKUP(L43,Controls!$A$5:$D$1418,3,FALSE)="finding",1,0),0) | P43: =IF(COUNTIFS($B$21:$B$304,M43,$C$21:$C$304,"random")=0,"",IF(COUNTIFS($B$21:$B$304,M43,$C$21:$C$304,"random",$H$21:$H$304,"adjustment")>0,1,0))
A44: AUD00024 | B44: T100741 | C44: random | D44: 2025-01-15 | E44: 2025-04-01 | F44: desk | G44: =IF(H44="adjustment",1,0) | H44: no adjustment | J44: 0 | L44: L0177527 | M44: T100260 | N44: 2025-11-23 | O44: =IFERROR(IF(VLOOKUP(L44,Controls!$A$5:$D$1418,3,FALSE)="finding",1,0),0) | P44: =IF(COUNTIFS($B$21:$B$304,M44,$C$21:$C$304,"random")=0,"",IF(COUNTIFS($B$21:$B$304,M44,$C$21:$C$304,"random",$H$21:$H$304,"adjustment")>0,1,0))
A45: AUD00025 | B45: T100758 | C45: random | D45: 2025-01-15 | E45: 2025-08-11 | F45: field | G45: =IF(H45="adjustment",1,0) | H45: no adjustment | J45: 0 | L45: L0181755 | M45: T100260 | N45: 2025-12-13 | O45: =IFERROR(IF(VLOOKUP(L45,Controls!$A$5:$D$1418,3,FALSE)="finding",1,0),0) | P45: =IF(COUNTIFS($B$21:$B$304,M45,$C$21:$C$304,"random")=0,"",IF(COUNTIFS($B$21:$B$304,M45,$C$21:$C$304,"random",$H$21:$H$304,"adjustment")>0,1,0))
A46: AUD00026 | B46: T100781 | C46: random | D46: 2025-01-15 | E46: 2025-06-08 | F46: field | G46: =IF(H46="adjustment",1,0) | H46: adjustment | I46: sales not declared | J46: 3843901 | L46: L0204909 | M46: T100260 | N46: 2026-03-20 | O46: =IFERROR(IF(VLOOKUP(L46,Controls!$A$5:$D$1418,3,FALSE)="finding",1,0),0) | P46: =IF(COUNTIFS($B$21:$B$304,M46,$C$21:$C$304,"random")=0,"",IF(COUNTIFS($B$21:$B$304,M46,$C$21:$C$304,"random",$H$21:$H$304,"adjustment")>0,1,0))
A47: AUD00027 | B47: T100799 | C47: random | D47: 2025-01-15 | E47: 2025-03-25 | F47: desk | G47: =IF(H47="adjustment",1,0) | H47: no adjustment | J47: 0 | L47: L0211000 | M47: T100260 | N47: 2026-04-14 | O47: =IFERROR(IF(VLOOKUP(L47,Controls!$A$5:$D$1418,3,FALSE)="finding",1,0),0) | P47: =IF(COUNTIFS($B$21:$B$304,M47,$C$21:$C$304,"random")=0,"",IF(COUNTIFS($B$21:$B$304,M47,$C$21:$C$304,"random",$H$21:$H$304,"adjustment")>0,1,0))
A48: AUD00028 | B48: T100811 | C48: random | D48: 2025-01-15 | E48: 2025-08-23 | F48: field | G48: =IF(H48="adjustment",1,0) | H48: no adjustment | J48: 0 | L48: L0215113 | M48: T100260 | N48: 2026-05-01 | O48: =IFERROR(IF(VLOOKUP(L48,Controls!$A$5:$D$1418,3,FALSE)="finding",1,0),0) | P48: =IF(COUNTIFS($B$21:$B$304,M48,$C$21:$C$304,"random")=0,"",IF(COUNTIFS($B$21:$B$304,M48,$C$21:$C$304,"random",$H$21:$H$304,"adjustment")>0,1,0))
A49: AUD00029 | B49: T100861 | C49: random | D49: 2025-01-15 | E49: 2025-03-25 | F49: desk | G49: =IF(H49="adjustment",1,0) | H49: no adjustment | J49: 0 | L49: L0240644 | M49: T100260 | N49: 2026-08-16 | O49: =IFERROR(IF(VLOOKUP(L49,Controls!$A$5:$D$1418,3,FALSE)="finding",1,0),0) | P49: =IF(COUNTIFS($B$21:$B$304,M49,$C$21:$C$304,"random")=0,"",IF(COUNTIFS($B$21:$B$304,M49,$C$21:$C$304,"random",$H$21:$H$304,"adjustment")>0,1,0))
A50: AUD00030 | B50: T100870 | C50: random | D50: 2025-01-15 | E50: 2025-03-15 | F50: desk | G50: =IF(H50="adjustment",1,0) | H50: no adjustment | J50: 0 | L50: L0168457 | M50: T100466 | N50: 2025-10-10 | O50: =IFERROR(IF(VLOOKUP(L50,Controls!$A$5:$D$1418,3,FALSE)="finding",1,0),0) | P50: =IF(COUNTIFS($B$21:$B$304,M50,$C$21:$C$304,"random")=0,"",IF(COUNTIFS($B$21:$B$304,M50,$C$21:$C$304,"random",$H$21:$H$304,"adjustment")>0,1,0))
A51: AUD00031 | B51: T100957 | C51: random | D51: 2025-01-15 | E51: 2025-08-25 | F51: field | G51: =IF(H51="adjustment",1,0) | H51: no adjustment | J51: 0 | L51: L0186176 | M51: T100466 | N51: 2026-01-04 | O51: =IFERROR(IF(VLOOKUP(L51,Controls!$A$5:$D$1418,3,FALSE)="finding",1,0),0) | P51: =IF(COUNTIFS($B$21:$B$304,M51,$C$21:$C$304,"random")=0,"",IF(COUNTIFS($B$21:$B$304,M51,$C$21:$C$304,"random",$H$21:$H$304,"adjustment")>0,1,0))
A52: AUD00032 | B52: T100987 | C52: random | D52: 2025-01-15 | E52: 2025-07-18 | F52: field | G52: =IF(H52="adjustment",1,0) | H52: no adjustment | J52: 0 | L52: L0190780 | M52: T100466 | N52: 2026-01-22 | O52: =IFERROR(IF(VLOOKUP(L52,Controls!$A$5:$D$1418,3,FALSE)="finding",1,0),0) | P52: =IF(COUNTIFS($B$21:$B$304,M52,$C$21:$C$304,"random")=0,"",IF(COUNTIFS($B$21:$B$304,M52,$C$21:$C$304,"random",$H$21:$H$304,"adjustment")>0,1,0))
A53: AUD00033 | B53: T101036 | C53: random | D53: 2025-01-15 | E53: 2025-03-23 | F53: desk | G53: =IF(H53="adjustment",1,0) | H53: no adjustment | J53: 0 | L53: L0195213 | M53: T100466 | N53: 2026-02-11 | O53: =IFERROR(IF(VLOOKUP(L53,Controls!$A$5:$D$1418,3,FALSE)="finding",1,0),0) | P53: =IF(COUNTIFS($B$21:$B$304,M53,$C$21:$C$304,"random")=0,"",IF(COUNTIFS($B$21:$B$304,M53,$C$21:$C$304,"random",$H$21:$H$304,"adjustment")>0,1,0))
A54: AUD00034 | B54: T101148 | C54: random | D54: 2025-01-15 | E54: 2025-03-02 | F54: desk | G54: =IF(H54="adjustment",1,0) | H54: no adjustment | J54: 0 | L54: L0204162 | M54: T100466 | N54: 2026-03-17 | O54: =IFERROR(IF(VLOOKUP(L54,Controls!$A$5:$D$1418,3,FALSE)="finding",1,0),0) | P54: =IF(COUNTIFS($B$21:$B$304,M54,$C$21:$C$304,"random")=0,"",IF(COUNTIFS($B$21:$B$304,M54,$C$21:$C$304,"random",$H$21:$H$304,"adjustment")>0,1,0))
A55: AUD00035 | B55: T101160 | C55: random | D55: 2025-01-15 | E55: 2025-07-14 | F55: field | G55: =IF(H55="adjustment",1,0) | H55: no adjustment | J55: 0 | L55: L0206575 | M55: T100466 | N55: 2026-03-26 | O55: =IFERROR(IF(VLOOKUP(L55,Controls!$A$5:$D$1418,3,FALSE)="finding",1,0),0) | P55: =IF(COUNTIFS($B$21:$B$304,M55,$C$21:$C$304,"random")=0,"",IF(COUNTIFS($B$21:$B$304,M55,$C$21:$C$304,"random",$H$21:$H$304,"adjustment")>0,1,0))
A56: AUD00036 | B56: T101178 | C56: random | D56: 2025-01-15 | E56: 2025-07-08 | F56: field | G56: =IF(H56="adjustment",1,0) | H56: adjustment | I56: sales not declared | J56: 47262 | L56: L0209645 | M56: T100466 | N56: 2026-04-09 | O56: =IFERROR(IF(VLOOKUP(L56,Controls!$A$5:$D$1418,3,FALSE)="finding",1,0),0) | P56: =IF(COUNTIFS($B$21:$B$304,M56,$C$21:$C$304,"random")=0,"",IF(COUNTIFS($B$21:$B$304,M56,$C$21:$C$304,"random",$H$21:$H$304,"adjustment")>0,1,0))
A57: AUD00037 | B57: T101202 | C57: random | D57: 2025-01-15 | E57: 2025-04-28 | F57: desk | G57: =IF(H57="adjustment",1,0) | H57: no adjustment | J57: 0 | L57: L0211020 | M57: T100466 | N57: 2026-04-14 | O57: =IFERROR(IF(VLOOKUP(L57,Controls!$A$5:$D$1418,3,FALSE)="finding",1,0),0) | P57: =IF(COUNTIFS($B$21:$B$304,M57,$C$21:$C$304,"random")=0,"",IF(COUNTIFS($B$21:$B$304,M57,$C$21:$C$304,"random",$H$21:$H$304,"adjustment")>0,1,0))
A58: AUD00038 | B58: T101224 | C58: random | D58: 2025-01-15 | E58: 2025-03-17 | F58: desk | G58: =IF(H58="adjustment",1,0) | H58: no adjustment | J58: 0 | L58: L0211836 | M58: T100466 | N58: 2026-04-17 | O58: =IFERROR(IF(VLOOKUP(L58,Controls!$A$5:$D$1418,3,FALSE)="finding",1,0),0) | P58: =IF(COUNTIFS($B$21:$B$304,M58,$C$21:$C$304,"random")=0,"",IF(COUNTIFS($B$21:$B$304,M58,$C$21:$C$304,"random",$H$21:$H$304,"adjustment")>0,1,0))
A59: AUD00039 | B59: T101250 | C59: random | D59: 2025-01-15 | E59: 2025-08-12 | F59: field | G59: =IF(H59="adjustment",1,0) | H59: no adjustment | J59: 0 | L59: L0236120 | M59: T100466 | N59: 2026-07-25 | O59: =IFERROR(IF(VLOOKUP(L59,Controls!$A$5:$D$1418,3,FALSE)="finding",1,0),0) | P59: =IF(COUNTIFS($B$21:$B$304,M59,$C$21:$C$304,"random")=0,"",IF(COUNTIFS($B$21:$B$304,M59,$C$21:$C$304,"random",$H$21:$H$304,"adjustment")>0,1,0))
A60: AUD00040 | B60: T101362 | C60: random | D60: 2025-01-15 | E60: 2025-06-09 | F60: field | G60: =IF(H60="adjustment",1,0) | H60: no adjustment | J60: 0 | L60: L0241094 | M60: T100466 | N60: 2026-08-18 | O60: =IFERROR(IF(VLOOKUP(L60,Controls!$A$5:$D$1418,3,FALSE)="finding",1,0),0) | P60: =IF(COUNTIFS($B$21:$B$304,M60,$C$21:$C$304,"random")=0,"",IF(COUNTIFS($B$21:$B$304,M60,$C$21:$C$304,"random",$H$21:$H$304,"adjustment")>0,1,0))
A61: AUD00041 | B61: T101426 | C61: random | D61: 2025-01-15 | E61: 2025-05-25 | F61: field | G61: =IF(H61="adjustment",1,0) | H61: no adjustment | J61: 0 | L61: L0170202 | M61: T100476 | N61: 2025-10-18 | O61: =IFERROR(IF(VLOOKUP(L61,Controls!$A$5:$D$1418,3,FALSE)="finding",1,0),0) | P61: =IF(COUNTIFS($B$21:$B$304,M61,$C$21:$C$304,"random")=0,"",IF(COUNTIFS($B$21:$B$304,M61,$C$21:$C$304,"random",$H$21:$H$304,"adjustment")>0,1,0))
A62: AUD00042 | B62: T101451 | C62: random | D62: 2025-01-15 | E62: 2025-04-03 | F62: desk | G62: =IF(H62="adjustment",1,0) | H62: adjustment | I62: sales not declared | J62: 852176 | L62: L0177979 | M62: T100476 | N62: 2025-11-25 | O62: =IFERROR(IF(VLOOKUP(L62,Controls!$A$5:$D$1418,3,FALSE)="finding",1,0),0) | P62: =IF(COUNTIFS($B$21:$B$304,M62,$C$21:$C$304,"random")=0,"",IF(COUNTIFS($B$21:$B$304,M62,$C$21:$C$304,"random",$H$21:$H$304,"adjustment")>0,1,0))
A63: AUD00043 | B63: T101458 | C63: random | D63: 2025-01-15 | E63: 2025-05-22 | F63: desk | G63: =IF(H63="adjustment",1,0) | H63: no adjustment | J63: 0 | L63: L0204671 | M63: T100476 | N63: 2026-03-19 | O63: =IFERROR(IF(VLOOKUP(L63,Controls!$A$5:$D$1418,3,FALSE)="finding",1,0),0) | P63: =IF(COUNTIFS($B$21:$B$304,M63,$C$21:$C$304,"random")=0,"",IF(COUNTIFS($B$21:$B$304,M63,$C$21:$C$304,"random",$H$21:$H$304,"adjustment")>0,1,0))
A64: AUD00044 | B64: T101459 | C64: random | D64: 2025-01-15 | E64: 2025-03-17 | F64: desk | G64: =IF(H64="adjustment",1,0) | H64: no adjustment | J64: 0 | L64: L0206301 | M64: T100476 | N64: 2026-03-25 | O64: =IFERROR(IF(VLOOKUP(L64,Controls!$A$5:$D$1418,3,FALSE)="finding",1,0),0) | P64: =IF(COUNTIFS($B$21:$B$304,M64,$C$21:$C$304,"random")=0,"",IF(COUNTIFS($B$21:$B$304,M64,$C$21:$C$304,"random",$H$21:$H$304,"adjustment")>0,1,0))
A65: AUD00045 | B65: T101550 | C65: random | D65: 2025-01-15 | E65: 2025-02-23 | F65: desk | G65: =IF(H65="adjustment",1,0) | H65: no adjustment | J65: 0 | L65: L0211321 | M65: T100476 | N65: 2026-04-15 | O65: =IFERROR(IF(VLOOKUP(L65,Controls!$A$5:$D$1418,3,FALSE)="finding",1,0),0) | P65: =IF(COUNTIFS($B$21:$B$304,M65,$C$21:$C$304,"random")=0,"",IF(COUNTIFS($B$21:$B$304,M65,$C$21:$C$304,"random",$H$21:$H$304,"adjustment")>0,1,0))
A66: AUD00046 | B66: T101562 | C66: random | D66: 2025-01-15 | E66: 2025-06-08 | F66: desk | G66: =IF(H66="adjustment",1,0) | H66: no adjustment | J66: 0 | L66: L0217633 | M66: T100476 | N66: 2026-05-10 | O66: =IFERROR(IF(VLOOKUP(L66,Controls!$A$5:$D$1418,3,FALSE)="finding",1,0),0) | P66: =IF(COUNTIFS($B$21:$B$304,M66,$C$21:$C$304,"random")=0,"",IF(COUNTIFS($B$21:$B$304,M66,$C$21:$C$304,"random",$H$21:$H$304,"adjustment")>0,1,0))
A67: AUD00047 | B67: T101651 | C67: random | D67: 2025-01-15 | E67: 2025-06-05 | F67: desk | G67: =IF(H67="adjustment",1,0) | H67: no adjustment | J67: 0 | L67: L0220039 | M67: T100476 | N67: 2026-05-19 | O67: =IFERROR(IF(VLOOKUP(L67,Controls!$A$5:$D$1418,3,FALSE)="finding",1,0),0) | P67: =IF(COUNTIFS($B$21:$B$304,M67,$C$21:$C$304,"random")=0,"",IF(COUNTIFS($B$21:$B$304,M67,$C$21:$C$304,"random",$H$21:$H$304,"adjustment")>0,1,0))
A68: AUD00048 | B68: T101656 | C68: random | D68: 2025-01-15 | E68: 2025-04-11 | F68: desk | G68: =IF(H68="adjustment",1,0) | H68: no adjustment | J68: 0 | L68: L0227989 | M68: T100476 | N68: 2026-06-21 | O68: =IFERROR(IF(VLOOKUP(L68,Controls!$A$5:$D$1418,3,FALSE)="finding",1,0),0) | P68: =IF(COUNTIFS($B$21:$B$304,M68,$C$21:$C$304,"random")=0,"",IF(COUNTIFS($B$21:$B$304,M68,$C$21:$C$304,"random",$H$21:$H$304,"adjustment")>0,1,0))
A69: AUD00049 | B69: T101660 | C69: random | D69: 2025-01-15 | E69: 2025-03-15 | F69: desk | G69: =IF(H69="adjustment",1,0) | H69: no adjustment | J69: 0 | L69: L0237360 | M69: T100476 | N69: 2026-08-02 | O69: =IFERROR(IF(VLOOKUP(L69,Controls!$A$5:$D$1418,3,FALSE)="finding",1,0),0) | P69: =IF(COUNTIFS($B$21:$B$304,M69,$C$21:$C$304,"random")=0,"",IF(COUNTIFS($B$21:$B$304,M69,$C$21:$C$304,"random",$H$21:$H$304,"adjustment")>0,1,0))
A70: AUD00050 | B70: T101683 | C70: random | D70: 2025-01-15 | E70: 2025-03-08 | F70: desk | G70: =IF(H70="adjustment",1,0) | H70: no adjustment | J70: 0 | L70: L0244470 | M70: T100476 | N70: 2026-09-04 | O70: =IFERROR(IF(VLOOKUP(L70,Controls!$A$5:$D$1418,3,FALSE)="finding",1,0),0) | P70: =IF(COUNTIFS($B$21:$B$304,M70,$C$21:$C$304,"random")=0,"",IF(COUNTIFS($B$21:$B$304,M70,$C$21:$C$304,"random",$H$21:$H$304,"adjustment")>0,1,0))
A71: AUD00051 | B71: T101700 | C71: random | D71: 2025-01-15 | E71: 2025-07-24 | F71: field | G71: =IF(H71="adjustment",1,0) | H71: no adjustment | J71: 0 | L71: L0246998 | M71: T100476 | N71: 2026-09-15 | O71: =IFERROR(IF(VLOOKUP(L71,Controls!$A$5:$D$1418,3,FALSE)="finding",1,0),0) | P71: =IF(COUNTIFS($B$21:$B$304,M71,$C$21:$C$304,"random")=0,"",IF(COUNTIFS($B$21:$B$304,M71,$C$21:$C$304,"random",$H$21:$H$304,"adjustment")>0,1,0))
A72: AUD00052 | B72: T101824 | C72: random | D72: 2025-01-15 | E72: 2025-05-27 | F72: desk | G72: =IF(H72="adjustment",1,0) | H72: no adjustment | J72: 0 | L72: L0173700 | M72: T100497 | N72: 2025-11-06 | O72: =IFERROR(IF(VLOOKUP(L72,Controls!$A$5:$D$1418,3,FALSE)="finding",1,0),0) | P72: =IF(COUNTIFS($B$21:$B$304,M72,$C$21:$C$304,"random")=0,"",IF(COUNTIFS($B$21:$B$304,M72,$C$21:$C$304,"random",$H$21:$H$304,"adjustment")>0,1,0))
A73: AUD00053 | B73: T101828 | C73: random | D73: 2025-01-15 | E73: 2025-06-07 | F73: field | G73: =IF(H73="adjustment",1,0) | H73: no adjustment | J73: 0 | L73: L0185411 | M73: T100497 | N73: 2026-01-01 | O73: =IFERROR(IF(VLOOKUP(L73,Controls!$A$5:$D$1418,3,FALSE)="finding",1,0),0) | P73: =IF(COUNTIFS($B$21:$B$304,M73,$C$21:$C$304,"random")=0,"",IF(COUNTIFS($B$21:$B$304,M73,$C$21:$C$304,"random",$H$21:$H$304,"adjustment")>0,1,0))
A74: AUD00054 | B74: T101861 | C74: random | D74: 2025-01-15 | E74: 2025-03-19 | F74: desk | G74: =IF(H74="adjustment",1,0) | H74: no adjustment | J74: 0 | L74: L0191320 | M74: T100497 | N74: 2026-01-24 | O74: =IFERROR(IF(VLOOKUP(L74,Controls!$A$5:$D$1418,3,FALSE)="finding",1,0),0) | P74: =IF(COUNTIFS($B$21:$B$304,M74,$C$21:$C$304,"random")=0,"",IF(COUNTIFS($B$21:$B$304,M74,$C$21:$C$304,"random",$H$21:$H$304,"adjustment")>0,1,0))
A75: AUD00055 | B75: T101970 | C75: random | D75: 2025-01-15 | E75: 2025-06-11 | F75: desk | G75: =IF(H75="adjustment",1,0) | H75: adjustment | I75: sales not declared | J75: 103007 | L75: L0223229 | M75: T100497 | N75: 2026-06-03 | O75: =IFERROR(IF(VLOOKUP(L75,Controls!$A$5:$D$1418,3,FALSE)="finding",1,0),0) | P75: =IF(COUNTIFS($B$21:$B$304,M75,$C$21:$C$304,"random")=0,"",IF(COUNTIFS($B$21:$B$304,M75,$C$21:$C$304,"random",$H$21:$H$304,"adjustment")>0,1,0))
A76: AUD00056 | B76: T101983 | C76: random | D76: 2025-01-15 | E76: 2025-07-09 | F76: field | G76: =IF(H76="adjustment",1,0) | H76: no adjustment | J76: 0 | L76: L0236892 | M76: T100497 | N76: 2026-07-28 | O76: =IFERROR(IF(VLOOKUP(L76,Controls!$A$5:$D$1418,3,FALSE)="finding",1,0),0) | P76: =IF(COUNTIFS($B$21:$B$304,M76,$C$21:$C$304,"random")=0,"",IF(COUNTIFS($B$21:$B$304,M76,$C$21:$C$304,"random",$H$21:$H$304,"adjustment")>0,1,0))
A77: AUD00057 | B77: T102074 | C77: random | D77: 2025-01-15 | E77: 2025-07-13 | F77: field | G77: =IF(H77="adjustment",1,0) | H77: no adjustment | J77: 0 | L77: L0171970 | M77: T100538 | N77: 2025-10-26 | O77: =IFERROR(IF(VLOOKUP(L77,Controls!$A$5:$D$1418,3,FALSE)="finding",1,0),0) | P77: =IF(COUNTIFS($B$21:$B$304,M77,$C$21:$C$304,"random")=0,"",IF(COUNTIFS($B$21:$B$304,M77,$C$21:$C$304,"random",$H$21:$H$304,"adjustment")>0,1,0))
A78: AUD00058 | B78: T102096 | C78: random | D78: 2025-01-15 | E78: 2025-05-09 | F78: field | G78: =IF(H78="adjustment",1,0) | H78: no adjustment | J78: 0 | L78: L0177739 | M78: T100538 | N78: 2025-11-24 | O78: =IFERROR(IF(VLOOKUP(L78,Controls!$A$5:$D$1418,3,FALSE)="finding",1,0),0) | P78: =IF(COUNTIFS($B$21:$B$304,M78,$C$21:$C$304,"random")=0,"",IF(COUNTIFS($B$21:$B$304,M78,$C$21:$C$304,"random",$H$21:$H$304,"adjustment")>0,1,0))
A79: AUD00059 | B79: T102294 | C79: random | D79: 2025-01-15 | E79: 2025-05-15 | F79: desk | G79: =IF(H79="adjustment",1,0) | H79: adjustment | I79: sales not declared | J79: 115812 | L79: L0179630 | M79: T100538 | N79: 2025-12-04 | O79: =IFERROR(IF(VLOOKUP(L79,Controls!$A$5:$D$1418,3,FALSE)="finding",1,0),0) | P79: =IF(COUNTIFS($B$21:$B$304,M79,$C$21:$C$304,"random")=0,"",IF(COUNTIFS($B$21:$B$304,M79,$C$21:$C$304,"random",$H$21:$H$304,"adjustment")>0,1,0))
A80: AUD00060 | B80: T102357 | C80: random | D80: 2025-01-15 | E80: 2025-04-28 | F80: desk | G80: =IF(H80="adjustment",1,0) | H80: no adjustment | J80: 0 | L80: L0182916 | M80: T100538 | N80: 2025-12-18 | O80: =IFERROR(IF(VLOOKUP(L80,Controls!$A$5:$D$1418,3,FALSE)="finding",1,0),0) | P80: =IF(COUNTIFS($B$21:$B$304,M80,$C$21:$C$304,"random")=0,"",IF(COUNTIFS($B$21:$B$304,M80,$C$21:$C$304,"random",$H$21:$H$304,"adjustment")>0,1,0))
A81: AUD00061 | B81: T102414 | C81: random | D81: 2025-01-15 | E81: 2025-05-25 | F81: desk | G81: =IF(H81="adjustment",1,0) | H81: no adjustment | J81: 0 | L81: L0184747 | M81: T100538 | N81: 2025-12-26 | O81: =IFERROR(IF(VLOOKUP(L81,Controls!$A$5:$D$1418,3,FALSE)="finding",1,0),0) | P81: =IF(COUNTIFS($B$21:$B$304,M81,$C$21:$C$304,"random")=0,"",IF(COUNTIFS($B$21:$B$304,M81,$C$21:$C$304,"random",$H$21:$H$304,"adjustment")>0,1,0))
A82: AUD00062 | B82: T102469 | C82: random | D82: 2025-01-15 | E82: 2025-03-02 | F82: desk | G82: =IF(H82="adjustment",1,0) | H82: no adjustment | J82: 0 | L82: L0188248 | M82: T100538 | N82: 2026-01-12 | O82: =IFERROR(IF(VLOOKUP(L82,Controls!$A$5:$D$1418,3,FALSE)="finding",1,0),0) | P82: =IF(COUNTIFS($B$21:$B$304,M82,$C$21:$C$304,"random")=0,"",IF(COUNTIFS($B$21:$B$304,M82,$C$21:$C$304,"random",$H$21:$H$304,"adjustment")>0,1,0))
A83: AUD00063 | B83: T102516 | C83: random | D83: 2025-01-15 | E83: 2025-04-17 | F83: desk | G83: =IF(H83="adjustment",1,0) | H83: no adjustment | J83: 0 | L83: L0188744 | M83: T100538 | N83: 2026-01-14 | O83: =IFERROR(IF(VLOOKUP(L83,Controls!$A$5:$D$1418,3,FALSE)="finding",1,0),0) | P83: =IF(COUNTIFS($B$21:$B$304,M83,$C$21:$C$304,"random")=0,"",IF(COUNTIFS($B$21:$B$304,M83,$C$21:$C$304,"random",$H$21:$H$304,"adjustment")>0,1,0))
A84: AUD00064 | B84: T102520 | C84: random | D84: 2025-01-15 | E84: 2025-05-04 | F84: desk | G84: =IF(H84="adjustment",1,0) | H84: no adjustment | J84: 0 | L84: L0200432 | M84: T100538 | N84: 2026-03-03 | O84: =IFERROR(IF(VLOOKUP(L84,Controls!$A$5:$D$1418,3,FALSE)="finding",1,0),0) | P84: =IF(COUNTIFS($B$21:$B$304,M84,$C$21:$C$304,"random")=0,"",IF(COUNTIFS($B$21:$B$304,M84,$C$21:$C$304,"random",$H$21:$H$304,"adjustment")>0,1,0))
A85: AUD00065 | B85: T102531 | C85: random | D85: 2025-01-15 | E85: 2025-07-05 | F85: field | G85: =IF(H85="adjustment",1,0) | H85: adjustment | I85: sales not declared | J85: 2987987 | L85: L0202568 | M85: T100538 | N85: 2026-03-11 | O85: =IFERROR(IF(VLOOKUP(L85,Controls!$A$5:$D$1418,3,FALSE)="finding",1,0),0) | P85: =IF(COUNTIFS($B$21:$B$304,M85,$C$21:$C$304,"random")=0,"",IF(COUNTIFS($B$21:$B$304,M85,$C$21:$C$304,"random",$H$21:$H$304,"adjustment")>0,1,0))
A86: AUD00066 | B86: T102616 | C86: random | D86: 2025-01-15 | E86: 2025-08-11 | F86: field | G86: =IF(H86="adjustment",1,0) | H86: no adjustment | J86: 0 | L86: L0206021 | M86: T100538 | N86: 2026-03-24 | O86: =IFERROR(IF(VLOOKUP(L86,Controls!$A$5:$D$1418,3,FALSE)="finding",1,0),0) | P86: =IF(COUNTIFS($B$21:$B$304,M86,$C$21:$C$304,"random")=0,"",IF(COUNTIFS($B$21:$B$304,M86,$C$21:$C$304,"random",$H$21:$H$304,"adjustment")>0,1,0))
A87: AUD00067 | B87: T102643 | C87: random | D87: 2025-01-15 | E87: 2025-04-18 | F87: desk | G87: =IF(H87="adjustment",1,0) | H87: adjustment | I87: sales not declared | J87: 148577 | L87: L0209118 | M87: T100538 | N87: 2026-04-07 | O87: =IFERROR(IF(VLOOKUP(L87,Controls!$A$5:$D$1418,3,FALSE)="finding",1,0),0) | P87: =IF(COUNTIFS($B$21:$B$304,M87,$C$21:$C$304,"random")=0,"",IF(COUNTIFS($B$21:$B$304,M87,$C$21:$C$304,"random",$H$21:$H$304,"adjustment")>0,1,0))
A88: AUD00068 | B88: T102647 | C88: random | D88: 2025-01-15 | E88: 2025-06-01 | F88: field | G88: =IF(H88="adjustment",1,0) | H88: no adjustment | J88: 0 | L88: L0209394 | M88: T100538 | N88: 2026-04-08 | O88: =IFERROR(IF(VLOOKUP(L88,Controls!$A$5:$D$1418,3,FALSE)="finding",1,0),0) | P88: =IF(COUNTIFS($B$21:$B$304,M88,$C$21:$C$304,"random")=0,"",IF(COUNTIFS($B$21:$B$304,M88,$C$21:$C$304,"random",$H$21:$H$304,"adjustment")>0,1,0))
A89: AUD00069 | B89: T102705 | C89: random | D89: 2025-01-15 | E89: 2025-06-14 | F89: field | G89: =IF(H89="adjustment",1,0) | H89: adjustment | I89: sales not declared | J89: 320740 | L89: L0212899 | M89: T100538 | N89: 2026-04-21 | O89: =IFERROR(IF(VLOOKUP(L89,Controls!$A$5:$D$1418,3,FALSE)="finding",1,0),0) | P89: =IF(COUNTIFS($B$21:$B$304,M89,$C$21:$C$304,"random")=0,"",IF(COUNTIFS($B$21:$B$304,M89,$C$21:$C$304,"random",$H$21:$H$304,"adjustment")>0,1,0))
A90: AUD00070 | B90: T102740 | C90: random | D90: 2025-01-15 | E90: 2025-08-11 | F90: field | G90: =IF(H90="adjustment",1,0) | H90: no adjustment | J90: 0 | L90: L0216214 | M90: T100538 | N90: 2026-05-05 | O90: =IFERROR(IF(VLOOKUP(L90,Controls!$A$5:$D$1418,3,FALSE)="finding",1,0),0) | P90: =IF(COUNTIFS($B$21:$B$304,M90,$C$21:$C$304,"random")=0,"",IF(COUNTIFS($B$21:$B$304,M90,$C$21:$C$304,"random",$H$21:$H$304,"adjustment")>0,1,0))
A91: AUD00071 | B91: T102784 | C91: random | D91: 2025-01-15 | E91: 2025-06-20 | F91: field | G91: =IF(H91="adjustment",1,0) | H91: adjustment | I91: sales not declared | J91: 536590 | L91: L0219772 | M91: T100538 | N91: 2026-05-18 | O91: =IFERROR(IF(VLOOKUP(L91,Controls!$A$5:$D$1418,3,FALSE)="finding",1,0),0) | P91: =IF(COUNTIFS($B$21:$B$304,M91,$C$21:$C$304,"random")=0,"",IF(COUNTIFS($B$21:$B$304,M91,$C$21:$C$304,"random",$H$21:$H$304,"adjustment")>0,1,0))
A92: AUD00072 | B92: T103006 | C92: random | D92: 2025-01-15 | E92: 2025-06-09 | F92: desk | G92: =IF(H92="adjustment",1,0) | H92: adjustment | I92: sales not declared | J92: 118848 | L92: L0222226 | M92: T100538 | N92: 2026-05-27 | O92: =IFERROR(IF(VLOOKUP(L92,Controls!$A$5:$D$1418,3,FALSE)="finding",1,0),0) | P92: =IF(COUNTIFS($B$21:$B$304,M92,$C$21:$C$304,"random")=0,"",IF(COUNTIFS($B$21:$B$304,M92,$C$21:$C$304,"random",$H$21:$H$304,"adjustment")>0,1,0))
A93: AUD00073 | B93: T103045 | C93: random | D93: 2025-01-15 | E93: 2025-02-17 | F93: desk | G93: =IF(H93="adjustment",1,0) | H93: no adjustment | J93: 0 | L93: L0231810 | M93: T100538 | N93: 2026-07-08 | O93: =IFERROR(IF(VLOOKUP(L93,Controls!$A$5:$D$1418,3,FALSE)="finding",1,0),0) | P93: =IF(COUNTIFS($B$21:$B$304,M93,$C$21:$C$304,"random")=0,"",IF(COUNTIFS($B$21:$B$304,M93,$C$21:$C$304,"random",$H$21:$H$304,"adjustment")>0,1,0))
A94: AUD00074 | B94: T103082 | C94: random | D94: 2025-01-15 | E94: 2025-06-03 | F94: desk | G94: =IF(H94="adjustment",1,0) | H94: no adjustment | J94: 0 | L94: L0243989 | M94: T100538 | N94: 2026-09-02 | O94: =IFERROR(IF(VLOOKUP(L94,Controls!$A$5:$D$1418,3,FALSE)="finding",1,0),0) | P94: =IF(COUNTIFS($B$21:$B$304,M94,$C$21:$C$304,"random")=0,"",IF(COUNTIFS($B$21:$B$304,M94,$C$21:$C$304,"random",$H$21:$H$304,"adjustment")>0,1,0))
A95: AUD00075 | B95: T103111 | C95: random | D95: 2025-01-15 | E95: 2025-05-24 | F95: field | G95: =IF(H95="adjustment",1,0) | H95: no adjustment | J95: 0 | L95: L0243990 | M95: T100538 | N95: 2026-09-02 | O95: =IFERROR(IF(VLOOKUP(L95,Controls!$A$5:$D$1418,3,FALSE)="finding",1,0),0) | P95: =IF(COUNTIFS($B$21:$B$304,M95,$C$21:$C$304,"random")=0,"",IF(COUNTIFS($B$21:$B$304,M95,$C$21:$C$304,"random",$H$21:$H$304,"adjustment")>0,1,0))
A96: AUD00076 | B96: T103125 | C96: random | D96: 2025-01-15 | E96: 2025-03-02 | F96: desk | G96: =IF(H96="adjustment",1,0) | H96: no adjustment | J96: 0 | L96: L0244233 | M96: T100538 | N96: 2026-09-03 | O96: =IFERROR(IF(VLOOKUP(L96,Controls!$A$5:$D$1418,3,FALSE)="finding",1,0),0) | P96: =IF(COUNTIFS($B$21:$B$304,M96,$C$21:$C$304,"random")=0,"",IF(COUNTIFS($B$21:$B$304,M96,$C$21:$C$304,"random",$H$21:$H$304,"adjustment")>0,1,0))
A97: AUD00077 | B97: T103173 | C97: random | D97: 2025-01-15 | E97: 2025-03-23 | F97: desk | G97: =IF(H97="adjustment",1,0) | H97: adjustment | I97: sales not declared | J97: 2213128 | L97: L0194918 | M97: T100631 | N97: 2026-02-10 | O97: =IFERROR(IF(VLOOKUP(L97,Controls!$A$5:$D$1418,3,FALSE)="finding",1,0),0) | P97: =IF(COUNTIFS($B$21:$B$304,M97,$C$21:$C$304,"random")=0,"",IF(COUNTIFS($B$21:$B$304,M97,$C$21:$C$304,"random",$H$21:$H$304,"adjustment")>0,1,0))
A98: AUD00078 | B98: T103192 | C98: random | D98: 2025-01-15 | E98: 2025-05-16 | F98: desk | G98: =IF(H98="adjustment",1,0) | H98: adjustment | I98: sales not declared | J98: 1164804 | L98: L0198879 | M98: T100631 | N98: 2026-02-25 | O98: =IFERROR(IF(VLOOKUP(L98,Controls!$A$5:$D$1418,3,FALSE)="finding",1,0),0) | P98: =IF(COUNTIFS($B$21:$B$304,M98,$C$21:$C$304,"random")=0,"",IF(COUNTIFS($B$21:$B$304,M98,$C$21:$C$304,"random",$H$21:$H$304,"adjustment")>0,1,0))
A99: AUD00079 | B99: T103274 | C99: random | D99: 2025-01-15 | E99: 2025-04-19 | F99: desk | G99: =IF(H99="adjustment",1,0) | H99: no adjustment | J99: 0 | L99: L0191062 | M99: T100680 | N99: 2026-01-23 | O99: =IFERROR(IF(VLOOKUP(L99,Controls!$A$5:$D$1418,3,FALSE)="finding",1,0),0) | P99: =IF(COUNTIFS($B$21:$B$304,M99,$C$21:$C$304,"random")=0,"",IF(COUNTIFS($B$21:$B$304,M99,$C$21:$C$304,"random",$H$21:$H$304,"adjustment")>0,1,0))
A100: AUD00080 | B100: T103377 | C100: random | D100: 2025-01-15 | E100: 2025-08-26 | F100: field | G100: =IF(H100="adjustment",1,0) | H100: no adjustment | J100: 0 | L100: L0216495 | M100: T100680 | N100: 2026-05-06 | O100: =IFERROR(IF(VLOOKUP(L100,Controls!$A$5:$D$1418,3,FALSE)="finding",1,0),0) | P100: =IF(COUNTIFS($B$21:$B$304,M100,$C$21:$C$304,"random")=0,"",IF(COUNTIFS($B$21:$B$304,M100,$C$21:$C$304,"random",$H$21:$H$304,"adjustment")>0,1,0))
A101: AUD00081 | B101: T103391 | C101: random | D101: 2025-01-15 | E101: 2025-05-27 | F101: desk | G101: =IF(H101="adjustment",1,0) | H101: no adjustment | J101: 0 | L101: L0221089 | M101: T100680 | N101: 2026-05-23 | O101: =IFERROR(IF(VLOOKUP(L101,Controls!$A$5:$D$1418,3,FALSE)="finding",1,0),0) | P101: =IF(COUNTIFS($B$21:$B$304,M101,$C$21:$C$304,"random")=0,"",IF(COUNTIFS($B$21:$B$304,M101,$C$21:$C$304,"random",$H$21:$H$304,"adjustment")>0,1,0))
A102: AUD00082 | B102: T103425 | C102: random | D102: 2025-01-15 | E102: 2025-04-16 | F102: field | G102: =IF(H102="adjustment",1,0) | H102: no adjustment | J102: 0 | L102: L0229867 | M102: T100680 | N102: 2026-06-28 | O102: =IFERROR(IF(VLOOKUP(L102,Controls!$A$5:$D$1418,3,FALSE)="finding",1,0),0) | P102: =IF(COUNTIFS($B$21:$B$304,M102,$C$21:$C$304,"random")=0,"",IF(COUNTIFS($B$21:$B$304,M102,$C$21:$C$304,"random",$H$21:$H$304,"adjustment")>0,1,0))
A103: AUD00083 | B103: T103507 | C103: random | D103: 2025-01-15 | E103: 2025-03-11 | F103: desk | G103: =IF(H103="adjustment",1,0) | H103: no adjustment | J103: 0 | L103: L0230348 | M103: T100680 | N103: 2026-07-02 | O103: =IFERROR(IF(VLOOKUP(L103,Controls!$A$5:$D$1418,3,FALSE)="finding",1,0),0) | P103: =IF(COUNTIFS($B$21:$B$304,M103,$C$21:$C$304,"random")=0,"",IF(COUNTIFS($B$21:$B$304,M103,$C$21:$C$304,"random",$H$21:$H$304,"adjustment")>0,1,0))
A104: AUD00084 | B104: T103555 | C104: random | D104: 2025-01-15 | E104: 2025-08-18 | F104: field | G104: =IF(H104="adjustment",1,0) | H104: no adjustment | J104: 0 | L104: L0244236 | M104: T100680 | N104: 2026-09-03 | O104: =IFERROR(IF(VLOOKUP(L104,Controls!$A$5:$D$1418,3,FALSE)="finding",1,0),0) | P104: =IF(COUNTIFS($B$21:$B$304,M104,$C$21:$C$304,"random")=0,"",IF(COUNTIFS($B$21:$B$304,M104,$C$21:$C$304,"random",$H$21:$H$304,"adjustment")>0,1,0))
A105: AUD00085 | B105: T103567 | C105: random | D105: 2025-01-15 | E105: 2025-02-20 | F105: desk | G105: =IF(H105="adjustment",1,0) | H105: no adjustment | J105: 0 | L105: L0247880 | M105: T100680 | N105: 2026-09-19 | O105: =IFERROR(IF(VLOOKUP(L105,Controls!$A$5:$D$1418,3,FALSE)="finding",1,0),0) | P105: =IF(COUNTIFS($B$21:$B$304,M105,$C$21:$C$304,"random")=0,"",IF(COUNTIFS($B$21:$B$304,M105,$C$21:$C$304,"random",$H$21:$H$304,"adjustment")>0,1,0))
A106: AUD00086 | B106: T103572 | C106: random | D106: 2025-01-15 | E106: 2025-03-24 | F106: desk | G106: =IF(H106="adjustment",1,0) | H106: no adjustment | J106: 0 | L106: L0166962 | M106: T100699 | N106: 2025-10-03 | O106: =IFERROR(IF(VLOOKUP(L106,Controls!$A$5:$D$1418,3,FALSE)="finding",1,0),0) | P106: =IF(COUNTIFS($B$21:$B$304,M106,$C$21:$C$304,"random")=0,"",IF(COUNTIFS($B$21:$B$304,M106,$C$21:$C$304,"random",$H$21:$H$304,"adjustment")>0,1,0))
A107: AUD00087 | B107: T103667 | C107: random | D107: 2025-01-15 | E107: 2025-04-28 | F107: desk | G107: =IF(H107="adjustment",1,0) | H107: no adjustment | J107: 0 | L107: L0169544 | M107: T100699 | N107: 2025-10-15 | O107: =IFERROR(IF(VLOOKUP(L107,Controls!$A$5:$D$1418,3,FALSE)="finding",1,0),0) | P107: =IF(COUNTIFS($B$21:$B$304,M107,$C$21:$C$304,"random")=0,"",IF(COUNTIFS($B$21:$B$304,M107,$C$21:$C$304,"random",$H$21:$H$304,"adjustment")>0,1,0))
A108: AUD00088 | B108: T103761 | C108: random | D108: 2025-01-15 | E108: 2025-05-17 | F108: field | G108: =IF(H108="adjustment",1,0) | H108: no adjustment | J108: 0 | L108: L0171109 | M108: T100699 | N108: 2025-10-22 | O108: =IFERROR(IF(VLOOKUP(L108,Controls!$A$5:$D$1418,3,FALSE)="finding",1,0),0) | P108: =IF(COUNTIFS($B$21:$B$304,M108,$C$21:$C$304,"random")=0,"",IF(COUNTIFS($B$21:$B$304,M108,$C$21:$C$304,"random",$H$21:$H$304,"adjustment")>0,1,0))
A109: AUD00089 | B109: T103835 | C109: random | D109: 2025-01-15 | E109: 2025-03-27 | F109: desk | G109: =IF(H109="adjustment",1,0) | H109: no adjustment | J109: 0 | L109: L0174627 | M109: T100699 | N109: 2025-11-10 | O109: =IFERROR(IF(VLOOKUP(L109,Controls!$A$5:$D$1418,3,FALSE)="finding",1,0),0) | P109: =IF(COUNTIFS($B$21:$B$304,M109,$C$21:$C$304,"random")=0,"",IF(COUNTIFS($B$21:$B$304,M109,$C$21:$C$304,"random",$H$21:$H$304,"adjustment")>0,1,0))
A110: AUD00090 | B110: T103855 | C110: random | D110: 2025-01-15 | E110: 2025-04-15 | F110: field | G110: =IF(H110="adjustment",1,0) | H110: no adjustment | J110: 0 | L110: L0175562 | M110: T100699 | N110: 2025-11-14 | O110: =IFERROR(IF(VLOOKUP(L110,Controls!$A$5:$D$1418,3,FALSE)="finding",1,0),0) | P110: =IF(COUNTIFS($B$21:$B$304,M110,$C$21:$C$304,"random")=0,"",IF(COUNTIFS($B$21:$B$304,M110,$C$21:$C$304,"random",$H$21:$H$304,"adjustment")>0,1,0))
...

Sheet Joint action
A1: Sprint 4 · the joint action: Breakout 4A's seven items, written from the customs side
A2: Written against your lists (S2) and networks (S3). A lock without an owner in each agency, or without a window and a held-out group, is not an action.
A4: 1 · One risk, one population (how many importers, how much VAT at stake)
A5: 2 · The key between the two (the tax number, or your matching rule and who checks the middle band)
A6: 3 · Explainable reasons (the check that put each trader on the list)
A7: 4 · A repeatable data flow (what customs sends, how often)
A8: 5 · An owner in each agency (by name)
A9: 6 · Outcomes sent back (registered? audited? amount assessed? and how customs uses them: S4)
A10: 7 · A window and a test (4 to 12 weeks, a group held out at random, the number read at the end)

Sheet Similarities
A1: Similarities · Computed for you
A2: Computed for you by a script (pairs_4b.csv): for each of the 25 importers, the tax register's record most like it, found by a search on the cleaned name and address, and how alike the two records' name, address and director are once cleaned (lower case, punctuation and legal suffixes out, Rd to Road): 0 nothing in common, 1 the same; empty when one side has no value. A fuzzy match needs a script, not a spreadsheet. S1 Match copies the four purple columns.
A3: the breakout's label | B3: customs' importer code | C3: the register's record most like the importer's: a candidate, not a match | D3: cleaned names compared, 0 to 1 | E3: cleaned addresses compared; empty when one is missing | F3: cleaned director names compared; empty when one is missing
A4: ref | B4: importer | C4: best candidate: tax ID | D4: name similarity | E4: address similarity | F4: director similarity
A5: I01 | B5: IMP00519 | C5: T103629 | D5: 1 | E5: 1 | F5: 1
A6: I02 | B6: IMP00753 | C6: T105264 | D6: 1 | E6: 1 | F6: 1
A7: I03 | B7: IMP00892 | C7: T106240 | D7: 1 | E7: 1 | F7: 1
A8: I04 | B8: IMP00340 | C8: T102376 | D8: 1 | E8: 1 | F8: 1
A9: I05 | B9: IMP00999 | C9: T106987 | D9: 1 | E9: 1 | F9: 1
A10: I06 | B10: IMP01037 | C10: T107258 | D10: 1 | E10: 1 | F10: 1
A11: I07 | B11: IMP00306 | C11: T102141 | D11: 1 | E11: 1 | F11: 1
A12: I08 | B12: IMP00147 | C12: T102182 | D12: 1 | E12: 0.615 | F12: 0.345
A13: I09 | B13: IMP00721 | C13: T514418 | D13: 1 | E13: 0.417 | F13: 0.4
A14: I10 | B14: IMP00448 | C14: T103130 | D14: 1 | F14: 1
A15: I11 | B15: IMP00005 | C15: T100033 | D15: 1 | E15: 1 | F15: 1
A16: I12 | B16: IMP00156 | C16: T109212 | D16: 1 | E16: 0.846 | F16: 0.32
A17: I13 | B17: IMP00950 | C17: T110150 | D17: 1 | E17: 0.846 | F17: 0.4
A18: I14 | B18: IMP01242 | C18: T108692 | D18: 1 | E18: 1 | F18: 1
A19: I15 | B19: IMP00011 | C19: T100070 | D19: 1 | E19: 1 | F19: 1
A20: I16 | B20: IMP01089 | C20: T107617 | D20: 1 | E20: 1 | F20: 1
A21: I17 | B21: IMP01481 | C21: T106372 | D21: 1 | E21: 0.857 | F21: 0.4
A22: I18 | B22: IMP01142 | C22: T107992 | D22: 1 | E22: 1 | F22: 1
A23: I19 | B23: IMP01310 | C23: T109167 | D23: 1 | E23: 1 | F23: 1
A24: I20 | B24: IMP00490 | C24: T103425 | D24: 1 | E24: 1 | F24: 1
A25: I21 | B25: IMP00063 | C25: T100440 | D25: 1 | E25: 1 | F25: 1
A26: I22 | B26: IMP00926 | C26: T106477 | D26: 1 | E26: 1 | F26: 1
... A29: I25 | B29: IMP00288 | C29: T102015 | D29: 1 | E29: 1 | F29: 1

Sheet Sectors
A1: Sectors · Computed for you
A2: Computed for you by a script (sector_usual_4b.csv): the median of sales ÷ imports over the tax numbers both sides know that filed at least 10 of their last 12 returns, sector by sector. A median per sector over 1,194 numbers needs a script. S2 Four lists reads column B.
A3: the sector of activity | B3: the median of sales ÷ imports in the sector | C3: how many tax numbers the median reads
A4: sector | B4: usual sales ÷ imports | C4: numbers in the median
A5: Cosmetics and personal care | B5: 1.53 | C5: 85
A6: Electronics | B6: 1.388 | C6: 85
A7: Food importers | B7: 1.4272497 | C7: 81
A8: Fuel and chemicals | B8: 1.3431467 | C8: 86
A9: Furniture and household | B9: 1.5845 | C9: 80
A10: General trading | B10: 1.4655 | C10: 90
A11: Machinery | B11: 1.4245 | C11: 82
A12: Medical devices | B12: 1.5223379 | C12: 85
A13: Pharmaceuticals | B13: 1.5179904 | C13: 79
A14: Steel and construction | B14: 1.3897967 | C14: 78
A15: Textiles and apparel | B15: 1.6816275 | C15: 108
A16: Tobacco and beverages | B16: 1.4557721 | C16: 76
A17: Vehicles and parts | B17: 1.477 | C17: 99

Sheet Customs importers
A1: Customs importers · from workshop_extract.xlsx, sheet Importers, every row: 1,502 rows
A2: The customs register of importers, every column (the extract calls the sheet Importers): S1 Match copies the 25 importers' rows, S3 Network counts the codes under a number and copies the rows of its 20 numbers. As recorded: no formula, nothing computed. Row 3 is the column in plain words, row 4 its code in the extract; the Fields sheet says what each column means.
A3: importer | B3: tax number | C3: legal name | D3: trading name | E3: address | F3: district | G3: phone | H3: director | I3: usual broker | J3: registered on | K3: sector | L3: status
A4: importer_id | B4: tin | C4: legal_name | D4: trading_name | E4: address_line | F4: district | G4: phone | H4: director_name | I4: default_broker_id | J4: registration_date | K4: sector | L4: status
A5: IMP00001 | B5: T100004 | C5: Metro Trading Co., Ltd | D5: Metro Trading Co., Ltd | E5: 369 Airport Road | F5: North | G5: 0800178993 | H5: Aisha Tanaka | I5: BRK060 | J5: 2022-08-23 | K5: Vehicles and parts | L5: suspended
A6: IMP00002 | B6: T100013 | C6: Prescott Imports Group Ltd | D6: Prescott Imports Group Ltd | E6: 102 Temple Street | F6: East | G6: 0844703272 | H6: Kenji Mwangi | I6: BRK078 | J6: 2022-05-14 | K6: Vehicles and parts | L6: active
A7: IMP00003 | B7: T100016 | C7: Saffron Trading & Sons | D7: Saffron Trade | E7: 53 Garden Lane | F7: Capital | G7: 0973133835 | H7: Omar Rahman | I7: BRK054 | J7: 2014-02-07 | K7: General trading | L7: active
A8: IMP00004 | B8: T100025 | C8: Harmony Fruits Co., Ltd | D8: Harmony Fruits Co., Ltd | E8: 297 Airport Road | F8: North | G8: 0328461006 | H8: Nadia Sato | I8: BRK080 | J8: 2008-08-08 | K8: Vehicles and parts | L8: active
A9: IMP00005 | B9: T100033 | C9: Central Foods Limited | D9: Central Foods Limited | E9: 24 Harbour Road | F9: East | G9: 0401520138 | H9: Farid Ibrahim | I9: BRK033 | J9: 2019-08-31 | K9: Steel and construction | L9: active
A10: IMP00006 | B10: T100033 | C10: Saffron Textiles Co. | D10: Saffron Textiles Co. | E10: 8 Mill Road | F10: North | G10: 0690619802 | H10: Grace Silva | I10: BRK059 | J10: 2017-06-10 | K10: Textiles and apparel | L10: active
A11: IMP00007 | C11: Silk Road Enterprises Partners Ltd | D11: Silk Road Enterprises Partners Ltd | E11: 241 Bazaar Lane | F11: Capital | G11: 0728834594 | H11: Somchai Al-Sayed | I11: BRK059 | J11: 2021-08-31 | K11: Tobacco and beverages | L11: active
